Workbook

Sheet Table of Contents
B2: Table of Contents
Q3: Remarks
Q4: 1 Reconcile sheet is comapring Tally Inventory with Tarka
Q5: 2.Review Purchase sheet is redundnt Started to compare Purchases & reconcile
Q6: 3.Qty Analysis is Made by Accounts dept
Q7: 4. Input -Purchase comes from Tally
Q8: 5.Input-Dirct Expns from Tally
Q9: 6.Input-Indirect Expns from Tally
Q10: 7.Input-Stock Vauation from Tally
Q11: 8.Input-Inventory Sales Recobciles Gross Sales to Net Sales
Q12: 9.Output- Cost OF Good Sold (COGS)
Q13: 10.Output-PAL1 Gross P& L compares with Tally P& L fro data Validation with Quantities
Q14: 11.Output_Trading PL is checking on Trading monthly performance
... Q17: 14,15,16,17 OUTPUT from abve sheets for MIS understanding

Sheet Reconcile(HMT)
B2: Op Stock | E2: Apr | H2: May | K2: Jun | N2: Jul | Q2: Aug | T2: Sep | W2: Oct | Z2: Nov | AC2: Dec | AF2: Jan | AI2: Feb | AL2: Mar
B3: HMT | C3: CRK | D3: Diff | E3: HMT | F3: CRK | G3: Diff | H3: HMT | I3: CRK | J3: Diff | K3: HMT | L3: CRK | M3: Diff | N3: HMT | O3: CRK | P3: Diff | Q3: HMT | R3: CRK | S3: Diff | T3: HMT | U3: CRK | V3: Diff | W3: HMT | X3: CRK | Y3: Diff | Z3: HMT | AA3: CRK | AB3: Diff | AC3: HMT | AD3: CRK | AE3: Diff | AF3: HMT | AG3: CRK | AH3: Diff | AI3: HMT | AJ3: CRK | AK3: Diff | AL3: HMT | AM3: CRK | AN3: Diff
A4: HDPE | B4: 195845 | C4: ='Stock Valuation (FIFO)'!B5 -> 141140 | D4: =B4-C4 -> 54705 | E4: 180315 | F4: ='Stock Valuation (FIFO)'!E5 -> 75695 | G4: =IF(F4=0,0,(E4-F4)) -> 104620 | H4: 147410 | I4: ='Stock Valuation (FIFO)'!H5 -> 90040 | J4: =IF(I4=0,0,(H4-I4)) -> 57370 | K4: 164125 | L4: ='Stock Valuation (FIFO)'!K5 -> 0 | M4: =IF(L4=0,0,(K4-L4)) -> 0 | N4: 146140 | O4: ='Stock Valuation (FIFO)'!N5 -> 0 | P4: =IF(O4=0,0,(N4-O4)) -> 0 | Q4: 187620 | R4: =' Qty Analysis'!N8 -> 0 | S4: =IF(R4=0,0,(Q4-R4)) -> 0 | T4: 114680 | U4: ='Stock Valuation (FIFO)'!T5 -> 0 | V4: =IF(U4=0,0,(T4-U4)) -> 0 | W4: 139725 | X4: ='Stock Valuation (FIFO)'!W5 -> 0 | Y4: =IF(X4=0,0,(W4-X4)) -> 0 | Z4: 164310 | AA4: ='Stock Valuation (FIFO)'!Z5 -> 0 | AB4: =IF(AA4=0,0,(Z4-AA4)) -> 0 | AC4: 135475 | AD4: ='Stock Valuation (FIFO)'!AC5 -> 0 | AE4: =IF(AD4=0,0,(AC4-AD4)) -> 0 | AF4: 174670 | AG4: 174670 | AH4: =IF(AG4=0,0,(AF4-AG4)) -> 0 | AI4: 154290 | AJ4: ='Stock Valuation (FIFO)'!AI5 -> 0 | AK4: =IF(AJ4=0,0,(AI4-AJ4)) -> 0 | AL4: 141140 | AM4: ='Stock Valuation (FIFO)'!AL5 -> 0 | AN4: =IF(AM4=0,0,(AL4-AM4)) -> 0
A5: MB | B5: 1664 | C5: ='Stock Valuation (FIFO)'!B6 -> 2330 | D5: =B5-C5 -> -666 | E5: 2120.4 | F5: ='Stock Valuation (FIFO)'!E6 -> 2392 | G5: =IF(F5=0,0,(E5-F5)) -> -271.6 | H5: 2293.7 | I5: ='Stock Valuation (FIFO)'!H6 -> 2239 | J5: =IF(I5=0,0,(H5-I5)) -> 54.7 | K5: 2613.1 | L5: ='Stock Valuation (FIFO)'!K6 -> 0 | M5: =IF(L5=0,0,(K5-L5)) -> 0 | N5: 2768.7 | O5: ='Stock Valuation (FIFO)'!N6 -> 0 | P5: =IF(O5=0,0,(N5-O5)) -> 0 | Q5: 3082.1 | R5: =' Qty Analysis'!N21 -> 0 | S5: =IF(R5=0,0,(Q5-R5)) -> 0 | T5: 2819.3 | U5: ='Stock Valuation (FIFO)'!T6 -> 0 | V5: =IF(U5=0,0,(T5-U5)) -> 0 | W5: 2895.3 | X5: ='Stock Valuation (FIFO)'!W6 -> 0 | Y5: =IF(X5=0,0,(W5-X5)) -> 0 | Z5: 2396.4 | AA5: ='Stock Valuation (FIFO)'!Z6 -> 0 | AB5: =IF(AA5=0,0,(Z5-AA5)) -> 0 | AC5: 2395.2 | AD5: ='Stock Valuation (FIFO)'!AC6 -> 0 | AE5: =IF(AD5=0,0,(AC5-AD5)) -> 0 | AF5: 2511.2 | AG5: 2511 | AH5: =IF(AG5=0,0,(AF5-AG5)) -> 0.2 | AI5: 3260.1 | AJ5: ='Stock Valuation (FIFO)'!AI6 -> 0 | AK5: =IF(AJ5=0,0,(AI5-AJ5)) -> 0 | AL5: 2329.6 | AM5: ='Stock Valuation (FIFO)'!AL6 -> 0 | AN5: =IF(AM5=0,0,(AL5-AM5)) -> 0
A6: CP | B6: 32 | C6: ='Stock Valuation (FIFO)'!B7 -> 19 | D6: =B6-C6 -> 13 | E6: 28.2 | F6: ='Stock Valuation (FIFO)'!E7 -> 21 | G6: =IF(F6=0,0,(E6-F6)) -> 7.2 | H6: 40.1 | I6: ='Stock Valuation (FIFO)'!H7 -> 20 | J6: =IF(I6=0,0,(H6-I6)) -> 20.1 | K6: 40.1 | L6: ='Stock Valuation (FIFO)'!K7 -> 0 | M6: =IF(L6=0,0,(K6-L6)) -> 0 | N6: 38.4 | O6: ='Stock Valuation (FIFO)'!N7 -> 0 | P6: =IF(O6=0,0,(N6-O6)) -> 0 | Q6: 25.6 | R6: =' Qty Analysis'!N33 -> 0 | S6: =IF(R6=0,0,(Q6-R6)) -> 0 | T6: 16.2 | U6: ='Stock Valuation (FIFO)'!T7 -> 0 | V6: =IF(U6=0,0,(T6-U6)) -> 0 | W6: 40.9 | X6: ='Stock Valuation (FIFO)'!W7 -> 0 | Y6: =IF(X6=0,0,(W6-X6)) -> 0 | Z6: 46 | AA6: ='Stock Valuation (FIFO)'!Z7 -> 0 | AB6: =IF(AA6=0,0,(Z6-AA6)) -> 0 | AC6: 40.3 | AD6: ='Stock Valuation (FIFO)'!AC7 -> 0 | AE6: =IF(AD6=0,0,(AC6-AD6)) -> 0 | AF6: 40.1 | AG6: 40 | AH6: =IF(AG6=0,0,(AF6-AG6)) -> 0.1 | AI6: 38.8 | AJ6: ='Stock Valuation (FIFO)'!AI7 -> 0 | AK6: =IF(AJ6=0,0,(AI6-AJ6)) -> 0 | AL6: 19 | AM6: ='Stock Valuation (FIFO)'!AL7 -> 0 | AN6: =IF(AM6=0,0,(AL6-AM6)) -> 0
A7: RM Total | B7: =SUM(B4:B6) -> 197541 | C7: =SUM(C4:C6) -> 143489 | D7: =B7-C7 -> 54052 | E7: =SUM(E4:E6) -> 182463.6 | F7: =SUM(F4:F6) -> 78108 | G7: =IF(F7=0,0,(E7-F7)) -> 104355.6 | H7: =SUM(H4:H6) -> 149743.8 | I7: =SUM(I4:I6) -> 92299 | J7: =IF(I7=0,0,(H7-I7)) -> 57444.8 | K7: =SUM(K4:K6) -> 166778.2 | L7: =SUM(L4:L6) -> 0 | M7: =IF(L7=0,0,(K7-L7)) -> 0 | N7: =SUM(N4:N6) -> 148947.1 | O7: =SUM(O4:O6) -> 0 | P7: =IF(O7=0,0,(N7-O7)) -> 0 | Q7: =SUM(Q4:Q6) -> 190727.7 | R7: =SUM(R4:R6) -> 0 | S7: =IF(R7=0,0,(Q7-R7)) -> 0 | T7: =SUM(T4:T6) -> 117515.5 | U7: =SUM(U4:U6) -> 0 | V7: =IF(U7=0,0,(T7-U7)) -> 0 | W7: =SUM(W4:W6) -> 142661.2 | X7: =SUM(X4:X6) -> 0 | Y7: =IF(X7=0,0,(W7-X7)) -> 0 | Z7: =SUM(Z4:Z6) -> 166752.4 | AA7: =SUM(AA4:AA6) -> 0 | AB7: =IF(AA7=0,0,(Z7-AA7)) -> 0 | AC7: =SUM(AC4:AC6) -> 137910.5 | AD7: =SUM(AD4:AD6) -> 0 | AE7: =IF(AD7=0,0,(AC7-AD7)) -> 0 | AF7: =SUM(AF4:AF6) -> 177221.3 | AG7: =SUM(AG4:AG6) -> 177221 | AH7: =IF(AG7=0,0,(AF7-AG7)) -> 0.3 | AI7: =SUM(AI4:AI6) -> 157588.9 | AJ7: =SUM(AJ4:AJ6) -> 0 | AK7: =IF(AJ7=0,0,(AI7-AJ7)) -> 0 | AL7: =SUM(AL4:AL6) -> 143488.6 | AM7: =SUM(AM4:AM6) -> 0 | AN7: =IF(AM7=0,0,(AL7-AM7)) -> 0
A8: Yarn Factory | B8: 49725 | C8: ='Stock Valuation (FIFO)'!B10 -> 37996 | D8: =B8-C8 -> 11729 | E8: 56270 | F8: ='Stock Valuation (FIFO)'!E10 -> 26660 | G8: =IF(F8=0,0,(E8-F8)) -> 29610 | H8: 46564 | I8: ='Stock Valuation (FIFO)'!H10 -> 17001 | J8: =IF(I8=0,0,(H8-I8)) -> 29563 | K8: 52761.2 | L8: ='Stock Valuation (FIFO)'!K10 -> 0 | M8: =IF(L8=0,0,(K8-L8)) -> 0 | N8: 48737.1 | O8: ='Stock Valuation (FIFO)'!N10 -> 0 | P8: =IF(O8=0,0,(N8-O8)) -> 0 | Q8: 49389.9 | R8: =' Qty Analysis'!N61 -> 77470.8 | S8: =IF(R8=0,0,(Q8-R8)) -> -28080.9 | T8: 56273.8 | U8: ='Stock Valuation (FIFO)'!T10 -> 0 | V8: =IF(U8=0,0,(T8-U8)) -> 0 | W8: 60795.6 | X8: ='Stock Valuation (FIFO)'!W10 -> 0 | Y8: =IF(X8=0,0,(W8-X8)) -> 0 | Z8: 57317.4 | AA8: ='Stock Valuation (FIFO)'!Z10 -> 0 | AB8: =IF(AA8=0,0,(Z8-AA8)) -> 0 | AC8: 54865.8 | AD8: ='Stock Valuation (FIFO)'!AC10 -> 0 | AE8: =IF(AD8=0,0,(AC8-AD8)) -> 0 | AF8: 47773.2 | AG8: 47774 | AH8: =IF(AG8=0,0,(AF8-AG8)) -> -0.8 | AI8: 51821.9 | AJ8: ='Stock Valuation (FIFO)'!AI10 -> 0 | AK8: =IF(AJ8=0,0,(AI8-AJ8)) -> 0 | AL8: 37996 | AM8: 37996 | AN8: =IF(AM8=0,0,(AL8-AM8)) -> -2.910383e-11
A9: Yarn Fabrctr | B9: 76468 | C9: ='Stock Valuation (FIFO)'!B11 -> 64171 | D9: =B9-C9 -> 12297 | E9: 63905.6 | F9: ='Stock Valuation (FIFO)'!E11 -> 50337 | G9: =IF(F9=0,0,(E9-F9)) -> 13568.6 | H9: 61851.2 | I9: ='Stock Valuation (FIFO)'!H11 -> 56663 | J9: =IF(I9=0,0,(H9-I9)) -> 5188.2 | K9: 66528 | L9: ='Stock Valuation (FIFO)'!K11 -> 0 | M9: =IF(L9=0,0,(K9-L9)) -> 0 | N9: 73740.4 | O9: ='Stock Valuation (FIFO)'!N11 -> 0 | P9: =IF(O9=0,0,(N9-O9)) -> 0 | Q9: 77586 | R9: =' Qty Analysis'!N71 -> 77584.9 | S9: =IF(R9=0,0,(Q9-R9)) -> 1.1 | T9: =79105.0999999999-25 -> 79080.1 | U9: ='Stock Valuation (FIFO)'!T11 -> 0 | V9: =IF(U9=0,0,(T9-U9)) -> 0 | W9: 80193.4 | X9: ='Stock Valuation (FIFO)'!W11 -> 0 | Y9: =IF(X9=0,0,(W9-X9)) -> 0 | Z9: 85004.2 | AA9: ='Stock Valuation (FIFO)'!Z11 -> 0 | AB9: =IF(AA9=0,0,(Z9-AA9)) -> 0 | AC9: 91727.2 | AD9: ='Stock Valuation (FIFO)'!AC11 -> 0 | AE9: =IF(AD9=0,0,(AC9-AD9)) -> 0 | AF9: 91742.2 | AG9: 91742 | AH9: =IF(AG9=0,0,(AF9-AG9)) -> 0.2 | AI9: 86543.9 | AJ9: ='Stock Valuation (FIFO)'!AI11 -> 0 | AK9: =IF(AJ9=0,0,(AI9-AJ9)) -> 0 | AL9: 84657.29 | AM9: 64171 | AN9: =IF(AM9=0,0,(AL9-AM9)) -> 20486.29
A10: Yarn Total | B10: =SUM(B8:B9) -> 126193 | C10: =SUM(C8:C9) -> 102167 | D10: =B10-C10 -> 24026 | E10: =SUM(E8:E9) -> 120175.6 | F10: =SUM(F8:F9) -> 76997 | G10: =IF(F10=0,0,(E10-F10)) -> 43178.6 | H10: =SUM(H8:H9) -> 108415.2 | I10: =SUM(I8:I9) -> 73664 | J10: =IF(I10=0,0,(H10-I10)) -> 34751.2 | K10: =SUM(K8:K9) -> 119289.2 | L10: =SUM(L8:L9) -> 0 | M10: =IF(L10=0,0,(K10-L10)) -> 0 | N10: =SUM(N8:N9) -> 122477.5 | O10: =SUM(O8:O9) -> 0 | P10: =IF(O10=0,0,(N10-O10)) -> 0 | Q10: =SUM(Q8:Q9) -> 126975.9 | R10: =SUM(R8:R9) -> 155055.7 | S10: =IF(R10=0,0,(Q10-R10)) -> -28079.8 | T10: =SUM(T8:T9) -> 135353.9 | U10: =SUM(U8:U9) -> 0 | V10: =IF(U10=0,0,(T10-U10)) -> 0 | W10: =SUM(W8:W9) -> 140989 | X10: =SUM(X8:X9) -> 0 | Y10: =IF(X10=0,0,(W10-X10)) -> 0 | Z10: =SUM(Z8:Z9) -> 142321.6 | AA10: =SUM(AA8:AA9) -> 0 | AB10: =IF(AA10=0,0,(Z10-AA10)) -> 0 | AC10: =SUM(AC8:AC9) -> 146593 | AD10: =SUM(AD8:AD9) -> 0 | AE10: =IF(AD10=0,0,(AC10-AD10)) -> 0 | AF10: =SUM(AF8:AF9) -> 139515.4 | AG10: =SUM(AG8:AG9) -> 139516 | AH10: =IF(AG10=0,0,(AF10-AG10)) -> -0.6 | AI10: =SUM(AI8:AI9) -> 138365.8 | AJ10: =SUM(AJ8:AJ9) -> 0 | AK10: =IF(AJ10=0,0,(AI10-AJ10)) -> 0 | AL10: =SUM(AL8:AL9) -> 122653.29 | AM10: =SUM(AM8:AM9) -> 102167 | AN10: =IF(AM10=0,0,(AL10-AM10)) -> 20486.29 | AO10: Water Content Fabricator
A11: Fabric | B11: 206027 | C11: ='Stock Valuation (FIFO)'!B14 -> 200810 | D11: =B11-C11 -> 5217 | E11: 224044.9 | F11: ='Stock Valuation (FIFO)'!E14 -> 216887 | G11: =IF(F11=0,0,(E11-F11)) -> 7157.9 | H11: 201846.3 | I11: ='Stock Valuation (FIFO)'!H14 -> 179666 | J11: =IF(I11=0,0,(H11-I11)) -> 22180.3 | K11: 191275.2 | L11: ='Stock Valuation (FIFO)'!K14 -> 0 | M11: =IF(L11=0,0,(K11-L11)) -> 0 | N11: 197795.1 | O11: ='Stock Valuation (FIFO)'!N14 -> 0 | P11: =IF(O11=0,0,(N11-O11)) -> 0 | Q11: 202309.3 | R11: ='Stock Valuation (FIFO)'!Q14 -> 0 | S11: =IF(R11=0,0,(Q11-R11)) -> 0 | T11: 228721.4 | U11: ='Stock Valuation (FIFO)'!T14 -> 0 | V11: =IF(U11=0,0,(T11-U11)) -> 0 | W11: 237947.3 | X11: ='Stock Valuation (FIFO)'!W14 -> 0 | Y11: =IF(X11=0,0,(W11-X11)) -> 0 | Z11: 218950.4 | AA11: ='Stock Valuation (FIFO)'!Z14 -> 0 | AB11: =IF(AA11=0,0,(Z11-AA11)) -> 0 | AC11: 255945.6 | AD11: ='Stock Valuation (FIFO)'!AC14 -> 0 | AE11: =IF(AD11=0,0,(AC11-AD11)) -> 0 | AF11: 261815 | AG11: 261816 | AH11: =IF(AG11=0,0,(AF11-AG11)) -> -1 | AI11: 239651.2 | AJ11: ='Stock Valuation (FIFO)'!AI14 -> 0 | AK11: =IF(AJ11=0,0,(AI11-AJ11)) -> 0 | AL11: 200810.4 | AM11: ='Stock Valuation (FIFO)'!AL14 -> 0 | AN11: =IF(AM11=0,0,(AL11-AM11)) -> 0
A12: TSN | B12: 244 | C12: ='Trading PL'!B42 -> 172 | D12: =B12-C12 -> 72 | E12: 256.6 | F12: ='Trading PL'!B35 -> 172 | G12: =IF(F12=0,0,(E12-F12)) -> 84.6 | H12: 257 | I12: ='Trading PL'!E35 -> 340 | J12: =IF(I12=0,0,(H12-I12)) -> -83 | K12: 197.1 | L12: ='Trading PL'!H35 -> 0 | M12: =IF(L12=0,0,(K12-L12)) -> 0 | N12: 197.1 | O12: ='Trading PL'!K35 -> 0 | P12: =IF(O12=0,0,(N12-O12)) -> 0 | Q12: 197.1 | R12: ='Trading PL'!N35 -> 0 | S12: =IF(R12=0,0,(Q12-R12)) -> 0 | T12: 183.1 | U12: ='Stock Valuation (FIFO)'!T16 -> 0 | V12: =IF(U12=0,0,(T12-U12)) -> 0 | W12: 183.1 | X12: ='Stock Valuation (FIFO)'!W16 -> 0 | Y12: =IF(X12=0,0,(W12-X12)) -> 0 | Z12: =423.5-36.5 -> 387 | AA12: ='Stock Valuation (FIFO)'!Z15 -> 0 | AB12: =IF(AA12=0,0,(Z12-AA12)) -> 0 | AC12: =423.5-AC16 -> 387 | AD12: ='Stock Valuation (FIFO)'!AC15 -> 0 | AE12: =IF(AD12=0,0,(AC12-AD12)) -> 0 | AF12: =423.5-37 -> 386.5 | AG12: 387 | AH12: =IF(AG12=0,0,(AF12-AG12)) -> -0.5 | AI12: =423.5-AI16 -> 386.5 | AJ12: ='Stock Valuation (FIFO)'!AI15 -> 0 | AK12: =IF(AJ12=0,0,(AI12-AJ12)) -> 0 | AL12: =423.5-AL16 -> 386.5 | AM12: ='Stock Valuation (FIFO)'!AL15 -> 0 | AN12: =IF(AM12=0,0,(AL12-AM12)) -> 0
A13: MSN | B13: 387 | C13: ='Trading PL'!B41 -> 387 | D13: =B13-C13 -> 0 | E13: 387 | F13: ='Trading PL'!B34 -> 387 | G13: =IF(F13=0,0,(E13-F13)) -> 0 | H13: 387 | I13: ='Trading PL'!E34 -> 387 | J13: =IF(I13=0,0,(H13-I13)) -> 0 | K13: 387 | L13: ='Trading PL'!H34 -> 0 | M13: =IF(L13=0,0,(K13-L13)) -> 0 | N13: 387 | O13: ='Trading PL'!K34 -> 0 | P13: =IF(O13=0,0,(N13-O13)) -> 0 | Q13: 404 | R13: ='Trading PL'!N34 -> 0 | S13: =IF(R13=0,0,(Q13-R13)) -> 0 | T13: 410 | U13: ='Stock Valuation (FIFO)'!T15 -> 0 | V13: =IF(U13=0,0,(T13-U13)) -> 0 | W13: 410 | X13: ='Stock Valuation (FIFO)'!W15 -> 0 | Y13: =IF(X13=0,0,(W13-X13)) -> 0 | Z13: 183.1 | AA13: ='Stock Valuation (FIFO)'!Z16 -> 0 | AB13: =IF(AA13=0,0,(Z13-AA13)) -> 0 | AC13: 179.1 | AD13: ='Stock Valuation (FIFO)'!AC16 -> 0 | AE13: =IF(AD13=0,0,(AC13-AD13)) -> 0 | AF13: 179.1 | AG13: 179 | AH13: =IF(AG13=0,0,(AF13-AG13)) -> 0.1 | AI13: 177.9 | AJ13: ='Stock Valuation (FIFO)'!AI16 -> 0 | AK13: =IF(AJ13=0,0,(AI13-AJ13)) -> 0 | AL13: 171.9 | AM13: ='Stock Valuation (FIFO)'!AL16 -> 0 | AN13: =IF(AM13=0,0,(AL13-AM13)) -> 0
A14: PP Sacks | C14: ='Trading PL'!B44 -> 0 | D14: =B14-C14 -> 0 | E14: 0 | F14: ='Trading PL'!B38 -> 36 | G14: =IF(F14=0,0,(E14-F14)) -> -36 | H14: 0 | I14: ='Trading PL'!E38 -> 36 | J14: =IF(I14=0,0,(H14-I14)) -> -36 | K14: 0 | L14: ='Trading PL'!H38 -> 0 | M14: =IF(L14=0,0,(K14-L14)) -> 0 | N14: 0 | O14: ='Trading PL'!K38 -> 0 | P14: =IF(O14=0,0,(N14-O14)) -> 0 | S14: =IF(R14=0,0,(Q14-R14)) -> 0 | T14: 0 | V14: =IF(U14=0,0,(T14-U14)) -> 0 | W14: 0 | Y14: =IF(X14=0,0,(W14-X14)) -> 0 | Z14: 804.1 | AA14: ='Stock Valuation (FIFO)'!Z17 -> 0 | AB14: =IF(AA14=0,0,(Z14-AA14)) -> 0 | AC14: 391.2 | AD14: ='Stock Valuation (FIFO)'!AC17 -> 0 | AE14: =IF(AD14=0,0,(AC14-AD14)) -> 0 | AF14: 196.2 | AG14: 196 | AH14: =IF(AG14=0,0,(AF14-AG14)) -> 0.2 | AK14: =IF(AJ14=0,0,(AI14-AJ14)) -> 0 | AL14: 0 | AN14: =IF(AM14=0,0,(AL14-AM14)) -> 0
A15: Weed Mat | B15: 75 | C15: ='Trading PL'!B43 -> 446 | D15: =B15-C15 -> -371 | E15: 46.8 | F15: ='Trading PL'!B37 -> 0 | G15: =IF(F15=0,0,(E15-F15)) -> 0 | H15: 36.1 | I15: ='Trading PL'!E37 -> 0 | J15: =IF(I15=0,0,(H15-I15)) -> 0 | K15: 26.1 | L15: ='Trading PL'!H37 -> 0 | M15: =IF(L15=0,0,(K15-L15)) -> 0 | N15: 129.1 | O15: ='Trading PL'!K37 -> 0 | P15: =IF(O15=0,0,(N15-O15)) -> 0 | Q15: 153.1 | R15: ='Trading PL'!N36 -> 0 | S15: =IF(R15=0,0,(R15-Q15)) -> 0 | T15: 450.1 | U15: ='Stock Valuation (FIFO)'!T17 -> 0 | V15: =IF(U15=0,0,(T15-U15)) -> 0 | W15: 172.1 | X15: ='Stock Valuation (FIFO)'!W17 -> 0 | Y15: =IF(X15=0,0,(W15-X15)) -> 0 | AB15: =IF(AA15=0,0,(Z15-AA15)) -> 0 | AD15: ='Stock Valuation (FIFO)'!AC18 -> 0 | AE15: =IF(AD15=0,0,(AC15-AD15)) -> 0 | AH15: =IF(AG15=0,0,(AF15-AG15)) -> 0 | AI15: 446.2 | AJ15: ='Stock Valuation (FIFO)'!AI17 -> 0 | AK15: =IF(AJ15=0,0,(AI15-AJ15)) -> 0 | AL15: 446.2 | AM15: ='Stock Valuation (FIFO)'!AL17 -> 0 | AN15: =IF(AM15=0,0,(AL15-AM15)) -> 0
A16: PP Fabric | D16: =B16-C16 -> 0 | G16: =IF(F16=0,0,(E16-F16)) -> 0 | J16: =IF(I16=0,0,(H16-I16)) -> 0 | M16: =IF(L16=0,0,(K16-L16)) -> 0 | P16: =IF(O16=0,0,(N16-O16)) -> 0 | R16: ='Trading PL'!N38 -> 0 | S16: =IF(R16=0,0,(R16-Q16)) -> 0 | U16: ='Stock Valuation (FIFO)'!T19 -> 0 | X16: ='Stock Valuation (FIFO)'!W19 -> 0 | Y16: =IF(X16=0,0,(W16-X16)) -> 0 | Z16: 36.5 | AA16: ='Stock Valuation (FIFO)'!Z19 -> 0 | AB16: =IF(AA16=0,0,(Z16-AA16)) -> 0 | AC16: 36.5 | AD16: ='Stock Valuation (FIFO)'!AC19 -> 0 | AE16: =IF(AD16=0,0,(AC16-AD16)) -> 0 | AF16: 37 | AG16: 37 | AH16: =IF(AG16=0,0,(AF16-AG16)) -> 0 | AI16: 37 | AJ16: ='Stock Valuation (FIFO)'!AI19 -> 0 | AK16: =IF(AJ16=0,0,(AI16-AJ16)) -> 0 | AL16: 37 | AM16: ='Stock Valuation (FIFO)'!AL19 -> 0 | AN16: =IF(AM16=0,0,(AL16-AM16)) -> 0
A17: Fabric Total | B17: =SUM(B11:B16) -> 206733 | C17: =SUM(C11:C16) -> 201815 | D17: =B17-C17 -> 4918 | E17: =SUM(E11:E16) -> 224735.3 | F17: =SUM(F11:F16) -> 217482 | G17: =IF(F17=0,0,(E17-F17)) -> 7253.3 | H17: =SUM(H11:H16) -> 202526.4 | I17: =SUM(I11:I16) -> 180429 | J17: =IF(I17=0,0,(H17-I17)) -> 22097.4 | K17: =SUM(K11:K16) -> 191885.4 | L17: =SUM(L11:L16) -> 0 | M17: =IF(L17=0,0,(K17-L17)) -> 0 | N17: =SUM(N11:N16) -> 198508.3 | O17: =SUM(O11:O16) -> 0 | P17: =IF(O17=0,0,(N17-O17)) -> 0 | Q17: =SUM(Q11:Q16) -> 203063.5 | R17: =SUM(R11:R15) -> 0 | S17: =IF(R17=0,0,(Q17-R17)) -> 0 | T17: =SUM(T11:T16) -> 229764.6 | U17: =SUM(U11:U16) -> 0 | V17: =IF(U17=0,0,(T17-U17)) -> 0 | W17: =SUM(W11:W16) -> 238712.5 | X17: =SUM(X11:X16) -> 0 | Y17: =IF(X17=0,0,(W17-X17)) -> 0 | Z17: =SUM(Z11:Z16) -> 220361.1 | AA17: =SUM(AA11:AA16) -> 0 | AB17: =IF(AA17=0,0,(Z17-AA17)) -> 0 | AC17: =SUM(AC11:AC16) -> 256939.4 | AD17: =SUM(AD11:AD16) -> 0 | AE17: =IF(AD17=0,0,(AC17-AD17)) -> 0 | AF17: =SUM(AF11:AF16) -> 262613.8 | AG17: =SUM(AG11:AG16) -> 262615 | AH17: =IF(AG17=0,0,(AF17-AG17)) -> -1.2 | AI17: =SUM(AI11:AI16) -> 240698.8 | AJ17: =SUM(AJ11:AJ16) -> 0 | AK17: =IF(AJ17=0,0,(AI17-AJ17)) -> 0 | AL17: =SUM(AL11:AL16) -> 201852 | AM17: =SUM(AM11:AM16) -> 0 | AN17: =IF(AM17=0,0,(AL17-AM17)) -> 0
A18: TOTAL | B18: =B7+B10+B17 -> 530467 | C18: =C7+C10+C17 -> 447471 | D18: =B18-C18 -> 82996 | E18: =E7+E10+E17 -> 527374.5 | F18: =F7+F10+F17 -> 372587 | G18: =IF(F18=0,0,(E18-F18)) -> 154787.5 | H18: =H7+H10+H17 -> 460685.4 | I18: =I7+I10+I17 -> 346392 | J18: =IF(I18=0,0,(H18-I18)) -> 114293.4 | K18: =K7+K10+K17 -> 477952.8 | L18: =L7+L10+L17 -> 0 | M18: =IF(L18=0,0,(K18-L18)) -> 0 | N18: =N7+N10+N17 -> 469932.9 | O18: =O7+O10+O17 -> 0 | P18: =IF(O18=0,0,(N18-O18)) -> 0 | Q18: =Q7+Q10+Q17 -> 520767.1 | R18: =R7+R10+R17 -> 155055.7 | S18: =IF(R18=0,0,(Q18-R18)) -> 365711.4 | T18: =T7+T10+T17 -> 482634 | U18: =U7+U10+U17 -> 0 | V18: =IF(U18=0,0,(T18-U18)) -> 0 | W18: =W7+W10+W17 -> 522362.7 | X18: =X7+X10+X17 -> 0 | Y18: =IF(X18=0,0,(W18-X18)) -> 0 | Z18: =Z7+Z10+Z17 -> 529435.1 | AA18: =AA7+AA10+AA17 -> 0 | AB18: =IF(AA18=0,0,(Z18-AA18)) -> 0 | AC18: =AC7+AC10+AC17 -> 541442.9 | AD18: =AD7+AD10+AD17 -> 0 | AE18: =IF(AD18=0,0,(AC18-AD18)) -> 0 | AF18: =AF7+AF10+AF17 -> 579350.5 | AG18: =AG7+AG10+AG17 -> 579352 | AH18: =IF(AG18=0,0,(AF18-AG18)) -> -1.5 | AI18: =AI7+AI10+AI17 -> 536653.5 | AJ18: =AJ7+AJ10+AJ17 -> 0 | AK18: =IF(AJ18=0,0,(AI18-AJ18)) -> 0 | AL18: =AL7+AL10+AL17 -> 467993.89 | AM18: =AM7+AM10+AM17 -> 102167 | AN18: =IF(AM18=0,0,(AL18-AM18)) -> 365826.89
A20: SFG/FG | B20: =B18-B7 -> 332926 | C20: =C18-C7 -> 303982 | D20: =B20-C20 -> 28944 | E20: =E18-E7 -> 344910.9 | F20: =F18-F7 -> 294479 | G20: =IF(F20=0,0,(E20-F20)) -> 50431.9 | H20: =H18-H7 -> 310941.6 | I20: =I18-I7 -> 254093 | J20: =IF(I20=0,0,(H20-I20)) -> 56848.6 | K20: =K18-K7 -> 311174.6 | L20: =L18-L7 -> 0 | M20: =IF(L20=0,0,(K20-L20)) -> 0 | N20: =N18-N7 -> 320985.8 | O20: =O18-O7 -> 0 | P20: =IF(O20=0,0,(N20-O20)) -> 0 | Q20: =Q18-Q7 -> 330039.4 | R20: =R18-R7 -> 155055.7 | S20: =IF(R20=0,0,(Q20-R20)) -> 174983.7 | T20: =T18-T7 -> 365118.5 | U20: =U18-U7 -> 0 | V20: =IF(U20=0,0,(T20-U20)) -> 0 | W20: =W18-W7 -> 379701.5 | X20: =X18-X7 -> 0 | Y20: =IF(X20=0,0,(W20-X20)) -> 0 | Z20: =Z18-Z7 -> 362682.7 | AA20: =AA18-AA7 -> 0 | AB20: =IF(AA20=0,0,(Z20-AA20)) -> 0 | AC20: =AC18-AC7 -> 403532.4 | AD20: =AD18-AD7 -> 0 | AE20: =IF(AD20=0,0,(AC20-AD20)) -> 0 | AF20: =AF18-AF7 -> 402129.2 | AG20: =AG18-AG7 -> 402131 | AH20: =IF(AG20=0,0,(AF20-AG20)) -> -1.8 | AI20: =AI18-AI7 -> 379064.6 | AJ20: =AJ18-AJ7 -> 0 | AK20: =IF(AJ20=0,0,(AI20-AJ20)) -> 0 | AL20: =AL18-AL7 -> 324505.29 | AM20: =AM18-AM7 -> 102167 | AN20: =IF(AM20=0,0,(AL20-AM20)) -> 222338.29
E21: =E20-B20 -> 11984.9 | H21: =H20-E20 -> -33969.3 | K21: =K20-H20 -> 233 | N21: =N20-K20 -> 9811.2 | Q21: =Q20-N20 -> 9053.6 | T21: =T20-Q20 -> 35079.1 | W21: =W20-T20 -> 14583
E22: =E20-$B$20 -> 11984.9 | H22: =H20-$B$20 -> -21984.4 | K22: =K20-$B$20 -> -21751.4 | N22: =N20-$B$20 -> -11940.2 | Q22: =Q20-$B$20 -> -2886.6 | T22: =T20-$B$20 -> 32192.5 | W22: =W20-$B$20 -> 46775.5
A23: Tarka->
A24: HDPE | H24: =63410+93000 -> 156410 | I24: =H4-H24 -> -9000
A25: MB | H25: 2240 | I25: =H5-H25 -> 53.7
A26: CP | H26: 80 | I26: =H6-H26 -> -39.9
A27: RM Total | H27: =SUM(H24:H26) -> 158730 | I27: =SUM(I24:I26) -> -8986.2
A28: Yarn Factory | H28: 30450 | I28: =H8-H28 -> 16114
A29: Yarn Fabrctr | H29: 64627 | I29: =H9-H29 -> -2775.8
A30: Yarn Total | H30: =SUM(H28:H29) -> 95077 | I30: =SUM(I28:I29) -> 13338.2
A31: Fabric | H31: 332260 | I31: =H11-H31 -> -130413.7
A32: TSN | H32: 108 | I32: =H12-H32 -> 149
A33: MSN | H33: 1015 | I33: =H13-H33 -> -628
A34: Weed Mat
A35: PP Fab
A36: PP Sacks | Q36: 942.6
A37: Fabric Total | H37: =SUM(H31:H36) -> 333383 | I37: =SUM(I31:I36) -> -130892.7
A38: TOTAL | H38: =H27+H30+H37 -> 587190 | I38: =I27+I30+I37 -> -126540.7
A40: SFG/FG | H40: =H38-H27 -> 428460 | I40: =I38-I27 -> -117554.5

Sheet Inventory Sales
A2: Particulars | B2: Apr | E2: May | H2: Jun | K2: Jul | N2: Aug | Q2: Sep | T2: Oct | W2: Nov | Z2: Dec | AC2: Jan | AF2: Feb | AI2: Mar | AL2: Total
A3: Finished Goods | B3: Outwards Qty | C3: Rate | D3: Amount | E3: Outwards Qty | F3: Rate | G3: Amount | H3: Outwards Qty | I3: Rate | J3: Amount | K3: Outwards Qty | L3: Rate | M3: Amount | N3: Outwards Qty | O3: Rate | P3: Amount | Q3: Outwards Qty | R3: Rate | S3: Amount | T3: Outwards Qty | U3: Rate | V3: Amount | W3: Outwards Qty | X3: Rate | Y3: Amount | Z3: Outwards Qty | AA3: Rate | AB3: Amount | AC3: Outwards Qty | AD3: Rate | AE3: Amount | AF3: Outwards Qty | AG3: Rate | AH3: Amount | AI3: Outwards Qty | AJ3: Rate | AK3: Amount | AL3: Outwards Qty | AM3: Rate | AN3: Amount
A5: MCF | B5: 29736 | C5: =IF(B5=0,0,D5/B5) -> 306.90207 | D5: 9126040 | E5: 42618.06 | F5: =IF(E5=0,0,G5/E5) -> 307.64997 | G5: 13111445 | I5: =IF(H5=0,0,J5/H5) -> 0 | L5: =IF(K5=0,0,M5/K5) -> 0 | O5: =IF(N5=0,0,P5/N5) -> 0 | R5: =IF(Q5=0,0,S5/Q5) -> 0 | U5: =IF(T5=0,0,V5/T5) -> 0 | X5: =IF(W5=0,0,Y5/W5) -> 0 | AA5: =IF(Z5=0,0,AB5/Z5) -> 0 | AD5: =IF(AC5=0,0,AE5/AC5) -> 0 | AG5: =IF(AF5=0,0,AH5/AF5) -> 0 | AJ5: =IF(AI5=0,0,AK5/AI5) -> 0 | AL5: =SUM(B5,E5,H5,K5,N5,Q5,T5,W5,Z5,AC5,AF5,AI5) -> 72354.06 | AM5: =IF(AL5=0,0,AN5/AL5) -> 307.3426 | AN5: =SUM(D5,G5,J5,M5,P5,S5,V5,Y5,AB5,AE5,AH5,AK5) -> 22237485
A6: WMF | B6: 60203 | C6: =IF(B6=0,0,D6/B6) -> 284.90781 | D6: 17152305 | E6: 65542.47 | F6: =IF(E6=0,0,G6/E6) -> 276.00743 | G6: 18090208 | I6: =IF(H6=0,0,J6/H6) -> 0 | L6: =IF(K6=0,0,M6/K6) -> 0 | O6: =IF(N6=0,0,P6/N6) -> 0 | R6: =IF(Q6=0,0,S6/Q6) -> 0 | U6: =IF(T6=0,0,V6/T6) -> 0 | X6: =IF(W6=0,0,Y6/W6) -> 0 | AA6: =IF(Z6=0,0,AB6/Z6) -> 0 | AD6: =IF(AC6=0,0,AE6/AC6) -> 0 | AG6: =IF(AF6=0,0,AH6/AF6) -> 0 | AJ6: =IF(AI6=0,0,AK6/AI6) -> 0 | AL6: =SUM(B6,E6,H6,K6,N6,Q6,T6,W6,Z6,AC6,AF6,AI6) -> 125745.47 | AM6: =IF(AL6=0,0,AN6/AL6) -> 280.26865 | AN6: =SUM(D6,G6,J6,M6,P6,S6,V6,Y6,AB6,AE6,AH6,AK6) -> 35242513
A7: MONOFILAMENT FABRIC INSECT BAGS | C7: =IF(B7=0,0,D7/B7) -> 0 | I7: =IF(H7=0,0,J7/H7) -> 0 | L7: =IF(K7=0,0,M7/K7) -> 0 | R7: =IF(Q7=0,0,S7/Q7) -> 0 | X7: =IF(W7=0,0,Y7/W7) -> 0 | AA7: =IF(Z7=0,0,AB7/Z7) -> 0 | AD7: =IF(AC7=0,0,AE7/AC7) -> 0 | AG7: =IF(AF7=0,0,AH7/AF7) -> 0 | AJ7: =IF(AI7=0,0,AK7/AI7) -> 0 | AL7: =SUM(B7,E7,H7,K7,N7,Q7,T7,W7,Z7,AC7,AF7,AI7) -> 0 | AM7: =IF(AL7=0,0,AN7/AL7) -> 0 | AN7: =SUM(D7,G7,J7,M7,P7,S7,V7,Y7,AB7,AE7,AH7,AK7) -> 0
A8: MONOFILAMENT FABRIC INSECT NET | C8: =IF(B8=0,0,D8/B8) -> 0 | I8: =IF(H8=0,0,J8/H8) -> 0 | L8: =IF(K8=0,0,M8/K8) -> 0 | R8: =IF(Q8=0,0,S8/Q8) -> 0 | U8: =IF(T8=0,0,V8/T8) -> 0 | X8: =IF(W8=0,0,Y8/W8) -> 0 | AA8: =IF(Z8=0,0,AB8/Z8) -> 0 | AD8: =IF(AC8=0,0,AE8/AC8) -> 0 | AG8: =IF(AF8=0,0,AH8/AF8) -> 0 | AJ8: =IF(AI8=0,0,AK8/AI8) -> 0 | AL8: =SUM(B8,E8,H8,K8,N8,Q8,T8,W8,Z8,AC8,AF8,AI8) -> 0 | AM8: =IF(AL8=0,0,AN8/AL8) -> 0 | AN8: =SUM(D8,G8,J8,M8,P8,S8,V8,Y8,AB8,AE8,AH8,AK8) -> 0
A9: MONOFILAMENT FABRIC HAPPA | B9: 5 | C9: =IF(B9=0,0,D9/B9) -> 900 | D9: 4500 | F9: =IF(E9=0,0,G9/E9) -> 0 | I9: =IF(H9=0,0,J9/H9) -> 0 | L9: =IF(K9=0,0,M9/K9) -> 0 | O9: =IF(N9=0,0,P9/N9) -> 0 | R9: =IF(Q9=0,0,S9/Q9) -> 0 | U9: =IF(T9=0,0,V9/T9) -> 0 | X9: =IF(W9=0,0,Y9/W9) -> 0 | AA9: =IF(Z9=0,0,AB9/Z9) -> 0 | AD9: =IF(AC9=0,0,AE9/AC9) -> 0 | AG9: =IF(AF9=0,0,AH9/AF9) -> 0 | AJ9: =IF(AI9=0,0,AK9/AI9) -> 0 | AL9: =SUM(B9,E9,H9,K9,N9,Q9,T9,W9,Z9,AC9,AF9,AI9) -> 5 | AM9: =IF(AL9=0,0,AN9/AL9) -> 900 | AN9: =SUM(D9,G9,J9,M9,P9,S9,V9,Y9,AB9,AE9,AH9,AK9) -> 4500
A10: NWF/Yarn / Twisted Yarn | B10: 6050 | C10: =IF(B10=0,0,D10/B10) -> 179.00826 | D10: 1083000 | E10: 4500 | F10: =IF(E10=0,0,G10/E10) -> 176.11111 | G10: 792500 | I10: =IF(H10=0,0,J10/H10) -> 0 | L10: =IF(K10=0,0,M10/K10) -> 0 | O10: =IF(N10=0,0,P10/N10) -> 0 | R10: =IF(Q10=0,0,S10/Q10) -> 0 | U10: =IF(T10=0,0,V10/T10) -> 0 | X10: =IF(W10=0,0,Y10/W10) -> 0 | AA10: =IF(Z10=0,0,AB10/Z10) -> 0 | AD10: =IF(AC10=0,0,AE10/AC10) -> 0 | AG10: =IF(AF10=0,0,AH10/AF10) -> 0 | AJ10: =IF(AI10=0,0,AK10/AI10) -> 0 | AL10: =SUM(B10,E10,H10,K10,N10,Q10,T10,W10,Z10,AC10,AF10,AI10) -> 10550 | AM10: =IF(AL10=0,0,AN10/AL10) -> 177.77251 | AN10: =SUM(D10,G10,J10,M10,P10,S10,V10,Y10,AB10,AE10,AH10,AK10) -> 1875500
B11: =SUM(B5:B10) -> 95994 | C11: =IF(B11=0,0,D11/B11) -> 285.0787 | D11: =SUM(D5:D10) -> 27365845 | E11: =SUM(E5:E10) -> 112660.53 | F11: =IF(E11=0,0,G11/E11) -> 283.98724 | G11: =SUM(G5:G10) -> 31994153 | H11: =SUM(H5:H10) -> 0 | I11: =IF(H11=0,0,J11/H11) -> 0 | J11: =SUM(J5:J10) -> 0 | K11: =SUM(K5:K10) -> 0 | L11: =IF(K11=0,0,M11/K11) -> 0 | M11: =SUM(M5:M10) -> 0 | N11: =SUM(N5:N10) -> 0 | O11: =IF(N11=0,0,P11/N11) -> 0 | P11: =SUM(P5:P10) -> 0 | Q11: =SUM(Q5:Q10) -> 0 | R11: =IF(Q11=0,0,S11/Q11) -> 0 | S11: =SUM(S5:S10) -> 0 | T11: =SUM(T5:T10) -> 0 | U11: =IF(T11=0,0,V11/T11) -> 0 | V11: =SUM(V5:V10) -> 0 | W11: =SUM(W5:W10) -> 0 | X11: =IF(W11=0,0,Y11/W11) -> 0 | Y11: =SUM(Y5:Y10) -> 0 | Z11: =SUM(Z5:Z10) -> 0 | AA11: =IF(Z11=0,0,AB11/Z11) -> 0 | AB11: =SUM(AB5:AB10) -> 0 | AC11: =SUM(AC5:AC10) -> 0 | AD11: =IF(AC11=0,0,AE11/AC11) -> 0 | AE11: =SUM(AE5:AE10) -> 0 | AF11: =SUM(AF5:AF10) -> 0 | AG11: =IF(AF11=0,0,AH11/AF11) -> 0 | AH11: =SUM(AH5:AH10) -> 0 | AI11: =SUM(AI5:AI10) -> 0 | AJ11: =IF(AI11=0,0,AK11/AI11) -> 0 | AK11: =SUM(AK5:AK10) -> 0 | AL11: =SUM(AL5:AL10) -> 208654.53 | AM11: =IF(AL11=0,0,AN11/AL11) -> 284.48938 | AN11: =SUM(AN5:AN10) -> 59359998
A12: MSN | B12: 1148 | C12: =IF(B12=0,0,D12/B12) -> 288.7108 | D12: 331440 | E12: 1087 | F12: =IF(E12=0,0,G12/E12) -> 306.53032 | G12: 333198.46 | I12: =IF(H12=0,0,J12/H12) -> 0 | O12: =IF(N12=0,0,P12/N12) -> 0 | R12: =IF(Q12=0,0,S12/Q12) -> 0 | U12: =IF(T12=0,0,V12/T12) -> 0 | X12: =IF(W12=0,0,Y12/W12) -> 0 | AA12: =IF(Z12=0,0,AB12/Z12) -> 0 | AD12: =IF(AC12=0,0,AE12/AC12) -> 0 | AG12: =IF(AF12=0,0,AH12/AF12) -> 0 | AJ12: =IF(AI12=0,0,AK12/AI12) -> 0 | AL12: =SUM(B12,E12,H12,K12,N12,Q12,T12,W12,Z12,AC12,AF12,AI12) -> 2235 | AM12: =IF(AL12=0,0,AN12/AL12) -> 297.37739 | AN12: =SUM(D12,G12,J12,M12,P12,S12,V12,Y12,AB12,AE12,AH12,AK12) -> 664638.46
A13: TSN | B13: 544 | C13: =IF(B13=0,0,D13/B13) -> 322.89154 | D13: 175653 | E13: 24 | F13: =IF(E13=0,0,G13/E13) -> 312.5 | G13: 7500 | I13: =IF(H13=0,0,J13/H13) -> 0 | L13: =IF(K13=0,0,M13/K13) -> 0 | R13: =IF(Q13=0,0,S13/Q13) -> 0 | U13: =IF(T13=0,0,V13/T13) -> 0 | X13: =IF(W13=0,0,Y13/W13) -> 0 | AA13: =IF(Z13=0,0,AB13/Z13) -> 0 | AD13: =IF(AC13=0,0,AE13/AC13) -> 0 | AG13: =IF(AF13=0,0,AH13/AF13) -> 0 | AJ13: =IF(AI13=0,0,AK13/AI13) -> 0 | AL13: =SUM(B13,E13,H13,K13,N13,Q13,T13,W13,Z13,AC13,AF13,AI13) -> 568 | AM13: =IF(AL13=0,0,AN13/AL13) -> 322.45246 | AN13: =SUM(D13,G13,J13,M13,P13,S13,V13,Y13,AB13,AE13,AH13,AK13) -> 183153
A14: PP Woven Sacks | B14: 6124 | C14: =IF(B14=0,0,D14/B14) -> 247.34634 | D14: 1514749 | E14: 3727.5 | F14: =IF(E14=0,0,G14/E14) -> 242.55158 | G14: 904111 | I14: =IF(H14=0,0,J14/H14) -> 0 | L14: =IF(K14=0,0,M14/K14) -> 0 | O14: =IF(N14=0,0,P14/N14) -> 0 | R14: =IF(Q14=0,0,S14/Q14) -> 0 | U14: =IF(T14=0,0,V14/T14) -> 0 | X14: =IF(W14=0,0,Y14/W14) -> 0 | AA14: =IF(Z14=0,0,AB14/Z14) -> 0 | AD14: =IF(AC14=0,0,AE14/AC14) -> 0 | AG14: =IF(AF14=0,0,AH14/AF14) -> 0 | AJ14: =IF(AI14=0,0,AK14/AI14) -> 0 | AL14: =SUM(B14,E14,H14,K14,N14,Q14,T14,W14,Z14,AC14,AF14,AI14) -> 9851.5 | AM14: =IF(AL14=0,0,AN14/AL14) -> 245.53215 | AN14: =SUM(D14,G14,J14,M14,P14,S14,V14,Y14,AB14,AE14,AH14,AK14) -> 2418860
A15: ANTI BIRD NET / Rope/MULCH/FIBC | B15: 455 | C15: =IF(B15=0,0,D15/B15) -> 197.64835 | D15: 89930 | O15: =IF(N15=0,0,P15/N15) -> 0 | R15: =IF(Q15=0,0,S15/Q15) -> 0 | X15: =IF(W15=0,0,Y15/W15) -> 0 | AA15: =IF(Z15=0,0,AB15/Z15) -> 0 | AD15: =IF(AC15=0,0,AE15/AC15) -> 0 | AJ15: =IF(AI15=0,0,AK15/AI15) -> 0 | AL15: =SUM(B15,E15,H15,K15,N15,Q15,T15,W15,Z15,AC15,AF15,AI15) -> 455 | AM15: =IF(AL15=0,0,AN15/AL15) -> 197.64835 | AN15: =SUM(D15,G15,J15,M15,P15,S15,V15,Y15,AB15,AE15,AH15,AK15) -> 89930
A16: Knitted Fabric 8" Red/60" D Green | B16: 168 | C16: =IF(B16=0,0,D16/B16) -> 608.92857 | D16: 102300 | I16: =IF(H16=0,0,J16/H16) -> 0 | O16: =IF(N16=0,0,P16/N16) -> 0 | R16: =IF(Q16=0,0,S16/Q16) -> 0 | U16: =IF(T16=0,0,V16/T16) -> 0 | X16: =IF(W16=0,0,Y16/W16) -> 0 | AA16: =IF(Z16=0,0,AB16/Z16) -> 0 | AD16: =IF(AC16=0,0,AE16/AC16) -> 0 | AG16: =IF(AF16=0,0,AH16/AF16) -> 0 | AJ16: =IF(AI16=0,0,AK16/AI16) -> 0 | AL16: =SUM(B16,E16,H16,K16,N16,Q16,T16,W16,Z16,AC16,AF16,AI16) -> 168 | AM16: =IF(AL16=0,0,AN16/AL16) -> 608.92857 | AN16: =SUM(D16,G16,J16,M16,P16,S16,V16,Y16,AB16,AE16,AH16,AK16) -> 102300
A17: Weed Mat | B17: 1150 | C17: =IF(B17=0,0,D17/B17) -> 250.86957 | D17: 288500 | E17: 1690.1 | F17: =IF(E17=0,0,G17/E17) -> 239.9858 | G17: 405600 | I17: =IF(H17=0,0,J17/H17) -> 0 | L17: =IF(K17=0,0,M17/K17) -> 0 | O17: =IF(N17=0,0,P17/N17) -> 0 | R17: =IF(Q17=0,0,S17/Q17) -> 0 | U17: =IF(T17=0,0,V17/T17) -> 0 | X17: =IF(W17=0,0,Y17/W17) -> 0 | AA17: =IF(Z17=0,0,AB17/Z17) -> 0 | AD17: =IF(AC17=0,0,AE17/AC17) -> 0 | AG17: =IF(AF17=0,0,AH17/AF17) -> 0 | AJ17: =IF(AI17=0,0,AK17/AI17) -> 0 | AL17: =SUM(B17,E17,H17,K17,N17,Q17,T17,W17,Z17,AC17,AF17,AI17) -> 2840.1 | AM17: =IF(AL17=0,0,AN17/AL17) -> 244.3928 | AN17: =SUM(D17,G17,J17,M17,P17,S17,V17,Y17,AB17,AE17,AH17,AK17) -> 694100
B18: =SUM(B12:B17) -> 9589 | C18: =IF(B18=0,0,D18/B18) -> 260.98363 | D18: =SUM(D12:D17) -> 2502572 | E18: =SUM(E12:E17) -> 6528.6 | F18: =IF(E18=0,0,G18/E18) -> 252.79684 | G18: =SUM(G12:G17) -> 1650409.5 | H18: =SUM(H12:H17) -> 0 | I18: =IF(H18=0,0,J18/H18) -> 0 | J18: =SUM(J12:J17) -> 0 | K18: =SUM(K12:K17) -> 0 | L18: =IF(K18=0,0,M18/K18) -> 0 | M18: =SUM(M12:M17) -> 0 | N18: =SUM(N12:N17) -> 0 | O18: =IF(N18=0,0,P18/N18) -> 0 | P18: =SUM(P12:P17) -> 0 | Q18: =SUM(Q12:Q17) -> 0 | R18: =IF(Q18=0,0,S18/Q18) -> 0 | S18: =SUM(S12:S17) -> 0 | T18: =SUM(T12:T17) -> 0 | U18: =IF(T18=0,0,V18/T18) -> 0 | V18: =SUM(V12:V17) -> 0 | W18: =SUM(W12:W17) -> 0 | X18: =IF(W18=0,0,Y18/W18) -> 0 | Y18: =SUM(Y12:Y17) -> 0 | Z18: =SUM(Z12:Z17) -> 0 | AA18: =IF(Z18=0,0,AB18/Z18) -> 0 | AB18: =SUM(AB12:AB17) -> 0 | AC18: =SUM(AC12:AC17) -> 0 | AD18: =IF(AC18=0,0,AE18/AC18) -> 0 | AE18: =SUM(AE12:AE17) -> 0 | AF18: =SUM(AF12:AF17) -> 0 | AG18: =IF(AF18=0,0,AH18/AF18) -> 0 | AH18: =SUM(AH12:AH17) -> 0 | AI18: =SUM(AI12:AI17) -> 0 | AJ18: =IF(AI18=0,0,AK18/AI18) -> 0 | AK18: =SUM(AK12:AK17) -> 0 | AL18: =SUM(AL12:AL17) -> 16117.6 | AM18: =IF(AL18=0,0,AN18/AL18) -> 257.66749 | AN18: =SUM(AN12:AN17) -> 4152981.5 | AO18: =AL11+AL18 -> 224772.13
A19: Flexible Intermediate Bulk Container | F19: =IF(E19=0,0,G19/E19) -> 0 | R19: =IF(Q19=0,0,S19/Q19) -> 0 | X19: =IF(W19=0,0,Y19/W19) -> 0 | AA19: =IF(Z19=0,0,AB19/Z19) -> 0 | AD19: =IF(AC19=0,0,AE19/AC19) -> 0 | AG19: =IF(AF19=0,0,AH19/AF19) -> 0 | AJ19: =IF(AI19=0,0,AK19/AI19) -> 0 | AL19: =SUM(B19,E19,H19,K19,N19,Q19,T19,W19,Z19,AC19,AF19,AI19) -> 0 | AM19: =IF(AL19=0,0,AN19/AL19) -> 0 | AN19: =SUM(D19,G19,J19,M19,P19,S19,V19,Y19,AB19,AE19,AH19,AK19) -> 0
A20: Packing Materials / Old use Batteries | F20: =IF(E20=0,0,G20/E20) -> 0 | R20: =IF(Q20=0,0,S20/Q20) -> 0 | X20: =IF(W20=0,0,Y20/W20) -> 0 | AA20: =IF(Z20=0,0,AB20/Z20) -> 0 | AD20: =IF(AC20=0,0,AE20/AC20) -> 0 | AG20: =IF(AF20=0,0,AH20/AF20) -> 0 | AL20: =SUM(B20,E20,H20,K20,N20,Q20,T20,W20,Z20,AC20,AF20,AI20) -> 0 | AM20: =IF(AL20=0,0,AN20/AL20) -> 0 | AN20: =SUM(D20,G20,J20,M20,P20,S20,V20,Y20,AB20,AE20,AH20,AK20) -> 0
A21: HDPE Monofilament Waste | B21: 2174 | C21: =IF(B21=0,0,D21/B21) -> 10 | D21: 21740 | E21: 7460 | F21: =IF(E21=0,0,G21/E21) -> 10 | G21: 74600 | I21: =IF(H21=0,0,J21/H21) -> 0 | L21: =IF(K21=0,0,M21/K21) -> 0 | O21: =IF(N21=0,0,P21/N21) -> 0 | R21: =IF(Q21=0,0,S21/Q21) -> 0 | U21: =IF(T21=0,0,V21/T21) -> 0 | X21: =IF(W21=0,0,Y21/W21) -> 0 | AA21: =IF(Z21=0,0,AB21/Z21) -> 0 | AD21: =IF(AC21=0,0,AE21/AC21) -> 0 | AG21: =IF(AF21=0,0,AH21/AF21) -> 0 | AJ21: =IF(AI21=0,0,AK21/AI21) -> 0 | AL21: =SUM(B21,E21,H21,K21,N21,Q21,T21,W21,Z21,AC21,AF21,AI21) -> 9634 | AM21: =IF(AL21=0,0,AN21/AL21) -> 10 | AN21: =SUM(D21,G21,J21,M21,P21,S21,V21,Y21,AB21,AE21,AH21,AK21) -> 96340
A22: Sale of Asset Etc | R22: =IF(Q22=0,0,S22/Q22) -> 0 | X22: =IF(W22=0,0,Y22/W22) -> 0 | AA22: =IF(Z22=0,0,AB22/Z22) -> 0 | AD22: =IF(AC22=0,0,AE22/AC22) -> 0 | AG22: =IF(AF22=0,0,AH22/AF22) -> 0 | AJ22: =IF(AI22=0,0,AK22/AI22) -> 0 | AL22: =SUM(B22,E22,H22,K22,N22,Q22,T22,W22,Z22,AC22,AF22,AI22) -> 0 | AM22: =IF(AL22=0,0,AN22/AL22) -> 0 | AN22: =SUM(D22,G22,J22,M22,P22,S22,V22,Y22,AB22,AE22,AH22,AK22) -> 0
A23: Colour Pigment | C23: =IF(B23=0,0,D23/B23) -> 0 | L23: =IF(K23=0,0,M23/K23) -> 0 | O23: =IF(N23=0,0,P23/N23) -> 0 | R23: =IF(Q23=0,0,S23/Q23) -> 0 | X23: =IF(W23=0,0,Y23/W23) -> 0 | AA23: =IF(Z23=0,0,AB23/Z23) -> 0 | AD23: =IF(AC23=0,0,AE23/AC23) -> 0 | AG23: =IF(AF23=0,0,AH23/AF23) -> 0 | AJ23: =IF(AI23=0,0,AK23/AI23) -> 0 | AL23: =SUM(B23,E23,H23,K23,N23,Q23,T23,W23,Z23,AC23,AF23,AI23) -> 0 | AM23: =IF(AL23=0,0,AN23/AL23) -> 0 | AN23: =SUM(D23,G23,J23,M23,P23,S23,V23,Y23,AB23,AE23,AH23,AK23) -> 0
A24: Master Batch | C24: =IF(B24=0,0,D24/B24) -> 0 | E24: 25 | F24: =IF(E24=0,0,G24/E24) -> 380 | G24: 9500 | I24: =IF(H24=0,0,J24/H24) -> 0 | L24: =IF(K24=0,0,M24/K24) -> 0 | O24: =IF(N24=0,0,P24/N24) -> 0 | R24: =IF(Q24=0,0,S24/Q24) -> 0 | U24: =IF(T24=0,0,V24/T24) -> 0 | X24: =IF(W24=0,0,Y24/W24) -> 0 | AA24: =IF(Z24=0,0,AB24/Z24) -> 0 | AD24: =IF(AC24=0,0,AE24/AC24) -> 0 | AG24: =IF(AF24=0,0,AH24/AF24) -> 0 | AJ24: =IF(AI24=0,0,AK24/AI24) -> 0 | AL24: =SUM(B24,E24,H24,K24,N24,Q24,T24,W24,Z24,AC24,AF24,AI24) -> 25 | AM24: =IF(AL24=0,0,AN24/AL24) -> 380 | AN24: =SUM(D24,G24,J24,M24,P24,S24,V24,Y24,AB24,AE24,AH24,AK24) -> 9500
A25: HDPE | C25: =IF(B25=0,0,D25/B25) -> 0 | F25: =IF(E25=0,0,G25/E25) -> 0 | I25: =IF(H25=0,0,J25/H25) -> 0 | L25: =IF(K25=0,0,M25/K25) -> 0 | O25: =IF(N25=0,0,P25/N25) -> 0 | R25: =IF(Q25=0,0,S25/Q25) -> 0 | U25: =IF(T25=0,0,V25/T25) -> 0 | X25: =IF(W25=0,0,Y25/W25) -> 0 | AA25: =IF(Z25=0,0,AB25/Z25) -> 0 | AD25: =IF(AC25=0,0,AE25/AC25) -> 0 | AG25: =IF(AF25=0,0,AH25/AF25) -> 0 | AJ25: =IF(AI25=0,0,AK25/AI25) -> 0 | AL25: =SUM(B25,E25,H25,K25,N25,Q25,T25,W25,Z25,AC25,AF25,AI25) -> 0 | AM25: =IF(AL25=0,0,AN25/AL25) -> 0 | AN25: =SUM(D25,G25,J25,M25,P25,S25,V25,Y25,AB25,AE25,AH25,AK25) -> 0 | AO25: =AO18+AL25 -> 224772.13
B26: =SUM(B19:B25) -> 2174 | C26: =IF(B26=0,0,D26/B26) -> 10 | D26: =SUM(D19:D25) -> 21740 | E26: =SUM(E19:E25) -> 7485 | F26: =IF(E26=0,0,G26/E26) -> 11.235805 | G26: =SUM(G19:G25) -> 84100 | H26: =SUM(H19:H25) -> 0 | I26: =IF(H26=0,0,J26/H26) -> 0 | J26: =SUM(J19:J25) -> 0 | K26: =SUM(K19:K25) -> 0 | L26: =IF(K26=0,0,M26/K26) -> 0 | M26: =SUM(M19:M25) -> 0 | N26: =SUM(N19:N25) -> 0 | O26: =IF(N26=0,0,P26/N26) -> 0 | P26: =SUM(P19:P25) -> 0 | Q26: =SUM(Q19:Q25) -> 0 | R26: =IF(Q26=0,0,S26/Q26) -> 0 | S26: =SUM(S19:S25) -> 0 | T26: =SUM(T19:T25) -> 0 | U26: =IF(T26=0,0,V26/T26) -> 0 | V26: =SUM(V19:V25) -> 0 | W26: =SUM(W19:W25) -> 0 | X26: =IF(W26=0,0,Y26/W26) -> 0 | Y26: =SUM(Y19:Y25) -> 0 | Z26: =SUM(Z19:Z25) -> 0 | AA26: =IF(Z26=0,0,AB26/Z26) -> 0 | AB26: =SUM(AB19:AB25) -> 0 | AC26: =SUM(AC19:AC25) -> 0 | AD26: =IF(AC26=0,0,AE26/AC26) -> 0 | AF26: =SUM(AF19:AF25) -> 0 | AG26: =IF(AF26=0,0,AH26/AF26) -> 0 | AH26: =SUM(AH19:AH25) -> 0 | AI26: =SUM(AI19:AI25) -> 0 | AJ26: =IF(AI26=0,0,AK26/AI26) -> 0 | AK26: =SUM(AK19:AK25) -> 0 | AL26: =SUM(AL19:AL25) -> 9659 | AM26: =IF(AL26=0,0,AN26/AL26) -> 10.957656 | AN26: =SUM(AN19:AN25) -> 105840
A27: Grand total: | B27: =SUM(B11,B18,B26) -> 107757 | C27: =IF(B27=0,0,D27/B27) -> 277.38483 | D27: =SUM(D11,D18,D26) -> 29890157 | E27: =SUM(E11,E18,E26) -> 126674.13 | F27: =IF(E27=0,0,G27/E27) -> 266.26323 | G27: =SUM(G11,G18,G26) -> 33728663 | H27: =SUM(H11,H18,H26) -> 0 | I27: =IF(H27=0,0,J27/H27) -> 0 | J27: =SUM(J11,J18,J26) -> 0 | K27: =SUM(K11,K18,K26) -> 0 | L27: =IF(K27=0,0,M27/K27) -> 0 | M27: =SUM(M11,M18,M26) -> 0 | N27: =SUM(N11,N18,N26) -> 0 | O27: =IF(N27=0,0,P27/N27) -> 0 | P27: =SUM(P11,P18,P26) -> 0 | Q27: =SUM(Q11,Q18,Q26) -> 0 | R27: =IF(Q27=0,0,S27/Q27) -> 0 | S27: =SUM(S11,S18,S26) -> 0 | T27: =SUM(T11,T18,T26) -> 0 | U27: =IF(T27=0,0,V27/T27) -> 0 | V27: =SUM(V11,V18,V26) -> 0 | W27: =SUM(W11,W18,W26) -> 0 | X27: =IF(W27=0,0,Y27/W27) -> 0 | Y27: =SUM(Y11,Y18,Y26) -> 0 | Z27: =SUM(Z11,Z18,Z26) -> 0 | AA27: =IF(Z27=0,0,AB27/Z27) -> 0 | AB27: =SUM(AB11,AB18,AB26) -> 0 | AC27: =SUM(AC11,AC18,AC26) -> 0 | AD27: =IF(AC27=0,0,AE27/AC27) -> 0 | AE27: =SUM(AE11,AE18,AE26) -> 0 | AF27: =SUM(AF11,AF18,AF26) -> 0 | AG27: =IF(AF27=0,0,AH27/AF27) -> 0 | AH27: =SUM(AH11,AH18,AH26) -> 0 | AI27: =SUM(AI11,AI18,AI26) -> 0 | AJ27: =IF(AI27=0,0,AK27/AI27) -> 0 | AK27: =SUM(AK11,AK18,AK26) -> 0 | AL27: =SUM(AL11,AL18,AL26) -> 234431.13 | AM27: =IF(AL27=0,0,AN27/AL27) -> 271.37531 | AN27: =SUM(AN11,AN18,AN26) -> 63618820 | AO27: =AN27-AN21 -> 63522480
A28: Other Income | D28: 65.46 | AN28: =SUM(D28,G28,J28,M28,P28,S28,V28,Y28,AB28,AE28,AH28,AK28) -> 65.46
D29: =ROUND((D27-D21),0) -> 29868417 | G29: =ROUND((G27-G21),0) -> 33654063 | J29: =ROUND((J27-J21),0) -> 0 | M29: =ROUND((M27-M21),0) -> 0 | P29: =ROUND((P27-P21),0) -> 0 | S29: =ROUND((S27-S21),0) -> 0 | V29: =ROUND((V27-V21),0) -> 0 | Y29: =ROUND((Y27-Y21),0) -> 0 | AB29: =ROUND((AB27-AB21),0) -> 0 | AE29: =ROUND((AE27-AE21),0) -> 0 | AH29: =ROUND((AH27-AH21),0) -> 0 | AK29: =ROUND((AK27-AK21),0) -> 0 | AL29: =AL11+AL18 -> 224772.13 | AM29: =AN29/AL29 -> 282.56608 | AN29: =AN11+AN18 -> 63512980 | AP29: Sales extract value | AQ29: Sales extract kgs
A30: Gross sales | D30: 31402963 | G30: 35360571 | AN30: =SUM(D30,G30,J30,M30,P30,S30,V30,Y30,AB30,AE30,AH30,AK30) -> 66763534 | AP30: 29890157 | AQ30: 107758.28
A31: tax | D31: 1527660.3 | G31: 1649708 | AN31: =SUM(D31,G31,J31,M31,P31,S31,V31,Y31,AB31,AE31,AH31,AK31) -> 3177368.3 | AP31: =AN27-AP30 -> 33728663 | AQ31: =AL27-AQ30 -> 126672.85
A32: TCS | D32: 0 | AN32: =SUM(D32,G32,J32,M32,P32,S32,V32,Y32,AB32,AE32,AH32,AK32) -> 0
D33: =D31+D32 -> 1527660.3 | G33: =G31+G32 -> 1649708 | J33: =J31+J32 -> 0 | M33: =M31+M32 -> 0 | P33: =P31+P32 -> 0 | S33: =S31+S32 -> 0 | V33: =V31+V32 -> 0 | Y33: =Y31+Y32 -> 0 | AB33: =AB31+AB32 -> 0 | AE33: =AE31+AE32 -> 0 | AH33: =AH31+AH32 -> 0 | AK33: =AK31+AK32 -> 0 | AN33: =SUM(AN31:AN32) -> 3177368.3 | AQ33: P/L sales
D34: =D30-D33 -> 29875303 | G34: =G30-G33 -> 33710863 | J34: =J30-J33 -> 0 | M34: =M30-M33 -> 0 | P34: =P30-P33 -> 0 | S34: =S30-S33 -> 0 | V34: =V30-V33 -> 0 | Y34: =Y30-Y33 -> 0 | AB34: =AB30-AB33 -> 0 | AE34: =AE30-AE33 -> 0 | AH34: =AH30-AH33 -> 0 | AK34: =AK30-AK33 -> 0 | AN34: =AN30-AN33 -> 63586166 | AQ34: 29875303 | AR34: =AQ34-AN34 -> -33710863
A35: Discount | D35: 14854 | G35: 17800 | AN35: =SUM(D35,G35,J35,M35,P35,S35,V35,Y35,AB35,AE35,AH35,AK35) -> 32654
D36: =D34+D35-D37 -> 29890157 | G36: =G34+G35-G37 -> 33728663 | J36: =J34+J35 -> 0 | M36: =M34+M35-M37 -> 0 | P36: =P34+P35 -> 0 | S36: =S34+S35 -> 0 | V36: =V34+V35 -> 0 | Y36: =Y34+Y35 -> 0 | AB36: =AB34+AB35 -> 0 | AE36: =AE34+AE35 -> 0 | AH36: =AH34+AH35 -> 0 | AK36: =AK34+AK35 -> 0 | AN36: =AN34+AN35 -> 63618820 | AO36: =AN27-AN36 -> 0.079999998
A37: Credit Note | Y37: =Y36-Y27 -> 0 | AB37: =AB36-AB27 -> 0 | AE37: =AE36-AE27 -> 0 | AH37: 42540 | AK37: 51048 | AN37: =SUM(D37,G37,J37,M37,P37,S37,V37,Y37,AB37,AE37,AH37,AK37) -> 93588
D38: =D27-D36 -> 0.080000002 | G38: =G27-G36 -> 0 | J38: =J27-J36 -> 0 | M38: =M27-M36 -> 0 | P38: =P27-P36 -> 0 | S38: =S27-S36 -> 0 | V38: =V27-V36 -> 0 | Y38: =Y27-Y36 -> 0 | AB38: =AB27-AB36 -> 0 | AE38: =AE27-AE36 -> 0 | AH38: =AH27-AH36 -> 0 | AK38: =AK27-AK36 -> 0 | AN38: =AN36-AN27 -> -0.079999998
A39: PAL I- FINAL SALES +Less Waste & Discount | D39: =ROUND((D27-(D21+D22+D35)),0) -> 29853563 | G39: =ROUND((G27-(G21+G35)),0) -> 33636263 | J39: =ROUND((J27-(J21+J22+J35)),0) -> 0 | M39: =ROUND((M27-(M21+M22+M35)),0) -> 0 | P39: =ROUND((P27-(P21+P22+P35)),0) -> 0 | S39: =ROUND((S27-(S21+S22+S35)),0) -> 0 | V39: =ROUND((V27-(V21+V22+V35)),0) -> 0 | Y39: =ROUND((Y27-(Y21+Y22+Y35)),0) -> 0 | AB39: =ROUND((AB27-(AB21+AB22+AB35)),0) -> 0 | AE39: =ROUND((AE27-(AE21+AE22+AE35)),0) -> 0 | AH39: =ROUND((AH27-(AH21+AH22+AH35)),0) -> 0 | AK39: =ROUND((AK27-(AK21+AK22+AK35)),0) -> 0 | AN39: =ROUND((AN27-(AN21+AN22+AN35)),0) -> 63489826
AN40: =ROUND((AN39-(AN5+AN6)),0) -> 6009828 | AR40: =AR38-AR39 -> 0
AN41: =AN36-AN27 -> -0.079999998
A42: RM Purchase for sales | B42: =B25 -> 0 | D42: =ROUND((B25*C42),0) -> 0 | E42: =E24 -> 25 | F42: 375 | G42: =ROUND((E42*F42),0) -> 9375 | H42: =H25 -> 0 | I42: 85.79 | J42: =ROUND((H25*I42),0) -> 0 | K42: =K25 -> 0 | L42: 102.13 | M42: =ROUND((K25*L42),0) -> 0 | N42: =N25 -> 0 | O42: 92.93 | P42: =ROUND((N25*O42),0) -> 0 | Q42: =Q25 -> 0 | R42: 99.79 | S42: =ROUND((Q25*R42),0) -> 0 | T42: =T25 -> 0 | U42: 96.12 | V42: =ROUND((T25*U42),0) -> 0 | W42: =W25 -> 0 | X42: 100.88 | Y42: =ROUND((W25*X42),0) -> 0 | Z42: =Z25 -> 0 | AA42: 97.44 | AB42: =ROUND((Z25*AA42),0) -> 0 | AC42: =AC25 -> 0 | AD42: 96.36 | AE42: =ROUND((AC25*AD42),0) -> 0 | AF42: =AF25 -> 0 | AG42: 98.91 | AH42: =ROUND((AF25*AG42),0) -> 0 | AI42: =AI25 -> 0 | AJ42: 96 | AK42: =ROUND((AI25*AJ42),0) -> 0 | AL42: =SUM(B42,E42,H42,K42,N42,Q42,T42,W42,Z42,AC42,AF42,AI42) -> 25 | AN42: =SUM(D42,G42,J42,M42,P42,S42,V42,Y42,AB42,AE42,AH42,AK42) -> 9375 | AP42: `
C43: =C25-C42 -> 0 | F43: =F24-F42 -> 5 | I43: =I25-I42 -> -85.79 | L43: =L25-L42 -> -102.13 | O43: =O25-O42 -> -92.93 | R43: =R25-R42 -> -99.79 | U43: =U25-U42 -> -96.12 | X43: =X25-X42 -> -100.88 | AA43: =AA25-AA42 -> -97.44 | AD43: =AD25-AD42 -> -96.36 | AG43: =AG25-AG42 -> -98.91 | AN43: =AN24-AN42 -> 125
A44: Monofil Fabric Sales | B44: =ROUND((B11-(B10)),0) -> 89944 | C44: =D44/B44 -> 292.04829 | D44: =ROUND((D11-(D10+D35)),0) -> 26267991 | E44: =E11-(E10) -> 108160.53 | F44: =G44/E44 -> 288.31084 | G44: =G11-(G10+G35) -> 31183853 | H44: =H11-(H10) -> 0 | I44: =J44/H44 -> #DIV/0! | J44: =J11-(J10+J35) -> 0 | K44: =K11-(K10) -> 0 | L44: =M44/K44 -> #DIV/0! | M44: =M11-(M10+M35) -> 0 | N44: =N11-(N10) -> 0 | O44: =P44/N44 -> #DIV/0! | P44: =P11-(P10+P35) -> 0 | Q44: =Q11-(Q10) -> 0 | R44: =S44/Q44 -> #DIV/0! | S44: =S11-(S10+S35) -> 0 | T44: =T11-(T10) -> 0 | U44: =V44/T44 -> #DIV/0! | V44: =V11-(V10+V35) -> 0 | W44: =W11-(W10) -> 0 | X44: =Y44/W44 -> #DIV/0! | Y44: =Y11-(Y10+Y35) -> 0 | Z44: =Z11-(Z10) -> 0 | AA44: =AB44/Z44 -> #DIV/0! | AB44: =AB11-(AB10+AB35) -> 0 | AL44: =SUM(B44,E44,H44,K44,N44,Q44,T44,W44,Z44,AC44,AF44,AI44) -> 198104.53 | AM44: =AN44/AL44 -> 290.00772 | AN44: =ROUND((AN11-(AN10+AN35)),0) -> 57451844
A45: Sales From Monofil Trading | B45: =Purchase!I22 -> 22533 | C45: =D45/B45 -> 292.04828 | D45: =ROUND((B45*C44),0) -> 6580724 | E45: =Purchase!I23 -> 9376 | F45: =G45/E45 -> 288.31079 | G45: =ROUND((E45*F44),0) -> 2703202 | AL45: =SUM(B45,E45,H45,K45,N45,Q45,T45,W45,Z45,AC45,AF45,AI45) -> 31909 | AM45: =AN45/AL45 -> 290.95008 | AN45: =SUM(D45,G45,J45,M45,P45,S45,V45,Y45,AB45,AE45,AH45,AK45) -> 9283926
B46: =B44-B45 -> 67411 | C46: =D46/B46 -> 292.04829 | D46: =D44-D45 -> 19687267 | E46: =E44-E45 -> 98784.53 | F46: =G46/E46 -> 288.31085 | G46: =G44-G45 -> 28480651 | AL46: =SUM(B46,E46,H46,K46,N46,Q46,T46,W46,Z46,AC46,AF46,AI46) -> 166195.53 | AM46: =AN46/AL46 -> 289.8268 | AN46: =SUM(D46,G46,J46,M46,P46,S46,V46,Y46,AB46,AE46,AH46,AK46) -> 48167918

Sheet Stock Valuation (FIFO)
B2: Opening Stock 01 Apr 26 | E2: 46113 | H2: 45778 | K2: 45809 | N2: 45839 | Q2: 45870 | T2: 45901 | W2: 45931 | Z2: 45962 | AC2: 45992 | AF2: 46023 | AI2: 46054 | AL2: 46082 | AO2: Bank Stock Statement
A3: RAW MATERIALS: | B3: QTY IN KGS. | C3: BASIC RATE | D3: BASIC VALUE | E3: QTY IN KGS. | F3: BASIC RATE | G3: BASIC VALUE | H3: QTY IN KGS. | I3: BASIC RATE | J3: BASIC VALUE | K3: QTY IN KGS. | L3: BASIC RATE | M3: BASIC VALUE | N3: QTY IN KGS. | O3: BASIC RATE | P3: BASIC VALUE | Q3: QTY IN KGS. | R3: BASIC RATE | S3: BASIC VALUE | T3: QTY IN KGS. | U3: BASIC RATE | V3: BASIC VALUE | W3: QTY IN KGS. | X3: BASIC RATE | Y3: BASIC VALUE | Z3: QTY IN KGS. | AA3: BASIC RATE | AB3: BASIC VALUE | AC3: QTY IN KGS. | AD3: BASIC RATE | AE3: BASIC VALUE | AF3: QTY IN KGS. | AG3: BASIC RATE | AH3: BASIC VALUE | AI3: QTY IN KGS. | AJ3: BASIC RATE | AL3: QTY IN KGS. | AM3: BASIC RATE | AN3: BASIC VALUE | AO3: QTY IN KGS. | AP3: BASIC RATE | AQ3: BASIC VALUE | AR3: QTY IN KGS. | AS3: BASIC RATE | AT3: BASIC VALUE | AU3: QTY IN KGS. | AV3: BASIC RATE | AW3: BASIC VALUE
AX4: Incr/(Decr)Stk | BA4: Stk frm Tarka as om 01 Apr(Srp) | BE4: Physical
A5: HDPE Granules | B5: 141140 | C5: =D5/B5+0.02 -> 121.99507 | D5: 17215561 | E5: 75695 | F5: =ROUND(IF(G5=0,0,(G5/E5)),0) -> 136 | G5: 10273379 | H5: 90040 | I5: =IF(J5=0,0,(J5/H5)) -> 152.60895 | J5: 13740910 | L5: =IF(M5=0,0,(M5/K5)) -> 0 | O5: =IF(P5=0,0,(P5/N5)) -> 0 | R5: =IF(S5=0,0,(S5/Q5)) -> 0 | U5: =IF(V5=0,0,(V5/T5)) -> 0 | X5: =IF(Y5=0,0,(Y5/W5)) -> 0 | AA5: =IF(AB5=0,0,(AB5/Z5)) -> 0 | AJ5: =IF(AK5=0,0,(AK5/AI5)) -> 0 | AP5: =IF(AQ5=0,0,(AQ5/AO5)) -> 0 | AR5: ='[1] Qty Analysis'!BE15 -> 0 | AT5: =ROUND((AS5*AR5),0) -> 0 | AU5: ='[1] Qty Analysis'!BH15 -> 0 | AW5: =ROUND((AV5*AU5),0) -> 0 | AX5: =Z5-B5 -> -141140 | AY5: =AX5/B5 -> -1 | BA5: =125000+40000 -> 165000 | BB5: 101 | BC5: =ROUND((BA5*BB5),0) -> 16665000 | BE5: 163575
A6: Master Batches | B6: 2330 | C6: =D6/B6+0.04 -> 226.96532 | D6: 528736 | E6: 2392 | F6: =ROUND(IF(G6=0,0,(G6/E6)),0) -> 245 | G6: 586833 | H6: 2239 | I6: =IF(J6=0,0,(J6/H6)) -> 258.70835 | J6: 579248 | L6: =IF(M6=0,0,(M6/K6)) -> 0 | O6: =IF(P6=0,0,(P6/N6)) -> 0 | R6: =IF(S6=0,0,(S6/Q6)) -> 0 | U6: =IF(V6=0,0,(V6/T6)) -> 0 | X6: =IF(Y6=0,0,(Y6/W6)) -> 0 | AA6: =IF(AB6=0,0,(AB6/Z6)) -> 0 | AJ6: =IF(AK6=0,0,(AK6/AI6)) -> 0 | AP6: =IF(AQ6=0,0,(AQ6/AO6)) -> 0 | AR6: ='[1] Qty Analysis'!BE27 -> 0 | AT6: =ROUND((AS6*AR6),0) -> 0 | AU6: ='[1] Qty Analysis'!BH27 -> 0 | AW6: =ROUND((AV6*AU6),0) -> 0 | AX6: =Z6-B6 -> -2330 | AY6: =AX6/B6 -> -1 | BA6: 2730 | BB6: 215 | BC6: =ROUND((BA6*BB6),0) -> 586950 | BE6: 2645
A7: Colour Pigments | B7: 19 | C7: =D7/B7-0.37 -> 1596.9984 | D7: 30350 | E7: 21 | F7: =ROUND(IF(G7=0,0,(G7/E7)),0) -> 1515 | G7: 31807 | H7: 20 | I7: =IF(J7=0,0,(J7/H7)) -> 1568.5 | J7: 31370 | L7: =IF(M7=0,0,(M7/K7)) -> 0 | O7: =IF(P7=0,0,(P7/N7)) -> 0 | R7: =IF(S7=0,0,(S7/Q7)) -> 0 | U7: =IF(V7=0,0,(V7/T7)) -> 0 | X7: =IF(Y7=0,0,(Y7/W7)) -> 0 | AA7: =IF(AB7=0,0,(AB7/Z7)) -> 0 | AJ7: =IF(AK7=0,0,(AK7/AI7)) -> 0 | AP7: =IF(AQ7=0,0,(AQ7/AO7)) -> 0 | AR7: ='[1] Qty Analysis'!BE39 -> 0 | AT7: =ROUND((AS7*AR7),0) -> 0 | AU7: ='[1] Qty Analysis'!BH39 -> 0 | AW7: =ROUND((AV7*AU7),0) -> 0 | AX7: =Z7-B7 -> -19 | AY7: =AX7/B7 -> -1 | BA7: 30 | BB7: 2280 | BC7: =ROUND((BA7*BB7),0) -> 68400 | BE7: 45.3
A8: Total | B8: =SUM(B5:B7) -> 143489 | C8: =D8/B8 -> 123.87463 | D8: =SUM(D5:D7) -> 17774647 | E8: =SUM(E5:E7) -> 78108 | F8: =IF(G8=0,0,(G8/E8)) -> 139.44819 | G8: =SUM(G5:G7) -> 10892019 | H8: =SUM(H5:H7) -> 92299 | I8: =IF(J8=0,0,(J8/H8)) -> 155.48953 | J8: =SUM(J5:J7) -> 14351528 | K8: =SUM(K5:K7) -> 0 | L8: =IF(M8=0,0,(M8/K8)) -> 0 | M8: =SUM(M5:M7) -> 0 | N8: =SUM(N5:N7) -> 0 | O8: =IF(P8=0,0,(P8/N8)) -> 0 | P8: =SUM(P5:P7) -> 0 | Q8: =SUM(Q5:Q7) -> 0 | R8: =IF(S8=0,0,(S8/Q8)) -> 0 | S8: =ROUND(SUM(S5:S7),0) -> 0 | T8: =SUM(T5:T7) -> 0 | U8: =IF(V8=0,0,(V8/T8)) -> 0 | V8: =SUM(V5:V7) -> 0 | W8: =SUM(W5:W7) -> 0 | X8: =IF(Y8=0,0,(Y8/W8)) -> 0 | Y8: =SUM(Y5:Y7) -> 0 | Z8: =SUM(Z5:Z7) -> 0 | AA8: =IF(AB8=0,0,(AB8/Z8)) -> 0 | AB8: =SUM(AB5:AB7) -> 0 | AC8: =SUM(AC5:AC7) -> 0 | AD8: =IF(AE8=0,0,(AE8/AC8)) -> 0 | AE8: =SUM(AE5:AE7) -> 0 | AF8: =SUM(AF5:AF7) -> 0 | AG8: =IF(AH8=0,0,(AH8/AF8)) -> 0 | AH8: =SUM(AH5:AH7) -> 0 | AI8: =SUM(AI5:AI7) -> 0 | AJ8: =IF(AK8=0,0,(AK8/AI8)) -> 0 | AK8: =SUM(AK5:AK7) -> 0 | AL8: =SUM(AL5:AL7) -> 0 | AM8: =IF(AN8=0,0,(AN8/AL8)) -> 0 | AN8: =SUM(AN5:AN7) -> 0 | AO8: =SUM(AO5:AO7) -> 0 | AP8: =IF(AQ8=0,0,(AQ8/AO8)) -> 0 | AQ8: =SUM(AQ5:AQ7) -> 0 | AR8: =SUM(AR5:AR7) -> 0 | AT8: =SUM(AT5:AT7) -> 0 | AU8: =SUM(AU5:AU7) -> 0 | AW8: =SUM(AW5:AW7) -> 0 | AX8: =Z8-B8 -> -143489 | AY8: =AX8/B8 -> -1 | BA8: =SUM(BA5:BA7) -> 167760 | BB8: =BC8/BA8 -> 103.24481 | BC8: =SUM(BC5:BC7) -> 17320350 | BE8: =SUM(BE5:BE7) -> 166265.3
A9: Work in Progress
A10: HDPE Tape - Factory | B10: 37996 | C10: 167 | D10: =B10*C10 -> 6345332 | E10: =26659.9+0.1 -> 26660 | F10: =66+116 -> 182 | G10: =ROUND(E10*F10,0) -> 4852120 | H10: 17001 | I10: 207 | J10: 3519207 | M10: =ROUND(K10*L10,0) -> 0 | P10: =ROUND(N10*O10,0) -> 0 | AB10: =ROUND((Z10*AA10),0) -> 0 | AE10: =ROUND((AC10*AD10),0) -> 0 | AH10: =ROUND((AF10*AG10),0) -> 0 | AK10: =ROUND((AI10*AJ10),0) -> 0 | AN10: =ROUND((AL10*AM10),0) -> 0 | AP10: =IF(AQ10=0,0,(AQ10/AO10)) -> 0 | AR10: ='[1] Qty Analysis'!BE66 -> 0 | AT10: =ROUND((AS10*AR10),0) -> 0 | AU10: ='[1] Qty Analysis'!BH66 -> 0 | AW10: =ROUND((AV10*AU10),0) -> 0 | AX10: =Z10-B10 -> -37996 | AY10: =AX10/B10 -> -1 | BA10: 24480 | BB10: 163 | BC10: =ROUND((BA10*BB10),0) -> 3990240 | BE10: 24112
A11: HDPE Tape - Job Work | B11: =64171.5-0.5 -> 64171 | C11: =C10 -> 167 | D11: =B11*C11 -> 10716557 | E11: 50337 | F11: =F10 -> 182 | G11: =ROUND(E11*F11,0) -> 9161334 | H11: 56663 | I11: 207 | J11: 11729241 | L11: =L10 -> 0 | M11: =ROUND(K11*L11,0) -> 0 | P11: =ROUND(N11*O11,0) -> 0 | R11: =R10 -> 0 | U11: =U10 -> 0 | AA11: =AA10 -> 0 | AB11: =ROUND((Z11*AA11),0) -> 0 | AE11: =ROUND((AC11*AD11),0) -> 0 | AH11: =ROUND((AF11*AG11),0) -> 0 | AJ11: =AJ10 -> 0 | AK11: =ROUND((AI11*AJ11),0) -> 0 | AM11: =AM10 -> 0 | AN11: =ROUND((AL11*AM11),0) -> 0 | AP11: =IF(AQ11=0,0,(AQ11/AO11)) -> 0 | AR11: ='[1] Qty Analysis'!BE81 -> 0 | AT11: =ROUND((AS11*AR11),0) -> 0 | AU11: ='[1] Qty Analysis'!BH81 -> 0 | AW11: =ROUND((AV11*AU11),0) -> 0 | AX11: =Z11-B11 -> -64171 | AY11: =AX11/B11 -> -1 | BA11: 66292 | BB11: 163 | BC11: =ROUND((BA11*BB11),0) -> 10805596 | BE11: 66292
A12: Total | B12: =SUM(B10:B11) -> 102167 | C12: =D12/B12 -> 167 | D12: =SUM(D10:D11) -> 17061889 | E12: =SUM(E10:E11) -> 76997 | F12: =G12/E12 -> 182 | G12: =SUM(G10:G11) -> 14013454 | H12: =SUM(H10:H11) -> 73664 | J12: =SUM(J10:J11) -> 15248448 | K12: =SUM(K10:K11) -> 0 | M12: =SUM(M10:M11) -> 0 | N12: =SUM(N10:N11) -> 0 | P12: =SUM(P10:P11) -> 0 | Q12: =SUM(Q10:Q11) -> 0 | S12: =SUM(S10:S11) -> 0 | T12: =SUM(T10:T11) -> 0 | V12: =SUM(V10:V11) -> 0 | W12: =SUM(W10:W11) -> 0 | X12: =IF(Y12=0,0,(Y12/W12)) -> 0 | Y12: =SUM(Y10:Y11) -> 0 | Z12: =SUM(Z10:Z11) -> 0 | AB12: =SUM(AB10:AB11) -> 0 | AC12: =SUM(AC10:AC11) -> 0 | AE12: =SUM(AE10:AE11) -> 0 | AF12: =SUM(AF10:AF11) -> 0 | AH12: =SUM(AH10:AH11) -> 0 | AI12: =SUM(AI10:AI11) -> 0 | AK12: =SUM(AK10:AK11) -> 0 | AL12: =SUM(AL10:AL11) -> 0 | AN12: =SUM(AN10:AN11) -> 0 | AO12: =SUM(AO10:AO11) -> 0 | AP12: =IF(AQ12=0,0,(AQ12/AO12)) -> 0 | AQ12: =SUM(AQ10:AQ11) -> 0 | AR12: =SUM(AR10:AR11) -> 0 | AT12: =SUM(AT10:AT11) -> 0 | AU12: =SUM(AU10:AU11) -> 0 | AW12: =SUM(AW10:AW11) -> 0 | AX12: =Z12-B12 -> -102167 | AY12: =AX12/B12 -> -1 | BA12: =SUM(BA10:BA11) -> 90772 | BB12: =BC12/BA12 -> 163 | BC12: =SUM(BC10:BC11) -> 14795836 | BE12: =SUM(BE10:BE11) -> 90404
A13: FINISHED GOODS:
A14: HDPE Fishnet Fabrics | B14: 200810 | C14: 238 | D14: =B14*C14 -> 47792780 | E14: 216887 | F14: =116+66+68 -> 250 | G14: =ROUND(E14*F14,0) -> 54221750 | H14: 179666 | I14: 278 | J14: 49947148 | U14: 221 | X14: =IF(Y14=0,0,(Y14/W14)) -> 0 | AA14: =IF(AB14=0,0,(AB14/Z14)) -> 0 | AD14: =IF(AE14=0,0,(AE14/AC14)) -> 0 | AP14: =IF(AQ14=0,0,(AQ14/AO14)) -> 0 | AR14: ='[1] Qty Analysis'!BE101 -> 0 | AT14: =ROUND((AS14*AR14),0) -> 0 | AU14: ='[1] Qty Analysis'!BH101 -> 0 | AW14: =ROUND((AV14*AU14),0) -> 0 | AX14: =Z14-B14 -> -200810 | AY14: =AX14/B14 -> -1 | BA14: 289350 | BB14: 228 | BC14: =ROUND((BA14*BB14),0) -> 65971800
A15: Monofilament Shade Net -MSN | B15: 387 | C15: =IF(B15=0,0,(D15/B15))+0.35 -> 215.00116 | D15: 83070 | E15: 387 | F15: =IF(E15=0,0,(G15/E15))-0.3 -> 240.00233 | G15: 92997 | H15: 387 | I15: =IF(H15=0,0,(J15/H15)) -> 241.70801 | J15: 93541 | L15: =IF(K15=0,0,(M15/K15)) -> 0 | O15: =IF(N15=0,0,(P15/N15)) -> 0 | U15: =V15/T15 -> #DIV/0! | X15: =IF(Y15=0,0,(Y15/W15)) -> 0 | AA15: =IF(AB15=0,0,(AB15/Z15)) -> 0 | AD15: =IF(AE15=0,0,(AE15/AC15)) -> 0 | AP15: =IF(AQ15=0,0,(AQ15/AO15)) -> 0 | AR15: ='[1] Qty Analysis'!BE122 -> 0 | AU15: ='[1] Qty Analysis'!BH122 -> 0 | AX15: =Z15-B15 -> -387 | AY15: =AX15/B15 -> -1 | BA15: 810 | BB15: =BC15/BA15 -> 214.81481 | BC15: 174000
A16: Tape Shade Net-TSN | B16: 172 | C16: =IF(B16=0,0,(D16/B16))+0.12 -> 240.86419 | D16: 41408 | E16: 172 | F16: =IF(E16=0,0,(G16/E16))+0.41 -> 266.84605 | G16: 45827 | H16: 340 | I16: =IF(H16=0,0,(J16/H16)) -> 258.02647 | J16: 87729 | L16: =IF(K16=0,0,(M16/K16)) -> 0 | O16: =IF(N16=0,0,(P16/N16)) -> 0 | U16: =V16/T16 -> #DIV/0! | X16: =IF(Y16=0,0,(Y16/W16)) -> 0 | AA16: =IF(AB16=0,0,(AB16/Z16)) -> 0 | AX16: =Z16-B16 -> -172 | AY16: =AX16/B16 -> -1
A17: Weed Mat | B17: 446 | C17: =IF(B17=0,0,(D17/B17))+0.5 -> 229.10314 | D17: 101957 | E17: 346 | F17: =IF(E17=0,0,(G17/E17))+0.5 -> 229.13295 | G17: 79107 | H17: 276 | I17: =IF(H17=0,0,(J17/H17)) -> 210.07609 | J17: 57981 | L17: =IF(K17=0,0,(M17/K17)) -> 0 | O17: =IF(N17=0,0,(P17/N17)) -> 0 | U17: =V17/T17 -> #DIV/0! | X17: =IF(Y17=0,0,(Y17/W17)) -> 0 | AA17: =IF(AB17=0,0,(AB17/Z17)) -> 0 | AX17: =Z17-B17 -> -446 | AY17: =AX17/B17 -> -1
A18: PP Fabric & Sacks | F18: =IF(E18=0,0,(G18/E18)) -> 0 | I18: =IF(H18=0,0,(J18/H18)) -> 0 | L18: =IF(K18=0,0,(M18/K18)) -> 0 | O18: =IF(N18=0,0,(P18/N18)) -> 0 | AA18: =IF(AB18=0,0,(AB18/Z18)) -> 0
A19: Miscellaneous | B19: 36 | C19: =IF(B19=0,0,(D19/B19))-0.01 -> 128.76778 | D19: 4636 | E19: 36 | F19: =IF(E19=0,0,(G19/E19))-0.14 -> 186.55444 | G19: 6721 | H19: 36 | I19: =IF(H19=0,0,(J19/H19)) -> 186.69444 | J19: 6721 | L19: =IF(K19=0,0,(M19/K19)) -> 0 | O19: =IF(N19=0,0,(P19/N19)) -> 0 | U19: =IF(V19=0,0,(V19/T19)) -> 0 | X19: =IF(Y19=0,0,(Y19/W19)) -> 0 | AA19: =IF(AB19=0,0,(AB19/Z19)) -> 0 | AP19: =IF(AQ19=0,0,(AQ19/AO19)) -> 0
A20: Total | B20: =SUM(B14:B19) -> 201851 | C20: =D20/B20 -> 237.91733 | D20: =SUM(D14:D19)-1 -> 48023850 | E20: =SUM(E14:E19) -> 217828 | F20: =G20/E20 -> 249.95135 | G20: =SUM(G14:G19) -> 54446402 | H20: =SUM(H14:H19) -> 180705 | J20: =SUM(J14:J19) -> 50193120 | K20: =SUM(K14:K19) -> 0 | M20: =SUM(M14:M19) -> 0 | N20: =SUM(N14:N19) -> 0 | P20: =SUM(P14:P19) -> 0 | Q20: =SUM(Q14:Q19) -> 0 | S20: =SUM(S14:S19) -> 0 | T20: =SUM(T14:T19) -> 0 | V20: =SUM(V14:V19) -> 0 | W20: =SUM(W14:W19) -> 0 | Y20: =SUM(Y14:Y19) -> 0 | Z20: =SUM(Z14:Z19) -> 0 | AB20: =SUM(AB14:AB19) -> 0 | AC20: =SUM(AC14:AC19) -> 0 | AE20: =SUM(AE14:AE19) -> 0 | AF20: =SUM(AF14:AF19) -> 0 | AH20: =SUM(AH14:AH19) -> 0 | AI20: =SUM(AI14:AI19) -> 0 | AK20: =SUM(AK14:AK19) -> 0 | AL20: =SUM(AL14:AL19) -> 0 | AN20: =SUM(AN14:AN19) -> 0 | AO20: =SUM(AO14:AO19) -> 0 | AP20: =AQ20/AO20 -> #DIV/0! | AQ20: =SUM(AQ14:AQ19) -> 0 | AR20: =SUM(AR14:AR19) -> 0 | AT20: =SUM(AT14:AT19) -> 0 | AU20: =SUM(AU14:AU19) -> 0 | AW20: =SUM(AW14:AW19) -> 0 | AX20: =Z20-B20 -> -201851 | AY20: =AX20/B20 -> -1 | BA20: =SUM(BA14:BA15) -> 290160 | BB20: =BC20/BA20 -> 227.96319 | BC20: =SUM(BC14:BC15) -> 66145800
A21: Trading Total | B21: =SUM(B15:B19) -> 1041 | C21: =IF(B21=0,0,(D21/B21)) -> 221.96926 | D21: =SUM(D15:D19)-1 -> 231070 | E21: =SUM(E15:E19) -> 941 | F21: =IF(E21=0,0,(G21/E21)) -> 238.73751 | G21: =SUM(G15:G19) -> 224652 | H21: =SUM(H15:H19) -> 1039 | I21: =IF(H21=0,0,(J21/H21)) -> 236.73917 | J21: =SUM(J15:J19) -> 245972 | K21: =SUM(K15:K19) -> 0 | L21: =IF(K21=0,0,(M21/K21)) -> 0 | M21: =SUM(M15:M19) -> 0 | N21: =SUM(N15:N19) -> 0 | O21: =IF(N21=0,0,(P21/N21)) -> 0 | P21: =SUM(P15:P19) -> 0 | Q21: =SUM(Q15:Q19) -> 0 | R21: =IF(Q21=0,0,(S21/Q21)) -> 0 | S21: =SUM(S15:S19) -> 0 | T21: =SUM(T15:T19) -> 0 | U21: =IF(T21=0,0,(V21/T21)) -> 0 | V21: =SUM(V15:V19) -> 0 | W21: =SUM(W15:W19) -> 0 | X21: =IF(W21=0,0,(Y21/W21)) -> 0 | Y21: =SUM(Y15:Y19) -> 0 | Z21: =SUM(Z15:Z19) -> 0 | AA21: =IF(Z21=0,0,(AB21/Z21)) -> 0 | AB21: =SUM(AB15:AB19) -> 0 | AC21: =SUM(AC15:AC19) -> 0 | AE21: =SUM(AE15:AE19) -> 0 | AF21: =SUM(AF15:AF19) -> 0 | AH21: =SUM(AH15:AH19) -> 0 | AI21: =SUM(AI15:AI19) -> 0 | AL21: =SUM(AL15:AL19) -> 0 | AM21: =IF(AL21=0,0,(AN21/AL21)) -> 0 | AN21: =SUM(AN15:AN19) -> 0 | AP21: S Dr
A22: Packing Materials | AP22: LC & Cr | AR22: ='[1] Qty Analysis'!BE44 -> 0 | AU22: ='[1] Qty Analysis'!BH44 -> 0
A23: Seconds | G23: =ROUND((E23*F23),0) -> 0 | J23: =ROUND((H23*I23),0) -> 0 | M23: =ROUND((K23*L23),0) -> 0 | P23: =ROUND((N23*O23),0) -> 0 | S23: =ROUND((Q23*R23),0) -> 0 | V23: =ROUND((T23*U23),0) -> 0 | Y23: =ROUND((W23*X23),0) -> 0 | AB23: =ROUND((Z23*AA23),0) -> 0 | AE23: =ROUND((AC23*AD23),0) -> 0 | AH23: =ROUND((AF23*AG23),0) -> 0 | AK23: =ROUND((AI23*AJ23),0) -> 0 | AN23: =ROUND((AL23*AM23),0) -> 0 | AR23: ='[1] Qty Analysis'!BE132 -> 0 | AU23: ='[1] Qty Analysis'!BH132 -> 0
A24: Total
A25: Grand Total | B25: =B20+B12+B8 -> 447507 | C25: =D25/B25 -> 185.15998 | D25: =D20+D12+D8 -> 82860386 | E25: =E20+E12+E8 -> 372933 | F25: =IF(E25=0,0,G25/E25) -> 212.77783 | G25: =G20+G12+G8 -> 79351875 | H25: =H20+H12+H8 -> 346668 | I25: =IF(H25=0,0,J25/H25) -> 230.17151 | J25: =J20+J12+J8 -> 79793096 | K25: =K20+K12+K8 -> 0 | L25: =IF(K25=0,0,M25/K25) -> 0 | M25: =M20+M12+M8 -> 0 | N25: =N20+N12+N8 -> 0 | O25: =IF(N25=0,0,P25/N25) -> 0 | P25: =P20+P12+P8 -> 0 | Q25: =Q20+Q12+Q8 -> 0 | R25: =IF(Q25=0,0,S25/Q25) -> 0 | S25: =S20+S12+S8 -> 0 | T25: =T20+T12+T8 -> 0 | U25: =IF(T25=0,0,V25/T25) -> 0 | V25: =V20+V12+V8 -> 0 | W25: =W20+W12+W8 -> 0 | X25: =IF(W25=0,0,Y25/W25) -> 0 | Y25: =Y20+Y12+Y8 -> 0 | Z25: =Z20+Z12+Z8 -> 0 | AA25: =IF(Z25=0,0,AB25/Z25) -> 0 | AB25: =AB20+AB12+AB8 -> 0 | AC25: =AC20+AC12+AC8 -> 0 | AD25: =IF(AC25=0,0,AE25/AC25) -> 0 | AE25: =AE20+AE12+AE8 -> 0 | AF25: =AF20+AF12+AF8 -> 0 | AG25: =IF(AF25=0,0,AH25/AF25) -> 0 | AH25: =AH20+AH12+AH8 -> 0 | AI25: =AI20+AI12+AI8 -> 0 | AJ25: =IF(AI25=0,0,AK25/AI25) -> 0 | AK25: =AK20+AK12+AK8 -> 0 | AL25: =AL20+AL12+AL8 -> 0 | AM25: =IF(AL25=0,0,AN25/AL25) -> 0 | AN25: =AN20+AN12+AN8 -> 0 | AO25: =AO20+AO12+AO8 -> 0 | AP25: =IF(AO25=0,0,AQ25/AO25) -> 0 | AQ25: =AQ8+AQ12+AQ20 -> 0 | AR25: =AR20+AR12+AR8 -> 0 | AT25: =AT20+AT12+AT8 -> 0 | AU25: =AU20+AU12+AU8 -> 0 | AW25: =AW20+AW12+AW8 -> 0 | AX25: =Z25-B25 -> -447507 | AY25: =AX25/B25 -> -1 | BA25: =BA20+BA12+BA8 -> 548692 | BB25: =IF(BA25=0,0,BC25/BA25) -> 179.08405 | BC25: =BC20+BC12+BC8 -> 98261986
A26: SFG/FG | B26: =B25-B8 -> 304018 | C26: =D26/B26 -> 214.08515 | D26: =D25-D8 -> 65085739 | E26: =E25-E8 -> 294825 | F26: =IF(E26=0,0,G26/E26) -> 232.20506 | G26: =G25-G8 -> 68459856 | H26: =H25-H8 -> 254369 | I26: =IF(H26=0,0,J26/H26) -> 257.27022 | J26: =J25-J8 -> 65441568 | K26: =K25-K8 -> 0 | L26: =IF(K26=0,0,M26/K26) -> 0 | M26: =M25-M8 -> 0 | N26: =N25-N8 -> 0 | O26: =IF(N26=0,0,P26/N26) -> 0 | P26: =P25-P8 -> 0 | Q26: =Q25-Q8 -> 0 | R26: =IF(Q26=0,0,S26/Q26) -> 0 | S26: =S25-S8 -> 0 | T26: =T25-T8 -> 0 | U26: =IF(T26=0,0,V26/T26) -> 0 | V26: =V25-V8 -> 0 | W26: =W25-W8 -> 0 | X26: =IF(W26=0,0,Y26/W26) -> 0 | Y26: =Y25-Y8 -> 0 | Z26: =Z25-Z8 -> 0 | AA26: =IF(Z26=0,0,AB26/Z26) -> 0 | AB26: =AB25-AB8 -> 0 | AC26: =AC25-AC8 -> 0 | AD26: =IF(AC26=0,0,AE26/AC26) -> 0 | AE26: =AE25-AE8 -> 0 | AF26: =AF25-AF8 -> 0 | AG26: =IF(AF26=0,0,AH26/AF26) -> 0 | AH26: =AH25-AH8 -> 0 | AI26: =AI25-AI8 -> 0 | AJ26: =IF(AI26=0,0,AK26/AI26) -> 0 | AK26: =AK25-AK8 -> 0 | AL26: =AL25-AL8 -> 0 | AM26: =IF(AL26=0,0,AN26/AL26) -> 0 | AN26: =AN25-AN8 -> 0 | AP26: 0.25 | AQ26: =ROUND(((AQ25+AQ21+AQ22)*25%),0) -> 0 | AR26: =AR25-AR8 -> 0 | AS26: =AT26/AR26 -> #DIV/0! | AT26: =AT25-AT8 -> 0 | AU26: =AU25-AU8 -> 0 | AV26: =AW26/AU26 -> #DIV/0! | AW26: =AW25-AW8 -> 0 | BA26: =BA25-BA8 -> 380932 | BC26: =BC25-BC8 -> 80941636
A27: Diff in SFG/FG | E27: =B26-E26 -> 9193 | G27: =D26-G26 -> -3374117 | H27: =E26-H26 -> 40456 | J27: =G26-J26 -> 3018288 | K27: =H26-K26 -> 254369 | M27: =J26-M26 -> 65441568 | N27: =K26-N26 -> 0 | O27: =P27/N27 -> #DIV/0! | P27: =M26-P26 -> 0 | Q27: =N26-Q26 -> 0 | R27: =S27/Q27 -> #DIV/0! | S27: =P26-S26 -> 0 | T27: =Q26-T26 -> 0 | U27: =V27/T27 -> #DIV/0! | V27: =S26-V26 -> 0 | W27: =T26-W26 -> 0 | X27: =Y27/W27 -> #DIV/0! | Y27: =V26-Y26 -> 0 | Z27: =W26-Z26 -> 0 | AA27: =AB27/Z27 -> #DIV/0! | AB27: =Y26-AB26 -> 0 | AC27: =Z26-AC26 -> 0 | AD27: =AE27/AC27 -> #DIV/0! | AE27: =AB26-AE26 -> 0 | AF27: =AC26-AF26 -> 0 | AG27: =AH27/AF27 -> #DIV/0! | AH27: =AE26-AH26 -> 0 | AI27: =AF26-AI26 -> 0 | AJ27: =AK27/AI27 -> #DIV/0! | AK27: =AH26-AK26 -> 0 | AL27: =AL26-AI26 -> 0 | AM27: =AN27/AL27 -> #DIV/0! | AN27: =AK26-AN26 -> 0 | AQ27: =(AQ25+AQ21+AQ22)-AQ26 -> 0 | AR27: =AO26-AR26 -> 0 | AS27: =AT27/AR27 -> #DIV/0! | AT27: =AQ26-AT26 -> 0 | AU27: =AR26-AU26 -> 0 | AV27: =AW27/AU27 -> #DIV/0! | AW27: =AT26-AW26 -> 0 | BB27: Month | BC27: =AK26-BC26 -> -80941636
A28: Monofil | E28: =E27-E29 -> 9093 | G28: =G27-G29 -> -3380536 | H28: =H27-H29 -> 40554 | J28: =J27-J29 -> 3039608 | K28: =K27-K29 -> 253330 | M28: =M27-M29 -> 65195596 | N28: =N27-N29 -> 0 | P28: =P27-P29 -> 0 | Q28: =Q27-Q29 -> 0 | S28: =S27-S29 -> 0 | T28: =T27-T29 -> 0 | V28: =V27-V29 -> 0 | W28: =W27-W29 -> 0 | Y28: =Y27-Y29 -> 0 | Z28: =Z27-Z29 -> 0 | AB28: =AB27-AB29 -> 0 | AC28: =AC27-AC29 -> 0 | AE28: =AE27-AE29 -> 0 | AH28: =AH27-AH29 -> 0 | AK28: =AK27-AK29 -> 0
A29: Trading | E29: =SUM(B15:B19)-SUM(E15:E19) -> 100 | G29: =SUM(D15:D19)-SUM(G15:G19) -> 6419 | H29: =SUM(E15:E19)-SUM(H15:H19) -> -98 | J29: =SUM(G15:G19)-SUM(J15:J19) -> -21320 | K29: =SUM(H15:H19)-SUM(K15:K19) -> 1039 | M29: =SUM(J15:J19)-SUM(M15:M19) -> 245972 | N29: =SUM(K15:K19)-SUM(N15:N19) -> 0 | P29: =SUM(M15:M19)-SUM(P15:P19) -> 0 | Q29: =SUM(N15:N19)-SUM(Q15:Q19) -> 0 | S29: =SUM(P15:P19)-SUM(S15:S19) -> 0 | T29: =SUM(Q15:Q19)-SUM(T15:T19) -> 0 | V29: =SUM(S15:S19)-SUM(V15:V19) -> 0 | W29: =SUM(T15:T19)-SUM(W15:W19) -> 0 | Y29: =SUM(V15:V19)-SUM(Y15:Y19) -> 0 | Z29: =SUM(W15:W19)-SUM(Z15:Z19) -> 0 | AB29: =SUM(Y15:Y19)-SUM(AB15:AB19) -> 0 | AC29: =SUM(Z15:Z19)-SUM(AC15:AC19) -> 0 | AE29: =SUM(AB15:AB19)-SUM(AE15:AE19) -> 0 | AH29: =SUM(AE15:AE19)-SUM(AH15:AH19) -> 0 | AK29: =SUM(AH15:AH19)-SUM(AK15:AK19) -> 0
E30: =$B$26-E26 -> 9193 | G30: =$D$26-G26 -> -3374117 | H30: =$B$26-H26 -> 49649 | J30: =$D$26-J26 -> -355829 | K30: =$B$26-K26 -> 304018 | M30: =$D$26-M26 -> 65085739 | N30: =$B$26-N26 -> 304018 | P30: =$D$26-P26 -> 65085739 | Q30: =$B$26-Q26 -> 304018 | S30: =$D$26-S26 -> 65085739 | T30: =$B$26-T26 -> 304018 | V30: =$D$26-V26 -> 65085739 | W30: =$B$26-W26 -> 304018 | Y30: =$D$26-Y26 -> 65085739 | Z30: =$B$26-Z26 -> 304018 | AB30: =$D$26-AB26 -> 65085739 | AC30: =T26-AC26 -> 0 | AE30: =V26-AE26 -> 0 | AH30: =Y26-AH26 -> 0 | AK30: =AB26-AK26 -> 0 | AL30: =B26-E26 -> 9193 | AN30: =D26-G26 -> -3374117 | AO30: =AQ25-M25 -> 0 | AR30: =AQ8-AQ30 -> 0 | AS30: =AT30/#REF! -> #REF! | AT30: =AH40-AT26 -> 0 | AU30: =AI40-AU26 -> #VALUE! | AV30: =AW30/AU30 -> #VALUE! | AW30: =AK41-AW26 -> 0 | BB30: YTD | BC30: =D26-BC26 -> -15855897
A31: Monofil | E31: =E30-E32 -> 9093 | G31: =G30-G32 -> -3380536 | H31: =H30-H32 -> 49647 | J31: =J30-J32 -> -340928 | K31: =K30-K32 -> 302977 | M31: =M30-M32 -> 64854668 | N31: =N30-N32 -> 302977 | P31: =P30-P32 -> 64854668 | Q31: =Q30-Q32 -> 302977 | S31: =S30-S32 -> 64854668 | T31: =T30-T32 -> 302977 | V31: =V30-V32 -> 64854668 | W31: =W30-W32 -> 302977 | Y31: =Y30-Y32 -> 64854668 | Z31: =Z30-Z32 -> 302977 | AB31: =AB30-AB32 -> 64854668 | AC31: =AC30-AC32 -> -1041 | AE31: =AE30-AE32 -> -231071 | AH31: =AH30-AH32 -> -231071 | AK31: =AK30-AK32 -> -231071
A32: Trading | E32: =SUM($B$15:$B$19)-SUM(E15:E19) -> 100 | G32: =SUM($D$15:$D$19)-SUM(G15:G19) -> 6419 | H32: =SUM($B$15:$B$19)-SUM(H15:H19) -> 2 | J32: =SUM($D$15:$D$19)-SUM(J15:J19) -> -14901 | K32: =SUM($B$15:$B$19)-SUM(K15:K19) -> 1041 | M32: =SUM($D$15:$D$19)-SUM(M15:M19) -> 231071 | N32: =SUM($B$15:$B$19)-SUM(N15:N19) -> 1041 | P32: =SUM($D$15:$D$19)-SUM(P15:P19) -> 231071 | Q32: =SUM($B$15:$B$19)-SUM(Q15:Q19) -> 1041 | S32: =SUM($D$15:$D$19)-SUM(S15:S19) -> 231071 | T32: =SUM($B$15:$B$19)-SUM(T15:T19) -> 1041 | V32: =SUM($D$15:$D$19)-SUM(V15:V19) -> 231071 | W32: =SUM($B$15:$B$19)-SUM(W15:W19) -> 1041 | Y32: =SUM($D$15:$D$19)-SUM(Y15:Y19) -> 231071 | Z32: =SUM($B$15:$B$19)-SUM(Z15:Z19) -> 1041 | AB32: =SUM($D$15:$D$19)-SUM(AB15:AB19) -> 231071 | AC32: =SUM($B$15:$B$19)-SUM(AC15:AC19) -> 1041 | AE32: =SUM($D$15:$D$19)-SUM(AE15:AE19) -> 231071 | AH32: =SUM($D$15:$D$19)-SUM(AH15:AH19) -> 231071 | AK32: =SUM($D$15:$D$19)-SUM(AK15:AK19) -> 231071
AL33: =AC26-AL26 -> 0 | AN33: =AE26-AN26 -> 0
A34: SFG RM (FIFO) | F34: 135 | G34: =E12*F34 -> 10394595 | I34: 147 | J34: =H12*I34 -> 10828608 | L34: 144 | M34: =K12*L34 -> 0 | O34: 147 | P34: =N12*O34 -> 0 | R34: 149 | S34: =Q12*R34 -> 0 | U34: 150 | V34: =T12*U34 -> 0 | X34: 100 | AA34: 101 | AD34: 96 | AG34: 100 | AJ34: 104 | AM34: 129 | AO34: Bank Cl Stk Value | AQ34: 90525848 | AS34: 78.57 | AT34: =AT12-(AR12*AR34) -> 0
A35: FG RM (FIFO) | F35: 116 | G35: =E14*F35 -> 25158892 | I35: 217 | J35: =H14*I35 -> 38987522 | L35: 214 | M35: =K14*L35 -> 0 | O35: 218 | P35: =N14*O35 -> 0 | R35: 220 | S35: =Q14*R35 -> 0 | U35: 221 | V35: =T14*U35 -> 0 | X35: 101 | AA35: 100 | AD35: 97 | AG35: 98 | AJ35: 102 | AM35: 117 | AQ35: =V25-AQ34 -> -90525848 | AS35: 78.25 | AT35: =AT14-(AR14*AR35) -> 0
J36: =SUM(J34:J35) -> 49816130 | M36: =SUM(M34:M35) -> 0 | P36: =SUM(P34:P35) -> 0 | S36: =SUM(S34:S35) -> 0 | V36: =SUM(V34:V35) -> 0 | AJ36: =(AK15+AK19)/(AI15+AI19) -> #DIV/0! | AT36: =SUM(AT34:AT35) -> 0
A37: YARN | G37: =G25-G38 -> 29062858 | J37: =(J12+J14)-J36 -> 15379466 | M37: =(M12+M14)-M36 -> 0 | P37: =(P12+P14)-P36 -> 0 | S37: =(S12+S14)-S36 -> 0 | V37: =(V12+V14)-V36 -> 0 | AI37: Rm | AJ37: =C8-AJ8 -> 123.87463 | AK37: =ROUND((AI8*AJ37),0) -> 0 | AQ37: =AQ25+AE33-AB36 -> 0
A38: Costing Report | G38: =G25-G14+G35 -> 50289017 | J38: =J25-J37 -> 64413630 | M38: =M25-M37 -> 0 | P38: =P25-P37 -> 0 | S38: =S25-S37 -> 0 | V38: =V25-V37 -> 0 | AI38: SFG | AJ38: =C12-AJ12 -> 167 | AK38: =ROUND((AI12*AJ38),0) -> 0 | AQ38: =AQ37-AQ34 -> -90525848
A39: CSV Report | AI39: FG | AJ39: =C14-AJ14 -> 238 | AK39: =ROUND((AI14*AJ39),0) -> 0
A40: FABRIC | AI40: Trading | AK40: =ROUND(((AI15+AI19)*AJ40),0) -> 0 | AQ40: =AQ38-AB39 -> -90525848
A41: Costing Report | AK41: =SUM(AK37:AK40) -> 0
A42: CSV Report
A46: Manufacturing SFG/FG | B46: =B12+B14 -> 302977 | C46: =D46/B46 -> 214.05806 | D46: =D12+D14 -> 64854669 | E46: =E12+E14 -> 293884 | F46: =G46/E46 -> 232.18414 | G46: =G12+G14 -> 68235204 | H46: =H12+H14 -> 253330 | I46: =J46/H46 -> 257.35442 | J46: =J12+J14 -> 65195596 | K46: =K12+K14 -> 0 | L46: =M46/K46 -> #DIV/0! | M46: =M12+M14 -> 0 | N46: =N12+N14 -> 0 | O46: =P46/N46 -> #DIV/0! | P46: =P12+P14 -> 0 | Q46: =Q12+Q14 -> 0 | R46: =S46/Q46 -> #DIV/0! | S46: =S12+S14 -> 0 | T46: =T12+T14 -> 0 | U46: =V46/T46 -> #DIV/0! | V46: =V12+V14 -> 0
A47: Trading SFG/FG | B47: =B15+B19 -> 423 | C47: =D47/B47 -> 207.34279 | D47: =D15+D19 -> 87706 | E47: =E15+E19 -> 423 | F47: =G47/E47 -> 235.73995 | G47: =G15+G19 -> 99718 | H47: =H15+H19 -> 423 | I47: =J47/H47 -> 237.026 | J47: =J15+J19 -> 100262 | K47: =K15+K19 -> 0 | L47: =M47/K47 -> #DIV/0! | M47: =M15+M19 -> 0 | N47: =N15+N19 -> 0 | O47: =P47/N47 -> #DIV/0! | P47: =P15+P19 -> 0 | Q47: =Q15+Q19 -> 0 | R47: =S47/Q47 -> #DIV/0! | S47: =S15+S19 -> 0 | T47: =T15+T19 -> 0 | U47: =V47/T47 -> #DIV/0! | V47: =V15+V19 -> 0
A48: Total | B48: =SUM(B46:B47) -> 303400 | C48: =D48/B48 -> 214.0487 | D48: =SUM(D46:D47) -> 64942375 | E48: =SUM(E46:E47) -> 294307 | F48: =G48/E48 -> 232.18925 | G48: =SUM(G46:G47) -> 68334922 | H48: =SUM(H46:H47) -> 253753 | I48: =J48/H48 -> 257.32054 | J48: =SUM(J46:J47) -> 65295858 | K48: =SUM(K46:K47) -> 0 | L48: =M48/K48 -> #DIV/0! | M48: =SUM(M46:M47) -> 0 | N48: =SUM(N46:N47) -> 0 | O48: =P48/N48 -> #DIV/0! | P48: =SUM(P46:P47) -> 0 | Q48: =SUM(Q46:Q47) -> 0 | R48: =S48/Q48 -> #DIV/0! | S48: =SUM(S46:S47) -> 0 | T48: =SUM(T46:T47) -> 0 | U48: =V48/T48 -> #DIV/0! | V48: =SUM(V46:V47) -> 0
A50: Manufacturing SFG/FG | E50: =B46-E46 -> 9093 | G50: =D46-G46 -> -3380535 | H50: =E46-H46 -> 40554 | J50: =G46-J46 -> 3039608 | K50: =H46-K46 -> 253330 | M50: =J46-M46 -> 65195596 | N50: =K46-N46 -> 0 | P50: =M46-P46 -> 0 | Q50: =N46-Q46 -> 0 | S50: =P46-S46 -> 0
A51: Trading SFG/FG | E51: =B47-E47 -> 0 | G51: =D47-G47 -> -12012 | H51: =E47-H47 -> 0 | J51: =G47-J47 -> -544 | K51: =H47-K47 -> 423 | M51: =J47-M47 -> 100262 | N51: =K47-N47 -> 0 | P51: =M47-P47 -> 0 | Q51: =N47-Q47 -> 0 | S51: =P47-S47 -> 0
A52: Total | E52: =SUM(E50:E51) -> 9093 | G52: =SUM(G50:G51) -> -3392547 | H52: =SUM(H50:H51) -> 40554 | J52: =SUM(J50:J51) -> 3039064 | K52: =SUM(K50:K51) -> 253753 | M52: =SUM(M50:M51) -> 65295858 | N52: =SUM(N50:N51) -> 0 | P52: =SUM(P50:P51) -> 0 | Q52: =SUM(Q50:Q51) -> 0 | S52: =SUM(S50:S51) -> 0
K54: =B46-K46 -> 302977 | M54: =D46-M46 -> 64854669
K55: =B47-K47 -> 423 | M55: =D47-M47 -> 87706
K56: =SUM(K54:K55) -> 303400 | M56: =SUM(M54:M55) -> 64942375

Sheet Purchase
B3: HDPE | E3: MB | H3: CP | K3: TOTAL | N3: Discount
A4: MONTH | B4: Kgs | C4: Value | D4: Rate | E4: Kgs | F4: Value | G4: Rate | H4: Kgs | I4: Value | J4: Rate | K4: Kgs | L4: Value | M4: Rate | O4: HD -Discount | P4: RM -Disc
A5: APRIL | D5: =IF(B5=0,0,C5/B5) -> 0 | E5: 823 | F5: 222664 | G5: =IF(E5=0,0,F5/E5) -> 270.55164 | H5: 4 | I5: 3380 | J5: =IF(H5=0,0,I5/H5) -> 845 | K5: =B5+E5+H5 -> 827 | L5: =C5+F5+I5 -> 226044 | M5: =IF(K5=0,0,L5/K5) -> 273.33011 | O5: =ROUND((C5-N5),0) -> 0 | P5: =ROUND((O5+F5+I5),0) -> 226044
A6: MAY | B6: 76000 | C6: 11611487 | D6: =IF(B6=0,0,C6/B6) -> 152.78272 | E6: 646.8 | F6: 170591 | G6: =IF(E6=0,0,F6/E6) -> 263.74613 | H6: 2 | I6: 1820 | J6: =IF(H6=0,0,I6/H6) -> 910 | K6: =B6+E6+H6 -> 76648.8 | L6: =C6+F6+I6 -> 11783898 | M6: =IF(K6=0,0,L6/K6) -> 153.73885 | N6: 349311 | O6: =ROUND((C6-N6),0) -> 11262176 | P6: =ROUND((O6+F6+I6),0) -> 11434587
A7: JUNE | D7: =IF(B7=0,0,C7/B7) -> 0 | G7: =IF(E7=0,0,F7/E7) -> 0 | J7: =IF(H7=0,0,I7/H7) -> 0 | K7: =B7+E7+H7 -> 0 | L7: =C7+F7+I7 -> 0 | M7: =IF(K7=0,0,L7/K7) -> 0 | O7: =ROUND((C7-N7),0) -> 0 | P7: =ROUND((O7+F7+I7),0) -> 0
A8: JULY | D8: =IF(B8=0,0,C8/B8) -> 0 | G8: =IF(E8=0,0,F8/E8) -> 0 | J8: =IF(H8=0,0,I8/H8) -> 0 | K8: =B8+E8+H8 -> 0 | L8: =C8+F8+I8 -> 0 | M8: =IF(K8=0,0,L8/K8) -> 0 | O8: =ROUND((C8-N8),0) -> 0 | P8: =ROUND((O8+F8+I8),0) -> 0
A9: AUGUST | D9: =IF(B9=0,0,C9/B9) -> 0 | G9: =IF(E9=0,0,F9/E9) -> 0 | J9: =IF(H9=0,0,I9/H9) -> 0 | K9: =B9+E9+H9 -> 0 | L9: =C9+F9+I9 -> 0 | M9: =IF(K9=0,0,L9/K9) -> 0 | O9: =ROUND((C9-N9),0) -> 0 | P9: =ROUND((O9+F9+I9),0) -> 0
A10: SEPT | D10: =IF(B10=0,0,C10/B10) -> 0 | G10: =IF(E10=0,0,F10/E10) -> 0 | J10: =IF(H10=0,0,I10/H10) -> 0 | K10: =B10+E10+H10 -> 0 | L10: =C10+F10+I10 -> 0 | M10: =IF(K10=0,0,L10/K10) -> 0 | O10: =ROUND((C10-N10),0) -> 0 | P10: =ROUND((O10+F10+I10),0) -> 0
A11: OCT | D11: =IF(B11=0,0,C11/B11) -> 0 | G11: =IF(E11=0,0,F11/E11) -> 0 | J11: =IF(H11=0,0,I11/H11) -> 0 | K11: =B11+E11+H11 -> 0 | L11: =C11+F11+I11 -> 0 | M11: =IF(K11=0,0,L11/K11) -> 0 | O11: =ROUND((C11-N11),0) -> 0 | P11: =ROUND((O11+F11+I11),0) -> 0
A12: NOV | D12: =IF(B12=0,0,C12/B12) -> 0 | G12: =IF(E12=0,0,F12/E12) -> 0 | J12: =IF(H12=0,0,I12/H12) -> 0 | K12: =B12+E12+H12 -> 0 | L12: =C12+F12+I12 -> 0 | M12: =IF(K12=0,0,L12/K12) -> 0 | O12: =ROUND((C12-N12),0) -> 0 | P12: =ROUND((O12+F12+I12),0) -> 0
A13: DEC | D13: =IF(B13=0,0,C13/B13) -> 0 | G13: =IF(E13=0,0,F13/E13) -> 0 | J13: =IF(H13=0,0,I13/H13) -> 0 | K13: =B13+E13+H13 -> 0 | L13: =C13+F13+I13 -> 0 | M13: =IF(K13=0,0,L13/K13) -> 0 | O13: =ROUND((C13-N13),0) -> 0 | P13: =ROUND((O13+F13+I13),0) -> 0
A14: JAN | D14: =IF(B14=0,0,C14/B14) -> 0 | G14: =IF(E14=0,0,F14/E14) -> 0 | J14: =IF(H14=0,0,I14/H14) -> 0 | K14: =B14+E14+H14 -> 0 | L14: =C14+F14+I14 -> 0 | M14: =IF(K14=0,0,L14/K14) -> 0 | O14: =ROUND((C14-N14),0) -> 0 | P14: =ROUND((O14+F14+I14),0) -> 0
A15: FEB | D15: =IF(B15=0,0,C15/B15) -> 0 | G15: =IF(E15=0,0,F15/E15) -> 0 | J15: =IF(H15=0,0,I15/H15) -> 0 | K15: =B15+E15+H15 -> 0 | L15: =C15+F15+I15 -> 0 | M15: =IF(K15=0,0,L15/K15) -> 0 | O15: =ROUND((C15-N15),0) -> 0 | P15: =ROUND((O15+F15+I15),0) -> 0
A16: MARCH | D16: =IF(B16=0,0,C16/B16) -> 0 | G16: =IF(E16=0,0,F16/E16) -> 0 | J16: =IF(H16=0,0,I16/H16) -> 0 | K16: =B16+E16+H16 -> 0 | L16: =C16+F16+I16 -> 0 | M16: =IF(K16=0,0,L16/K16) -> 0 | O16: =ROUND((C16-N16),0) -> 0 | P16: =ROUND((O16+F16+I16),0) -> 0
A17: TOTAL | B17: =SUM(B5:B16) -> 76000 | C17: =SUM(C5:C16) -> 11611487 | D17: =IF(B17=0,0,(C17/B17)) -> 152.78272 | E17: =SUM(E5:E16) -> 1469.8 | F17: =SUM(F5:F16) -> 393255 | G17: =IF(E17=0,0,(F17/E17)) -> 267.55681 | H17: =SUM(H5:H16) -> 6 | I17: =SUM(I5:I16) -> 5200 | J17: =IF(H17=0,0,(I17/H17)) -> 866.66667 | K17: =SUM(K5:K16) -> 77475.8 | L17: =SUM(L5:L16) -> 12009942 | M17: =IF(K17=0,0,(L17/K17)) -> 155.0154 | N17: =SUM(N5:N16) -> 349311 | O17: =SUM(O5:O16) -> 11262176 | P17: =SUM(P5:P16) -> 11660631
L18: =L17-N17 -> 11660631 | N18: =N17/B17 -> 4.5961974
A20: Misc Monofil Purchases
A21: MONTH | B21: Sravya | E21: Other Purchases | H21: Consumables | I21: Monofil Fabric Purchase | L21: Yarn Purchase | O21: Mono Fabric Pur | Q21: PL cons
A22: APRIL | B22: =[2]Srvaya!B29 -> 5222 | C22: =[2]Srvaya!C29 -> 1458702 | D22: =IF(B22=0,0,C22/B22) -> 279.3378 | E22: =22528.36+5-B22-0.4 -> 17310.96 | F22: =5990692+2960-C22 -> 4534950 | G22: =IF(E22=0,0,F22/E22) -> 261.96987 | H22: 283632.3 | I22: =ROUND((B22+E22),0) -> 22533 | J22: =ROUND((C22+F22+H22),0) -> 6277284 | K22: =IF(I22=0,0,J22/I22) -> 278.58181 | L22: =3668 -> 3668 | M22: 668801 | N22: =IF(L22=0,0,M22/L22) -> 182.33397 | O22: =ROUND((I22+L22),0) -> 26201 | P22: =ROUND((J22+M22),0) -> 6946085 | Q22: 6939485.3 | R22: =P22-Q22 -> 6599.7
A23: MAY | B23: 192 | C23: 48300 | D23: =IF(B23=0,0,C23/B23) -> 251.5625 | E23: 9183.5 | F23: 2443256 | G23: =IF(E23=0,0,F23/E23) -> 266.04846 | H23: 285732.25 | I23: =ROUND((B23+E23),0) -> 9376 | J23: =ROUND((C23+F23+H23),0) -> 2777288 | K23: =IF(I23=0,0,J23/I23) -> 296.21246 | L23: 4150 | M23: 462250 | N23: =IF(L23=0,0,M23/L23) -> 111.38554 | O23: =ROUND((I23+L23),0) -> 13526 | P23: =ROUND((J23+M23),0) -> 3239538 | R23: =P23-Q23 -> 3239538
A24: JUNE | D24: =IF(B24=0,0,C24/B24) -> 0 | G24: =IF(E24=0,0,F24/E24) -> 0 | I24: =ROUND((B24+E24),0) -> 0 | J24: =ROUND((C24+F24+H24),0) -> 0 | K24: =IF(I24=0,0,J24/I24) -> 0 | N24: =IF(L24=0,0,M24/L24) -> 0 | O24: =ROUND((I24+L24),0) -> 0 | P24: =ROUND((J24+M24),0) -> 0 | R24: =P24-Q24 -> 0
A25: JULY | D25: =IF(B25=0,0,C25/B25) -> 0 | G25: =IF(E25=0,0,F25/E25) -> 0 | I25: =ROUND((B25+E25),0) -> 0 | J25: =ROUND((C25+F25+H25),0) -> 0 | K25: =IF(I25=0,0,J25/I25) -> 0 | N25: =IF(L25=0,0,M25/L25) -> 0 | O25: =ROUND((I25+L25),0) -> 0 | P25: =ROUND((J25+M25),0) -> 0 | R25: =P25-Q25 -> 0
A26: AUGUST | D26: =IF(B26=0,0,C26/B26) -> 0 | G26: =IF(E26=0,0,F26/E26) -> 0 | I26: =ROUND((B26+E26),0) -> 0 | J26: =ROUND((C26+F26+H26),0) -> 0 | K26: =IF(I26=0,0,J26/I26) -> 0 | N26: =IF(L26=0,0,M26/L26) -> 0 | O26: =ROUND((I26+L26),0) -> 0 | P26: =ROUND((J26+M26),0) -> 0 | R26: =P26-Q26 -> 0
A27: SEPT | D27: =IF(B27=0,0,C27/B27) -> 0 | G27: =IF(E27=0,0,F27/E27) -> 0 | I27: =ROUND((B27+E27),0) -> 0 | J27: =ROUND((C27+F27+H27),0) -> 0 | K27: =IF(I27=0,0,J27/I27) -> 0 | N27: =IF(L27=0,0,M27/L27) -> 0 | O27: =ROUND((I27+L27),0) -> 0 | P27: =ROUND((J27+M27),0) -> 0 | R27: =P27-Q27 -> 0
A28: OCT | D28: =IF(B28=0,0,C28/B28) -> 0 | G28: =IF(E28=0,0,F28/E28) -> 0 | I28: =ROUND((B28+E28),0) -> 0 | J28: =ROUND((C28+F28+H28),0) -> 0 | K28: =IF(I28=0,0,J28/I28) -> 0 | N28: =IF(L28=0,0,M28/L28) -> 0 | O28: =ROUND((I28+L28),0) -> 0 | P28: =ROUND((J28+M28),0) -> 0 | R28: =P28-Q28 -> 0
A29: NOV | D29: =IF(B29=0,0,C29/B29) -> 0 | G29: =IF(E29=0,0,F29/E29) -> 0 | I29: =ROUND((B29+E29),0) -> 0 | J29: =ROUND((C29+F29+H29),0) -> 0 | K29: =IF(I29=0,0,J29/I29) -> 0 | N29: =IF(L29=0,0,M29/L29) -> 0 | O29: =ROUND((I29+L29),0) -> 0 | P29: =ROUND((J29+M29),0) -> 0 | R29: =P29-Q29 -> 0
A30: DEC | D30: =IF(B30=0,0,C30/B30) -> 0 | G30: =IF(E30=0,0,F30/E30) -> 0 | I30: =B30+E30 -> 0 | J30: =ROUND(C30+F30+H30,0) -> 0 | K30: =IF(I30=0,0,J30/I30) -> 0 | N30: =IF(L30=0,0,M30/L30) -> 0 | O30: =ROUND((I30+L30),0) -> 0 | P30: =ROUND((J30+M30),0) -> 0 | R30: =P30-Q30 -> 0
A31: JAN | D31: =IF(B31=0,0,C31/B31) -> 0 | G31: =IF(E31=0,0,F31/E31) -> 0 | I31: =B31+E31 -> 0 | J31: =C31+F31+H31 -> 0 | K31: =IF(I31=0,0,J31/I31) -> 0 | N31: =IF(L31=0,0,M31/L31) -> 0 | O31: =ROUND((I31+L31),0) -> 0 | P31: =ROUND((J31+M31),0) -> 0 | R31: =P31-Q31 -> 0
A32: FEB | D32: =IF(B32=0,0,C32/B32) -> 0 | G32: =IF(E32=0,0,F32/E32) -> 0 | I32: =B32+E32 -> 0 | J32: =C32+F32+H32 -> 0 | K32: =IF(I32=0,0,J32/I32) -> 0 | N32: =IF(L32=0,0,M32/L32) -> 0 | O32: =ROUND((I32+L32),0) -> 0 | P32: =ROUND((J32+M32),0) -> 0 | R32: =P32-Q32 -> 0
A33: MARCH | D33: =IF(B33=0,0,C33/B33) -> 0 | G33: =IF(E33=0,0,F33/E33) -> 0 | I33: =B33+E33 -> 0 | J33: =C33+F33+H33 -> 0 | K33: =IF(I33=0,0,J33/I33) -> 0 | N33: =IF(L33=0,0,M33/L33) -> 0 | O33: =ROUND((I33+L33),0) -> 0 | P33: =ROUND((J33+M33),0) -> 0 | R33: =P33-Q33 -> 0
A34: TOTAL | B34: =SUM(B22:B33) -> 5414 | C34: =SUM(C22:C33) -> 1507002 | D34: =IF(B34=0,0,(C34/B34)) -> 278.35279 | E34: =SUM(E22:E33) -> 26494.46 | F34: =SUM(F22:F33) -> 6978206 | G34: =IF(E34=0,0,(F34/E34)) -> 263.38359 | H34: =SUM(H22:H33) -> 569364.55 | I34: =B34+E34 -> 31908.46 | J34: =ROUND((C34+F34+H34),0) -> 9054573 | K34: =IF(I34=0,0,J34/I34) -> 283.76716 | L34: =SUM(L22:L33) -> 7818 | M34: =SUM(M22:M33) -> 1131051 | N34: =IF(L34=0,0,(M34/L34)) -> 144.67268 | O34: =SUM(O22:O33) -> 39727 | P34: =SUM(P22:P33) -> 10185623 | Q34: =SUM(Q22:Q33) -> 6939485.3 | R34: =SUM(R22:R33) -> 3246137.7
A36: MONTH | B36: TSN | E36: MSN | H36: PPS | K36: TOTAL
A37: APRIL | B37: 544.4 | C37: 144459 | D37: =IF(B37=0,0,C37/B37) -> 265.35452 | E37: =1147.7+150+18.5 -> 1316.2 | F37: =275565+70950+10057 -> 356572 | G37: =IF(E37=0,0,F37/E37) -> 270.9102 | H37: 6124.2 | I37: 1399839 | J37: =IF(H37=0,0,I37/H37) -> 228.575 | K37: =SUM(B37,E37,H37) -> 7984.8 | L37: =SUM(C37,F37,I37) -> 1900870 | M37: =IF(K37=0,0,L37/K37) -> 238.06107
A38: MAY | B38: 192 | C38: 48300 | D38: =IF(B38=0,0,C38/B38) -> 251.5625 | E38: 1087 | F38: 261589 | G38: =IF(E38=0,0,F38/E38) -> 240.65225 | H38: 3727.5 | I38: 820165 | J38: =IF(H38=0,0,I38/H38) -> 220.03085 | K38: =SUM(B38,E38,H38) -> 5006.5 | L38: =SUM(C38,F38,I38) -> 1130054 | M38: =IF(K38=0,0,L38/K38) -> 225.71737
A39: JUNE | D39: =IF(B39=0,0,C39/B39) -> 0 | G39: =IF(E39=0,0,F39/E39) -> 0 | J39: =IF(H39=0,0,I39/H39) -> 0 | K39: =SUM(B39,E39,H39) -> 0 | L39: =SUM(C39,F39,I39) -> 0 | M39: =IF(K39=0,0,L39/K39) -> 0
A40: JULY | D40: =IF(B40=0,0,C40/B40) -> 0 | G40: =IF(E40=0,0,F40/E40) -> 0 | J40: =IF(H40=0,0,I40/H40) -> 0 | K40: =SUM(B40,E40,H40) -> 0 | L40: =SUM(C40,F40,I40) -> 0 | M40: =IF(K40=0,0,L40/K40) -> 0
A41: AUGUST | D41: =IF(B41=0,0,C41/B41) -> 0 | G41: =IF(E41=0,0,F41/E41) -> 0 | J41: =IF(H41=0,0,I41/H41) -> 0 | K41: =SUM(B41,E41,H41) -> 0 | L41: =SUM(C41,F41,I41) -> 0 | M41: =IF(K41=0,0,L41/K41) -> 0
A42: SEPT | D42: =IF(B42=0,0,C42/B42) -> 0 | G42: =IF(E42=0,0,F42/E42) -> 0 | J42: =IF(H42=0,0,I42/H42) -> 0 | K42: =SUM(B42,E42,H42) -> 0 | L42: =SUM(C42,F42,I42) -> 0 | M42: =IF(K42=0,0,L42/K42) -> 0
A43: OCT | D43: =IF(B43=0,0,C43/B43) -> 0 | G43: =IF(E43=0,0,F43/E43) -> 0 | J43: =IF(H43=0,0,I43/H43) -> 0 | K43: =SUM(B43,E43,H43) -> 0 | L43: =SUM(C43,F43,I43) -> 0 | M43: =IF(K43=0,0,L43/K43) -> 0
A44: NOV | D44: =IF(B44=0,0,C44/B44) -> 0 | G44: =IF(E44=0,0,F44/E44) -> 0 | J44: =IF(H44=0,0,I44/H44) -> 0 | K44: =SUM(B44,E44,H44) -> 0 | L44: =SUM(C44,F44,I44) -> 0 | M44: =IF(K44=0,0,L44/K44) -> 0
A45: DEC | D45: =IF(B45=0,0,C45/B45) -> 0 | G45: =IF(E45=0,0,F45/E45) -> 0 | J45: =IF(H45=0,0,I45/H45) -> 0 | K45: =SUM(B45,E45,H45) -> 0 | L45: =SUM(C45,F45,I45) -> 0 | M45: =IF(K45=0,0,L45/K45) -> 0
A46: JAN | D46: =IF(B46=0,0,C46/B46) -> 0 | G46: =IF(E46=0,0,F46/E46) -> 0 | J46: =IF(H46=0,0,I46/H46) -> 0 | K46: =SUM(B46,E46,H46) -> 0 | L46: =SUM(C46,F46,I46) -> 0 | M46: =IF(K46=0,0,L46/K46) -> 0
A47: FEB | D47: =IF(B47=0,0,C47/B47) -> 0 | G47: =IF(E47=0,0,F47/E47) -> 0 | J47: =IF(H47=0,0,I47/H47) -> 0 | K47: =SUM(B47,E47,H47) -> 0 | L47: =SUM(C47,F47,I47) -> 0 | M47: =IF(K47=0,0,L47/K47) -> 0
A48: MARCH | D48: =IF(B48=0,0,C48/B48) -> 0 | G48: =IF(E48=0,0,F48/E48) -> 0 | J48: =IF(H48=0,0,I48/H48) -> 0 | K48: =SUM(B48,E48,H48) -> 0 | L48: =SUM(C48,F48,I48) -> 0 | M48: =IF(K48=0,0,L48/K48) -> 0
A49: TOTAL | B49: =SUM(B37:B48) -> 736.4 | C49: =SUM(C37:C48) -> 192759 | D49: =IF(B49=0,0,(C49/B49)) -> 261.75856 | E49: =SUM(E37:E48) -> 2403.2 | F49: =SUM(F37:F48) -> 618161 | G49: =IF(E49=0,0,(F49/E49)) -> 257.22412 | H49: =SUM(H37:H48) -> 9851.7 | I49: =SUM(I37:I48) -> 2220004 | J49: =IF(H49=0,0,(I49/H49)) -> 225.34223 | K49: =SUM(K37:K48) -> 12991.3 | L49: =SUM(L37:L48) -> 3030924 | M49: =IF(K49=0,0,(L49/K49)) -> 233.30413
K50: =K49+B64 -> 15661.3
A51: MONTH | B51: Weed Mat | E51: Misc | H51: TOTAL | K51: TOTAL TRADING PURCHASES
A52: APRIL | B52: 1050 | C52: 239925 | D52: =IF(B52=0,0,C52/B52) -> 228.5 | E52: 455 | F52: 83784 | G52: =IF(E52=0,0,F52/E52) -> 184.14066 | H52: =B52+E52 -> 1505 | I52: =C52+F52 -> 323709 | J52: =IF(H52=0,0,I52/H52) -> 215.08904 | K52: =K37+H52 -> 9489.8 | L52: =ROUNDDOWN((L37+I52),0) -> 2224579 | M52: =IF(K52=0,0,L52/K52) -> 234.4179
A53: MAY | B53: 1620 | C53: 340200 | D53: =IF(B53=0,0,C53/B53) -> 210 | G53: =IF(E53=0,0,F53/E53) -> 0 | H53: =B53+E53 -> 1620 | I53: =C53+F53 -> 340200 | J53: =IF(H53=0,0,I53/H53) -> 210 | K53: =K38+H53 -> 6626.5 | L53: =L38+I53 -> 1470254 | M53: =IF(K53=0,0,L53/K53) -> 221.8749
A54: JUNE | D54: =IF(B54=0,0,C54/B54) -> 0 | G54: =IF(E54=0,0,F54/E54) -> 0 | H54: =B54+E54 -> 0 | I54: =C54+F54 -> 0 | J54: =IF(H54=0,0,I54/H54) -> 0 | K54: =K39+H54 -> 0 | L54: =L39+I54 -> 0 | M54: =IF(K54=0,0,L54/K54) -> 0
A55: JULY | D55: =IF(B55=0,0,C55/B55) -> 0 | G55: =IF(E55=0,0,F55/E55) -> 0 | H55: =B55+E55 -> 0 | I55: =C55+F55 -> 0 | J55: =IF(H55=0,0,I55/H55) -> 0 | K55: =K40+H55 -> 0 | L55: =L40+I55 -> 0 | M55: =IF(K55=0,0,L55/K55) -> 0
A56: AUGUST | D56: =IF(B56=0,0,C56/B56) -> 0 | G56: =IF(E56=0,0,F56/E56) -> 0 | H56: =B56+E56 -> 0 | I56: =C56+F56 -> 0 | J56: =IF(H56=0,0,I56/H56) -> 0 | K56: =K41+H56 -> 0 | L56: =L41+I56 -> 0 | M56: =IF(K56=0,0,L56/K56) -> 0
A57: SEPT | D57: =IF(B57=0,0,C57/B57) -> 0 | G57: =IF(E57=0,0,F57/E57) -> 0 | H57: =B57+E57 -> 0 | I57: =C57+F57 -> 0 | J57: =IF(H57=0,0,I57/H57) -> 0 | K57: =K42+H57 -> 0 | L57: =L42+I57 -> 0 | M57: =IF(K57=0,0,L57/K57) -> 0
A58: OCT | D58: =IF(B58=0,0,C58/B58) -> 0 | G58: =IF(E58=0,0,F58/E58) -> 0 | H58: =B58+E58 -> 0 | I58: =C58+F58 -> 0 | J58: =IF(H58=0,0,I58/H58) -> 0 | K58: =K43+H58 -> 0 | L58: =L43+I58 -> 0 | M58: =IF(K58=0,0,L58/K58) -> 0
A59: NOV | D59: =IF(B59=0,0,C59/B59) -> 0 | G59: =IF(E59=0,0,F59/E59) -> 0 | H59: =B59+E59 -> 0 | I59: =C59+F59 -> 0 | J59: =IF(H59=0,0,I59/H59) -> 0 | K59: =K44+H59 -> 0 | L59: =L44+I59 -> 0 | M59: =IF(K59=0,0,L59/K59) -> 0
A60: DEC | D60: =IF(B60=0,0,C60/B60) -> 0 | G60: =IF(E60=0,0,F60/E60) -> 0 | H60: =B60+E60 -> 0 | I60: =C60+F60 -> 0 | J60: =IF(H60=0,0,I60/H60) -> 0 | K60: =K45+H60 -> 0 | L60: =L45+I60 -> 0 | M60: =IF(K60=0,0,L60/K60) -> 0
A61: JAN | D61: =IF(B61=0,0,C61/B61) -> 0 | G61: =IF(E61=0,0,F61/E61) -> 0 | H61: =B61+E61 -> 0 | I61: =C61+F61 -> 0 | J61: =IF(H61=0,0,I61/H61) -> 0 | K61: =K46+B61 -> 0 | L61: =L46+I61 -> 0 | M61: =IF(K61=0,0,L61/K61) -> 0
A62: FEB | D62: =IF(B62=0,0,C62/B62) -> 0 | G62: =IF(E62=0,0,F62/E62) -> 0 | H62: =B62+E62 -> 0 | I62: =C62+F62 -> 0 | J62: =IF(H62=0,0,I62/H62) -> 0 | K62: =K47+B62 -> 0 | L62: =L47+I62 -> 0 | M62: =IF(K62=0,0,L62/K62) -> 0
A63: MARCH | D63: =IF(B63=0,0,C63/B63) -> 0 | G63: =IF(E63=0,0,F63/E63) -> 0 | H63: =B63+E63 -> 0 | I63: =C63+F63 -> 0 | J63: =IF(H63=0,0,I63/H63) -> 0 | K63: =K48+B63 -> 0 | L63: =L48+I63 -> 0 | M63: =IF(K63=0,0,L63/K63) -> 0
A64: TOTAL | B64: =SUM(B52:B63) -> 2670 | C64: =SUM(C52:C63) -> 580125 | D64: =IF(B64=0,0,(C64/B64)) -> 217.27528 | E64: =SUM(E52:E63) -> 455 | F64: =SUM(F52:F63) -> 83784 | G64: =IF(E64=0,0,(F64/E64)) -> 184.14066 | H64: =SUM(H52:H63) -> 3125 | I64: =SUM(I52:I63) -> 663909 | J64: =IF(H64=0,0,(I64/H64)) -> 212.45088 | K64: =SUM(K52:K63) -> 16116.3 | L64: =SUM(L52:L63) -> 3694833 | M64: =L64/K64 -> 229.26062
O66: =M66+N66 -> 0
N67: PL
M68: con | N68: 6939485.3 | O68: =P34 -> 10185623 | P68: =N68-O68 -> -3246137.7
M69: RM | N69: 226044 | O69: =L17 -> 12009942 | P69: =N69-O69 -> -11783898
M70: Tr | N70: 2224579.1 | O70: =L64 -> 3694833 | P70: =N70-O70 -> -1470253.9
N71: =SUM(N68:N70) -> 9390108.4 | O71: =SUM(O68:O70) -> 25890398 | P71: =N71-O71 -> -16500290
M72: Dis | N72: 236050 | O72: =N17 -> 349311 | P72: =N72-O72 -> -113261
N73: =N71-N72 -> 9154058.4 | O73: =O71-O72 -> 25541087 | P73: =N73-O73 -> -16387029 | Q73: =P73+R33 -> -16387029

Sheet Direct Expns
A1: Group Summary
A2: Particulars | B2: Apr | C2: May | D2: Jun | E2: Jul | F2: Aug | G2: Sep | H2: Oct | I2: Nov | J2: Dec | K2: Jan | L2: Feb | M2: Mar | N2: Total | O2: Average | S2: ='[2]Inventory Sales'!$B$11 -> 95994 | T2: ='[2]Inventory Sales'!$E$11 -> 0 | U2: ='[2]Inventory Sales'!$H$11 -> 0 | V2: ='[2]Inventory Sales'!$K$11 -> 0 | W2: ='[2]Inventory Sales'!$N$11 -> 0 | X2: ='[2]Inventory Sales'!$Q$11 -> 0 | Y2: ='[2]Inventory Sales'!$T$11 -> 0 | Z2: ='[2]Inventory Sales'!$W$11 -> 0 | AA2: ='[2]Inventory Sales'!$Z$11 -> 0 | AB2: ='[2]Inventory Sales'!$AC$11 -> 0 | AC2: ='[2]Inventory Sales'!$AF$11 -> 0 | AD2: ='[2]Inventory Sales'!$AI$11 -> 0 | AE2: =SUM(S2:AD2) -> 95994
A3: Manufacturing Expenses | O3: 2 | R3: VARIABLE & DIRECT EXPNS | S3: Apr | T3: May | U3: Jun | V3: Jul | W3: Aug | X3: Sep | Y3: Oct | Z3: Nov | AA3: Dec | AB3: Jan | AC3: Feb | AD3: Mar | AE3: Total | AG3: Avg
A4: Employees Remunaration & Benefits | B4: 3225980 | C4: 3219870 | N4: =SUM(B4:M4) -> 6445850 | O4: =ROUND((N4/$O$3),0) -> 3222925 | R4: Wages-Fabric | S4: 260305 | T4: 276414 | AE4: =SUM(S4:AD4) -> 536719 | AF4: =AE4/$AE$2 -> 5.5911724 | AG4: =AE4/12 -> 44726.583
A5: Cooli & Cartage | B5: 2180 | C5: 4224 | N5: =SUM(B5:M5) -> 6404 | O5: =ROUND((N5/$O$3),0) -> 3202 | R5: Wages-Inspection & Dispatch | S5: 641461 | T5: 614155 | AE5: =SUM(S5:AD5) -> 1255616 | AF5: =AE5/$AE$2 -> 13.080151 | AG5: =AE5/12 -> 104634.67
A6: Depreciation | B6: 125000 | C6: 125000 | N6: =SUM(B6:M6) -> 250000 | O6: =ROUND((N6/$O$3),0) -> 125000 | R6: Fabrication charges | S6: =B7+B8 -> 6451860.5 | T6: =C7+C8 -> 4564887.5 | AE6: =SUM(S6:AD6) -> 11016748 | AF6: =AE6/$AE$2 -> 114.76496 | AG6: =AE6/12 -> 918062.33
A7: Fabrication Charges - B-Lore. | B7: =1371448+4052920 -> 5424368 | C7: 3933012.5 | N7: =SUM(B7:M7) -> 9357380.5 | O7: =ROUND((N7/$O$3),0) -> 4678690 | R7: Wages-Yarn | S7: 799051 | T7: 787540 | AE7: =SUM(S7:AD7) -> 1586591 | AF7: =AE7/$AE$2 -> 16.528023 | AG7: =AE7/12 -> 132215.92
A8: Fabrication Charges-M/H & TN | B8: 1027492.5 | C8: 631875 | N8: =SUM(B8:M8) -> 1659367.5 | O8: =ROUND((N8/$O$3),0) -> 829684 | R8: Yarn Processing charges | S8: =B20 -> 425385.2 | T8: =C20 -> 421217.5 | AE8: =SUM(S8:AD8) -> 846602.7 | AF8: =AE8/$AE$2 -> 8.8193293 | AG8: =AE8/12 -> 70550.225
A9: Factory Repairs & Maintanance | B9: 39720 | C9: 66093 | N9: =SUM(B9:M9) -> 105813 | O9: =ROUND((N9/$O$3),0) -> 52907 | R9: Freight Inward | S9: =B11 -> 63932.45 | T9: =C11 -> 12148.87 | AE9: =SUM(S9:AD9) -> 76081.32 | AF9: =AE9/$AE$2 -> 0.79256329 | AG9: =AE9/12 -> 6340.11
A10: Forwarding Charges Paid | N10: =SUM(B10:M10) -> 0 | O10: =ROUND((N10/$O$3),0) -> 0 | R10: Power Bill | S10: =B16 -> 492773 | T10: =C16 -> 576288 | AE10: =SUM(S10:AD10) -> 1069061 | AF10: =AE10/$AE$2 -> 11.136748 | AG10: =AE10/12 -> 89088.417
A11: Freight Inwards | B11: 63932.45 | C11: 12148.87 | N11: =SUM(B11:M11) -> 76081.32 | O11: =ROUND((N11/$O$3),0) -> 38041 | R11: R & M-Machinery | S11: =B9 -> 39720 | T11: =C9 -> 66093 | AE11: =SUM(S11:AD11) -> 105813 | AF11: =AE11/$AE$2 -> 1.1022876 | AG11: =AE11/12 -> 8817.75
A12: Insurance on Assets | B12: 14750 | C12: 40674 | N12: =SUM(B12:M12) -> 55424 | O12: =ROUND((N12/$O$3),0) -> 27712 | R12: R & M-Electricals | S12: =B19 -> 9746 | T12: =C19 -> 26405 | AE12: =SUM(S12:AD12) -> 36151 | AF12: =AE12/$AE$2 -> 0.37659645 | AG12: =AE12/12 -> 3012.5833
A13: ITC Reversal 2018-19 | N13: =SUM(B13:K13) -> 0 | O13: =ROUND((N13/$O$3),0) -> 0 | R13: Rent | S13: =B18 -> 530150 | T13: =C18 -> 530150 | AE13: =SUM(S13:AD13) -> 1060300 | AF13: =AE13/$AE$2 -> 11.045482 | AG13: =AE13/12 -> 88358.333
A14: Medical Exps | N14: =SUM(B14:L14) -> 0 | O14: =ROUND((N14/$O$3),0) -> 0 | R14: Packing charges | AE14: =SUM(S14:AD14) -> 0 | AF14: =AE14/$AE$2 -> 0 | AG14: =AE14/12 -> 0
A15: Packing Materials (Consumables) | N15: =SUM(B15:M15) -> 0 | O15: =ROUND((N15/$O$3),0) -> 0 | R15: Misc | S15: =B5+B12+B17 -> 33730 | T15: =C5+C12+C17 -> 44898 | AE15: =SUM(S15:AD15) -> 78628 | AF15: =AE15/$AE$2 -> 0.81909286 | AG15: =AE15/12 -> 6552.3333
A16: Electricity & power | B16: 492773 | C16: 576288 | N16: =SUM(B16:M16) -> 1069061 | O16: =ROUND((N16/$O$3),0) -> 534531 | S16: =SUM(S4:S15) -> 9748114.1 | T16: =SUM(T4:T15) -> 7920196.9 | U16: =SUM(U4:U15) -> 0 | V16: =SUM(V4:V15) -> 0 | W16: =SUM(W4:W15) -> 0 | X16: =SUM(X4:X15) -> 0 | Y16: =SUM(Y4:Y15) -> 0 | Z16: =SUM(Z4:Z15) -> 0 | ... AE16: =SUM(AE4:AE15) -> 17668311 | AF16: =AE16/$AE$2 -> 184.05641 | AG16: =SUM(AG4:AG15) -> 1472359.3
A17: Processing Charges | B17: 16800 | N17: =SUM(B17:M17) -> 16800 | O17: =ROUND((N17/$O$3),0) -> 8400 | R17: Working Capital-Bank Charges | T17: ='Indirect Expns'!B42 -> 0 | AD17: ='[2]Indirect Expns'!M42+'[2]Indirect Expns'!M50 -> 0 | AE17: =SUM(S17:AD17) -> 0 | AF17: =AE17/$AE$2 -> 0 | AG17: =AE17/12 -> 0
A18: Rent | B18: =23000+334450+172700 -> 530150 | C18: 530150 | N18: =SUM(B18:M18) -> 1060300 | O18: =ROUND((N18/$O$3),0) -> 530150 | R18: Working Capital-LC | S18: ='Indirect Expns'!B43 -> 25279.82 | T18: ='Indirect Expns'!C43 -> 26301.08 | AD18: ='[2]Indirect Expns'!M43 -> 0 | AE18: =SUM(S18:AD18) -> 51580.9 | AF18: =AE18/$AE$2 -> 0.53733463 | AG18: =AE18/12 -> 4298.4083
A19: Repair & Maintenance AMC | B19: 9746 | C19: 26405 | N19: =SUM(B19:M19) -> 36151 | O19: =ROUND((N19/$O$3),0) -> 18076 | R19: Working Capital-OCC | S19: ='Indirect Expns'!B46 -> 348690 | T19: ='Indirect Expns'!C46 -> 237164 | AD19: ='[2]Indirect Expns'!M46 -> 0 | AE19: =SUM(S19:AD19) -> 585854 | AF19: =AE19/$AE$2 -> 6.1030273 | AG19: =AE19/12 -> 48821.167
A20: Yarn Processing Charges | B20: =154835+270550.2 -> 425385.2 | C20: 421217.5 | N20: =SUM(B20:M20) -> 846602.7 | O20: =ROUND((N20/$O$3),0) -> 423301 | S20: =SUM(S17:S19) -> 373969.82 | T20: =SUM(T17:T19) -> 263465.08 | U20: =SUM(U17:U19) -> 0 | V20: =SUM(V17:V19) -> 0 | W20: =SUM(W17:W19) -> 0 | X20: =SUM(X17:X19) -> 0 | Y20: =SUM(Y17:Y19) -> 0 | Z20: =SUM(Z17:Z19) -> 0 | ... AE20: =SUM(AE17:AE19) -> 637434.9 | AF20: =AE20/$AE$2 -> 6.6403619 | AG20: =SUM(AG17:AG19) -> 53119.575
O21: =+N21/$O$3 -> 0 | S21: =S16+S20 -> 10122084 | T21: =T16+T20 -> 8183662 | U21: =U16+U20 -> 0 | V21: =V16+V20 -> 0 | W21: =W16+W20 -> 0 | X21: =X16+X20 -> 0 | Y21: =Y16+Y20 -> 0 | Z21: =Z16+Z20 -> 0 | ... AE21: =AE16+AE20 -> 18305746 | AF21: =AE21/$AE$2 -> 190.69677 | AG21: =AG16+AG20 -> 1525478.8
A22: Grand Total | B22: =SUM(B4:B21) -> 11398277 | C22: =SUM(C4:C21) -> 9586957.9 | D22: =SUM(D4:D21) -> 0 | E22: =SUM(E4:E21) -> 0 | F22: =SUM(F4:F21) -> 0 | G22: =SUM(G4:G21) -> 0 | H22: =SUM(H4:H21) -> 0 | I22: =SUM(I4:I21) -> 0 | ... O22: =SUM(O4:O21) -> 10492619 | P22: 13543324 | AE22: Less Fabrn | AF22: =(AE21-AE6)/AE2 -> 75.931807
R23: FIXED EXPNS | AF23: =AE23/$AE$2 -> 0
A24: Manufacturing | B24: =ROUND((B22-(B25+B26+B27+B29)),0) -> 4205631 | C24: =ROUND((C22-(C25+C26+C27+C29)),0) -> 4233967 | D24: =ROUND((D22-(D25+D26+D27+D29)),0) -> 0 | E24: =ROUND((E22-(E25+E26+E27+E29)),0) -> 0 | F24: =ROUND((F22-(F25+F26+F27+F29)),0) -> 0 | G24: =ROUND((G22-(G25+G26+G27+G29)),0) -> 0 | H24: =ROUND((H22-(H25+H26+H27+H29)),0) -> 0 | I24: =ROUND((I22-(I25+I26+I27+I29)),0) -> 0 | ... N24: =ROUND((N22-(N25+N26+N27+N29)),0) -> 8439598 | O24: =ROUND((N24/$O$3),0) -> 4219799 | R24: Employees welfare exp | S24: =B4-(S4+S5+S7+S25+S26) -> 629089 | T24: =C4-(T4+T5+T7+T25+T26) -> 618961 | AE24: =N4-(AE4+AE5+AE7+AE25+AE26) -> 1248050 | AF24: =AE24/$AE$2 -> 13.001333 | AG24: =AE24/12 -> 104004.17
A25: ITC Reversed | B25: =B13 -> 0 | C25: =C13 -> 0 | D25: =D13 -> 0 | E25: =E13 -> 0 | F25: =F13 -> 0 | G25: =G13 -> 0 | H25: =H13 -> 0 | I25: =J13 -> 0 | K25: =K13 -> 0 | L25: =L13 -> 0 | M25: =M13 -> 0 | N25: =N13 -> 0 | O25: =+N25/$O$3 -> 0 | R25: Salaries Office | S25: 371074 | T25: 397800 | AE25: =SUM(S25:AD25) -> 768874 | AF25: =AE25/$AE$2 -> 8.0096048 | AG25: =AE25/12 -> 64072.833
A26: In House Fabrn | B26: 615785 | C26: 663103 | N26: =SUM(B26:M26) -> 1278888 | O26: =ROUND((N26/$O$3),0) -> 639444 | R26: Directors Remuneration | S26: 525000 | T26: 525000 | AE26: =SUM(S26:AD26) -> 1050000 | AF26: =AE26/$AE$2 -> 10.938184 | AG26: =AE26/12 -> 87500
A27: Fabrn | B27: =ROUND((B7+B8),0) -> 6451861 | C27: =ROUND((C7+C8),0) -> 4564888 | D27: =ROUND((D7+D8),0) -> 0 | E27: =ROUND((E7+E8),0) -> 0 | F27: =ROUND((F7+F8),0) -> 0 | G27: =ROUND((G7+G8),0) -> 0 | H27: =ROUND((H7+H8),0) -> 0 | I27: =ROUND((I7+I8),0) -> 0 | ... L27: =ROUND((L7+L8),0) -> 0 | M27: =M7+M8 -> 0 | N27: =SUM(B27:M27) -> 11016749 | O27: =ROUND((N27/$O$3),0) -> 5508375 | R27: Depreciation | S27: 125000 | T27: 125000 | AE27: =SUM(S27:AD27) -> 250000 | AF27: =AE27/$AE$2 -> 2.6043294 | AG27: =AE27/12 -> 20833.333
A28: Direct Expns | B28: =SUM(B24:B27) -> 11273277 | C28: =SUM(C24:C27) -> 9461958 | D28: =SUM(D24:D27) -> 0 | E28: =SUM(E24:E27) -> 0 | F28: =SUM(F24:F27) -> 0 | G28: =SUM(G24:G27) -> 0 | H28: =SUM(H24:H27) -> 0 | I28: =SUM(I24:I27) -> 0 | ... M28: =SUM(M24:M27) -> 0 | N28: =SUM(B28:M28) -> 20735235 | O28: =ROUND((N28/$O$3),0) -> 10367618 | R28: Admn Expns | S28: ='Indirect Expns'!B3 -> 435923.15 | T28: ='Indirect Expns'!C3 -> 342281.87 | AE28: =SUM(S28:AD28) -> 778205.02 | AF28: =AE28/$AE$2 -> 8.106809 | AG28: =AE28/12 -> 64850.418
A29: Deprn | B29: =B6 -> 125000 | C29: =C6 -> 125000 | D29: =D6 -> 0 | E29: =E6 -> 0 | F29: =F6 -> 0 | G29: =G6 -> 0 | H29: =H6 -> 0 | I29: =I6 -> 0 | ... N29: =N6 -> 250000 | O29: =ROUND((N29/$O$3),0) -> 125000 | R29: Selling Expns | S29: ='Indirect Expns'!B52 -> 67163.26 | T29: ='Indirect Expns'!C52 -> 121589.15 | AE29: =SUM(S29:AD29) -> 188752.41 | AF29: =AE29/$AE$2 -> 1.9662938 | AG29: =AE29/12 -> 15729.368
A30: Total | B30: =SUM(B28:B29) -> 11398277 | C30: =SUM(C28:C29) -> 9586958 | D30: =SUM(D28:D29) -> 0 | E30: =SUM(E28:E29) -> 0 | F30: =SUM(F28:F29) -> 0 | G30: =SUM(G28:G29) -> 0 | H30: =SUM(H28:H29) -> 0 | I30: =SUM(I28:I29) -> 0 | ... N30: =SUM(N28:N29) -> 20985235 | O30: =ROUND((N30/$O$3),0) -> 10492618 | R30: Finance Cost-Int On Term Loan | S30: ='Indirect Expns'!B50 -> 11281 | T30: ='Indirect Expns'!C50 -> 10904 | AE30: =SUM(S30:AD30) -> 22185 | AF30: =AE30/$AE$2 -> 0.23110819 | AG30: =AE30/12 -> 1848.75
A31: Fabrn | B31: =B26+B27 -> 7067646 | C31: =C26+C27 -> 5227991 | D31: =D26+D27 -> 0 | E31: =E26+E27 -> 0 | F31: =F26+F27 -> 0 | G31: =G26+G27 -> 0 | H31: =H26+H27 -> 0 | I31: =I26+I27 -> 0 | ... N31: =N26+N27 -> 12295637 | O31: =ROUND((N31/$O$3),0) -> 6147819 | R31: Finance Cost-Int On Deposits | S31: ='Indirect Expns'!B44 -> 73333 | T31: ='Indirect Expns'!C44 -> 73333 | AE31: =SUM(S31:AD31) -> 146666 | AF31: =AE31/$AE$2 -> 1.5278663 | AG31: =AE31/12 -> 12222.167
S32: =SUM(S24:S31) -> 2237863.4 | T32: =SUM(T24:T31) -> 2214869 | U32: =SUM(U24:U31) -> 0 | V32: =SUM(V24:V31) -> 0 | W32: =SUM(W24:W31) -> 0 | X32: =SUM(X24:X31) -> 0 | Y32: =SUM(Y24:Y31) -> 0 | Z32: =SUM(Z24:Z31) -> 0 | ... AE32: =SUM(AE24:AE31) -> 4452732.4 | AF32: =AE32/$AE$2 -> 46.385529 | AG32: =SUM(AG24:AG31) -> 371061.04
A33: In House Qty | B33: 7232.2 | C33: 6503.7 | N33: =SUM(B33:M33) -> 13735.9 | R33: Total Expns | S33: =S21+S32 -> 12359947 | T33: =T21+T32 -> 10398531 | U33: =U21+U32 -> 0 | V33: =V21+V32 -> 0 | W33: =W21+W32 -> 0 | X33: =X21+X32 -> 0 | Y33: =Y21+Y32 -> 0 | Z33: =Z21+Z32 -> 0 | ... AE33: =AE21+AE32 -> 22758478 | AF33: =AE33/$AE$2 -> 237.0823
A34: Fabricators Qty | B34: 76251.7 | C34: 55242.6 | N34: =SUM(B34:M34) -> 131494.3 | S34: =B37-S33 -> -0.38 | T34: =C37-T33 -> 0.029999999
A35: Yarn Processing Qty (In & Out) | B35: =47678+17129 -> 64807 | C35: 62434 | N35: =SUM(B35:M35) -> 127241 | R35: Variable-Yarn Cost | S35: =ROUND((S21-(S36+S37+S38)),0) -> 2320599 | T35: =ROUND((T21-(T36+T37+T38)),0) -> 2395041 | U35: =ROUND((U21-(U36+U37+U38)),0) -> 0 | V35: =ROUND((V21-(V36+V37+V38)),0) -> 0 | W35: =ROUND((W21-(W36+W37+W38)),0) -> 0 | X35: =ROUND((X21-(X36+X37+X38)),0) -> 0 | Y35: =ROUND((Y21-(Y36+Y37+Y38)),0) -> 0 | Z35: =ROUND((Z21-(Z36+Z37+Z38)),0) -> 0 | ... AE35: =ROUND((AE21-(AE36+AE37+AE38)),0) -> 4715641
A36: Indirect | B36: =ROUND(('Indirect Expns'!B75),0) -> 961670 | C36: =ROUND(('Indirect Expns'!C65),0) -> 811573 | D36: ='[2]Indirect Expns'!D75 -> 0 | E36: ='[2]Indirect Expns'!E75 -> 0 | F36: ='[2]Indirect Expns'!F75 -> 0 | G36: ='[2]Indirect Expns'!G75 -> 0 | H36: ='[2]Indirect Expns'!H75 -> 0 | I36: ='[2]Indirect Expns'!I75 -> 0 | J36: ='[2]Indirect Expns'!J75 -> 0 | K36: ='[2]Indirect Expns'!K75 -> 0 | ... M36: ='[2]Indirect Expns'!M75 -> 0 | N36: ='Indirect Expns'!N75 -> 1773243 | R36: Variable-Fabric Cost | S36: =SUM(S4:S6) -> 7353626.5 | T36: =SUM(T4:T6) -> 5455456.5 | U36: =SUM(U4:U6) -> 0 | V36: =SUM(V4:V6) -> 0 | W36: =SUM(W4:W6) -> 0 | X36: =SUM(X4:X6) -> 0 | Y36: =SUM(Y4:Y6) -> 0 | Z36: =SUM(Z4:Z6) -> 0 | ... AE36: =SUM(AE4:AE6) -> 12809083
A37: Total Expns | B37: =B30+B36 -> 12359947 | C37: =C30+C36 -> 10398531 | D37: =D30+D36 -> 0 | E37: =E30+E36 -> 0 | F37: =F30+F36 -> 0 | G37: =G30+G36 -> 0 | H37: =H30+H36 -> 0 | I37: =I30+I36 -> 0 | ... N37: =N30+N36 -> 22758478 | R37: Variable-Trading | S37: =99168 -> 99168 | T37: 96000 | AE37: =SUM(S37:AD37) -> 195168
R38: Variable-Finance | S38: =ROUND((S19),0) -> 348690 | T38: =ROUND((T19),0) -> 237164 | AE38: =ROUND((AE19),0) -> 585854
A39: P/L | B39: 11397815 | N39: 11397815 | R39: Fixed Cost | S39: =ROUND((S32-S40),0) -> 2112863 | T39: =ROUND((T32-T40),0) -> 2089869 | U39: =ROUND((U32-U40),0) -> 0 | V39: =ROUND((V32-V40),0) -> 0 | W39: =ROUND((W32-W40),0) -> 0 | X39: =ROUND((X32-X40),0) -> 0 | Y39: =ROUND((Y32-Y40),0) -> 0 | Z39: =ROUND((Z32-Z40),0) -> 0 | ... AE39: =ROUND((AE32-AE40),0) -> 4202732
B40: =B22-B39 -> 462.5 | C40: =C22-C39 -> 9586957.9 | D40: =D22-D39 -> 0 | E40: =E22-E39 -> 0 | F40: =F22-F39 -> 0 | G40: =G22-G39 -> 0 | H40: =H22-H39 -> 0 | I40: =I22-I39 -> 0 | ... L40: =L22-L39 -> 0 | N40: =N39-N22 -> -9587420.4 | R40: Deprn | S40: =S27 -> 125000 | T40: =T27 -> 125000 | U40: =U27 -> 0 | V40: =V27 -> 0 | W40: =W27 -> 0 | X40: =X27 -> 0 | Y40: =Y27 -> 0 | Z40: =Z27 -> 0 | ... AE40: =AE27 -> 250000
S41: =SUM(S35:S40) -> 12359946 | T41: =SUM(T35:T40) -> 10398530 | U41: =SUM(U35:U40) -> 0 | V41: =SUM(V35:V40) -> 0 | W41: =SUM(W35:W40) -> 0 | X41: =SUM(X35:X40) -> 0 | Y41: =SUM(Y35:Y40) -> 0 | Z41: =SUM(Z35:Z40) -> 0 | ... AE41: =SUM(AE35:AE40) -> 22758478
N42: =N22-N39 -> 9587420.4 | R42: Fixed Expns Break up
R43: Salaries | S43: =SUM(S24:S26) -> 1525163 | T43: =SUM(T24:T26) -> 1541761 | U43: =SUM(U24:U26) -> 0 | V43: =SUM(V24:V26) -> 0 | W43: =SUM(W24:W26) -> 0 | X43: =SUM(X24:X26) -> 0 | Y43: =SUM(Y24:Y26) -> 0 | Z43: =SUM(Z24:Z26) -> 0 | ... AE43: =SUM(AE24:AE26) -> 3066924
R44: Admn | S44: =SUM(S28) -> 435923.15 | T44: =ROUND((SUM(T28)),0) -> 342282 | U44: =ROUND((SUM(U28)),0) -> 0 | V44: =ROUND((SUM(V28)),0) -> 0 | W44: =ROUND((SUM(W28)),0) -> 0 | X44: =ROUND((SUM(X28)),0) -> 0 | Y44: =ROUND((SUM(Y28)),0) -> 0 | Z44: =ROUND((SUM(Z28)),0) -> 0 | AA44: =ROUND((SUM(AA28)),0) -> 0 | ... AE44: =ROUND((SUM(AE28)),0) -> 778205
R45: Selling | S45: =SUM(S29) -> 67163.26 | T45: =ROUND((SUM(T29)),0) -> 121589 | U45: =ROUND((SUM(U29)),0) -> 0 | V45: =ROUND((SUM(V29)),0) -> 0 | W45: =ROUND((SUM(W29)),0) -> 0 | X45: =ROUND((SUM(X29)),0) -> 0 | Y45: =ROUND((SUM(Y29)),0) -> 0 | Z45: =ROUND((SUM(Z29)),0) -> 0 | AA45: =ROUND((SUM(AA29)),0) -> 0 | ... AE45: =ROUND((SUM(AE29)),0) -> 188752
R46: Deprnn | S46: =ROUND((S27),0) -> 125000 | T46: =ROUND((T27),0) -> 125000 | U46: =ROUND((U16),0) -> 0 | V46: =ROUND((V16),0) -> 0 | W46: =ROUND((W16),0) -> 0 | X46: =ROUND((X16),0) -> 0 | Y46: =ROUND((Y16),0) -> 0 | Z46: =ROUND((Z16),0) -> 0 | AA46: =ROUND((AA16),0) -> 0 | AB46: =ROUND((AB16),0) -> 0 | ... AE46: =ROUND((AE16),0) -> 17668311
R47: Interest | S47: =SUM(S20+S30+S31) -> 458583.82 | T47: =ROUND((SUM(T20+T30+T31)),0) -> 347702 | U47: =ROUND((SUM(U20+U30+U31)),0) -> 0 | V47: =ROUND((SUM(V20+V30+V31)),0) -> 0 | W47: =ROUND((SUM(W20+W30+W31)),0) -> 0 | X47: =ROUND((SUM(X20+X30+X31)),0) -> 0 | Y47: =ROUND((SUM(Y20+Y30+Y31)),0) -> 0 | Z47: =ROUND((SUM(Z20+Z30+Z31)),0) -> 0 | AA47: =ROUND((SUM(AA20+AA30+AA31)),0) -> 0 | ... AE47: =ROUND((SUM(AE20+AE30+AE31)),0) -> 806286
S48: =SUM(S43:S47) -> 2611833.2 | T48: =SUM(T43:T47) -> 2478334 | U48: =SUM(U43:U47) -> 0 | V48: =SUM(V43:V47) -> 0 | W48: =SUM(W43:W47) -> 0 | X48: =SUM(X43:X47) -> 0 | Y48: =SUM(Y43:Y47) -> 0 | Z48: =SUM(Z43:Z47) -> 0 | ... AE48: =SUM(AE43:AE47) -> 22508478
R50: Wages | S50: =SUM(S4:S5)+S7+SUM(S24:S26) -> 3225980 | T50: =SUM(T4:T5)+T7+SUM(T24:T26) -> 3219870 | U50: =SUM(U4:U5)+U7+SUM(U24:U26) -> 0 | V50: =SUM(V4:V5)+V7+SUM(V24:V26) -> 0 | W50: =SUM(W4:W5)+W7+SUM(W24:W26) -> 0 | X50: =SUM(X4:X5)+X7+SUM(X24:X26) -> 0 | Y50: =SUM(Y4:Y5)+Y7+SUM(Y24:Y26) -> 0 | Z50: =SUM(Z4:Z5)+Z7+SUM(Z24:Z26) -> 0 | ... AE50: =SUM(AE4:AE5)+AE7+SUM(AE24:AE26) -> 6445850

Sheet Indirect Expns
A1: Indirect Expenses
A2: Particulars | B2: Apr | C2: May | D2: Jun | E2: Jul | F2: Aug | G2: Sep | H2: Oct | I2: Nov | J2: Dec | K2: Jan | L2: Feb | M2: Mar | N2: TOTAL | Q2: Veh Expns | R2: Apr | S2: May | T2: Jun | U2: Jul | V2: Aug | W2: Sep | X2: Oct | Y2: Nov | Z2: Dec | AA2: Jan | AB2: Feb | AC2: Mar | AD2: Total
A3: Administrative Expenses | B3: =SUM(B4:B40) -> 435923.15 | C3: =SUM(C4:C40) -> 342281.87 | D3: =SUM(D4:D40) -> 0 | E3: =SUM(E4:E40) -> 0 | F3: =SUM(F4:F40) -> 0 | G3: =SUM(G4:G40) -> 0 | H3: =SUM(H4:H40) -> 0 | I3: =SUM(I4:I40) -> 0 | ... M3: =SUM(M4:M40) -> 0 | N3: =SUM(B3:M3) -> 778205.02 | Q3: Tempo 6749 | R3: 29983 | S3: 33769 | T3: 39757 | U3: 69701 | AD3: =SUM(R3:AC3) -> 173210
A4: Vehicle Four Wheelers Expenses | B4: 52033 | C4: 67390 | N4: =SUM(B4:M4) -> 119423 | Q4: Leyland 8979 | R4: 3097 | S4: 3094 | T4: 2859 | U4: 3000 | AD4: =SUM(R4:AC4) -> 12050
A5: Installation & Programming Charges | N5: =SUM(B5:M5) -> 0 | Q5: Tata 407 | R5: 18818 | S5: 14494 | T5: 11754 | U5: 16711 | AD5: =SUM(R5:AC5) -> 61777
A6: Arrears of Tax | N6: =SUM(B6:M6) -> 0 | R6: =SUM(R3:R5) -> 51898 | S6: =SUM(S3:S5) -> 51357 | T6: =SUM(T3:T5) -> 54370 | U6: =SUM(U3:U5) -> 89412 | V6: =SUM(V3:V5) -> 0 | W6: =SUM(W3:W5) -> 0 | X6: =SUM(X3:X5) -> 0 | Y6: =SUM(Y3:Y5) -> 0 | ... AD6: =SUM(AD3:AD5) -> 247037
A7: Audit Fees | B7: 30000 | C7: 30000 | N7: =SUM(B7:M7) -> 60000 | Q7: SantaFe | R7: 8341 | S7: 46772 | T7: 4400 | U7: 5996 | AD7: =SUM(R7:AC7) -> 65509
A8: Books & Periodical | B8: 310 | N8: =SUM(B8:M8) -> 310 | Q8: Hyundai I20 | T8: 2996 | U8: 8710 | AD8: =SUM(R8:AC8) -> 11706
A9: Building Repair & Maintence Exp | N9: =SUM(B9:M9) -> 0 | Q9: Celerio | R9: 2995 | S9: 5016 | AD9: =SUM(R9:AC9) -> 8011
A10: Computer Stores & Maint. | B10: 38983.06 | C10: 44760 | N10: =SUM(B10:M10) -> 83743.06 | Q10: Hyundai I10 | R10: 19530 | S10: 23438 | T10: 19376 | U10: 11020 | AD10: =SUM(R10:AC10) -> 73364
A11: Conveyance Charges | B11: 3168 | C11: 1000 | N11: =SUM(B11:M11) -> 4168 | Q11: Ertiga | R11: 9608 | S11: 5569 | AD11: =SUM(R11:AC11) -> 15177
A12: Contract/Consultancy Service Chrgs 18% | N12: =SUM(B12:M12) -> 0 | Q12: Brezza | T12: 4473 | U12: 7703 | AD12: =SUM(R12:AC12) -> 12176
A13: Donation | N13: =SUM(B13:M13) -> 0 | R13: =SUM(R7:R12) -> 40474 | S13: =SUM(S7:S12) -> 80795 | T13: =SUM(T7:T12) -> 31245 | U13: =SUM(U7:U12) -> 33429 | V13: =SUM(V7:V12) -> 0 | W13: =SUM(W7:W12) -> 0 | X13: =SUM(X7:X12) -> 0 | Y13: =SUM(Y7:Y12) -> 0 | ... AD13: =SUM(AD7:AD12) -> 185943
A14: General Expenses | B14: 1461.12 | C14: 6281 | N14: =SUM(B14:M14) -> 7742.12 | R14: =R6+R13 -> 92372 | S14: =S6+S13 -> 132152 | T14: =T6+T13 -> 85615 | U14: =U6+U13 -> 122841 | V14: =V6+V13 -> 0 | W14: =W6+W13 -> 0 | X14: =X6+X13 -> 0 | Y14: =Y6+Y13 -> 0 | ... AD14: =AD6+AD13 -> 432980
A15: General Repairs & Maintanance | N15: =SUM(B15:M15) -> 0
A16: Audit Fees GST | N16: =SUM(B16:M16) -> 0
A17: Income Tax Exps | N17: =SUM(B17:M17) -> 0
A18: Medical Expenses | N18: =SUM(B18:M18) -> 0
A19: Mediclaim Exps | N19: =SUM(B19:M19) -> 0
A20: Office Maintenance | B20: 2200 | C20: 2200 | N20: =SUM(B20:M20) -> 4400
A21: Pooja Expenses | B21: 5190 | C21: 5550 | N21: =SUM(B21:M21) -> 10740
A22: Postage,Tel, Telex Charges | B22: 2442.87 | C22: 9159.87 | N22: =SUM(B22:M22) -> 11602.74
A23: Printing & Stationary | B23: 34615 | C23: 24928.8 | N23: =SUM(B23:M23) -> 59543.8
A24: Professional Charges | B24: 5500 | C24: 5500 | N24: =SUM(B24:M24) -> 11000
A25: Professional Consultation Charges | C25: 31500 | N25: =SUM(B25:M25) -> 31500
A26: Rates & Taxes | N26: =SUM(B26:M26) -> 0
A27: Registration & Renewal | B27: 10000 | N27: =SUM(B27:M27) -> 10000
A28: Repairs & Service Charges | N28: =SUM(B28:M28) -> 0
A29: Freight charges | N29: =SUM(B29:M29) -> 0
A30: Round Off (+-) | B30: 11.7 | C30: 23.95 | N30: =SUM(B30:M30) -> 35.65
A31: Seminar, Training, Dvpt. Exp. | N31: =SUM(B31:M31) -> 0
A32: Software maintenance | B32: 99440.58 | C32: 26368.97 | N32: =SUM(B32:M32) -> 125809.55
A33: RCM Freight paid | N33: =SUM(B33:M33) -> 0
A34: Subscription & Membership | B34: 53513 | N34: =SUM(B34:M34) -> 53513
A35: TDS - Interest on TDS | C35: 9 | N35: =SUM(B35:M35) -> 9
A36: Telephone Charges-Airtel | B36: 16046.82 | C36: 6603.28 | N36: =SUM(B36:M36) -> 22650.1
A37: Telephone Charges-BSNL | B37: 4008 | C37: 4007 | N37: =SUM(B37:M37) -> 8015
A38: Fluctuation In Foreign Currency | N38: =SUM(B38:M38) -> 0
A39: VEHICLE MAINTENANCE | N39: =SUM(B39:M39) -> 0
A40: Watch & Ward | B40: 77000 | C40: 77000 | N40: =SUM(B40:M40) -> 154000
A41: Financial Expenses | B41: =SUM(B42:B51) -> 458583.82 | C41: =SUM(C42:C51) -> 347702.08 | D41: =SUM(D42:D51) -> 0 | E41: =SUM(E42:E51) -> 0 | F41: =SUM(F42:F51) -> 0 | G41: =SUM(G42:G51) -> 0 | H41: =SUM(H42:H51) -> 0 | I41: =SUM(I42:I51) -> 0 | ... M41: =SUM(M42:M51) -> 0 | N41: =SUM(B41:M41) -> 806285.9
A42: Bank Charges | N42: =SUM(B42:M42) -> 0
A43: Interest & Bank Charges -ILC | B43: 25279.82 | C43: 26301.08 | N43: =SUM(B43:M43) -> 51580.9
A44: Interest on Unsecured Loans (Monthly) | B44: 73333 | C44: 73333 | N44: =SUM(B44:M44) -> 146666
A45: Interest on Car Loans | N45: =SUM(B45:M45) -> 0
A46: Interest on O.C.C | B46: 348690 | C46: 237164 | N46: =SUM(B46:M46) -> 585854
A47: Interest on PNB Housing Finance | N47: =SUM(B47:M47) -> 0
A48: Interest On Term Loan | N48: =SUM(B48:M48) -> 0
A49: Loan Processing charges | N49: =SUM(B49:M49) -> 0
A50: Interest to others (VSL) | B50: 11281 | C50: 10904 | N50: =SUM(B50:M50) -> 22185
A51: Interest to Depositors | N51: =SUM(B51:M51) -> 0
A52: Selling Expenses | B52: =SUM(B53:B64) -> 67163.26 | C52: =SUM(C53:C64) -> 121589.15 | D52: =SUM(D53:D64) -> 0 | E52: =SUM(E53:E64) -> 0 | F52: =SUM(F53:F64) -> 0 | G52: =SUM(G53:G64) -> 0 | H52: =SUM(H53:H64) -> 0 | I52: =SUM(I53:I64) -> 0 | ... M52: =SUM(M53:M64) -> 0 | N52: =SUM(B52:M52) -> 188752.41
A53: Advertisement | N53: =SUM(B53:M53) -> 0
A54: Lab Testing Charges | N54: =SUM(B54:M54) -> 0
A55: Commission on sales | N55: =SUM(B55:M55) -> 0
A56: Debit Balances Written Off | B56: 1.26 | C56: 21.15 | N56: =SUM(B56:M56) -> 22.41
A57: Freight Outwards/Ocean Freight | B57: 62810 | C57: 86900 | N57: =SUM(B57:M57) -> 149710
A58: Gift Articles | N58: =SUM(B58:M58) -> 0
A59: Marketing Expenses | B59: 3040 | C59: 4500 | N59: =SUM(B59:M59) -> 7540
A60: Sales Promotion | N60: =SUM(B60:M60) -> 0
A61: Transportation charges | B61: 1312 | C61: 30168 | N61: =SUM(B61:M61) -> 31480
A62: Travelling Expenses | N62: =SUM(B62:M62) -> 0
A63: Discount Allowed | N63: =SUM(B63:M63) -> 0
A64: Discount | N64: =SUM(B64:M64) -> 0
A65: Grand Total | B65: =SUM(B52+B41+B3) -> 961670.23 | C65: =SUM(C52+C41+C3) -> 811573.1 | D65: =SUM(D52+D41+D3) -> 0 | E65: =SUM(E52+E41+E3) -> 0 | F65: =SUM(F52+F41+F3) -> 0 | G65: =SUM(G52+G41+G3) -> 0 | H65: =SUM(H52+H41+H3) -> 0 | I65: =SUM(I52+I41+I3) -> 0 | ... N65: =SUM(N52+N41+N3) -> 1773243.3
A67: Admn | B67: =ROUND((B3),0) -> 435923 | C67: =ROUND((C3),0) -> 342282 | D67: =ROUND((D3),0) -> 0 | E67: =ROUND((E3),0) -> 0 | F67: =ROUND((F3),0) -> 0 | G67: =ROUND((G3),0) -> 0 | H67: =ROUND((H3),0) -> 0 | I67: =ROUND((I3),0) -> 0 | ... N67: =ROUND((N3),0) -> 778205
A68: =A52 -> Selling Expenses | B68: =ROUND((B52),0) -> 67163 | C68: =ROUND((C52),0) -> 121589 | D68: =ROUND((D52),0) -> 0 | E68: =ROUND((E52),0) -> 0 | F68: =ROUND((F52),0) -> 0 | G68: =ROUND((G52),0) -> 0 | H68: =ROUND((H52),0) -> 0 | I68: =ROUND((I52),0) -> 0 | ... N68: =ROUND((N52),0) -> 188752 | O68: =O42 -> 0 | P68: =P42 -> 0 | AE68: =AE42 -> 0 | AF68: =AF42 -> 0 | AG68: =AG42 -> 0 | AH68: =AH42 -> 0 | AI68: =AI42 -> 0 | AJ68: =AJ42 -> 0 | AK68: =AK42 -> 0 | AL68: =AL42 -> 0 | ... IT68: =IT42 -> 0
A69: Indirect W/o Fin | B69: =B67+B68 -> 503086 | C69: =C67+C68 -> 463871 | D69: =D67+D68 -> 0 | E69: =E67+E68 -> 0 | F69: =F67+F68 -> 0 | G69: =G67+G68 -> 0 | H69: =H67+H68 -> 0 | I69: =I67+I68 -> 0 | ... N69: =N67+N68 -> 966957 | O69: =O45 -> 0 | P69: =P45 -> 0 | AE69: =AE45 -> 0 | AF69: =AF45 -> 0 | AG69: =AG45 -> 0 | AH69: =AH45 -> 0 | AI69: =AI45 -> 0 | AJ69: =AJ45 -> 0 | AK69: =AK45 -> 0 | AL69: =AL45 -> 0 | ... IT69: =IT45 -> 0
A70: W Cap Int | B70: =ROUND((B42+B43+B46),0) -> 373970 | C70: =ROUND((C42+C43+C46),0) -> 263465 | D70: =ROUND((D42+D43+D46),0) -> 0 | E70: =ROUND((E42+E43+E46),0) -> 0 | F70: =ROUND((F42+F43+F46),0) -> 0 | G70: =ROUND((G42+G43+G46),0) -> 0 | H70: =ROUND((H42+H43+H46),0) -> 0 | I70: =ROUND((I42+I43+I46),0) -> 0 | ... K70: =ROUND((K42+K43+K46),0) -> 0 | L70: =ROUND((L42+L43+L46),0)+L49 -> 0 | M70: =ROUND((M42+M43+M46),0) -> 0 | N70: =ROUND((N42+N43+N46),0) -> 637435 | Q70: =Q44 -> 0 | R70: =R44 -> 0 | S70: =S44 -> 0 | T70: =T44 -> 0 | U70: =U44 -> 0 | V70: =V44 -> 0 | W70: =W44 -> 0 | X70: =X44 -> 0 | ... AD70: =AD44 -> 0
A71: Term Loan | B71: =ROUND((B45),0) -> 0 | C71: =ROUND((C45),0) -> 0 | D71: =D49 -> 0 | E71: 0 | F71: =ROUND((F45),0) -> 0 | G71: =ROUND((G45),0) -> 0 | H71: =ROUND((H45),0) -> 0 | I71: =ROUND((I45),0) -> 0 | J71: =ROUND((J45),0) -> 0 | K71: =ROUND((K45),0) -> 0 | L71: =ROUND((L45),0) -> 0 | M71: =ROUND((M45),0) -> 0 | N71: =N49 -> 0 | Q71: =Q47 -> 0 | R71: =R47 -> 0 | S71: =S47 -> 0 | T71: =T47 -> 0 | U71: =U47 -> 0 | V71: =V47 -> 0 | W71: =W47 -> 0 | X71: =X47 -> 0 | ... AD71: =AD47 -> 0
A72: COVID LOAN Int | B72: =ROUND((B48),0) -> 0 | C72: =ROUND((C48),0) -> 0 | D72: =ROUND((D48),0) -> 0 | E72: =ROUND((E48),0) -> 0 | F72: =ROUND((F48),0) -> 0 | G72: =ROUND((G48),0) -> 0 | H72: 0 | I72: =ROUND((I48),0) -> 0 | J72: =ROUND((J48),0) -> 0 | K72: =ROUND((K48),0) -> 0 | L72: =ROUND((L48),0) -> 0 | M72: =ROUND((M48),0) -> 0 | N72: =ROUND((N48),0) -> 0
A73: Int On Others | B73: =ROUND((B44+B50+B51),0) -> 84614 | C73: =ROUND((C44+C50+C51),0) -> 84237 | D73: =ROUND((D44+D50+D51),0) -> 0 | E73: =ROUND((E44+E50+E51),0) -> 0 | F73: =ROUND((F44+F50+F51),0) -> 0 | G73: =ROUND((G44+G50+G51),0) -> 0 | H73: =ROUND((H44+H50+H51),0) -> 0 | I73: =ROUND((I44+I50+I51),0) -> 0 | ... N73: =ROUND((N44+N50+N51),0) -> 168851
A74: FIN Cost | B74: =SUM(B70:B73) -> 458584 | C74: =SUM(C70:C73) -> 347702 | D74: =SUM(D70:D73) -> 0 | E74: =SUM(E70:E73) -> 0 | F74: =SUM(F70:F73) -> 0 | G74: =SUM(G70:G73) -> 0 | H74: =SUM(H70:H73) -> 0 | I74: =SUM(I70:I73) -> 0 | ... N74: =SUM(N70:N73) -> 806286
A75: Indirect COST | B75: =B69+B74 -> 961670 | C75: =C69+C74 -> 811573 | D75: =D69+D74 -> 0 | E75: =E69+E74 -> 0 | F75: =F69+F74 -> 0 | G75: =G69+G74 -> 0 | H75: =H69+H74 -> 0 | I75: =I69+I74 -> 0 | ... N75: =N69+N74 -> 1773243
J76: =J65-J75 -> 0 | K76: =K65-K75 -> 0 | L76: =L65-L75 -> 0 | M76: =M65-M75 -> 0
A78: P/L | B78: 961720.23 | N78: 961720.23
B79: =B65-B78 -> -50 | C79: =C65-C78 -> 811573.1 | D79: =D65-D78 -> 0 | E79: =E65-E78 -> 0 | F79: =F65-F78 -> 0 | G79: =G65-G78 -> 0 | H79: =H65-H78 -> 0 | I79: =I65-I78 -> 0 | ... N79: =N65-N78 -> 811523.1
N80: =K79-N79+L79 -> -811523.1

Sheet CONSUMPTION
A1: Quantitative Analysis of Raw Materials for the Financial Year 2025-26
A2: Particulars | B2: 45748 | E2: 45778 | H2: 45809 | K2: 45474 | N2: 45870 | Q2: 45901 | T2: 45931 | W2: 45962 | Z2: 45992 | AC2: 45658 | AF2: 45689 | AI2: 45717 | AL2: Total | AO2: Srp
A3: HDPE
A4: Opening Stock | B4: ='Stock Valuation (FIFO)'!B5 -> 141140 | C4: =IF(B4=0,0,(D4/B4)) -> 121.97507 | D4: ='Stock Valuation (FIFO)'!D5 -> 17215561 | E4: =B9 -> 75695 | F4: =IF(E4=0,0,(G4/E4)) -> 135.72071 | G4: =D9 -> 10273379 | H4: =E9 -> 90040 | I4: =IF(H4=0,0,(J4/H4)) -> 152.60895 | J4: =G9 -> 13740910 | K4: =H9 -> 0 | L4: =IF(K4=0,0,(M4/K4)) -> 0 | M4: =J9 -> 0 | N4: =K9 -> 0 | O4: =IF(N4=0,0,(P4/N4)) -> 0 | P4: =M9 -> 0 | Q4: =N9 -> 0 | R4: =IF(Q4=0,0,(S4/Q4)) -> 0 | S4: =P9 -> 0 | T4: =Q9 -> 0 | U4: =IF(T4=0,0,(V4/T4)) -> 0 | V4: =S9 -> 0 | W4: =T9 -> 0 | X4: =IF(W4=0,0,(Y4/W4)) -> 0 | Y4: =V9 -> 0 | Z4: =W9 -> 0 | AA4: =IF(Z4=0,0,(AB4/Z4)) -> 0 | AB4: =Y9 -> 0 | AC4: =Z9 -> 0 | AD4: =IF(AC4=0,0,(AE4/AC4)) -> 0 | AE4: =AB9 -> 0 | AF4: =AC9 -> 0 | AG4: =IF(AF4=0,0,(AH4/AF4)) -> 0 | AH4: =AE9 -> 0 | AI4: =AF9 -> 0 | AJ4: =IF(AI4=0,0,(AK4/AI4)) -> 0 | AK4: =AH9 -> 0 | AL4: =B4 -> 141140 | AM4: =IF(AL4=0,0,(AN4/AL4)) -> 121.97507 | AN4: =D4 -> 17215561
A5: Add:- Purchases | B5: =ROUND((Purchase!$B5),0) -> 0 | C5: =IF(B5=0,0,(D5/B5)) -> 0 | D5: =Purchase!$O5 -> 0 | E5: =ROUND((Purchase!$B6),0) -> 76000 | F5: =IF(E5=0,0,(G5/E5)) -> 148.18653 | G5: =Purchase!$O6 -> 11262176 | H5: =Purchase!B7 -> 0 | I5: =IF(H5=0,0,(J5/H5)) -> 0 | J5: =Purchase!$O7 -> 0 | K5: =Purchase!B8 -> 0 | L5: =IF(K5=0,0,(M5/K5)) -> 0 | M5: =Purchase!$O8 -> 0 | N5: =Purchase!B9 -> 0 | O5: =IF(N5=0,0,(P5/N5)) -> 0 | P5: =Purchase!$O9 -> 0 | Q5: =Purchase!B10 -> 0 | R5: =IF(Q5=0,0,(S5/Q5)) -> 0 | S5: =Purchase!$O10 -> 0 | T5: =Purchase!B11 -> 0 | U5: =IF(T5=0,0,(V5/T5)) -> 0 | V5: =Purchase!$O11 -> 0 | W5: =Purchase!B12 -> 0 | X5: =IF(W5=0,0,(Y5/W5)) -> 0 | Y5: =Purchase!$O12 -> 0 | Z5: =Purchase!B13 -> 0 | AA5: =IF(Z5=0,0,(AB5/Z5)) -> 0 | AB5: =Purchase!$O13 -> 0 | AC5: =Purchase!B14 -> 0 | AD5: =IF(AC5=0,0,(AE5/AC5)) -> 0 | AE5: =Purchase!$O14 -> 0 | AF5: =Purchase!B15 -> 0 | AG5: =IF(AF5=0,0,(AH5/AF5)) -> 0 | AH5: =Purchase!$O15 -> 0 | AI5: =Purchase!B16 -> 0 | AJ5: =IF(AI5=0,0,(AK5/AI5)) -> 0 | AK5: =Purchase!$O16 -> 0 | AL5: =SUM(B5,E5,H5,K5,N5,Q5,T5,W5,Z5,AC5,AF5,AI5) -> 76000 | AM5: =IF(AL5=0,0,(AN5/AL5)) -> 148.18653 | AN5: =SUM(D5,G5,J5,M5,P5,S5,V5,Y5,AB5,AE5,AH5,AK5) -> 11262176 | AO5: =Purchase!O17 -> 11262176 | AP5: =AN5-AO5 -> 0
A6: Add:- Consumables | C6: =IF(B6=0,0,(D6/B6)) -> 0 | AL6: =SUM(B6:AI6) -> 0
A7: Less:- Purchase return | C7: =IF(B7=0,0,(D7/B7)) -> 0 | AL7: =SUM(B7:AI7) -> 0
A8: Less :- Sales | B8: ='Inventory Sales'!B25 -> 0 | C8: =IF(B8=0,0,(D8/B8)) -> 0 | D8: ='Inventory Sales'!D42-(D16+D24) -> 0 | E8: ='Inventory Sales'!E25 -> 0 | F8: =IF(E8=0,0,(G8/E8)) -> 0 | H8: ='Inventory Sales'!H25 -> 0 | I8: =IF(H8=0,0,(J8/H8)) -> 0 | J8: ='Inventory Sales'!J42-(J16+J24) -> 0 | K8: ='Inventory Sales'!K25 -> 0 | L8: =IF(K8=0,0,(M8/K8)) -> 0 | M8: ='Inventory Sales'!M42-(M16+M24) -> 0 | N8: ='Inventory Sales'!N25 -> 0 | O8: =IF(N8=0,0,(P8/N8)) -> 0 | P8: ='Inventory Sales'!P42-(P16+P24) -> 0 | Q8: ='Inventory Sales'!Q25 -> 0 | R8: =IF(Q8=0,0,(S8/Q8)) -> 0 | S8: ='Inventory Sales'!S42-(S16+S24) -> 0 | T8: ='Inventory Sales'!T25 -> 0 | U8: =IF(T8=0,0,(V8/T8)) -> 0 | V8: ='Inventory Sales'!V42-(V16+V24) -> 0 | W8: ='Inventory Sales'!W25 -> 0 | X8: =IF(W8=0,0,(Y8/W8)) -> 0 | Y8: ='Inventory Sales'!Y42-(Y16+Y24) -> 0 | Z8: ='Inventory Sales'!Z25 -> 0 | AA8: =IF(Z8=0,0,(AB8/Z8)) -> 0 | AB8: ='Inventory Sales'!AB42-(AB16+AB24) -> 0 | AC8: ='Inventory Sales'!AC25 -> 0 | AD8: =IF(AC8=0,0,(AE8/AC8)) -> 0 | AE8: ='Inventory Sales'!AE42-(AE16+AE24) -> 0 | AF8: ='Inventory Sales'!AF25 -> 0 | AG8: =IF(AF8=0,0,(AH8/AF8)) -> 0 | AH8: ='Inventory Sales'!AH42-(AH16+AH24) -> 0 | AI8: ='Inventory Sales'!AI25 -> 0 | AJ8: =IF(AI8=0,0,(AK8/AI8)) -> 0 | AK8: ='Inventory Sales'!AK42-(AK16+AK24) -> 0 | AL8: =SUM(B8,E8,H8,K8,N8,Q8,T8,W8,Z8,AC8,AF8,AI8) -> 0 | AM8: =IF(AL8=0,0,(AN8/AL8)) -> 0 | AN8: =SUM(D8,G8,J8,M8,P8,S8,V8,Y8,AB8,AE8,AH8,AK8) -> 0 | AO8: ='Inventory Sales'!AN42-(AO16+AO24) -> -125 | AP8: =AN8-AO8 -> 125
A9: Closing Stock | B9: ='Stock Valuation (FIFO)'!E5 -> 75695 | C9: =IF(B9=0,0,(D9/B9)) -> 135.72071 | D9: ='Stock Valuation (FIFO)'!G5 -> 10273379 | E9: ='Stock Valuation (FIFO)'!H5 -> 90040 | F9: =IF(E9=0,0,(G9/E9)) -> 152.60895 | G9: ='Stock Valuation (FIFO)'!J5 -> 13740910 | H9: ='Stock Valuation (FIFO)'!K5 -> 0 | I9: =IF(H9=0,0,(J9/H9)) -> 0 | J9: ='Stock Valuation (FIFO)'!M5 -> 0 | K9: ='Stock Valuation (FIFO)'!N5 -> 0 | L9: =IF(K9=0,0,(M9/K9)) -> 0 | M9: ='Stock Valuation (FIFO)'!P5 -> 0 | N9: ='Stock Valuation (FIFO)'!Q5 -> 0 | O9: =IF(N9=0,0,(P9/N9)) -> 0 | P9: ='Stock Valuation (FIFO)'!S5 -> 0 | Q9: ='Stock Valuation (FIFO)'!T5 -> 0 | R9: =IF(Q9=0,0,(S9/Q9)) -> 0 | S9: ='Stock Valuation (FIFO)'!V5 -> 0 | T9: ='Stock Valuation (FIFO)'!W5 -> 0 | U9: =IF(T9=0,0,(V9/T9)) -> 0 | V9: ='Stock Valuation (FIFO)'!Y5 -> 0 | W9: ='Stock Valuation (FIFO)'!Z5 -> 0 | X9: =IF(W9=0,0,(Y9/W9)) -> 0 | Y9: ='Stock Valuation (FIFO)'!AB5 -> 0 | Z9: ='Stock Valuation (FIFO)'!AC5 -> 0 | AA9: =IF(Z9=0,0,(AB9/Z9)) -> 0 | AB9: ='Stock Valuation (FIFO)'!AE5 -> 0 | AC9: ='Stock Valuation (FIFO)'!AF5 -> 0 | AD9: =IF(AC9=0,0,(AE9/AC9)) -> 0 | AE9: ='Stock Valuation (FIFO)'!AH5 -> 0 | AF9: ='Stock Valuation (FIFO)'!AI5 -> 0 | AG9: =IF(AF9=0,0,(AH9/AF9)) -> 0 | AH9: ='Stock Valuation (FIFO)'!AK5 -> 0 | AI9: ='Stock Valuation (FIFO)'!AL5 -> 0 | AJ9: =IF(AI9=0,0,(AK9/AI9)) -> 0 | AK9: ='Stock Valuation (FIFO)'!AN5 -> 0 | AL9: =AI9 -> 0 | AM9: =IF(AL9=0,0,(AN9/AL9)) -> 0 | AN9: =AK9 -> 0 | AO9: ='Stock Valuation (FIFO)'!AN5 -> 0 | AP9: =AN9-AO9 -> 0
A10: Consumption HDPE | B10: =(B4+B5+B6)-(B8+B9) -> 65445 | C10: =IF(B10=0,0,(D10/B10)) -> 106.07658 | D10: =(D4+D5)-(D8+D9) -> 6942182 | E10: =(E4+E5)-(E8+E9) -> 61655 | F10: =IF(E10=0,0,(G10/E10)) -> 126.42357 | G10: =(G4+G5)-(G8+G9) -> 7794645 | H10: =(H4+H5)-(H8+H9) -> 90040 | I10: =IF(H10=0,0,(J10/H10)) -> 152.60895 | J10: =(J4+J5)-(J8+J9) -> 13740910 | K10: =(K4+K5)-(K8+K9) -> 0 | L10: =IF(K10=0,0,(M10/K10)) -> 0 | M10: =(M4+M5)-(M8+M9) -> 0 | N10: =(N4+N5)-(N8+N9) -> 0 | O10: =IF(N10=0,0,(P10/N10)) -> 0 | P10: =(P4+P5)-(P8+P9) -> 0 | Q10: =(Q4+Q5)-(Q8+Q9) -> 0 | R10: =IF(Q10=0,0,(S10/Q10)) -> 0 | S10: =(S4+S5)-(S8+S9) -> 0 | T10: =(T4+T5)-(T8+T9) -> 0 | U10: =IF(T10=0,0,(V10/T10)) -> 0 | V10: =(V4+V5)-(V8+V9) -> 0 | W10: =(W4+W5)-(W8+W9) -> 0 | X10: =IF(W10=0,0,(Y10/W10)) -> 0 | Y10: =(Y4+Y5)-(Y8+Y9) -> 0 | Z10: =(Z4+Z5)-(Z8+Z9) -> 0 | AA10: =IF(Z10=0,0,(AB10/Z10)) -> 0 | AB10: =(AB4+AB5)-(AB8+AB9) -> 0 | AC10: =(AC4+AC5)-(AC8+AC9) -> 0 | AD10: =IF(AC10=0,0,(AE10/AC10)) -> 0 | AE10: =(AE4+AE5)-(AE8+AE9) -> 0 | AF10: =(AF4+AF5)-(AF8+AF9) -> 0 | AG10: =IF(AF10=0,0,(AH10/AF10)) -> 0 | AH10: =(AH4+AH5)-(AH8+AH9) -> 0 | AI10: =(AI4+AI5)-(AI8+AI9) -> 0 | AJ10: =IF(AI10=0,0,(AK10/AI10)) -> 0 | AK10: =(AK4+AK5)-(AK8+AK9) -> 0 | AL10: =(AL4+AL5)-(AL8+AL9) -> 217140 | AM10: =IF(AL10=0,0,(AN10/AL10)) -> 131.1492 | AN10: =(AN4+AN5)-(AN8+AN9) -> 28477737
A11: MB
A12: Opening Stock | B12: ='Stock Valuation (FIFO)'!B6 -> 2330 | C12: =IF(B12=0,0,(D12/B12)) -> 226.92532 | D12: ='Stock Valuation (FIFO)'!D6 -> 528736 | E12: =B17 -> 2392 | F12: =IF(E12=0,0,(G12/E12)) -> 245.33152 | G12: =D17 -> 586833 | H12: =E17 -> 2239 | I12: =IF(H12=0,0,(J12/H12)) -> 258.70835 | J12: =G17 -> 579248 | K12: =H17 -> 0 | L12: =IF(K12=0,0,(M12/K12)) -> 0 | M12: =J17 -> 0 | N12: =K17 -> 0 | O12: =IF(N12=0,0,(P12/N12)) -> 0 | P12: =M17 -> 0 | Q12: =N17 -> 0 | R12: =IF(Q12=0,0,(S12/Q12)) -> 0 | S12: =P17 -> 0 | T12: =Q17 -> 0 | U12: =IF(T12=0,0,(V12/T12)) -> 0 | V12: =S17 -> 0 | W12: =T17 -> 0 | X12: =IF(W12=0,0,(Y12/W12)) -> 0 | Y12: =V17 -> 0 | Z12: =W17 -> 0 | AA12: =IF(Z12=0,0,(AB12/Z12)) -> 0 | AB12: =Y17 -> 0 | AC12: =Z17 -> 0 | AD12: =IF(AC12=0,0,(AE12/AC12)) -> 0 | AE12: =AB17 -> 0 | AF12: =AC17 -> 0 | AG12: =IF(AF12=0,0,(AH12/AF12)) -> 0 | AH12: =AE17 -> 0 | AI12: =AF17 -> 0 | AJ12: =IF(AI12=0,0,(AK12/AI12)) -> 0 | AK12: =AH17 -> 0 | AL12: =B12 -> 2330 | AM12: =IF(AL12=0,0,(AN12/AL12)) -> 226.92532 | AN12: =D12 -> 528736
A13: Add:- Purchases | B13: =ROUND((Purchase!$E5),0) -> 823 | C13: =IF(B13=0,0,(D13/B13)) -> 270.55164 | D13: =ROUND((Purchase!$F5),0) -> 222664 | E13: =ROUND((Purchase!$E6),) -> 647 | F13: =IF(E13=0,0,(G13/E13)) -> 263.66461 | G13: =ROUND((Purchase!$F6),0) -> 170591 | H13: =ROUND((Purchase!$E7),0) -> 0 | I13: =IF(H13=0,0,(J13/H13)) -> 0 | J13: =ROUND((Purchase!$F7),0) -> 0 | K13: =ROUND((Purchase!$E8),0) -> 0 | L13: =IF(K13=0,0,(M13/K13)) -> 0 | M13: =ROUND((Purchase!$F8),0) -> 0 | N13: =ROUND((Purchase!$E9),0) -> 0 | O13: =IF(N13=0,0,(P13/N13)) -> 0 | P13: =ROUND((Purchase!$F9),0) -> 0 | Q13: =ROUND((Purchase!$E10),0) -> 0 | R13: =IF(Q13=0,0,(S13/Q13)) -> 0 | S13: =ROUND((Purchase!$F10),0) -> 0 | T13: =ROUND((Purchase!$E11),0) -> 0 | U13: =IF(T13=0,0,(V13/T13)) -> 0 | V13: =ROUND((Purchase!$F11),0) -> 0 | W13: =ROUND((Purchase!$E12),0) -> 0 | X13: =IF(W13=0,0,(Y13/W13)) -> 0 | Y13: =ROUND((Purchase!$F12),) -> 0 | Z13: =ROUND((Purchase!E13),0) -> 0 | AA13: =IF(Z13=0,0,(AB13/Z13)) -> 0 | AB13: =ROUND((Purchase!F13),0) -> 0 | AC13: =ROUND((Purchase!E14),0) -> 0 | AD13: =IF(AC13=0,0,(AE13/AC13)) -> 0 | AE13: =ROUND((Purchase!F14),0) -> 0 | AF13: =ROUND((Purchase!E15),0) -> 0 | AG13: =IF(AF13=0,0,(AH13/AF13)) -> 0 | AH13: =ROUND((Purchase!F15),0) -> 0 | AI13: =Purchase!E16 -> 0 | AJ13: =IF(AI13=0,0,(AK13/AI13)) -> 0 | AK13: =ROUND((Purchase!F16),0) -> 0 | AL13: =SUM(B13,E13,H13,K13,N13,Q13,T13,W13,Z13,AC13,AF13,AI13) -> 1470 | AM13: =IF(AL13=0,0,(AN13/AL13)) -> 267.52041 | AN13: =SUM(D13,G13,J13,M13,P13,S13,V13,Y13,AB13,AE13,AH13,AK13) -> 393255 | AO13: =ROUND((Purchase!F17),0) -> 393255 | AP13: =AN13-AO13 -> 0
A14: Add:- Job Work Rcpts | C14: =IF(B14=0,0,(D14/B14)) -> 0 | F14: =IF(E14=0,0,(G14/E14)) -> 0 | I14: =IF(H14=0,0,(J14/H14)) -> 0 | L14: =IF(K14=0,0,(M14/K14)) -> 0 | O14: =IF(N14=0,0,(P14/N14)) -> 0 | R14: =IF(Q14=0,0,(S14/Q14)) -> 0 | U14: =IF(T14=0,0,(V14/T14)) -> 0 | X14: =IF(W14=0,0,(Y14/W14)) -> 0 | AA14: =IF(Z14=0,0,(AB14/Z14)) -> 0 | AD14: =IF(AC14=0,0,(AE14/AC14)) -> 0 | AG14: =IF(AF14=0,0,(AH14/AF14)) -> 0 | AJ14: =IF(AI14=0,0,(AK14/AI14)) -> 0 | AL14: =SUM(B14:AI14) -> 0
A15: Less:- Purchase return | C15: =IF(B15=0,0,(D15/B15)) -> 0 | F15: =IF(E15=0,0,(G15/E15)) -> 0 | I15: =IF(H15=0,0,(J15/H15)) -> 0 | L15: =IF(K15=0,0,(M15/K15)) -> 0 | O15: =IF(N15=0,0,(P15/N15)) -> 0 | R15: =IF(Q15=0,0,(S15/Q15)) -> 0 | U15: =IF(T15=0,0,(V15/T15)) -> 0 | X15: =IF(W15=0,0,(Y15/W15)) -> 0 | AA15: =IF(Z15=0,0,(AB15/Z15)) -> 0 | AD15: =IF(AC15=0,0,(AE15/AC15)) -> 0 | AG15: =IF(AF15=0,0,(AH15/AF15)) -> 0 | AJ15: =IF(AI15=0,0,(AK15/AI15)) -> 0 | AL15: =SUM(B15:AI15) -> 0
A16: Less :- Sales | B16: ='Inventory Sales'!B24 -> 0 | C16: =IF(B16=0,0,(D16/B16)) -> 0 | D16: ='Inventory Sales'!D24 -> 0 | E16: ='Inventory Sales'!E24 -> 25 | F16: =IF(E16=0,0,(G16/E16)) -> 380 | G16: ='Inventory Sales'!G24 -> 9500 | H16: ='Inventory Sales'!H24 -> 0 | I16: =IF(H16=0,0,(J16/H16)) -> 0 | J16: ='Inventory Sales'!J24 -> 0 | K16: ='Inventory Sales'!K24 -> 0 | L16: =IF(K16=0,0,(M16/K16)) -> 0 | M16: ='Inventory Sales'!M24 -> 0 | N16: ='Inventory Sales'!N24 -> 0 | O16: =IF(N16=0,0,(P16/N16)) -> 0 | P16: ='Inventory Sales'!P24 -> 0 | Q16: ='Inventory Sales'!Q24 -> 0 | R16: =IF(Q16=0,0,(S16/Q16)) -> 0 | S16: ='Inventory Sales'!S24 -> 0 | T16: ='Inventory Sales'!T24 -> 0 | U16: =IF(T16=0,0,(V16/T16)) -> 0 | V16: ='Inventory Sales'!V24 -> 0 | W16: ='Inventory Sales'!W24 -> 0 | X16: =IF(W16=0,0,(Y16/W16)) -> 0 | Y16: ='Inventory Sales'!Y24 -> 0 | Z16: ='Inventory Sales'!Z24 -> 0 | AA16: =IF(Z16=0,0,(AB16/Z16)) -> 0 | AB16: ='Inventory Sales'!AB24 -> 0 | AC16: ='Inventory Sales'!AC24 -> 0 | AD16: =IF(AC16=0,0,(AE16/AC16)) -> 0 | AE16: ='Inventory Sales'!AE24 -> 0 | AF16: ='Inventory Sales'!AF24 -> 0 | AG16: =IF(AF16=0,0,(AH16/AF16)) -> 0 | AH16: ='Inventory Sales'!AH24 -> 0 | AI16: ='Inventory Sales'!AI24 -> 0 | AJ16: =IF(AI16=0,0,(AK16/AI16)) -> 0 | AK16: ='Inventory Sales'!AK24 -> 0 | AL16: =SUM(B16,E16,H16,K16,N16,Q16,T16,W16,Z16,AC16,AF16,AI16) -> 25 | AM16: =IF(AL16=0,0,(AN16/AL16)) -> 380 | AN16: =SUM(D16,G16,J16,M16,P16,S16,V16,Y16,AB16,AE16,AH16,AK16) -> 9500 | AO16: ='Inventory Sales'!AN24 -> 9500
A17: Closing Stock | B17: ='Stock Valuation (FIFO)'!E6 -> 2392 | C17: =IF(B17=0,0,(D17/B17)) -> 245.33152 | D17: ='Stock Valuation (FIFO)'!G6 -> 586833 | E17: ='Stock Valuation (FIFO)'!H6 -> 2239 | F17: =IF(E17=0,0,(G17/E17)) -> 258.70835 | G17: ='Stock Valuation (FIFO)'!J6 -> 579248 | H17: ='Stock Valuation (FIFO)'!K6 -> 0 | I17: =IF(H17=0,0,(J17/H17)) -> 0 | J17: ='Stock Valuation (FIFO)'!M6 -> 0 | K17: ='Stock Valuation (FIFO)'!N6 -> 0 | L17: =IF(K17=0,0,(M17/K17)) -> 0 | M17: ='Stock Valuation (FIFO)'!P6 -> 0 | N17: ='Stock Valuation (FIFO)'!Q6 -> 0 | O17: =IF(N17=0,0,(P17/N17)) -> 0 | P17: ='Stock Valuation (FIFO)'!S6 -> 0 | Q17: ='Stock Valuation (FIFO)'!T6 -> 0 | R17: =IF(Q17=0,0,(S17/Q17)) -> 0 | S17: ='Stock Valuation (FIFO)'!V6 -> 0 | T17: ='Stock Valuation (FIFO)'!W6 -> 0 | U17: =IF(T17=0,0,(V17/T17)) -> 0 | V17: ='Stock Valuation (FIFO)'!Y6 -> 0 | W17: ='Stock Valuation (FIFO)'!Z6 -> 0 | X17: =IF(W17=0,0,(Y17/W17)) -> 0 | Y17: ='Stock Valuation (FIFO)'!AB6 -> 0 | Z17: ='Stock Valuation (FIFO)'!AC6 -> 0 | AA17: =IF(Z17=0,0,(AB17/Z17)) -> 0 | AB17: ='Stock Valuation (FIFO)'!AE6 -> 0 | AC17: ='Stock Valuation (FIFO)'!AF6 -> 0 | AD17: =IF(AC17=0,0,(AE17/AC17)) -> 0 | AE17: ='Stock Valuation (FIFO)'!AH6 -> 0 | AF17: ='Stock Valuation (FIFO)'!AI6 -> 0 | AG17: =IF(AF17=0,0,(AH17/AF17)) -> 0 | AH17: ='Stock Valuation (FIFO)'!AK6 -> 0 | AI17: ='Stock Valuation (FIFO)'!AL6 -> 0 | AJ17: =IF(AI17=0,0,(AK17/AI17)) -> 0 | AK17: ='Stock Valuation (FIFO)'!AN6 -> 0 | AL17: =AI17 -> 0 | AM17: =IF(AL17=0,0,(AN17/AL17)) -> 0 | AN17: =AK17 -> 0 | AO17: ='Stock Valuation (FIFO)'!AN6 -> 0 | AP17: =AN17-AO17 -> 0
A18: Consumption MB | B18: =(B12+B13)-(B16+B17) -> 761 | C18: =IF(B18=0,0,(D18/B18)) -> 216.25099 | D18: =(D12+D13)-(D16+D17) -> 164567 | E18: =(E12+E13)-(E16+E17) -> 775 | F18: =IF(E18=0,0,(G18/E18)) -> 217.64645 | G18: =(G12+G13)-(G16+G17) -> 168676 | H18: =(H12+H13)-(H16+H17) -> 2239 | I18: =IF(H18=0,0,(J18/H18)) -> 258.70835 | J18: =(J12+J13)-(J16+J17) -> 579248 | K18: =(K12+K13)-(K16+K17) -> 0 | L18: =IF(K18=0,0,(M18/K18)) -> 0 | M18: =(M12+M13)-(M16+M17) -> 0 | N18: =(N12+N13)-(N16+N17) -> 0 | O18: =IF(N18=0,0,(P18/N18)) -> 0 | P18: =(P12+P13)-(P16+P17) -> 0 | Q18: =(Q12+Q13)-(Q16+Q17) -> 0 | R18: =IF(Q18=0,0,(S18/Q18)) -> 0 | S18: =(S12+S13)-(S16+S17) -> 0 | T18: =(T12+T13)-(T16+T17) -> 0 | U18: =IF(T18=0,0,(V18/T18)) -> 0 | V18: =(V12+V13)-(V16+V17) -> 0 | W18: =(W12+W13)-(W16+W17) -> 0 | X18: =IF(W18=0,0,(Y18/W18)) -> 0 | Y18: =(Y12+Y13)-(Y16+Y17) -> 0 | Z18: =(Z12+Z13)-(Z16+Z17) -> 0 | AA18: =IF(Z18=0,0,(AB18/Z18)) -> 0 | AB18: =(AB12+AB13)-(AB16+AB17) -> 0 | AC18: =(AC12+AC13)-(AC16+AC17) -> 0 | AD18: =IF(AC18=0,0,(AE18/AC18)) -> 0 | AE18: =(AE12+AE13)-(AE16+AE17) -> 0 | AF18: =(AF12+AF13)-(AF16+AF17) -> 0 | AG18: =IF(AF18=0,0,(AH18/AF18)) -> 0 | AH18: =(AH12+AH13)-(AH16+AH17) -> 0 | AI18: =(AI12+AI13)-(AI16+AI17) -> 0 | AJ18: =IF(AI18=0,0,(AK18/AI18)) -> 0 | AK18: =(AK12+AK13)-(AK16+AK17) -> 0 | AL18: =(AL12+AL13)-(AL16+AL17) -> 3775 | AM18: =IF(AL18=0,0,(AN18/AL18)) -> 241.71947 | AN18: =(AN12+AN13)-(AN16+AN17) -> 912491
A19: CP
A20: Opening Stock | B20: ='Stock Valuation (FIFO)'!B7 -> 19 | C20: =IF(B20=0,0,(D20/B20)) -> 1597.3684 | D20: ='Stock Valuation (FIFO)'!D7 -> 30350 | E20: =B25 -> 21 | F20: =IF(E20=0,0,(G20/E20)) -> 1514.619 | G20: =D25 -> 31807 | H20: =E25 -> 20 | I20: =IF(H20=0,0,(J20/H20)) -> 1568.5 | J20: =G25 -> 31370 | K20: =H25 -> 0 | L20: =IF(K20=0,0,(M20/K20)) -> 0 | M20: =J25 -> 0 | N20: =K25 -> 0 | O20: =IF(N20=0,0,(P20/N20)) -> 0 | P20: =M25 -> 0 | Q20: =N25 -> 0 | R20: =IF(Q20=0,0,(S20/Q20)) -> 0 | S20: =P25 -> 0 | T20: =Q25 -> 0 | U20: =IF(T20=0,0,(V20/T20)) -> 0 | V20: =S25 -> 0 | W20: =T25 -> 0 | X20: =IF(W20=0,0,(Y20/W20)) -> 0 | Y20: =V25 -> 0 | Z20: =W25 -> 0 | AA20: =IF(Z20=0,0,(AB20/Z20)) -> 0 | AB20: =Y25 -> 0 | AC20: =Z25 -> 0 | AD20: =IF(AC20=0,0,(AE20/AC20)) -> 0 | AE20: =AB25 -> 0 | AF20: =AC25 -> 0 | AG20: =IF(AF20=0,0,(AH20/AF20)) -> 0 | AH20: =AE25 -> 0 | AI20: =AF25 -> 0 | AJ20: =IF(AI20=0,0,(AK20/AI20)) -> 0 | AK20: =AH25 -> 0 | AL20: =B20 -> 19 | AM20: =IF(AL20=0,0,(AN20/AL20)) -> 1597.3684 | AN20: =D20 -> 30350
A21: Add:- Purchases | B21: =Purchase!$H5 -> 4 | C21: =IF(B21=0,0,(D21/B21)) -> 845 | D21: =Purchase!$I5 -> 3380 | E21: =Purchase!$H6 -> 2 | F21: =IF(E21=0,0,(G21/E21)) -> 910 | G21: =Purchase!$I6 -> 1820 | H21: =Purchase!$H7 -> 0 | I21: =IF(H21=0,0,(J21/H21)) -> 0 | J21: =Purchase!$I7 -> 0 | K21: =Purchase!$H8 -> 0 | L21: =IF(K21=0,0,(M21/K21)) -> 0 | M21: =Purchase!$I8 -> 0 | N21: =ROUND((Purchase!$H9),0)-1 -> -1 | O21: =IF(N21=0,0,(P21/N21)) -> 0 | P21: =Purchase!$I9 -> 0 | Q21: =Purchase!$H10 -> 0 | R21: =IF(Q21=0,0,(S21/Q21)) -> 0 | S21: =Purchase!$I10 -> 0 | T21: =ROUND((Purchase!$H11),0) -> 0 | U21: =IF(T21=0,0,(V21/T21)) -> 0 | V21: =Purchase!$I11 -> 0 | W21: =Purchase!$H12 -> 0 | X21: =IF(W21=0,0,(Y21/W21)) -> 0 | Y21: =Purchase!$I12 -> 0 | Z21: =Purchase!H13 -> 0 | AA21: =IF(Z21=0,0,(AB21/Z21)) -> 0 | AB21: =Purchase!I13 -> 0 | AC21: =Purchase!H14 -> 0 | AD21: =IF(AC21=0,0,(AE21/AC21)) -> 0 | AE21: =Purchase!I14 -> 0 | AF21: =Purchase!H15 -> 0 | AG21: =IF(AF21=0,0,(AH21/AF21)) -> 0 | AH21: =Purchase!I15 -> 0 | AI21: =Purchase!H16 -> 0 | AJ21: =IF(AI21=0,0,(AK21/AI21)) -> 0 | AK21: =Purchase!I16 -> 0 | AL21: =SUM(B21,E21,H21,K21,N21,Q21,T21,W21,Z21,AC21,AF21,AI21) -> 5 | AM21: =IF(AL21=0,0,(AN21/AL21)) -> 1040 | AN21: =SUM(D21,G21,J21,M21,P21,S21,V21,Y21,AB21,AE21,AH21,AK21) -> 5200 | AO21: =Purchase!I17 -> 5200 | AP21: =AN21-AO21 -> 0
A22: Add:- Job Work Rcpts | C22: =IF(B22=0,0,(D22/B22)) -> 0 | F22: =IF(E22=0,0,(G22/E22)) -> 0 | I22: =IF(H22=0,0,(J22/H22)) -> 0 | L22: =IF(K22=0,0,(M22/K22)) -> 0 | O22: =IF(N22=0,0,(P22/N22)) -> 0 | R22: =IF(Q22=0,0,(S22/Q22)) -> 0 | U22: =IF(T22=0,0,(V22/T22)) -> 0 | X22: =IF(W22=0,0,(Y22/W22)) -> 0 | AA22: =IF(Z22=0,0,(AB22/Z22)) -> 0 | AD22: =IF(AC22=0,0,(AE22/AC22)) -> 0 | AG22: =IF(AF22=0,0,(AH22/AF22)) -> 0 | AJ22: =IF(AI22=0,0,(AK22/AI22)) -> 0 | AL22: =SUM(B22:AI22) -> 0
A23: Less:- Purchase return | C23: =IF(B23=0,0,(D23/B23)) -> 0 | F23: =IF(E23=0,0,(G23/E23)) -> 0 | I23: =IF(H23=0,0,(J23/H23)) -> 0 | L23: =IF(K23=0,0,(M23/K23)) -> 0 | O23: =IF(N23=0,0,(P23/N23)) -> 0 | R23: =IF(Q23=0,0,(S23/Q23)) -> 0 | U23: =IF(T23=0,0,(V23/T23)) -> 0 | X23: =IF(W23=0,0,(Y23/W23)) -> 0 | AA23: =IF(Z23=0,0,(AB23/Z23)) -> 0 | AD23: =IF(AC23=0,0,(AE23/AC23)) -> 0 | AG23: =IF(AF23=0,0,(AH23/AF23)) -> 0 | AJ23: =IF(AI23=0,0,(AK23/AI23)) -> 0 | AL23: =SUM(B23:AI23) -> 0
A24: Less :- Sales | B24: ='Inventory Sales'!B23 -> 0 | C24: =IF(B24=0,0,(D24/B24)) -> 0 | D24: ='Inventory Sales'!D23 -> 0 | F24: =IF(E24=0,0,(G24/E24)) -> 0 | I24: =IF(H24=0,0,(J24/H24)) -> 0 | K24: ='Inventory Sales'!K23 -> 0 | L24: =IF(K24=0,0,(M24/K24)) -> 0 | M24: ='Inventory Sales'!M23 -> 0 | N24: ='Inventory Sales'!N23 -> 0 | O24: =IF(N24=0,0,(P24/N24)) -> 0 | P24: ='Inventory Sales'!P23 -> 0 | R24: =IF(Q24=0,0,(S24/Q24)) -> 0 | U24: =IF(T24=0,0,(V24/T24)) -> 0 | X24: =IF(W24=0,0,(Y24/W24)) -> 0 | AA24: =IF(Z24=0,0,(AB24/Z24)) -> 0 | AD24: =IF(AC24=0,0,(AE24/AC24)) -> 0 | AG24: =IF(AF24=0,0,(AH24/AF24)) -> 0 | AJ24: =IF(AI24=0,0,(AK24/AI24)) -> 0 | AL24: =SUM(B24,E24,H24,K24,N24,Q24,T24,W24,Z24,AC24,AF24,AI24) -> 0 | AM24: =IF(AL24=0,0,(AN24/AL24)) -> 0 | AN24: =SUM(D24,G24,J24,M24,P24,S24,V24,Y24,AB24,AE24,AH24,AK24) -> 0 | AO24: ='Inventory Sales'!AN23 -> 0
A25: Closing Stock | B25: ='Stock Valuation (FIFO)'!E7 -> 21 | C25: =IF(B25=0,0,(D25/B25)) -> 1514.619 | D25: ='Stock Valuation (FIFO)'!G7 -> 31807 | E25: ='Stock Valuation (FIFO)'!H7 -> 20 | F25: =IF(E25=0,0,(G25/E25)) -> 1568.5 | G25: ='Stock Valuation (FIFO)'!J7 -> 31370 | H25: ='Stock Valuation (FIFO)'!K7 -> 0 | I25: =IF(H25=0,0,(J25/H25)) -> 0 | J25: ='Stock Valuation (FIFO)'!M7 -> 0 | K25: ='Stock Valuation (FIFO)'!N7 -> 0 | L25: =IF(K25=0,0,(M25/K25)) -> 0 | M25: ='Stock Valuation (FIFO)'!P7 -> 0 | N25: ='Stock Valuation (FIFO)'!Q7 -> 0 | O25: =IF(N25=0,0,(P25/N25)) -> 0 | P25: ='Stock Valuation (FIFO)'!S7 -> 0 | Q25: ='Stock Valuation (FIFO)'!T7 -> 0 | R25: =IF(Q25=0,0,(S25/Q25)) -> 0 | S25: ='Stock Valuation (FIFO)'!V7 -> 0 | T25: ='Stock Valuation (FIFO)'!W7 -> 0 | U25: =IF(T25=0,0,(V25/T25)) -> 0 | V25: ='Stock Valuation (FIFO)'!Y7 -> 0 | W25: ='Stock Valuation (FIFO)'!Z7 -> 0 | X25: =IF(W25=0,0,(Y25/W25)) -> 0 | Y25: ='Stock Valuation (FIFO)'!AB7 -> 0 | Z25: ='Stock Valuation (FIFO)'!AC7 -> 0 | AA25: =IF(Z25=0,0,(AB25/Z25)) -> 0 | AB25: ='Stock Valuation (FIFO)'!AE7 -> 0 | AC25: ='Stock Valuation (FIFO)'!AF7 -> 0 | AD25: =IF(AC25=0,0,(AE25/AC25)) -> 0 | AE25: ='Stock Valuation (FIFO)'!AH7 -> 0 | AF25: ='Stock Valuation (FIFO)'!AI7 -> 0 | AG25: =IF(AF25=0,0,(AH25/AF25)) -> 0 | AH25: ='Stock Valuation (FIFO)'!AK7 -> 0 | AI25: ='Stock Valuation (FIFO)'!AL7 -> 0 | AJ25: =IF(AI25=0,0,(AK25/AI25)) -> 0 | AK25: ='Stock Valuation (FIFO)'!AN7 -> 0 | AL25: =AI25 -> 0 | AM25: =IF(AL25=0,0,(AN25/AL25)) -> 0 | AN25: =AK25 -> 0 | AO25: ='Stock Valuation (FIFO)'!AN7 -> 0 | AP25: =AN25-AO25 -> 0
A26: Consumption CP | B26: =(B20+B21)-(B24+B25) -> 2 | C26: =IF(B26=0,0,(D26/B26)) -> 961.5 | D26: =(D20+D21)-(D24+D25) -> 1923 | E26: =(E20+E21)-(E24+E25) -> 3 | F26: =IF(E26=0,0,(G26/E26)) -> 752.33333 | G26: =(G20+G21)-(G24+G25) -> 2257 | H26: =(H20+H21)-(H24+H25) -> 20 | I26: =IF(H26=0,0,(J26/H26)) -> 1568.5 | J26: =(J20+J21)-(J24+J25) -> 31370 | K26: =(K20+K21)-(K24+K25) -> 0 | M26: =(M20+M21)-(M24+M25) -> 0 | N26: =(N20+N21)-(N24+N25) -> -1 | O26: =IF(N26=0,0,(P26/N26)) -> 0 | P26: =(P20+P21)-(P24+P25) -> 0 | Q26: =(Q20+Q21)-(Q24+Q25) -> 0 | R26: =IF(Q26=0,0,(S26/Q26)) -> 0 | S26: =(S20+S21)-(S24+S25) -> 0 | T26: =(T20+T21)-(T24+T25) -> 0 | U26: =IF(T26=0,0,(V26/T26)) -> 0 | V26: =(V20+V21)-(V24+V25) -> 0 | W26: =(W20+W21)-(W24+W25) -> 0 | X26: =IF(W26=0,0,(Y26/W26)) -> 0 | Y26: =(Y20+Y21)-(Y24+Y25) -> 0 | Z26: =(Z20+Z21)-(Z24+Z25) -> 0 | AA26: =IF(Z26=0,0,(AB26/Z26)) -> 0 | AB26: =(AB20+AB21)-(AB24+AB25) -> 0 | AC26: =(AC20+AC21)-(AC24+AC25) -> 0 | AD26: =IF(AC26=0,0,(AE26/AC26)) -> 0 | AE26: =(AE20+AE21)-(AE24+AE25) -> 0 | AF26: =(AF20+AF21)-(AF24+AF25) -> 0 | AG26: =IF(AF26=0,0,(AH26/AF26)) -> 0 | AH26: =(AH20+AH21)-(AH24+AH25) -> 0 | AI26: =(AI20+AI21)-(AI24+AI25) -> 0 | AJ26: =IF(AI26=0,0,(AK26/AI26)) -> 0 | AK26: =(AK20+AK21)-(AK24+AK25) -> 0 | AL26: =(AL20+AL21)-(AL24+AL25) -> 24 | AM26: =IF(AL26=0,0,(AN26/AL26)) -> 1481.25 | AN26: =(AN20+AN21)-(AN24+AN25) -> 35550
A27: RM CONSUMPTION
A28: Opening Stock | B28: =B4+B12+B20 -> 143489 | C28: =IF(B28=0,0,(D28/B28)) -> 123.87463 | D28: =D4+D12+D20 -> 17774647 | E28: =E4+E12+E20 -> 78108 | F28: =IF(E28=0,0,(G28/E28)) -> 139.44819 | G28: =G4+G12+G20 -> 10892019 | H28: =H4+H12+H20 -> 92299 | I28: =IF(H28=0,0,(J28/H28)) -> 155.48953 | J28: =J4+J12+J20 -> 14351528 | K28: =K4+K12+K20 -> 0 | L28: =IF(K28=0,0,(M28/K28)) -> 0 | M28: =M4+M12+M20 -> 0 | N28: =N4+N12+N20 -> 0 | O28: =IF(N28=0,0,(P28/N28)) -> 0 | P28: =P4+P12+P20 -> 0 | Q28: =Q4+Q12+Q20 -> 0 | R28: =IF(Q28=0,0,(S28/Q28)) -> 0 | S28: =S4+S12+S20 -> 0 | T28: =T4+T12+T20 -> 0 | U28: =IF(T28=0,0,(V28/T28)) -> 0 | V28: =V4+V12+V20 -> 0 | W28: =W4+W12+W20 -> 0 | X28: =IF(W28=0,0,(Y28/W28)) -> 0 | Y28: =Y4+Y12+Y20 -> 0 | Z28: =W33 -> 0 | AA28: =IF(Z28=0,0,(AB28/Z28)) -> 0 | AB28: =Y33 -> 0 | AC28: =Z33 -> 0 | AD28: =IF(AC28=0,0,(AE28/AC28)) -> 0 | AE28: =AB33 -> 0 | AF28: =AC33 -> 0 | AG28: =IF(AF28=0,0,(AH28/AF28)) -> 0 | AH28: =AE33 -> 0 | AI28: =AF33 -> 0 | AJ28: =IF(AI28=0,0,(AK28/AI28)) -> 0 | AK28: =AH33 -> 0 | AL28: =B28 -> 143489 | AM28: =IF(AL28=0,0,(AN28/AL28)) -> 123.87463 | AN28: =D28 -> 17774647
A29: Add:- Purchases | B29: =B5+B13+B21 -> 827 | C29: =IF(B29=0,0,(D29/B29)) -> 273.33011 | D29: =D5+D13+D21 -> 226044 | E29: =E5+E13+E21 -> 76649 | F29: =IF(E29=0,0,(G29/E29)) -> 149.18116 | G29: =G5+G13+G21 -> 11434587 | H29: =H5+H13+H21 -> 0 | I29: =IF(H29=0,0,(J29/H29)) -> 0 | J29: =J5+J13+J21 -> 0 | K29: =K5+K13+K21 -> 0 | L29: =IF(K29=0,0,(M29/K29)) -> 0 | M29: =M5+M13+M21 -> 0 | N29: =N5+N13+N21 -> -1 | O29: =IF(N29=0,0,(P29/N29)) -> 0 | P29: =P5+P13+P21 -> 0 | Q29: =Q5+Q13+Q21 -> 0 | R29: =IF(Q29=0,0,(S29/Q29)) -> 0 | S29: =S5+S13+S21 -> 0 | T29: =T5+T13+T21 -> 0 | U29: =IF(T29=0,0,(V29/T29)) -> 0 | V29: =V5+V13+V21 -> 0 | W29: =W5+W13+W21 -> 0 | X29: =IF(W29=0,0,(Y29/W29)) -> 0 | Y29: =Y5+Y13+Y21 -> 0 | Z29: =Z5+Z13+Z21 -> 0 | AA29: =IF(Z29=0,0,(AB29/Z29)) -> 0 | AB29: =AB5+AB13+AB21 -> 0 | AC29: =AC5+AC13+AC21 -> 0 | AD29: =IF(AC29=0,0,(AE29/AC29)) -> 0 | AE29: =AE5+AE13+AE21 -> 0 | AF29: =AF5+AF13+AF21 -> 0 | AG29: =IF(AF29=0,0,(AH29/AF29)) -> 0 | AH29: =AH5+AH13+AH21 -> 0 | AI29: =AI5+AI13+AI21 -> 0 | AJ29: =IF(AI29=0,0,(AK29/AI29)) -> 0 | AK29: =AK5+AK13+AK21 -> 0 | AL29: =AL5+AL13+AL21 -> 77475 | AM29: =IF(AL29=0,0,(AN29/AL29)) -> 150.50831 | AN29: =AN5+AN13+AN21 -> 11660631 | AO29: =AO5+AO13+AO21 -> 11660631 | AP29: =AN29-AO29 -> 0
A30: Add:- Job Work Rcpts | B30: =B6+B14+B22 -> 0 | C30: =IF(B30=0,0,(D30/B30)) -> 0 | D30: =D6+D14+D22 -> 0 | E30: =E6+E14+E22 -> 0 | F30: =IF(E30=0,0,(G30/E30)) -> 0 | G30: =G6+G14+G22 -> 0 | H30: =H6+H14+H22 -> 0 | I30: =IF(H30=0,0,(J30/H30)) -> 0 | J30: =J6+J14+J22 -> 0 | K30: =K6+K14+K22 -> 0 | L30: =IF(K30=0,0,(M30/K30)) -> 0 | M30: =M6+M14+M22 -> 0 | N30: =N6+N14+N22 -> 0 | O30: =IF(N30=0,0,(P30/N30)) -> 0 | P30: =P6+P14+P22 -> 0 | Q30: =Q6+Q14+Q22 -> 0 | R30: =IF(Q30=0,0,(S30/Q30)) -> 0 | S30: =S6+S14+S22 -> 0 | T30: =T6+T14+T22 -> 0 | U30: =IF(T30=0,0,(V30/T30)) -> 0 | V30: =V6+V14+V22 -> 0 | W30: =W6+W14+W22 -> 0 | X30: =IF(W30=0,0,(Y30/W30)) -> 0 | Y30: =Y6+Y14+Y22 -> 0 | Z30: =Z6+Z14+Z22 -> 0 | AA30: =IF(Z30=0,0,(AB30/Z30)) -> 0 | AB30: =AB6+AB14+AB22 -> 0 | AC30: =AC6+AC14+AC22 -> 0 | AD30: =IF(AC30=0,0,(AE30/AC30)) -> 0 | AE30: =AE6+AE14+AE22 -> 0 | AF30: =AF6+AF14+AF22 -> 0 | AG30: =IF(AF30=0,0,(AH30/AF30)) -> 0 | AH30: =AH6+AH14+AH22 -> 0 | AI30: =AI6+AI14+AI22 -> 0 | AJ30: =IF(AI30=0,0,(AK30/AI30)) -> 0 | AK30: =AK6+AK14+AK22 -> 0 | AL30: =SUM(B30:AI30) -> 0
A31: Less:- Purchase return | C31: =IF(B31=0,0,(D31/B31)) -> 0 | F31: =IF(E31=0,0,(G31/E31)) -> 0 | I31: =IF(H31=0,0,(J31/H31)) -> 0 | L31: =IF(K31=0,0,(M31/K31)) -> 0 | O31: =IF(N31=0,0,(P31/N31)) -> 0 | R31: =IF(Q31=0,0,(S31/Q31)) -> 0 | U31: =IF(T31=0,0,(V31/T31)) -> 0 | X31: =IF(W31=0,0,(Y31/W31)) -> 0 | AA31: =IF(Z31=0,0,(AB31/Z31)) -> 0 | AD31: =IF(AC31=0,0,(AE31/AC31)) -> 0 | AG31: =IF(AF31=0,0,(AH31/AF31)) -> 0 | AJ31: =IF(AI31=0,0,(AK31/AI31)) -> 0 | AL31: =SUM(B31:AI31) -> 0
A32: Less :- Sales | B32: =B8+B16+B24 -> 0 | C32: =IF(B32=0,0,(D32/B32)) -> 0 | D32: =D8+D16+D24 -> 0 | E32: =E8+E16+E24 -> 25 | F32: =IF(E32=0,0,(G32/E32)) -> 380 | G32: =G8+G16+G24 -> 9500 | H32: =H8+H16+H24 -> 0 | I32: =IF(H32=0,0,(J32/H32)) -> 0 | J32: =J8+J16+J24 -> 0 | K32: =K8+K16+K24 -> 0 | L32: =IF(K32=0,0,(M32/K32)) -> 0 | M32: =M8+M16+M24 -> 0 | N32: =N8+N16+N24 -> 0 | O32: =IF(N32=0,0,(P32/N32)) -> 0 | P32: =P8+P16+P24 -> 0 | Q32: =Q8+Q16+Q24 -> 0 | R32: =IF(Q32=0,0,(S32/Q32)) -> 0 | S32: =S8+S16+S24 -> 0 | T32: =T8+T16+T24 -> 0 | U32: =IF(T32=0,0,(V32/T32)) -> 0 | V32: =V8+V16+V24 -> 0 | W32: =W8+W16+W24 -> 0 | X32: =IF(W32=0,0,(Y32/W32)) -> 0 | Y32: =Y8+Y16+Y24 -> 0 | Z32: =Z8+Z16+Z24 -> 0 | AA32: =IF(Z32=0,0,(AB32/Z32)) -> 0 | AB32: =AB8+AB16+AB24 -> 0 | AC32: =AC8+AC16+AC24 -> 0 | AD32: =IF(AC32=0,0,(AE32/AC32)) -> 0 | AE32: =AE8+AE16+AE24 -> 0 | AF32: =AF8+AF16+AF24 -> 0 | AG32: =IF(AF32=0,0,(AH32/AF32)) -> 0 | AH32: =AH8+AH16+AH24 -> 0 | AI32: =AI8+AI16+AI24 -> 0 | AJ32: =IF(AI32=0,0,(AK32/AI32)) -> 0 | AK32: =AK8+AK16+AK24 -> 0 | AL32: =SUM(B32,E32,H32,K32,N32,Q32,T32,W32,Z32,AC32,AF32,AI32) -> 25 | AM32: =IF(AL32=0,0,(AN32/AL32)) -> 380 | AN32: =SUM(D32,G32,J32,M32,P32,S32,V32,Y32,AB32,AE32,AH32,AK32) -> 9500
A33: Closing Stock | B33: =B9+B17+B25 -> 78108 | C33: =IF(B33=0,0,(D33/B33)) -> 139.44819 | D33: =D9+D17+D25 -> 10892019 | E33: =E9+E17+E25 -> 92299 | F33: =IF(E33=0,0,(G33/E33)) -> 155.48953 | G33: =G9+G17+G25 -> 14351528 | H33: =H9+H17+H25 -> 0 | I33: =IF(H33=0,0,(J33/H33)) -> 0 | J33: =J9+J17+J25 -> 0 | K33: =K9+K17+K25 -> 0 | L33: =IF(K33=0,0,(M33/K33)) -> 0 | M33: =M9+M17+M25 -> 0 | N33: =N9+N17+N25 -> 0 | O33: =IF(N33=0,0,(P33/N33)) -> 0 | P33: =P9+P17+P25 -> 0 | Q33: =Q9+Q17+Q25 -> 0 | R33: =IF(Q33=0,0,(S33/Q33)) -> 0 | S33: =S9+S17+S25 -> 0 | T33: =T9+T17+T25 -> 0 | U33: =IF(T33=0,0,(V33/T33)) -> 0 | V33: =V9+V17+V25 -> 0 | W33: =W9+W17+W25 -> 0 | X33: =IF(W33=0,0,(Y33/W33)) -> 0 | Y33: =Y9+Y17+Y25 -> 0 | Z33: =Z9+Z17+Z25 -> 0 | AA33: =IF(Z33=0,0,(AB33/Z33)) -> 0 | AB33: =AB9+AB17+AB25 -> 0 | AC33: =AC9+AC17+AC25 -> 0 | AD33: =IF(AC33=0,0,(AE33/AC33)) -> 0 | AE33: =AE9+AE17+AE25 -> 0 | AF33: =AF9+AF17+AF25 -> 0 | AG33: =IF(AF33=0,0,(AH33/AF33)) -> 0 | AH33: =AH9+AH17+AH25 -> 0 | AI33: =AI9+AI17+AI25 -> 0 | AJ33: =IF(AI33=0,0,(AK33/AI33)) -> 0 | AK33: =AK9+AK17+AK25 -> 0 | AL33: =AL9+AL17+AL25 -> 0 | AM33: =IF(AL33=0,0,(AN33/AL33)) -> 0 | AN33: =AN9+AN17+AN25 -> 0
A34: Consumption RM | B34: =(B28+B29)-(B32+B33) -> 66208 | C34: =IF(B34=0,0,(D34/B34)) -> 107.36878 | D34: =(D28+D29)-(D32+D33) -> 7108672 | E34: =(E28+E29)-(E32+E33) -> 62433 | F34: =IF(E34=0,0,(G34/E34)) -> 127.58602 | G34: =(G28+G29)-(G32+G33) -> 7965578 | H34: =(H28+H29)-(H32+H33) -> 92299 | I34: =IF(H34=0,0,(J34/H34)) -> 155.48953 | J34: =(J28+J29)-(J32+J33) -> 14351528 | K34: =(K28+K29)-(K32+K33) -> 0 | L34: =IF(K34=0,0,(M34/K34)) -> 0 | M34: =(M28+M29)-(M32+M33) -> 0 | N34: =(N28+N29)-(N32+N33) -> -1 | O34: =IF(N34=0,0,(P34/N34)) -> 0 | P34: =(P28+P29)-(P32+P33) -> 0 | Q34: =(Q28+Q29)-(Q32+Q33) -> 0 | R34: =IF(Q34=0,0,(S34/Q34)) -> 0 | S34: =(S28+S29)-(S32+S33) -> 0 | T34: =(T28+T29)-(T32+T33) -> 0 | U34: =IF(T34=0,0,(V34/T34)) -> 0 | V34: =(V28+V29)-(V32+V33) -> 0 | W34: =(W28+W29)-(W32+W33) -> 0 | X34: =IF(W34=0,0,(Y34/W34)) -> 0 | Y34: =(Y28+Y29)-(Y32+Y33) -> 0 | Z34: =(Z28+Z29)-(Z32+Z33) -> 0 | AA34: =IF(Z34=0,0,(AB34/Z34)) -> 0 | AB34: =(AB28+AB29)-(AB32+AB33) -> 0 | AC34: =(AC28+AC29)-(AC32+AC33) -> 0 | AD34: =IF(AC34=0,0,(AE34/AC34)) -> 0 | AE34: =(AE28+AE29)-(AE32+AE33) -> 0 | AF34: =(AF28+AF29)-(AF32+AF33) -> 0 | AG34: =IF(AF34=0,0,(AH34/AF34)) -> 0 | AH34: =(AH28+AH29)-(AH32+AH33) -> 0 | AI34: =(AI28+AI29)-(AI32+AI33) -> 0 | AJ34: =IF(AI34=0,0,(AK34/AI34)) -> 0 | AK34: =(AK28+AK29)-(AK32+AK33) -> 0 | AL34: =(AL28+AL29)-(AL32+AL33) -> 220939 | AM34: =IF(AL34=0,0,(AN34/AL34)) -> 133.18508 | AN34: =(AN28+AN29)-(AN32+AN33) -> 29425778
A35: COGS -HD | C35: =C10 -> 106.07658 | F35: =F10 -> 126.42357 | I35: =I10 -> 152.60895 | L35: =L10 -> 0 | O35: =O10 -> 0 | R35: =R10 -> 0 | U35: =U10 -> 0 | X35: =X10 -> 0 | AA35: =AA10 -> 0 | AD35: =AD10 -> 0 | AG35: =AG10 -> 0 | AJ35: =AJ10 -> 0 | AM35: =AM10 -> 131.1492
A36: COGS- MB/CP | C36: =C34-C35 -> 1.2921938 | F36: =F34-F35 -> 1.1624536 | I36: =I34-I35 -> 2.880577 | L36: =L34-L35 -> 0 | O36: =O34-O35 -> 0 | R36: =R34-R35 -> 0 | U36: =U34-U35 -> 0 | X36: =X34-X35 -> 0 | AA36: =AA34-AA35 -> 0 | AD36: =AD34-AD35 -> 0 | AG36: =AG34-AG35 -> 0 | AJ36: =AJ34-AJ35 -> 0 | AM36: =AM34-AM35 -> 2.0358796
A38: Monofil Purchases
A39: Opening Stock | C39: =IF(B39=0,0,(D39/B39)) -> 0 | F39: =IF(E39=0,0,(G39/E39)) -> 0 | I39: =IF(H39=0,0,(J39/H39)) -> 0 | L39: =IF(K39=0,0,(M39/K39)) -> 0 | N39: =K48 -> 0 | Q39: =N48 -> 0 | T39: =Q48 -> 0 | W39: =T48 -> 0 | Z39: =W48 -> 0 | AC39: =Z48 -> 0 | AF39: =AC48 -> 0 | AI39: =AF48 -> 0 | AL39: =B39 -> 0 | AM39: =IF(AL39=0,0,(AN39/AL39)) -> 0 | AN39: =D39 -> 0
A40: Add:- Purchases Yarn | B40: =ROUND((Purchase!L22),0) -> 3668 | C40: =IF(B40=0,0,(D40/B40)) -> 182.33397 | D40: =ROUND((Purchase!M22),0) -> 668801 | E40: =ROUND((Purchase!L23),0) -> 4150 | F40: =IF(E40=0,0,(G40/E40)) -> 111.38554 | G40: =ROUND((Purchase!M23),0) -> 462250 | H40: =ROUND((Purchase!L24),0) -> 0 | I40: =IF(H40=0,0,(J40/H40)) -> 0 | J40: =ROUND((Purchase!M24),0) -> 0 | K40: =ROUND((Purchase!L25),0) -> 0 | L40: =IF(K40=0,0,(M40/K40)) -> 0 | M40: =ROUND((Purchase!M25),0) -> 0 | N40: =ROUND((Purchase!$L26),) -> 0 | O40: =IF(N40=0,0,(P40/N40)) -> 0 | P40: =ROUND((Purchase!M26),0) -> 0 | Q40: =ROUND((Purchase!$L27),0) -> 0 | R40: =IF(Q40=0,0,(S40/Q40)) -> 0 | S40: =ROUND((Purchase!$M27),0) -> 0 | T40: =ROUND((Purchase!$L28),0) -> 0 | U40: =IF(T40=0,0,(V40/T40)) -> 0 | V40: =ROUND((Purchase!$M28),0) -> 0 | W40: =ROUND((Purchase!$L29),0) -> 0 | X40: =IF(W40=0,0,(Y40/W40)) -> 0 | Y40: =ROUND((Purchase!$M29),0) -> 0 | Z40: =ROUND((Purchase!L30),0) -> 0 | AA40: =IF(Z40=0,0,(AB40/Z40)) -> 0 | AB40: =ROUND((Purchase!M30),0) -> 0 | AC40: =ROUND((Purchase!$L31),0) -> 0 | AD40: =IF(AC40=0,0,(AE40/AC40)) -> 0 | AE40: =ROUND((Purchase!M31),0) -> 0 | AF40: =ROUND((Purchase!$L32),0) -> 0 | AG40: =IF(AF40=0,0,(AH40/AF40)) -> 0 | AH40: =Purchase!M32 -> 0 | AI40: =ROUND((Purchase!$L33),0) -> 0 | AJ40: =IF(AI40=0,0,(AK40/AI40)) -> 0 | AK40: =ROUND((Purchase!M33),0) -> 0 | AL40: =SUM(B40,E40,H40,K40,N40,Q40,T40,W40,Z40,AC40,AF40,AI40) -> 7818 | AM40: =IF(AL40=0,0,(AN40/AL40)) -> 144.67268 | AN40: =SUM(D40,G40,J40,M40,P40,S40,V40,Y40,AB40,AE40,AH40,AK40) -> 1131051 | AO40: =ROUND((Purchase!M34),0) -> 1131051 | AP40: =AN40-AO40 -> 0
A41: Porchase Others | B41: =Purchase!$E22 -> 17310.96 | C41: =IF(B41=0,0,(D41/B41)) -> 261.96987 | D41: =Purchase!$F22 -> 4534950 | E41: =ROUND((Purchase!$E23),0) -> 9184 | F41: =IF(E41=0,0,(G41/E41)) -> 266.03397 | G41: =Purchase!$F23 -> 2443256 | H41: =Purchase!$E24 -> 0 | I41: =IF(H41=0,0,(J41/H41)) -> 0 | J41: =Purchase!$F24 -> 0 | K41: =ROUND((Purchase!$E25),0) -> 0 | L41: =IF(K41=0,0,(M41/K41)) -> 0 | M41: =ROUND((Purchase!$F25),0) -> 0 | N41: =ROUND((Purchase!$E26),0) -> 0 | O41: =IF(N41=0,0,(P41/N41)) -> 0 | P41: =Purchase!$F26 -> 0 | Q41: =ROUND((Purchase!$E27),0) -> 0 | R41: =IF(Q41=0,0,(S41/Q41)) -> 0 | S41: =Purchase!$F27 -> 0 | T41: =ROUND((Purchase!$E28),0) -> 0 | U41: =IF(T41=0,0,(V41/T41)) -> 0 | V41: =ROUND((Purchase!$F28),0) -> 0 | W41: =ROUND((Purchase!E29),0) -> 0 | X41: =IF(W41=0,0,(Y41/W41)) -> 0 | Y41: =Purchase!F29 -> 0 | Z41: =ROUND((Purchase!E30),0) -> 0 | AA41: =IF(Z41=0,0,(AB41/Z41)) -> 0 | AB41: =ROUND((Purchase!F30),0) -> 0 | AC41: =ROUND((Purchase!E31),0) -> 0 | AD41: =IF(AC41=0,0,(AE41/AC41)) -> 0 | AE41: =ROUND((Purchase!F31),0) -> 0 | AF41: =ROUND((Purchase!E32),0) -> 0 | AG41: =IF(AF41=0,0,(AH41/AF41)) -> 0 | AH41: =ROUND((Purchase!F32),0) -> 0 | AI41: =ROUND((Purchase!E33),0) -> 0 | AJ41: =IF(AI41=0,0,(AK41/AI41)) -> 0 | AK41: =ROUND((Purchase!F33),0) -> 0 | AL41: =ROUND((Purchase!E34),0) -> 26494 | AM41: =IF(AL41=0,0,(AN41/AL41)) -> 263.38816 | AN41: =ROUND((Purchase!F34),0) -> 6978206 | AO41: =ROUND((Purchase!F34),0) -> 6978206 | AP41: =AN41-AO41 -> 0
A42: Purchase Fabric | B42: =ROUND((Purchase!B22),0) -> 5222 | C42: =IF(B42=0,0,(D42/B42)) -> 279.3378 | D42: =ROUND((Purchase!C22),0) -> 1458702 | E42: =ROUND((Purchase!B23),0) -> 192 | F42: =IF(E42=0,0,(G42/E42)) -> 251.5625 | G42: =ROUND((Purchase!C23),0) -> 48300 | H42: =ROUND((Purchase!B24),0) -> 0 | I42: =IF(H42=0,0,(J42/H42)) -> 0 | J42: =ROUND((Purchase!C24),0) -> 0 | K42: =ROUND((Purchase!B25),0) -> 0 | L42: =IF(K42=0,0,(M42/K42)) -> 0 | M42: =ROUND((Purchase!C25),0) -> 0 | N42: =ROUND((Purchase!B26),0) -> 0 | O42: =IF(N42=0,0,(P42/N42)) -> 0 | P42: =ROUND((Purchase!C26),0) -> 0 | Q42: =ROUND((Purchase!B27),0) -> 0 | R42: =IF(Q42=0,0,(S42/Q42)) -> 0 | S42: =ROUND((Purchase!C27),0) -> 0 | T42: =ROUND((Purchase!B28),0) -> 0 | U42: =IF(T42=0,0,(V42/T42)) -> 0 | V42: =Purchase!C28 -> 0 | W42: =ROUND((Purchase!B29),0) -> 0 | X42: =IF(W42=0,0,(Y42/W42)) -> 0 | Y42: =ROUND((Purchase!C29),0) -> 0 | Z42: =ROUND((Purchase!B30),0) -> 0 | AA42: =IF(Z42=0,0,(AB42/Z42)) -> 0 | AB42: =ROUND((Purchase!C30),0) -> 0 | AC42: =ROUND((Purchase!$B31),0) -> 0 | AD42: =IF(AC42=0,0,(AE42/AC42)) -> 0 | AE42: =ROUND((Purchase!C31),0) -> 0 | AF42: =ROUND((Purchase!$B32),0) -> 0 | AG42: =IF(AF42=0,0,(AH42/AF42)) -> 0 | AH42: =ROUND((Purchase!C32),0) -> 0 | AI42: =ROUND((Purchase!$B33),0) -> 0 | AJ42: =IF(AI42=0,0,(AK42/AI42)) -> 0 | AK42: =ROUND((Purchase!C33),0) -> 0 | AL42: =SUM(B42,E42,H42,K42,N42,Q42,T42,W42,Z42,AC42,AF42,AI42) -> 5414 | AM42: =IF(AL42=0,0,(AN42/AL42)) -> 278.35279 | AN42: =SUM(D42,G42,J42,M42,P42,S42,V42,Y42,AB42,AE42,AH42,AK42) -> 1507002 | AO42: =ROUND((Purchase!C34),0) -> 1507002 | AP42: =AN42-AO42 -> 0
A43: Purchase Consumables | C43: =IF(B43=0,0,(D43/B43)) -> 0 | D43: =ROUND((Purchase!H22),0) -> 283632 | G43: =ROUND((Purchase!H23),0) -> 285732 | J43: =ROUND((Purchase!H24),0) -> 0 | M43: =ROUND((Purchase!H25),0) -> 0 | P43: =ROUND((Purchase!H26),0) -> 0 | S43: =ROUND((Purchase!H27),0) -> 0 | V43: =ROUND((Purchase!H28),0) -> 0 | Y43: =ROUND((Purchase!H29),0) -> 0 | AB43: =ROUND((Purchase!H30),0) -> 0 | AE43: =ROUND((Purchase!H31),0) -> 0 | AH43: =ROUND((Purchase!H32),0) -> 0 | AK43: =ROUND((Purchase!H33),0) -> 0 | AL43: =SUM(B43,E43,H43,K43,N43,Q43,T43,W43,Z43,AC43,AF43,AI43) -> 0 | AM43: =IF(AL43=0,0,(AN43/AL43)) -> 0 | AN43: =SUM(D43,G43,J43,M43,P43,S43,V43,Y43,AB43,AE43,AH43,AK43) -> 569364 | AO43: =ROUND((Purchase!H34),0) -> 569365 | AP43: =AN43-AO43 -> -1
C44: =IF(B44=0,0,(D44/B44)) -> 0
A45: Total Purchases | B45: =SUM(B40:B44) -> 26200.96 | C45: =IF(B45=0,0,(D45/B45)) -> 265.10803 | D45: =SUM(D40:D44) -> 6946085 | E45: =SUM(E40:E44) -> 13526 | F45: =IF(E45=0,0,(G45/E45)) -> 239.50451 | G45: =SUM(G40:G44) -> 3239538 | H45: =SUM(H40:H44) -> 0 | I45: =IF(H45=0,0,(J45/H45)) -> 0 | J45: =SUM(J40:J44) -> 0 | K45: =SUM(K40:K44) -> 0 | L45: =IF(K45=0,0,(M45/K45)) -> 0 | M45: =SUM(M40:M44) -> 0 | N45: =SUM(N40:N44) -> 0 | O45: =IF(N45=0,0,(P45/N45)) -> 0 | P45: =SUM(P40:P44) -> 0 | Q45: =SUM(Q40:Q44) -> 0 | R45: =IF(Q45=0,0,(S45/Q45)) -> 0 | S45: =SUM(S40:S44) -> 0 | T45: =SUM(T40:T44) -> 0 | U45: =IF(T45=0,0,(V45/T45)) -> 0 | V45: =SUM(V40:V44) -> 0 | W45: =SUM(W40:W44) -> 0 | X45: =IF(W45=0,0,(Y45/W45)) -> 0 | Y45: =SUM(Y40:Y44) -> 0 | Z45: =SUM(Z40:Z44) -> 0 | AA45: =IF(Z45=0,0,(AB45/Z45)) -> 0 | AB45: =SUM(AB40:AB44) -> 0 | AC45: =SUM(AC40:AC44) -> 0 | AD45: =IF(AC45=0,0,(AE45/AC45)) -> 0 | AE45: =SUM(AE40:AE44) -> 0 | AF45: =SUM(AF40:AF44) -> 0 | AG45: =IF(AF45=0,0,(AH45/AF45)) -> 0 | AH45: =SUM(AH40:AH44) -> 0 | AI45: =SUM(AI40:AI44) -> 0 | AJ45: =IF(AI45=0,0,(AK45/AI45)) -> 0 | AK45: =SUM(AK40:AK44) -> 0 | AL45: =SUM(AL40:AL44) -> 39726 | AM45: =IF(AL45=0,0,(AN45/AL45)) -> 256.39689 | AN45: =SUM(AN40:AN44) -> 10185623
A46: Less:- Purchase return | C46: =IF(B46=0,0,(D46/B46)) -> 0 | F46: =IF(E46=0,0,(G46/E46)) -> 0 | I46: =IF(H46=0,0,(J46/H46)) -> 0 | L46: =IF(K46=0,0,(M46/K46)) -> 0 | AL46: =SUM(B46:AI46) -> 0 | AN46: =SUM(D47,G47,J47,M47,P47,S47,V47,Y47,AB47,AE47,AH47,AK47) -> 0
A47: Less :- Sales | C47: =IF(B47=0,0,(D47/B47)) -> 0 | D47: =D11+D19+D27 -> 0 | F47: =IF(E47=0,0,(G47/E47)) -> 0 | G47: =G11+G19+G27 -> 0 | I47: =IF(H47=0,0,(J47/H47)) -> 0 | J47: =J11+J19+J27 -> 0 | L47: =IF(K47=0,0,(M47/K47)) -> 0 | M47: =M11+M19+M27 -> 0 | AM47: =IF(AL47=0,0,(AN46/AL47)) -> 0 | AN47: =AN11+AN19+AN27 -> 0
A48: Closing Stock | C48: =IF(B48=0,0,(D48/B48)) -> 0 | F48: =IF(E48=0,0,(G48/E48)) -> 0 | I48: =IF(H48=0,0,(J48/H48)) -> 0 | L48: =IF(K48=0,0,(M48/K48)) -> 0 | AL48: =T48 -> 0 | AM48: =IF(AL48=0,0,(AN48/AL48)) -> 0 | AN48: =V48 -> 0
A49: Consumption Monofil | B49: =(B39+B45)-(B46+B47+B48) -> 26200.96 | C49: =IF(B49=0,0,(D49/B49)) -> 265.10803 | D49: =(D39+D45)-(D46+D47+D48) -> 6946085 | E49: =(E39+E45)-(E46+E47+E48) -> 13526 | F49: =IF(E49=0,0,(G49/E49)) -> 239.50451 | G49: =(G39+G45)-(G46+G47+G48) -> 3239538 | H49: =(H39+H45)-(H46+H47+H48) -> 0 | I49: =IF(H49=0,0,(J49/H49)) -> 0 | J49: =(J39+J45)-(J46+J47+J48) -> 0 | K49: =(K39+K45)-(K46+K47+K48) -> 0 | L49: =IF(K49=0,0,(M49/K49)) -> 0 | M49: =(M39+M45)-(M46+M47+M48) -> 0 | N49: =(N39+N45)-(N46+N47+N48) -> 0 | O49: =IF(N49=0,0,(P49/N49)) -> 0 | P49: =(P39+P45)-(P46+P47+P48) -> 0 | Q49: =(Q39+Q45)-(Q46+Q47+Q48) -> 0 | R49: =IF(Q49=0,0,(S49/Q49)) -> 0 | S49: =(S39+S45)-(S46+S47+S48) -> 0 | T49: =(T39+T45)-(T46+T47+T48) -> 0 | U49: =IF(T49=0,0,(V49/T49)) -> 0 | V49: =(V39+V45)-(V46+V47+V48) -> 0 | W49: =(W39+W45)-(W46+W47+W48) -> 0 | X49: =IF(W49=0,0,(Y49/W49)) -> 0 | Y49: =(Y39+Y45)-(Y46+Y47+Y48) -> 0 | Z49: =(Z39+Z45)-(Z46+Z47+Z48) -> 0 | AA49: =IF(Z49=0,0,(AB49/Z49)) -> 0 | AB49: =(AB39+AB45)-(AB46+AB47+AB48) -> 0 | AC49: =(AC39+AC45)-(AC46+AC47+AC48) -> 0 | AD49: =IF(AC49=0,0,(AE49/AC49)) -> 0 | AE49: =(AE39+AE45)-(AE46+AE47+AE48) -> 0 | AF49: =(AF39+AF45)-(AF46+AF47+AF48) -> 0 | AG49: =IF(AF49=0,0,(AH49/AF49)) -> 0 | AH49: =(AH39+AH45)-(AH46+AH47+AH48) -> 0 | AI49: =(AI39+AI45)-(AI46+AI47+AI48) -> 0 | AJ49: =IF(AI49=0,0,(AK49/AI49)) -> 0 | AK49: =(AK39+AK45)-(AK46+AK47+AK48) -> 0 | AL49: =(AL39+AL45)-(AL46+AL47+AL48) -> 39726 | AM49: =IF(AL49=0,0,(AN49/AL49)) -> 256.39689 | AN49: =(AN39+AN45)-(AN46+AN47+AN48) -> 10185623
A51: MONOFIL CONSUMPTION | B51: =B34+B49 -> 92408.96 | C51: =D51/B51 -> 152.09301 | D51: =D34+D49 -> 14054757 | E51: =E34+E49 -> 75959 | F51: =G51/E51 -> 147.51532 | G51: =G34+G49 -> 11205116 | H51: =H34+H49 -> 92299 | I51: =J51/H51 -> 155.48953 | J51: =J34+J49 -> 14351528 | K51: =K34+K49 -> 0 | L51: =M51/K51 -> #DIV/0! | M51: =M34+M49 -> 0 | N51: =N34+N49 -> -1 | O51: =P51/N51 -> 0 | P51: =P34+P49 -> 0 | Q51: =Q34+Q49 -> 0 | R51: =S51/Q51 -> #DIV/0! | S51: =S34+S49 -> 0 | T51: =T34+T49 -> 0 | U51: =V51/T51 -> #DIV/0! | V51: =V34+V49 -> 0 | W51: =W34+W49 -> 0 | X51: =Y51/W51 -> #DIV/0! | Y51: =Y34+Y49 -> 0 | Z51: =Z34+Z49 -> 0 | AA51: =AB51/Z51 -> #DIV/0! | AB51: =AB34+AB49 -> 0 | AC51: =AC34+AC49 -> 0 | AD51: =AE51/AC51 -> #DIV/0! | AE51: =AE34+AE49 -> 0 | AF51: =AF34+AF49 -> 0 | AG51: =AH51/AF51 -> #DIV/0! | AH51: =AH34+AH49 -> 0 | AI51: =AI34+AI49 -> 0 | AJ51: =AK51/AI51 -> #DIV/0! | AK51: =AK34+AK49 -> 0 | AL51: =AL34+AL49 -> 260665 | AM51: =AN51/AL51 -> 151.96287 | AN51: =AN34+AN49 -> 39611401
A53: Trading Consumption
A54: Opening Stock | B54: ='Stock Valuation (FIFO)'!B21 -> 1041 | C54: =IF(B54=0,0,(D54/B54)) -> 221.96926 | D54: ='Stock Valuation (FIFO)'!D21 -> 231070 | E54: =B59 -> 941 | F54: =IF(E54=0,0,(G54/E54)) -> 238.73751 | G54: =D59 -> 224652 | H54: =E59 -> 1039 | I54: =IF(H54=0,0,(J54/H54)) -> 236.73917 | J54: =G59 -> 245972 | K54: =H59 -> 0 | L54: =IF(K54=0,0,(M54/K54)) -> 0 | M54: =J59 -> 0 | N54: =K59 -> 0 | O54: =IF(N54=0,0,(P54/N54)) -> 0 | P54: =M59 -> 0 | Q54: =N59 -> 0 | R54: =IF(Q54=0,0,(S54/Q54)) -> 0 | S54: =P59 -> 0 | T54: =Q59 -> 0 | U54: =IF(T54=0,0,(V54/T54)) -> 0 | V54: =S59 -> 0 | W54: =T59 -> 0 | X54: =IF(W54=0,0,(Y54/W54)) -> 0 | Y54: =V59 -> 0 | Z54: =W59 -> 0 | AA54: =IF(Z54=0,0,(AB54/Z54)) -> 0 | AB54: =Y59 -> 0 | AC54: =Z59 -> 0 | AD54: =IF(AC54=0,0,(AE54/AC54)) -> 0 | AE54: =AB59 -> 0 | AF54: =AC59 -> 0 | AG54: =IF(AF54=0,0,(AH54/AF54)) -> 0 | AH54: =AE59 -> 0 | AI54: =AF59 -> 0 | AJ54: =IF(AI54=0,0,(AK54/AI54)) -> 0 | AK54: =AH59 -> 0 | AL54: =B54 -> 1041 | AM54: =IF(AL54=0,0,(AN54/AL54)) -> 221.96926 | AN54: =D54 -> 231070
A55: Add:- Purchases | B55: =ROUND((Purchase!$K52),0) -> 9490 | C55: =IF(B55=0,0,(D55/B55)) -> 234.41296 | D55: =ROUND((Purchase!$L52),0) -> 2224579 | E55: =ROUND((Purchase!$K53),0) -> 6627 | F55: =IF(E55=0,0,(G55/E55)) -> 221.85816 | G55: =ROUND((Purchase!$L53),0) -> 1470254 | H55: =ROUND((Purchase!$K54),0) -> 0 | I55: =IF(H55=0,0,(J55/H55)) -> 0 | J55: =ROUND((Purchase!$L54),0) -> 0 | K55: =ROUND((Purchase!$K55),0) -> 0 | L55: =IF(K55=0,0,(M55/K55)) -> 0 | M55: =ROUND((Purchase!$L55),0) -> 0 | N55: =ROUND((Purchase!$K56),0) -> 0 | O55: =IF(N55=0,0,(P55/N55)) -> 0 | P55: =ROUND((Purchase!$L56),0) -> 0 | Q55: =ROUND((Purchase!$K57),0) -> 0 | R55: =IF(Q55=0,0,(S55/Q55)) -> 0 | S55: =ROUND((Purchase!$L57),0) -> 0 | T55: =ROUND((Purchase!$K58),0) -> 0 | U55: =IF(T55=0,0,(V55/T55)) -> 0 | V55: =ROUND((Purchase!$L58),0) -> 0 | W55: =ROUND((Purchase!$K59),0) -> 0 | X55: =IF(W55=0,0,(Y55/W55)) -> 0 | Y55: =ROUND((Purchase!$L59),0) -> 0 | Z55: =ROUND((Purchase!$K60),0) -> 0 | AA55: =IF(Z55=0,0,(AB55/Z55)) -> 0 | AB55: =ROUND((Purchase!$L60),0) -> 0 | AC55: =ROUND((Purchase!$K61),0) -> 0 | AD55: =IF(AC55=0,0,(AE55/AC55)) -> 0 | AE55: =ROUND((Purchase!$L61),0) -> 0 | AF55: =ROUND((Purchase!$K62),0) -> 0 | AG55: =IF(AF55=0,0,(AH55/AF55)) -> 0 | AH55: =ROUND((Purchase!$L62),0) -> 0 | AI55: =ROUND((Purchase!$K63),0) -> 0 | AJ55: =IF(AI55=0,0,(AK55/AI55)) -> 0 | AK55: =ROUND((Purchase!$L63),0) -> 0 | AL55: =ROUND((Purchase!K64),0) -> 16116 | AM55: =IF(AL55=0,0,(AN55/AL55)) -> 229.26489 | AN55: =ROUND((Purchase!L64),0) -> 3694833 | AO55: =Purchase!L64 -> 3694833 | AP55: =AN55-AO55 -> 0
A56: Add:- Job Work Rcpts | C56: =IF(B56=0,0,(D56/B56)) -> 0 | F56: =IF(E56=0,0,(G56/E56)) -> 0 | I56: =IF(H56=0,0,(J56/H56)) -> 0 | L56: =IF(K56=0,0,(M56/K56)) -> 0 | O56: =IF(N56=0,0,(P56/N56)) -> 0 | R56: =IF(Q56=0,0,(S56/Q56)) -> 0 | U56: =IF(T56=0,0,(V56/T56)) -> 0 | X56: =IF(W56=0,0,(Y56/W56)) -> 0 | AA56: =IF(Z56=0,0,(AB56/Z56)) -> 0 | AD56: =IF(AC56=0,0,(AE56/AC56)) -> 0 | AG56: =IF(AF56=0,0,(AH56/AF56)) -> 0 | AJ56: =IF(AI56=0,0,(AK56/AI56)) -> 0 | AL56: =SUM(B56:AI56) -> 0
A57: Less:- Purchase return | C57: =IF(B57=0,0,(D57/B57)) -> 0 | F57: =IF(E57=0,0,(G57/E57)) -> 0 | I57: =IF(H57=0,0,(J57/H57)) -> 0 | L57: =IF(K57=0,0,(M57/K57)) -> 0 | O57: =IF(N57=0,0,(P57/N57)) -> 0 | R57: =IF(Q57=0,0,(S57/Q57)) -> 0 | U57: =IF(T57=0,0,(V57/T57)) -> 0 | X57: =IF(W57=0,0,(Y57/W57)) -> 0 | AA57: =IF(Z57=0,0,(AB57/Z57)) -> 0 | AD57: =IF(AC57=0,0,(AE57/AC57)) -> 0 | AG57: =IF(AF57=0,0,(AH57/AF57)) -> 0 | AJ57: =IF(AI57=0,0,(AK57/AI57)) -> 0 | AL57: =SUM(B57:AI57) -> 0
A58: Less :- Sales | B58: =B19+B27+B35 -> 0 | C58: =IF(B58=0,0,(D58/B58)) -> 0 | D58: =D19+D27+D35 -> 0 | E58: =E19+E27+E35 -> 0 | F58: =IF(E58=0,0,(G58/E58)) -> 0 | G58: =G19+G27+G35 -> 0 | H58: =H19+H27+H35 -> 0 | I58: =IF(H58=0,0,(J58/H58)) -> 0 | J58: =J19+J27+J35 -> 0 | K58: =K19+K27+K35 -> 0 | L58: =IF(K58=0,0,(M58/K58)) -> 0 | M58: =M19+M27+M35 -> 0 | N58: =N19+N27+N35 -> 0 | O58: =IF(N58=0,0,(P58/N58)) -> 0 | P58: =P19+P27+P35 -> 0 | Q58: =Q19+Q27+Q35 -> 0 | R58: =IF(Q58=0,0,(S58/Q58)) -> 0 | S58: =S19+S27+S35 -> 0 | T58: =T19+T27+T35 -> 0 | U58: =IF(T58=0,0,(V58/T58)) -> 0 | V58: =V19+V27+V35 -> 0 | W58: =W19+W27+W35 -> 0 | X58: =IF(W58=0,0,(Y58/W58)) -> 0 | Y58: =Y19+Y27+Y35 -> 0 | AA58: =IF(Z58=0,0,(AB58/Z58)) -> 0 | AD58: =IF(AC58=0,0,(AE58/AC58)) -> 0 | AG58: =IF(AF58=0,0,(AH58/AF58)) -> 0 | AJ58: =IF(AI58=0,0,(AK58/AI58)) -> 0 | AL58: =SUM(B58,E58,H58,K58,N58,Q58,T58,W58,Z58,AC58,AF58,AI58) -> 0 | AM58: =IF(AL58=0,0,(AN58/AL58)) -> 0 | AN58: =SUM(D58,G58,J58,M58,P58,S58,V58,Y58,AB58,AE58,AH58,AK58) -> 0
A59: Closing Stock | B59: =ROUND(('Stock Valuation (FIFO)'!E21),0) -> 941 | C59: =IF(B59=0,0,(D59/B59)) -> 238.73751 | D59: =ROUND(('Stock Valuation (FIFO)'!G21),0) -> 224652 | E59: =ROUND(('Stock Valuation (FIFO)'!H21),0) -> 1039 | F59: =IF(E59=0,0,(G59/E59)) -> 236.73917 | G59: =ROUND(('Stock Valuation (FIFO)'!J21),0) -> 245972 | H59: =ROUND(('Stock Valuation (FIFO)'!K21),0) -> 0 | I59: =IF(H59=0,0,(J59/H59)) -> 0 | J59: =ROUND(('Stock Valuation (FIFO)'!M21),0) -> 0 | K59: =ROUND(('Stock Valuation (FIFO)'!N21),0) -> 0 | L59: =IF(K59=0,0,(M59/K59)) -> 0 | M59: =ROUND(('Stock Valuation (FIFO)'!P21),0) -> 0 | N59: =ROUND(('Stock Valuation (FIFO)'!Q21),0) -> 0 | O59: =IF(N59=0,0,(P59/N59)) -> 0 | P59: =ROUND(('Stock Valuation (FIFO)'!S21),0) -> 0 | Q59: =ROUND(('Stock Valuation (FIFO)'!T21),0) -> 0 | R59: =IF(Q59=0,0,(S59/Q59)) -> 0 | S59: =ROUND(('Stock Valuation (FIFO)'!V21),0) -> 0 | T59: =ROUND(('Stock Valuation (FIFO)'!W21),0) -> 0 | U59: =IF(T59=0,0,(V59/T59)) -> 0 | V59: =ROUND(('Stock Valuation (FIFO)'!Y21),0) -> 0 | W59: ='Stock Valuation (FIFO)'!Z21 -> 0 | X59: =IF(W59=0,0,(Y59/W59)) -> 0 | Y59: ='Stock Valuation (FIFO)'!AB21 -> 0 | Z59: ='Stock Valuation (FIFO)'!AC21 -> 0 | AA59: =IF(Z59=0,0,(AB59/Z59)) -> 0 | AB59: ='Stock Valuation (FIFO)'!AE21 -> 0 | AC59: ='Stock Valuation (FIFO)'!AF21 -> 0 | AD59: =IF(AC59=0,0,(AE59/AC59)) -> 0 | AE59: ='Stock Valuation (FIFO)'!AH21 -> 0 | AF59: ='Stock Valuation (FIFO)'!AI21 -> 0 | AG59: =IF(AF59=0,0,(AH59/AF59)) -> 0 | AH59: ='Stock Valuation (FIFO)'!AK21 -> 0 | AI59: ='Stock Valuation (FIFO)'!AL21 -> 0 | AJ59: =IF(AI59=0,0,(AK59/AI59)) -> 0 | AK59: ='Stock Valuation (FIFO)'!AN21 -> 0 | AL59: =AI59 -> 0 | AM59: =IF(AL59=0,0,(AN59/AL59)) -> 0 | AN59: =AK59 -> 0
A60: Consumption Trading | B60: =(B54+B55)-(B58+B59) -> 9590 | C60: =IF(B60=0,0,(D60/B60)) -> 232.63785 | D60: =(D54+D55)-(D58+D59) -> 2230997 | E60: =(E54+E55)-(E58+E59) -> 6529 | F60: =IF(E60=0,0,(G60/E60)) -> 221.92281 | G60: =(G54+G55)-(G58+G59) -> 1448934 | H60: =(H54+H55)-(H58+H59) -> 1039 | I60: =IF(H60=0,0,(J60/H60)) -> 236.73917 | J60: =(J54+J55)-(J58+J59) -> 245972 | K60: =(K54+K55)-(K58+K59) -> 0 | L60: =IF(K60=0,0,(M60/K60)) -> 0 | M60: =(M54+M55)-(M58+M59) -> 0 | N60: =(N54+N55)-(N58+N59) -> 0 | O60: =IF(N60=0,0,(P60/N60)) -> 0 | P60: =(P54+P55)-(P58+P59) -> 0 | Q60: =(Q54+Q55)-(Q58+Q59) -> 0 | R60: =IF(Q60=0,0,(S60/Q60)) -> 0 | S60: =(S54+S55)-(S58+S59) -> 0 | T60: =(T54+T55)-(T58+T59) -> 0 | U60: =IF(T60=0,0,(V60/T60)) -> 0 | V60: =(V54+V55)-(V58+V59) -> 0 | W60: =(W54+W55)-(W58+W59) -> 0 | X60: =IF(W60=0,0,(Y60/W60)) -> 0 | Y60: =(Y54+Y55)-(Y58+Y59) -> 0 | Z60: =(Z54+Z55)-(Z58+Z59) -> 0 | AA60: =IF(Z60=0,0,(AB60/Z60)) -> 0 | AB60: =(AB54+AB55)-(AB58+AB59) -> 0 | AC60: =(AC54+AC55)-(AC58+AC59) -> 0 | AD60: =IF(AC60=0,0,(AE60/AC60)) -> 0 | AE60: =(AE54+AE55)-(AE58+AE59) -> 0 | AF60: =(AF54+AF55)-(AF58+AF59) -> 0 | AG60: =IF(AF60=0,0,(AH60/AF60)) -> 0 | AH60: =(AH54+AH55)-(AH58+AH59) -> 0 | AI60: =(AI54+AI55)-(AI58+AI59) -> 0 | AJ60: =IF(AI60=0,0,(AK60/AI60)) -> 0 | AK60: =(AK54+AK55)-(AK58+AK59) -> 0 | AL60: =(AL54+AL55)-(AL58+AL59) -> 17157 | AM60: =IF(AL60=0,0,(AN60/AL60)) -> 228.82223 | AN60: =(AN54+AN55)-(AN58+AN59) -> 3925903
A62: Total CONSUMPTION Priyafil
A63: Opening Stock | B63: =B28+B39 -> 143489 | C63: =IF(B63=0,0,(D63/B63)) -> 123.87463 | D63: =D28+D39 -> 17774647 | E63: =B73 -> 79049 | F63: =IF(E63=0,0,(G63/E63)) -> 140.63013 | G63: =D73 -> 11116671 | H63: =E73 -> 93338 | I63: =IF(H63=0,0,(J63/H63)) -> 156.39397 | J63: =G73 -> 14597500 | K63: =H73 -> 0 | L63: =IF(K63=0,0,(M63/K63)) -> 0 | M63: =J73 -> 0 | N63: =K73 -> 0 | O63: =IF(N63=0,0,(P63/N63)) -> 0 | P63: =M73 -> 0 | Q63: =N73 -> 0 | R63: =IF(Q63=0,0,(S63/Q63)) -> 0 | S63: =P73 -> 0 | T63: =Q73 -> 0 | U63: =IF(T63=0,0,(V63/T63)) -> 0 | V63: =S73 -> 0 | W63: =T73 -> 0 | X63: =IF(W63=0,0,(Y63/W63)) -> 0 | Y63: =V73 -> 0 | Z63: =W73 -> 0 | AA63: =IF(Z63=0,0,(AB63/Z63)) -> 0 | AB63: =Y73 -> 0 | AC63: =Z73 -> 0 | AD63: =IF(AC63=0,0,(AE63/AC63)) -> 0 | AE63: =AB73 -> 0 | AF63: =AC73 -> 0 | AG63: =IF(AF63=0,0,(AH63/AF63)) -> 0 | AH63: =AE73 -> 0 | AI63: =AF73 -> 0 | AJ63: =IF(AI63=0,0,(AK63/AI63)) -> 0 | AK63: =AH73 -> 0 | AL63: =AL28+AL39 -> 143489 | AM63: =IF(AL63=0,0,(AN63/AL63)) -> 123.87463 | AN63: =AN28+AN39 -> 17774647
A64: Add:- Purchases HD | B64: =B5 -> 0 | C64: =IF(B64=0,0,(D64/B64)) -> 0 | D64: =D5 -> 0 | E64: =E5 -> 76000 | F64: =IF(E64=0,0,(G64/E64)) -> 148.18653 | G64: =G5 -> 11262176 | H64: =H5 -> 0 | I64: =IF(H64=0,0,(J64/H64)) -> 0 | J64: =J5 -> 0 | K64: =K5 -> 0 | L64: =IF(K64=0,0,(M64/K64)) -> 0 | M64: =M5 -> 0 | N64: =N5 -> 0 | O64: =IF(N64=0,0,(P64/N64)) -> 0 | P64: =P5 -> 0 | Q64: =Q5 -> 0 | R64: =IF(Q64=0,0,(S64/Q64)) -> 0 | S64: =S5 -> 0 | T64: =T5 -> 0 | U64: =IF(T64=0,0,(V64/T64)) -> 0 | V64: =V5 -> 0 | W64: =W5 -> 0 | X64: =IF(W64=0,0,(Y64/W64)) -> 0 | Y64: =Y5 -> 0 | Z64: =Z5 -> 0 | AA64: =IF(Z64=0,0,(AB64/Z64)) -> 0 | AB64: =AB5 -> 0 | AC64: =AC5 -> 0 | AD64: =IF(AC64=0,0,(AE64/AC64)) -> 0 | AE64: =AE5 -> 0 | AF64: =AF5 -> 0 | AG64: =IF(AF64=0,0,(AH64/AF64)) -> 0 | AH64: =AH5 -> 0 | AI64: =AI5 -> 0 | AJ64: =IF(AI64=0,0,(AK64/AI64)) -> 0 | AK64: =AK5 -> 0 | AL64: =AL5 -> 76000 | AM64: =IF(AL64=0,0,(AN64/AL64)) -> 148.18653 | AN64: =AN5 -> 11262176 | AO64: =AO5 -> 11262176 | AP64: =AN64-AO64 -> 0
A65: Add:- Purchases MB | B65: =B13 -> 823 | C65: =IF(B65=0,0,(D65/B65)) -> 270.55164 | D65: =D13 -> 222664 | E65: =E13 -> 647 | F65: =IF(E65=0,0,(G65/E65)) -> 263.66461 | G65: =G13 -> 170591 | H65: =H13 -> 0 | I65: =IF(H65=0,0,(J65/H65)) -> 0 | J65: =J13 -> 0 | K65: =K13 -> 0 | L65: =IF(K65=0,0,(M65/K65)) -> 0 | M65: =M13 -> 0 | N65: =N13 -> 0 | O65: =IF(N65=0,0,(P65/N65)) -> 0 | P65: =P13 -> 0 | Q65: =Q13 -> 0 | R65: =IF(Q65=0,0,(S65/Q65)) -> 0 | S65: =S13 -> 0 | T65: =T13 -> 0 | U65: =IF(T65=0,0,(V65/T65)) -> 0 | V65: =V13 -> 0 | W65: =W13 -> 0 | X65: =IF(W65=0,0,(Y65/W65)) -> 0 | Y65: =Y13 -> 0 | Z65: =Z13 -> 0 | AA65: =IF(Z65=0,0,(AB65/Z65)) -> 0 | AB65: =AB13 -> 0 | AC65: =AC13 -> 0 | AD65: =IF(AC65=0,0,(AE65/AC65)) -> 0 | AE65: =AE13 -> 0 | AF65: =AF13 -> 0 | AG65: =IF(AF65=0,0,(AH65/AF65)) -> 0 | AH65: =AH13 -> 0 | AI65: =AI13 -> 0 | AJ65: =IF(AI65=0,0,(AK65/AI65)) -> 0 | AK65: =AK13 -> 0 | AL65: =AL13 -> 1470 | AM65: =IF(AL65=0,0,(AN65/AL65)) -> 267.52041 | AN65: =AN13 -> 393255 | AO65: =AO13 -> 393255 | AP65: =AN65-AO65 -> 0
A66: Add:- Purchases CP | B66: =B21 -> 4 | C66: =IF(B66=0,0,(D66/B66)) -> 845 | D66: =D21 -> 3380 | E66: =E21 -> 2 | F66: =IF(E66=0,0,(G66/E66)) -> 910 | G66: =G21 -> 1820 | H66: =H21 -> 0 | I66: =IF(H66=0,0,(J66/H66)) -> 0 | J66: =J21 -> 0 | K66: =K21 -> 0 | L66: =IF(K66=0,0,(M66/K66)) -> 0 | M66: =M21 -> 0 | N66: =N21 -> -1 | O66: =IF(N66=0,0,(P66/N66)) -> 0 | P66: =P21 -> 0 | Q66: =Q21 -> 0 | R66: =IF(Q66=0,0,(S66/Q66)) -> 0 | S66: =S21 -> 0 | T66: =T21 -> 0 | U66: =IF(T66=0,0,(V66/T66)) -> 0 | V66: =V21 -> 0 | W66: =W21 -> 0 | X66: =IF(W66=0,0,(Y66/W66)) -> 0 | Y66: =Y21 -> 0 | Z66: =Z21 -> 0 | AA66: =IF(Z66=0,0,(AB66/Z66)) -> 0 | AB66: =AB21 -> 0 | AC66: =AC21 -> 0 | AD66: =IF(AC66=0,0,(AE66/AC66)) -> 0 | AE66: =AE21 -> 0 | AF66: =AF21 -> 0 | AG66: =IF(AF66=0,0,(AH66/AF66)) -> 0 | AH66: =AH21 -> 0 | AI66: =AI21 -> 0 | AJ66: =IF(AI66=0,0,(AK66/AI66)) -> 0 | AK66: =AK21 -> 0 | AL66: =AL21 -> 5 | AM66: =IF(AL66=0,0,(AN66/AL66)) -> 1040 | AN66: =AN21 -> 5200 | AO66: =AO21 -> 5200 | AP66: =AN66-AO66 -> 0
A67: Add:- Purchases Monofil Yarn | B67: =B40 -> 3668 | C67: =IF(B67=0,0,(D67/B67)) -> 182.33397 | D67: =D40 -> 668801 | E67: =E40 -> 4150 | F67: =IF(E67=0,0,(G67/E67)) -> 111.38554 | G67: =G40 -> 462250 | H67: =H40 -> 0 | I67: =IF(H67=0,0,(J67/H67)) -> 0 | J67: =J40 -> 0 | K67: =K40 -> 0 | L67: =IF(K67=0,0,(M67/K67)) -> 0 | M67: =M40 -> 0 | N67: =N40 -> 0 | O67: =IF(N67=0,0,(P67/N67)) -> 0 | P67: =P40 -> 0 | Q67: =Q40 -> 0 | R67: =IF(Q67=0,0,(S67/Q67)) -> 0 | S67: =S40 -> 0 | T67: =T40 -> 0 | U67: =IF(T67=0,0,(V67/T67)) -> 0 | V67: =V40 -> 0 | W67: =W40 -> 0 | X67: =IF(W67=0,0,(Y67/W67)) -> 0 | Y67: =Y40 -> 0 | Z67: =Z40 -> 0 | AA67: =IF(Z67=0,0,(AB67/Z67)) -> 0 | AB67: =AB40 -> 0 | AC67: =AC40 -> 0 | AD67: =IF(AC67=0,0,(AE67/AC67)) -> 0 | AE67: =AE40 -> 0 | AF67: =AF40 -> 0 | AG67: =IF(AF67=0,0,(AH67/AF67)) -> 0 | AH67: =AH40 -> 0 | AI67: =AI40 -> 0 | AJ67: =IF(AI67=0,0,(AK67/AI67)) -> 0 | AK67: =AK40 -> 0 | AL67: =AL40 -> 7818 | AM67: =IF(AL67=0,0,(AN67/AL67)) -> 144.67268 | AN67: =AN40 -> 1131051
A68: Add:- Purchases Monofil Fab | B68: =B41+B42 -> 22532.96 | C68: =IF(B68=0,0,(D68/B68)) -> 278.58231 | D68: =D41+D42+D43 -> 6277284 | E68: =E41+E42 -> 9376 | F68: =IF(E68=0,0,(G68/E68)) -> 296.21246 | G68: =G41+G42+G43 -> 2777288 | H68: =H41+H42 -> 0 | I68: =IF(H68=0,0,(J68/H68)) -> 0 | J68: =J41+J42+J43 -> 0 | K68: =K41+K42 -> 0 | L68: =IF(K68=0,0,(M68/K68)) -> 0 | M68: =M41+M42+M43 -> 0 | N68: =N41+N42 -> 0 | O68: =IF(N68=0,0,(P68/N68)) -> 0 | P68: =P41+P42+P43 -> 0 | Q68: =Q41+Q42 -> 0 | R68: =IF(Q68=0,0,(S68/Q68)) -> 0 | S68: =S41+S42+S43 -> 0 | T68: =T41+T42 -> 0 | U68: =IF(T68=0,0,(V68/T68)) -> 0 | V68: =V41+V42+V43 -> 0 | W68: =W41+W42 -> 0 | X68: =IF(W68=0,0,(Y68/W68)) -> 0 | Y68: =Y41+Y42+Y43 -> 0 | Z68: =Z41+Z42 -> 0 | AA68: =IF(Z68=0,0,(AB68/Z68)) -> 0 | AB68: =AB41+AB42+AB43 -> 0 | AC68: =AC41+AC42 -> 0 | AD68: =IF(AC68=0,0,(AE68/AC68)) -> 0 | AE68: =AE41+AE42+AE43 -> 0 | AF68: =AF41+AF42 -> 0 | AG68: =IF(AF68=0,0,(AH68/AF68)) -> 0 | AH68: =AH41+AH42+AH43 -> 0 | AI68: =AI41+AI42 -> 0 | AJ68: =IF(AI68=0,0,(AK68/AI68)) -> 0 | AK68: =AK41+AK42+AK43 -> 0 | AL68: =AL41+AL42 -> 31908 | AM68: =IF(AL68=0,0,(AN68/AL68)) -> 283.77122 | AN68: =AN41+AN42+AN43 -> 9054572 | AO68: =AO41+AO42+AO43 -> 9054573 | AP68: =AN68-AO68 -> -1
A69: Add:- Purchase Trading | B69: =B55 -> 9490 | C69: =IF(B69=0,0,(D69/B69)) -> 234.41296 | D69: =D55 -> 2224579 | E69: =E55 -> 6627 | F69: =IF(E69=0,0,(G69/E69)) -> 221.85816 | G69: =G55 -> 1470254 | H69: =H55 -> 0 | I69: =IF(H69=0,0,(J69/H69)) -> 0 | J69: =J55 -> 0 | K69: =K55 -> 0 | L69: =IF(K69=0,0,(M69/K69)) -> 0 | M69: =M55 -> 0 | N69: =N55 -> 0 | O69: =IF(N69=0,0,(P69/N69)) -> 0 | P69: =P55 -> 0 | Q69: =Q55 -> 0 | R69: =IF(Q69=0,0,(S69/Q69)) -> 0 | S69: =S55 -> 0 | T69: =T55 -> 0 | U69: =IF(T69=0,0,(V69/T69)) -> 0 | V69: =V55 -> 0 | W69: =W55 -> 0 | X69: =IF(W69=0,0,(Y69/W69)) -> 0 | Y69: =Y55 -> 0 | Z69: =Z55 -> 0 | AA69: =IF(Z69=0,0,(AB69/Z69)) -> 0 | AB69: =AB55 -> 0 | AC69: =AC55 -> 0 | AD69: =IF(AC69=0,0,(AE69/AC69)) -> 0 | AE69: =AE55 -> 0 | AF69: =AF55 -> 0 | AG69: =IF(AF69=0,0,(AH69/AF69)) -> 0 | AH69: =AH55 -> 0 | AI69: =AI55 -> 0 | AJ69: =IF(AI69=0,0,(AK69/AI69)) -> 0 | AK69: =AK55 -> 0 | AL69: =AL55 -> 16116 | AM69: =IF(AL69=0,0,(AN69/AL69)) -> 229.26489 | AN69: =AN55 -> 3694833 | AO69: =AO55 -> 3694833 | AP69: =AN69-AO69 -> 0
B70: =SUM(B64:B69) -> 36517.96 | C70: =D70/B70 -> 257.31744 | D70: =SUM(D64:D69) -> 9396708 | E70: =SUM(E64:E69) -> 96802 | F70: =G70/E70 -> 166.77733 | G70: =SUM(G64:G69) -> 16144379 | H70: =SUM(H64:H69) -> 0 | I70: =J70/H70 -> #DIV/0! | J70: =SUM(J64:J69) -> 0 | K70: =SUM(K64:K69) -> 0 | L70: =M70/K70 -> #DIV/0! | M70: =SUM(M64:M69) -> 0 | N70: =SUM(N64:N69) -> -1 | O70: =P70/N70 -> 0 | P70: =SUM(P64:P69) -> 0 | Q70: =SUM(Q64:Q69) -> 0 | R70: =S70/Q70 -> #DIV/0! | S70: =SUM(S64:S69) -> 0 | T70: =SUM(T64:T69) -> 0 | U70: =V70/T70 -> #DIV/0! | V70: =SUM(V64:V69) -> 0 | W70: =SUM(W64:W69) -> 0 | X70: =Y70/W70 -> #DIV/0! | Y70: =SUM(Y64:Y69) -> 0 | Z70: =SUM(Z64:Z69) -> 0 | AA70: =AB70/Z70 -> #DIV/0! | AB70: =SUM(AB64:AB69) -> 0 | AC70: =SUM(AC64:AC69) -> 0 | AD70: =AE70/AC70 -> #DIV/0! | AE70: =SUM(AE64:AE69) -> 0 | AF70: =SUM(AF64:AF69) -> 0 | AG70: =AH70/AF70 -> #DIV/0! | AH70: =SUM(AH64:AH69) -> 0 | AI70: =SUM(AI64:AI69) -> 0 | AJ70: =AK70/AI70 -> #DIV/0! | AK70: =SUM(AK64:AK69) -> 0 | AL70: =SUM(AL64:AL69) -> 133317 | AM70: =AN70/AL70 -> 191.58162 | AN70: =SUM(AN64:AN69) -> 25541087 | AO70: =SUM(AO64:AO69) -> 24410037 | AP70: =SUM(AP64:AP69) -> -1
A71: Less:- Purchase return | C71: =IF(B71=0,0,(D71/B71)) -> 0 | F71: =IF(E71=0,0,(G71/E71)) -> 0 | I71: =IF(H71=0,0,(J71/H71)) -> 0 | L71: =IF(K71=0,0,(M71/K71)) -> 0 | O71: =IF(N71=0,0,(P71/N71)) -> 0 | R71: =IF(Q71=0,0,(S71/Q71)) -> 0 | U71: =IF(T71=0,0,(V71/T71)) -> 0 | X71: =IF(W71=0,0,(Y71/W71)) -> 0 | AA71: =IF(Z71=0,0,(AB71/Z71)) -> 0 | AD71: =IF(AC71=0,0,(AE71/AC71)) -> 0 | AG71: =IF(AF71=0,0,(AH71/AF71)) -> 0 | AJ71: =IF(AI71=0,0,(AK71/AI71)) -> 0 | AM71: =IF(AL71=0,0,(AN71/AL71)) -> 0
A72: Less :- RM Sales | B72: =B32 -> 0 | C72: =IF(B72=0,0,(D72/B72)) -> 0 | D72: =D32 -> 0 | E72: =E32 -> 25 | F72: =IF(E72=0,0,(G72/E72)) -> 380 | G72: =G32 -> 9500 | H72: =H32 -> 0 | I72: =IF(H72=0,0,(J72/H72)) -> 0 | J72: =J32 -> 0 | K72: =K32 -> 0 | L72: =IF(K72=0,0,(M72/K72)) -> 0 | M72: =M32 -> 0 | N72: =N32 -> 0 | O72: =IF(N72=0,0,(P72/N72)) -> 0 | P72: =P32 -> 0 | Q72: =Q32 -> 0 | R72: =IF(Q72=0,0,(S72/Q72)) -> 0 | S72: =S32 -> 0 | T72: =T32 -> 0 | U72: =IF(T72=0,0,(V72/T72)) -> 0 | V72: =V32 -> 0 | W72: =W32 -> 0 | X72: =IF(W72=0,0,(Y72/W72)) -> 0 | Y72: =Y32 -> 0 | Z72: =Z32 -> 0 | AA72: =IF(Z72=0,0,(AB72/Z72)) -> 0 | AB72: =AB32 -> 0 | AC72: =AC32 -> 0 | AD72: =IF(AC72=0,0,(AE72/AC72)) -> 0 | AE72: =AE32 -> 0 | AF72: =AF32 -> 0 | AG72: =IF(AF72=0,0,(AH72/AF72)) -> 0 | AH72: =AH32 -> 0 | AI72: =AI32 -> 0 | AJ72: =IF(AI72=0,0,(AK72/AI72)) -> 0 | AK72: =AK32 -> 0 | AL72: =AL32 -> 25 | AM72: =IF(AL72=0,0,(AN72/AL72)) -> 380 | AN72: =AN32 -> 9500
A73: Closing Stock | B73: =B33+B59 -> 79049 | C73: =IF(B73=0,0,(D73/B73)) -> 140.63013 | D73: =D33+D59 -> 11116671 | E73: =E33+E59 -> 93338 | F73: =IF(E73=0,0,(G73/E73)) -> 156.39397 | G73: =G33+G59 -> 14597500 | H73: =H33+H59 -> 0 | I73: =IF(H73=0,0,(J73/H73)) -> 0 | J73: =J33+J59 -> 0 | K73: =K33+K59 -> 0 | L73: =IF(K73=0,0,(M73/K73)) -> 0 | M73: =M33+M59 -> 0 | N73: =N33+N59 -> 0 | O73: =IF(N73=0,0,(P73/N73)) -> 0 | P73: =P33+P59 -> 0 | Q73: =Q33+Q59 -> 0 | R73: =IF(Q73=0,0,(S73/Q73)) -> 0 | S73: =S33+S59 -> 0 | T73: =T33+T59 -> 0 | U73: =IF(T73=0,0,(V73/T73)) -> 0 | V73: =V33+V59 -> 0 | W73: =W33+W59 -> 0 | X73: =IF(W73=0,0,(Y73/W73)) -> 0 | Y73: =Y33+Y59 -> 0 | Z73: =Z33+Z59 -> 0 | AA73: =IF(Z73=0,0,(AB73/Z73)) -> 0 | AB73: =AB33+AB59 -> 0 | AC73: =AC33+AC59 -> 0 | AD73: =IF(AC73=0,0,(AE73/AC73)) -> 0 | AE73: =AE33+AE59 -> 0 | AF73: =AF33+AF59 -> 0 | AG73: =IF(AF73=0,0,(AH73/AF73)) -> 0 | AH73: =AH33+AH59 -> 0 | AI73: =AI33+AI59 -> 0 | AJ73: =IF(AI73=0,0,(AK73/AI73)) -> 0 | AK73: =AK33+AK59 -> 0 | AL73: =AL33+AL59 -> 0 | AM73: =IF(AL73=0,0,(AN73/AL73)) -> 0 | AN73: =AN33+AN59 -> 0
A74: Total Consmpn Priyafil | B74: =(B63+B70)-(B72+B73) -> 100957.96 | C74: =IF(B74=0,0,(D74/B74)) -> 159.02346 | D74: =(D63+D70)-(D72+D73) -> 16054684 | E74: =(E63+E70)-(E72+E73) -> 82488 | F74: =IF(E74=0,0,(G74/E74)) -> 153.40474 | G74: =(G63+G70)-(G72+G73) -> 12654050 | H74: =(H63+H70)-(H72+H73) -> 93338 | I74: =IF(H74=0,0,(J74/H74)) -> 156.39397 | J74: =(J63+J70)-(J72+J73) -> 14597500 | K74: =(K63+K70)-(K72+K73) -> 0 | L74: =IF(K74=0,0,(M74/K74)) -> 0 | M74: =(M63+M70)-(M72+M73) -> 0 | N74: =(N63+N70)-(N72+N73) -> -1 | O74: =IF(N74=0,0,(P74/N74)) -> 0 | P74: =(P63+P70)-(P72+P73) -> 0 | Q74: =(Q63+Q70)-(Q72+Q73) -> 0 | R74: =IF(Q74=0,0,(S74/Q74)) -> 0 | S74: =(S63+S70)-(S72+S73) -> 0 | T74: =(T63+T70)-(T72+T73) -> 0 | U74: =IF(T74=0,0,(V74/T74)) -> 0 | V74: =(V63+V70)-(V72+V73) -> 0 | W74: =(W63+W70)-(W72+W73) -> 0 | X74: =IF(W74=0,0,(Y74/W74)) -> 0 | Y74: =(Y63+Y70)-(Y72+Y73) -> 0 | Z74: =(Z63+Z70)-(Z72+Z73) -> 0 | AA74: =IF(Z74=0,0,(AB74/Z74)) -> 0 | AB74: =(AB63+AB70)-(AB72+AB73) -> 0 | AC74: =(AC63+AC70)-(AC72+AC73) -> 0 | AD74: =IF(AC74=0,0,(AE74/AC74)) -> 0 | AE74: =(AE63+AE70)-(AE72+AE73) -> 0 | AF74: =(AF63+AF70)-(AF72+AF73) -> 0 | AG74: =IF(AF74=0,0,(AH74/AF74)) -> 0 | AH74: =(AH63+AH70)-(AH72+AH73) -> 0 | AI74: =(AI63+AI70)-(AI72+AI73) -> 0 | AJ74: =IF(AI74=0,0,(AK74/AI74)) -> 0 | AK74: =(AK63+AK70)-(AK72+AK73) -> 0 | AL74: =(AL63+AL70)-(AL72+AL73) -> 276781 | AM74: =IF(AL74=0,0,(AN74/AL74)) -> 156.4639 | AN74: =(AN63+AN70)-(AN72+AN73) -> 43306234
A76: MONOFIL SFG & FG
A77: Opening Stock
A78: SFG-Yarn | B78: ='Stock Valuation (FIFO)'!B12 -> 102167 | C78: =IF(B78=0,0,D78/B78) -> 167 | D78: ='Stock Valuation (FIFO)'!D12 -> 17061889 | E78: =B88 -> 76997 | F78: =IF(E78=0,0,G78/E78) -> 182 | G78: =D88 -> 14013454 | H78: =E88 -> 73664 | I78: =IF(H78=0,0,J78/H78) -> 207 | J78: =G88 -> 15248448 | K78: =H88 -> 0 | L78: =IF(K78=0,0,M78/K78) -> 0 | M78: =J88 -> 0 | N78: =K88 -> 0 | O78: =IF(N78=0,0,P78/N78) -> 0 | P78: =M88 -> 0 | Q78: =N88 -> 0 | R78: =IF(Q78=0,0,S78/Q78) -> 0 | S78: =P88 -> 0 | T78: =Q88 -> 0 | U78: =IF(T78=0,0,V78/T78) -> 0 | V78: =S88 -> 0 | W78: =T88 -> 0 | X78: =IF(W78=0,0,Y78/W78) -> 0 | Y78: =V88 -> 0 | Z78: =W88 -> 0 | AA78: =IF(Z78=0,0,AB78/Z78) -> 0 | AB78: =Y88 -> 0 | AC78: =Z88 -> 0 | AD78: =IF(AC78=0,0,AE78/AC78) -> 0 | AE78: =AB88 -> 0 | AF78: =AC88 -> 0 | AG78: =IF(AF78=0,0,AH78/AF78) -> 0 | AH78: =AE88 -> 0 | AI78: =AF88 -> 0 | AJ78: =IF(AI78=0,0,AK78/AI78) -> 0 | AK78: =AH88 -> 0 | AL78: =B78 -> 102167 | AM78: =IF(AL78=0,0,AN78/AL78) -> 167 | AN78: =D78 -> 17061889
A79: FG-Fabric | B79: ='Stock Valuation (FIFO)'!B14 -> 200810 | C79: =IF(B79=0,0,D79/B79) -> 238 | D79: ='Stock Valuation (FIFO)'!D14 -> 47792780 | E79: =B89 -> 216887 | F79: =IF(E79=0,0,G79/E79) -> 250 | G79: =D89 -> 54221750 | H79: =E89 -> 179666 | I79: =IF(H79=0,0,J79/H79) -> 278 | J79: =G89 -> 49947148 | K79: =H89 -> 0 | L79: =IF(K79=0,0,M79/K79) -> 0 | M79: =J89 -> 0 | N79: =K89 -> 0 | O79: =IF(N79=0,0,P79/N79) -> 0 | P79: =M89 -> 0 | Q79: =N89 -> 0 | R79: =IF(Q79=0,0,S79/Q79) -> 0 | S79: =P89 -> 0 | T79: =Q89 -> 0 | U79: =IF(T79=0,0,V79/T79) -> 0 | V79: =S89 -> 0 | W79: =T89 -> 0 | X79: =IF(W79=0,0,Y79/W79) -> 0 | Y79: =V89 -> 0 | Z79: =W89 -> 0 | AA79: =IF(Z79=0,0,AB79/Z79) -> 0 | AB79: =Y89 -> 0 | AC79: =Z89 -> 0 | AD79: =IF(AC79=0,0,AE79/AC79) -> 0 | AE79: =AB89 -> 0 | AF79: =AC89 -> 0 | AG79: =IF(AF79=0,0,AH79/AF79) -> 0 | AH79: =AE89 -> 0 | AI79: =AF89 -> 0 | AJ79: =IF(AI79=0,0,AK79/AI79) -> 0 | AK79: =AH89 -> 0 | AL79: =B79 -> 200810 | AM79: =IF(AL79=0,0,AN79/AL79) -> 238 | AN79: =D79 -> 47792780
B80: =SUM(B78:B79) -> 302977 | C80: =IF(B80=0,0,D80/B80) -> 214.05806 | D80: =SUM(D78:D79) -> 64854669 | E80: =SUM(E78:E79) -> 293884 | F80: =IF(E80=0,0,G80/E80) -> 232.18414 | G80: =SUM(G78:G79) -> 68235204 | H80: =SUM(H78:H79) -> 253330 | I80: =IF(H80=0,0,J80/H80) -> 257.35442 | J80: =SUM(J78:J79) -> 65195596 | K80: =SUM(K78:K79) -> 0 | L80: =IF(K80=0,0,M80/K80) -> 0 | M80: =SUM(M78:M79) -> 0 | N80: =SUM(N78:N79) -> 0 | O80: =IF(N80=0,0,P80/N80) -> 0 | P80: =SUM(P78:P79) -> 0 | Q80: =SUM(Q78:Q79) -> 0 | R80: =IF(Q80=0,0,S80/Q80) -> 0 | S80: =SUM(S78:S79) -> 0 | T80: =SUM(T78:T79) -> 0 | U80: =IF(T80=0,0,V80/T80) -> 0 | V80: =SUM(V78:V79) -> 0 | W80: =SUM(W78:W79) -> 0 | X80: =IF(W80=0,0,Y80/W80) -> 0 | Y80: =SUM(Y78:Y79) -> 0 | Z80: =SUM(Z78:Z79) -> 0 | AA80: =IF(Z80=0,0,AB80/Z80) -> 0 | AB80: =SUM(AB78:AB79) -> 0 | AC80: =SUM(AC78:AC79) -> 0 | AD80: =IF(AC80=0,0,AE80/AC80) -> 0 | AE80: =SUM(AE78:AE79) -> 0 | AF80: =SUM(AF78:AF79) -> 0 | AG80: =IF(AF80=0,0,AH80/AF80) -> 0 | AH80: =SUM(AH78:AH79) -> 0 | AI80: =SUM(AI78:AI79) -> 0 | AJ80: =IF(AI80=0,0,AK80/AI80) -> 0 | AK80: =SUM(AK78:AK79) -> 0 | AL80: =SUM(AL78:AL79) -> 302977 | AM80: =IF(AL80=0,0,AN80/AL80) -> 214.05806 | AN80: =SUM(AN78:AN79) -> 64854669
A82: Purchases
A83: SFG-Yarn | B83: =B40 -> 3668 | C83: =IF(B83=0,0,D83/B83) -> 182.33397 | D83: =D40 -> 668801 | E83: =E40 -> 4150 | F83: =IF(E83=0,0,G83/E83) -> 111.38554 | G83: =G40 -> 462250 | H83: =H40 -> 0 | I83: =IF(H83=0,0,J83/H83) -> 0 | J83: =J40 -> 0 | K83: =K40 -> 0 | L83: =IF(K83=0,0,M83/K83) -> 0 | M83: =M40 -> 0 | N83: =N40 -> 0 | O83: =IF(N83=0,0,P83/N83) -> 0 | P83: =P40 -> 0 | Q83: =Q40 -> 0 | R83: =IF(Q83=0,0,S83/Q83) -> 0 | S83: =S40 -> 0 | T83: =T40 -> 0 | U83: =IF(T83=0,0,V83/T83) -> 0 | V83: =V40 -> 0 | W83: =W40 -> 0 | X83: =IF(W83=0,0,Y83/W83) -> 0 | Y83: =Y40 -> 0 | Z83: =Z40 -> 0 | AA83: =IF(Z83=0,0,AB83/Z83) -> 0 | AB83: =AB40 -> 0 | AC83: =AC40 -> 0 | AD83: =IF(AC83=0,0,AE83/AC83) -> 0 | AE83: =AE40 -> 0 | AF83: =AF40 -> 0 | AG83: =IF(AF83=0,0,AH83/AF83) -> 0 | AH83: =AH40 -> 0 | AI83: =AI40 -> 0 | AJ83: =IF(AI83=0,0,AK83/AI83) -> 0 | AK83: =AK40 -> 0 | AL83: =SUM(B83,E83,H83,K83,N83,Q83,T83,W83,Z83,AC83,AF83,AI83) -> 7818 | AM83: =IF(AL83=0,0,AN83/AL83) -> 144.67268 | AN83: =SUM(D83,G83,J83,M83,P83,S83,V83,Y83,AB83,AE83,AH83,AK83) -> 1131051
A84: FG-Fabric | B84: =B41+B42 -> 22532.96 | C84: =IF(B84=0,0,D84/B84) -> 265.99488 | D84: =D41+D42 -> 5993652 | E84: =E41+E42 -> 9376 | F84: =IF(E84=0,0,G84/E84) -> 265.73763 | G84: =G41+G42 -> 2491556 | H84: =H41+H42 -> 0 | I84: =IF(H84=0,0,J84/H84) -> 0 | J84: =J41+J42 -> 0 | K84: =K41+K42 -> 0 | L84: =IF(K84=0,0,M84/K84) -> 0 | M84: =M41+M42 -> 0 | N84: =N41+N42 -> 0 | O84: =IF(N84=0,0,P84/N84) -> 0 | P84: =P41+P42 -> 0 | Q84: =Q41+Q42 -> 0 | R84: =IF(Q84=0,0,S84/Q84) -> 0 | S84: =S41+S42 -> 0 | T84: =T41+T42 -> 0 | U84: =IF(T84=0,0,V84/T84) -> 0 | V84: =V41+V42 -> 0 | W84: =W41+W42 -> 0 | X84: =IF(W84=0,0,Y84/W84) -> 0 | Y84: =Y41+Y42 -> 0 | Z84: =Z41+Z42 -> 0 | AA84: =IF(Z84=0,0,AB84/Z84) -> 0 | AB84: =AB41+AB42 -> 0 | AC84: =AC41+AC42 -> 0 | AD84: =IF(AC84=0,0,AE84/AC84) -> 0 | AE84: =AE41+AE42 -> 0 | AF84: =AF41+AF42 -> 0 | AG84: =IF(AF84=0,0,AH84/AF84) -> 0 | AH84: =AH41+AH42 -> 0 | AI84: =AI41+AI42 -> 0 | AJ84: =IF(AI84=0,0,AK84/AI84) -> 0 | AK84: =AK41+AK42 -> 0 | AL84: =SUM(B84,E84,H84,K84,N84,Q84,T84,W84,Z84,AC84,AF84,AI84) -> 31908.96 | AM84: =IF(AL84=0,0,AN84/AL84) -> 265.91929 | AN84: =SUM(D84,G84,J84,M84,P84,S84,V84,Y84,AB84,AE84,AH84,AK84) -> 8485208
A85: Consumables | D85: =D43 -> 283632 | G85: =G43 -> 285732 | J85: =J43 -> 0 | M85: =M43 -> 0 | P85: =P43 -> 0 | S85: =S43 -> 0 | V85: =V43 -> 0 | Y85: =Y43 -> 0 | AB85: =AB43 -> 0 | AE85: =AE43 -> 0 | AH85: =AH43 -> 0 | AK85: =AK43 -> 0 | AN85: =SUM(D85,G85,J85,M85,P85,S85,V85,Y85,AB85,AE85,AH85,AK85) -> 569364
B86: =SUM(B83:B85) -> 26200.96 | C86: =IF(B86=0,0,D86/B86) -> 265.10803 | D86: =SUM(D83:D85) -> 6946085 | E86: =SUM(E83:E85) -> 13526 | F86: =IF(E86=0,0,G86/E86) -> 239.50451 | G86: =SUM(G83:G85) -> 3239538 | H86: =SUM(H83:H85) -> 0 | I86: =IF(H86=0,0,J86/H86) -> 0 | J86: =SUM(J83:J85) -> 0 | K86: =SUM(K83:K85) -> 0 | L86: =IF(K86=0,0,M86/K86) -> 0 | M86: =SUM(M83:M85) -> 0 | N86: =SUM(N83:N84) -> 0 | O86: =IF(N86=0,0,P86/N86) -> 0 | P86: =SUM(P83:P85) -> 0 | Q86: =SUM(Q83:Q84) -> 0 | R86: =IF(Q86=0,0,S86/Q86) -> 0 | S86: =SUM(S83:S85) -> 0 | T86: =SUM(T83:T84) -> 0 | U86: =IF(T86=0,0,V86/T86) -> 0 | V86: =SUM(V83:V85) -> 0 | W86: =SUM(W83:W84) -> 0 | X86: =IF(W86=0,0,Y86/W86) -> 0 | Y86: =SUM(Y83:Y85) -> 0 | Z86: =SUM(Z83:Z85) -> 0 | AA86: =IF(Z86=0,0,AB86/Z86) -> 0 | AB86: =SUM(AB83:AB85) -> 0 | AC86: =SUM(AC83:AC85) -> 0 | AD86: =IF(AC86=0,0,AE86/AC86) -> 0 | AE86: =SUM(AE83:AE85) -> 0 | AF86: =SUM(AF83:AF85) -> 0 | AG86: =IF(AF86=0,0,AH86/AF86) -> 0 | AH86: =SUM(AH83:AH85) -> 0 | AI86: =SUM(AI83:AI85) -> 0 | AJ86: =IF(AI86=0,0,AK86/AI86) -> 0 | AK86: =SUM(AK83:AK85) -> 0 | AL86: =SUM(AL83:AL85) -> 39726.96 | AM86: =IF(AL86=0,0,AN86/AL86) -> 256.3907 | AN86: =SUM(AN83:AN85) -> 10185623 | AO86: =Purchase!P34 -> 10185623 | AP86: =AN86-AO86 -> 0
A87: Closing Stock
A88: SFG-Yarn | B88: ='Stock Valuation (FIFO)'!E12 -> 76997 | C88: =IF(B88=0,0,D88/B88) -> 182 | D88: ='Stock Valuation (FIFO)'!G12 -> 14013454 | E88: ='Stock Valuation (FIFO)'!H12 -> 73664 | F88: =IF(E88=0,0,G88/E88) -> 207 | G88: ='Stock Valuation (FIFO)'!J12 -> 15248448 | H88: ='Stock Valuation (FIFO)'!K12 -> 0 | I88: =IF(H88=0,0,J88/H88) -> 0 | J88: ='Stock Valuation (FIFO)'!M12 -> 0 | K88: ='Stock Valuation (FIFO)'!N12 -> 0 | L88: =IF(K88=0,0,M88/K88) -> 0 | M88: ='Stock Valuation (FIFO)'!P12 -> 0 | N88: ='Stock Valuation (FIFO)'!Q12 -> 0 | O88: =IF(N88=0,0,P88/N88) -> 0 | P88: ='Stock Valuation (FIFO)'!S12 -> 0 | Q88: ='Stock Valuation (FIFO)'!T12 -> 0 | R88: =IF(Q88=0,0,S88/Q88) -> 0 | S88: ='Stock Valuation (FIFO)'!V12 -> 0 | T88: ='Stock Valuation (FIFO)'!W12 -> 0 | U88: =IF(T88=0,0,V88/T88) -> 0 | V88: ='Stock Valuation (FIFO)'!Y12 -> 0 | W88: ='Stock Valuation (FIFO)'!Z12 -> 0 | X88: =IF(W88=0,0,Y88/W88) -> 0 | Y88: ='Stock Valuation (FIFO)'!AB12 -> 0 | Z88: ='Stock Valuation (FIFO)'!AC12 -> 0 | AA88: =IF(Z88=0,0,AB88/Z88) -> 0 | AB88: ='Stock Valuation (FIFO)'!AE12 -> 0 | AC88: ='Stock Valuation (FIFO)'!AF12 -> 0 | AD88: =IF(AC88=0,0,AE88/AC88) -> 0 | AE88: ='Stock Valuation (FIFO)'!AH12 -> 0 | AF88: ='Stock Valuation (FIFO)'!AI12 -> 0 | AG88: =IF(AF88=0,0,AH88/AF88) -> 0 | AH88: ='Stock Valuation (FIFO)'!AK12 -> 0 | AI88: ='Stock Valuation (FIFO)'!AL12 -> 0 | AJ88: =IF(AI88=0,0,AK88/AI88) -> 0 | AK88: ='Stock Valuation (FIFO)'!AN12 -> 0 | AL88: =AI88 -> 0 | AM88: =IF(AL88=0,0,(AN88/AL88)) -> 0 | AN88: =AK88 -> 0
A89: FG-Fabric | B89: ='Stock Valuation (FIFO)'!E14 -> 216887 | C89: =IF(B89=0,0,D89/B89) -> 250 | D89: ='Stock Valuation (FIFO)'!G14 -> 54221750 | E89: ='Stock Valuation (FIFO)'!H14 -> 179666 | F89: =IF(E89=0,0,G89/E89) -> 278 | G89: ='Stock Valuation (FIFO)'!J14 -> 49947148 | H89: ='Stock Valuation (FIFO)'!K14 -> 0 | I89: =IF(H89=0,0,J89/H89) -> 0 | J89: ='Stock Valuation (FIFO)'!M14 -> 0 | K89: ='Stock Valuation (FIFO)'!N14 -> 0 | L89: =IF(K89=0,0,M89/K89) -> 0 | M89: ='Stock Valuation (FIFO)'!P14 -> 0 | N89: ='Stock Valuation (FIFO)'!Q14 -> 0 | O89: =IF(N89=0,0,P89/N89) -> 0 | P89: ='Stock Valuation (FIFO)'!S14 -> 0 | Q89: ='Stock Valuation (FIFO)'!T14 -> 0 | R89: =IF(Q89=0,0,S89/Q89) -> 0 | S89: ='Stock Valuation (FIFO)'!V14 -> 0 | T89: ='Stock Valuation (FIFO)'!W14 -> 0 | U89: =IF(T89=0,0,V89/T89) -> 0 | V89: ='Stock Valuation (FIFO)'!Y14 -> 0 | W89: ='Stock Valuation (FIFO)'!Z14 -> 0 | X89: =IF(W89=0,0,Y89/W89) -> 0 | Y89: ='Stock Valuation (FIFO)'!AB14 -> 0 | Z89: ='Stock Valuation (FIFO)'!AC14 -> 0 | AA89: =IF(Z89=0,0,AB89/Z89) -> 0 | AB89: ='Stock Valuation (FIFO)'!AE14 -> 0 | AC89: ='Stock Valuation (FIFO)'!AF14 -> 0 | AD89: =IF(AC89=0,0,AE89/AC89) -> 0 | AE89: ='Stock Valuation (FIFO)'!AH14 -> 0 | AF89: ='Stock Valuation (FIFO)'!AI14 -> 0 | AG89: =IF(AF89=0,0,AH89/AF89) -> 0 | AH89: ='Stock Valuation (FIFO)'!AK14 -> 0 | AI89: ='Stock Valuation (FIFO)'!AL14 -> 0 | AJ89: =IF(AI89=0,0,AK89/AI89) -> 0 | AK89: ='Stock Valuation (FIFO)'!AN14 -> 0 | AL89: =AI89 -> 0 | AM89: =IF(AL89=0,0,(AN89/AL89)) -> 0 | AN89: =AK89 -> 0
B90: =SUM(B88:B89) -> 293884 | C90: =IF(B90=0,0,D90/B90) -> 232.18414 | D90: =SUM(D88:D89) -> 68235204 | E90: =SUM(E88:E89) -> 253330 | F90: =IF(E90=0,0,G90/E90) -> 257.35442 | G90: =SUM(G88:G89) -> 65195596 | H90: =SUM(H88:H89) -> 0 | I90: =IF(H90=0,0,J90/H90) -> 0 | J90: =SUM(J88:J89) -> 0 | K90: =SUM(K88:K89) -> 0 | L90: =IF(K90=0,0,M90/K90) -> 0 | M90: =SUM(M88:M89) -> 0 | N90: =SUM(N88:N89) -> 0 | O90: =IF(N90=0,0,P90/N90) -> 0 | P90: =SUM(P88:P89) -> 0 | Q90: =SUM(Q88:Q89) -> 0 | R90: =IF(Q90=0,0,S90/Q90) -> 0 | S90: =SUM(S88:S89) -> 0 | T90: =SUM(T88:T89) -> 0 | U90: =IF(T90=0,0,V90/T90) -> 0 | V90: =SUM(V88:V89) -> 0 | W90: =SUM(W88:W89) -> 0 | X90: =IF(W90=0,0,Y90/W90) -> 0 | Y90: =SUM(Y88:Y89) -> 0 | Z90: =SUM(Z88:Z89) -> 0 | AA90: =IF(Z90=0,0,AB90/Z90) -> 0 | AB90: =SUM(AB88:AB89) -> 0 | AC90: =SUM(AC88:AC89) -> 0 | AD90: =IF(AC90=0,0,AE90/AC90) -> 0 | AE90: =SUM(AE88:AE89) -> 0 | AF90: =SUM(AF88:AF89) -> 0 | AG90: =IF(AF90=0,0,AH90/AF90) -> 0 | AH90: =SUM(AH88:AH89) -> 0 | AI90: =SUM(AI88:AI89) -> 0 | AJ90: =IF(AI90=0,0,AK90/AI90) -> 0 | AK90: =SUM(AK88:AK89) -> 0 | AL90: =SUM(AL88:AL89) -> 0 | AM90: =IF(AL90=0,0,AN90/AL90) -> 0 | AN90: =SUM(AN88:AN89) -> 0
A92: Difference in Stocks | B92: =B80-B90 -> 9093 | D92: =D80-D90 -> -3380535 | E92: =E80-E90 -> 40554 | G92: =G80-G90 -> 3039608 | H92: =H80-H90 -> 253330 | J92: =J80-J90 -> 65195596 | K92: =K80-K90 -> 0 | M92: =M80-M90 -> 0 | N92: =N80-N90 -> 0 | O92: =IF(N92=0,0,P92/N92) -> 0 | P92: =P80-P90 -> 0 | Q92: =Q80-Q90 -> 0 | R92: =IF(Q92=0,0,S92/Q92) -> 0 | S92: =S80-S90 -> 0 | T92: =T80-T90 -> 0 | U92: =IF(T92=0,0,V92/T92) -> 0 | V92: =V80-V90 -> 0 | W92: =W80-W90 -> 0 | X92: =IF(W92=0,0,Y92/W92) -> 0 | Y92: =Y80-Y90 -> 0 | Z92: =Z80-Z90 -> 0 | AA92: =IF(Z92=0,0,AB92/Z92) -> 0 | AB92: =AB80-AB90 -> 0 | AC92: =AC80-AC90 -> 0 | AD92: =IF(AC92=0,0,AE92/AC92) -> 0 | AE92: =AE80-AE90 -> 0 | AF92: =AF80-AF90 -> 0 | AG92: =IF(AF92=0,0,AH92/AF92) -> 0 | AH92: =AH80-AH90 -> 0 | AI92: =AI80-AI90 -> 0 | AJ92: =IF(AI92=0,0,AK92/AI92) -> 0 | AK92: =AK80-AK90 -> 0 | AL92: =AL80-AL90 -> 302977 | AM92: =IF(AL92=0,0,AN92/AL92) -> 214.05806 | AN92: =AN80-AN90 -> 64854669
A94: Trading
A95: Op Stock | B95: ='Stock Valuation (FIFO)'!B21 -> 1041 | C95: =IF(B95=0,0,D95/B95) -> 221.96926 | D95: ='Stock Valuation (FIFO)'!D21 -> 231070 | E95: =B96 -> 941 | F95: =IF(E95=0,0,G95/E95) -> 238.73751 | G95: =D96 -> 224652 | H95: =E96 -> 1039 | I95: =IF(H95=0,0,J95/H95) -> 236.73917 | J95: =G96 -> 245972 | K95: =H96 -> 0 | L95: =IF(K95=0,0,M95/K95) -> 0 | M95: =J96 -> 0 | N95: =K96 -> 0 | O95: =IF(N95=0,0,P95/N95) -> 0 | P95: =M96 -> 0 | Q95: =N96 -> 0 | R95: =IF(Q95=0,0,S95/Q95) -> 0 | S95: =P96 -> 0 | T95: =Q96 -> 0 | U95: =IF(T95=0,0,V95/T95) -> 0 | V95: =S96 -> 0 | W95: =T96 -> 0 | X95: =IF(W95=0,0,Y95/W95) -> 0 | Y95: =V96 -> 0 | Z95: =W96 -> 0 | AA95: =IF(Z95=0,0,AB95/Z95) -> 0 | AB95: =Y96 -> 0 | AC95: =Z96 -> 0 | AD95: =IF(AC95=0,0,AE95/AC95) -> 0 | AE95: =AB96 -> 0 | AF95: =AC96 -> 0 | AG95: =IF(AF95=0,0,AH95/AF95) -> 0 | AH95: =AE96 -> 0 | AI95: =AF96 -> 0 | AJ95: =IF(AI95=0,0,AK95/AI95) -> 0 | AK95: =AH96 -> 0 | AL95: =B95 -> 1041 | AM95: =IF(AL95=0,0,AN95/AL95) -> 221.96926 | AN95: =D95 -> 231070
A96: Cl Stock | B96: =B59 -> 941 | C96: =IF(B96=0,0,D96/B96) -> 238.73751 | D96: =D59 -> 224652 | E96: =E59 -> 1039 | F96: =IF(E96=0,0,G96/E96) -> 236.73917 | G96: =G59 -> 245972 | H96: =H59 -> 0 | I96: =IF(H96=0,0,J96/H96) -> 0 | J96: =J59 -> 0 | K96: =K59 -> 0 | L96: =IF(K96=0,0,M96/K96) -> 0 | M96: =M59 -> 0 | N96: =N59 -> 0 | O96: =IF(N96=0,0,P96/N96) -> 0 | P96: =P59 -> 0 | Q96: =Q59 -> 0 | R96: =IF(Q96=0,0,S96/Q96) -> 0 | S96: =S59 -> 0 | T96: =T59 -> 0 | U96: =IF(T96=0,0,V96/T96) -> 0 | V96: =V59 -> 0 | W96: =W59 -> 0 | X96: =IF(W96=0,0,Y96/W96) -> 0 | Y96: =Y59 -> 0 | Z96: =Z59 -> 0 | AA96: =IF(Z96=0,0,AB96/Z96) -> 0 | AB96: =AB59 -> 0 | AC96: =AC59 -> 0 | AD96: =IF(AC96=0,0,AE96/AC96) -> 0 | AE96: =AE59 -> 0 | AF96: =AF59 -> 0 | AG96: =IF(AF96=0,0,AH96/AF96) -> 0 | AH96: =AH59 -> 0 | AI96: =AI59 -> 0 | AJ96: =IF(AI96=0,0,AK96/AI96) -> 0 | AK96: =AK59 -> 0 | AL96: =AL59 -> 0 | AM96: =IF(AL96=0,0,(AN96/AL96)) -> 0 | AN96: =AN59 -> 0
A97: Difference in Stocks | B97: =B95-B96 -> 100 | C97: =IF(B97=0,0,D97/B97) -> 64.18 | D97: =D95-D96 -> 6418 | E97: =E95-E96 -> -98 | F97: =IF(E97=0,0,G97/E97) -> 217.55102 | G97: =G95-G96 -> -21320 | H97: =H95-H96 -> 1039 | I97: =IF(H97=0,0,J97/H97) -> 236.73917 | J97: =J95-J96 -> 245972 | K97: =K95-K96 -> 0 | L97: =IF(K97=0,0,M97/K97) -> 0 | M97: =M95-M96 -> 0 | N97: =N95-N96 -> 0 | O97: =IF(N97=0,0,P97/N97) -> 0 | P97: =P95-P96 -> 0 | Q97: =Q95-Q96 -> 0 | R97: =IF(Q97=0,0,S97/Q97) -> 0 | S97: =S95-S96 -> 0 | T97: =T95-T96 -> 0 | U97: =IF(T97=0,0,V97/T97) -> 0 | V97: =V95-V96 -> 0 | W97: =W95-W96 -> 0 | Y97: =Y95-Y96 -> 0 | Z97: =Z95-Z96 -> 0 | AA97: =IF(Z97=0,0,AB97/Z97) -> 0 | AB97: =AB95-AB96 -> 0 | AC97: =AC95-AC96 -> 0 | AD97: =IF(AC97=0,0,AE97/AC97) -> 0 | AE97: =AE95-AE96 -> 0 | AF97: =AF95-AF96 -> 0 | AG97: =IF(AF97=0,0,AH97/AF97) -> 0 | AH97: =AH95-AH96 -> 0 | AI97: =AI95-AI96 -> 0 | AK97: =AK95-AK96 -> 0 | AL97: =AL95-AL96 -> 1041 | AM97: =IF(AL97=0,0,AN97/AL97) -> 221.96926 | AN97: =AN95-AN96 -> 231070
A99: Difference in stocks
A100: Monofil | B100: =B92 -> 9093 | C100: =IF(B100=0,0,D100/B100) -> -371.77334 | D100: =D92 -> -3380535 | E100: =E92 -> 40554 | F100: =IF(E100=0,0,G100/E100) -> 74.952113 | G100: =G92 -> 3039608 | H100: =H92 -> 253330 | I100: =IF(H100=0,0,J100/H100) -> 257.35442 | J100: =J92 -> 65195596 | K100: =K92 -> 0 | L100: =IF(K100=0,0,M100/K100) -> 0 | M100: =M92 -> 0 | N100: =N92 -> 0 | O100: =IF(N100=0,0,P100/N100) -> 0 | P100: =P92 -> 0 | Q100: =Q92 -> 0 | R100: =IF(Q100=0,0,S100/Q100) -> 0 | S100: =S92 -> 0 | T100: =T92 -> 0 | U100: =IF(T100=0,0,V100/T100) -> 0 | V100: =V92 -> 0 | W100: =W92 -> 0 | X100: =IF(W100=0,0,Y100/W100) -> 0 | Y100: =Y92 -> 0 | Z100: =Z92 -> 0 | AA100: =IF(Z100=0,0,AB100/Z100) -> 0 | AB100: =AB92 -> 0 | AC100: =AC92 -> 0 | AD100: =IF(AC100=0,0,AE100/AC100) -> 0 | AE100: =AE92 -> 0 | AF100: =AF92 -> 0 | AG100: =IF(AF100=0,0,AH100/AF100) -> 0 | AH100: =AH92 -> 0 | AI100: =AI92 -> 0 | AJ100: =IF(AI100=0,0,AK100/AI100) -> 0 | AK100: =AK92 -> 0 | AL100: =AL92 -> 302977 | AM100: =IF(AL100=0,0,AN100/AL100) -> 214.05806 | AN100: =AN92 -> 64854669
A101: Trading | B101: =B97 -> 100 | C101: =IF(B101=0,0,D101/B101) -> 64.18 | D101: =D97 -> 6418 | E101: =E97 -> -98 | F101: =IF(E101=0,0,G101/E101) -> 217.55102 | G101: =G97 -> -21320 | H101: =H97 -> 1039 | I101: =IF(H101=0,0,J101/H101) -> 236.73917 | J101: =J97 -> 245972 | K101: =K97 -> 0 | L101: =IF(K101=0,0,M101/K101) -> 0 | M101: =M97 -> 0 | N101: =N97 -> 0 | O101: =IF(N101=0,0,P101/N101) -> 0 | P101: =P97 -> 0 | Q101: =Q97 -> 0 | R101: =IF(Q101=0,0,S101/Q101) -> 0 | S101: =S97 -> 0 | T101: =T97 -> 0 | U101: =IF(T101=0,0,V101/T101) -> 0 | V101: =V97 -> 0 | W101: =W97 -> 0 | X101: =IF(W101=0,0,Y101/W101) -> 0 | Y101: =Y97 -> 0 | Z101: =Z97 -> 0 | AA101: =IF(Z101=0,0,AB101/Z101) -> 0 | AB101: =AB97 -> 0 | AC101: =AC97 -> 0 | AD101: =IF(AC101=0,0,AE101/AC101) -> 0 | AE101: =AE97 -> 0 | AF101: =AF97 -> 0 | AG101: =IF(AF101=0,0,AH101/AF101) -> 0 | AH101: =AH97 -> 0 | AI101: =AI97 -> 0 | AK101: =AK97 -> 0 | AL101: =AL97 -> 1041 | AM101: =IF(AL101=0,0,AN101/AL101) -> 221.96926 | AN101: =AN97 -> 231070
A102: Total Diff in Stocks | B102: =SUM(B100:B101) -> 9193 | C102: =IF(B102=0,0,D102/B102) -> -367.03111 | D102: =SUM(D100:D101) -> -3374117 | E102: =SUM(E100:E101) -> 40456 | F102: =IF(E102=0,0,G102/E102) -> 74.606684 | G102: =SUM(G100:G101) -> 3018288 | H102: =SUM(H100:H101) -> 254369 | I102: =IF(H102=0,0,J102/H102) -> 257.27022 | J102: =SUM(J100:J101) -> 65441568 | K102: =SUM(K100:K101) -> 0 | L102: =IF(K102=0,0,M102/K102) -> 0 | M102: =SUM(M100:M101) -> 0 | N102: =SUM(N100:N101) -> 0 | O102: =IF(N102=0,0,P102/N102) -> 0 | P102: =SUM(P100:P101) -> 0 | Q102: =SUM(Q100:Q101) -> 0 | R102: =IF(Q102=0,0,S102/Q102) -> 0 | S102: =SUM(S100:S101) -> 0 | T102: =SUM(T100:T101) -> 0 | U102: =IF(T102=0,0,V102/T102) -> 0 | V102: =SUM(V100:V101) -> 0 | W102: =SUM(W100:W101) -> 0 | X102: =IF(W102=0,0,Y102/W102) -> 0 | Y102: =SUM(Y100:Y101) -> 0 | Z102: =Z92+Z97 -> 0 | AA102: =IF(Z102=0,0,AB102/Z102) -> 0 | AB102: =AB92+AB97 -> 0 | AC102: =AC92+AC97 -> 0 | AD102: =IF(AC102=0,0,AE102/AC102) -> 0 | AE102: =AE92+AE97 -> 0 | AF102: =AF92+AF97 -> 0 | AG102: =IF(AF102=0,0,AH102/AF102) -> 0 | AH102: =AH92+AH97 -> 0 | AI102: =AI92+AI97 -> 0 | AJ102: =IF(AI102=0,0,AK102/AI102) -> 0 | AK102: =AK92+AK97 -> 0 | AL102: =SUM(AL100:AL101) -> 304018 | AM102: =IF(AL102=0,0,AN102/AL102) -> 214.08515 | AN102: =SUM(AN100:AN101) -> 65085739
N103: ='Stock Valuation (FIFO)'!Q27 -> 0 | P103: ='Stock Valuation (FIFO)'!S27 -> 0 | Q103: ='Stock Valuation (FIFO)'!T27 -> 0 | S103: ='Stock Valuation (FIFO)'!V27 -> 0 | T103: ='Stock Valuation (FIFO)'!W27 -> 0 | V103: ='Stock Valuation (FIFO)'!Y27 -> 0 | W103: ='Stock Valuation (FIFO)'!Z27 -> 0 | Y103: ='Stock Valuation (FIFO)'!AB27 -> 0 | Z103: ='Stock Valuation (FIFO)'!AC27 -> 0 | AB103: ='Stock Valuation (FIFO)'!AE27 -> 0 | AC103: ='Stock Valuation (FIFO)'!AF27 -> 0 | AE103: ='Stock Valuation (FIFO)'!AH27 -> 0 | AK103: FIFO Sheet-> | AL103: ='Stock Valuation (FIFO)'!AL30 -> 9193 | AN103: ='Stock Valuation (FIFO)'!AN30 -> -3374117
N104: =N102-N103 -> 0 | P104: =P102-P103 -> 0 | AL104: =AL102-AL103 -> 294825 | AN104: =AN102-AN103 -> 68459856
A105: OP Stock RM | B105: =B28 -> 143489 | C105: =D105/B105 -> 123.87463 | D105: =D28 -> 17774647 | E105: =E28 -> 78108 | F105: =G105/E105 -> 139.44819 | G105: =G28 -> 10892019 | H105: =H28 -> 92299 | I105: =J105/H105 -> 155.48953 | J105: =J28 -> 14351528 | K105: =K28 -> 0 | L105: =M105/K105 -> #DIV/0! | M105: =M28 -> 0 | N105: =N28 -> 0 | O105: =P105/N105 -> #DIV/0! | P105: =P28 -> 0 | Q105: =Q28 -> 0 | R105: =S105/Q105 -> #DIV/0! | S105: =S28 -> 0 | T105: =T28 -> 0 | U105: =V105/T105 -> #DIV/0! | V105: =V28 -> 0 | W105: =W28 -> 0 | X105: =Y105/W105 -> #DIV/0! | Y105: =Y28 -> 0 | Z105: =Z28 -> 0 | AA105: =AB105/Z105 -> #DIV/0! | AB105: =AB28 -> 0 | AC105: =AC28 -> 0 | AD105: =AE105/AC105 -> #DIV/0! | AE105: =AE28 -> 0 | AF105: =AF28 -> 0 | AG105: =AH105/AF105 -> #DIV/0! | AH105: =AH28 -> 0 | AI105: =AI28 -> 0 | AJ105: =AK105/AI105 -> #DIV/0! | AK105: =AK28 -> 0 | AL105: =AL28 -> 143489 | AM105: =AN105/AL105 -> 123.87463 | AN105: =AN28 -> 17774647
A106: Purchase RM | B106: =B29 -> 827 | C106: =D106/B106 -> 273.33011 | D106: =D29 -> 226044 | E106: =E29 -> 76649 | F106: =G106/E106 -> 149.18116 | G106: =G29 -> 11434587 | H106: =H29 -> 0 | I106: =J106/H106 -> #DIV/0! | J106: =J29 -> 0 | K106: =K29 -> 0 | L106: =M106/K106 -> #DIV/0! | M106: =M29 -> 0 | N106: =N29 -> -1 | O106: =P106/N106 -> 0 | P106: =P29 -> 0 | Q106: =Q29 -> 0 | R106: =S106/Q106 -> #DIV/0! | S106: =S29 -> 0 | T106: =T29 -> 0 | U106: =V106/T106 -> #DIV/0! | V106: =V29 -> 0 | W106: =W29 -> 0 | X106: =Y106/W106 -> #DIV/0! | Y106: =Y29 -> 0 | Z106: =Z29 -> 0 | AA106: =AB106/Z106 -> #DIV/0! | AB106: =AB29 -> 0 | AC106: =AC29 -> 0 | AD106: =AE106/AC106 -> #DIV/0! | AE106: =AE29 -> 0 | AF106: =AF29 -> 0 | AG106: =AH106/AF106 -> #DIV/0! | AH106: =AH29 -> 0 | AI106: =AI29 -> 0 | AJ106: =AK106/AI106 -> #DIV/0! | AK106: =AK29 -> 0 | AL106: =AL29 -> 77475 | AM106: =AN106/AL106 -> 150.50831 | AN106: =AN29 -> 11660631
A107: Closing Stock RM | B107: =B33 -> 78108 | C107: =D107/B107 -> 139.44819 | D107: =D33 -> 10892019 | E107: =E33 -> 92299 | F107: =G107/E107 -> 155.48953 | G107: =G33 -> 14351528 | H107: =H33 -> 0 | I107: =J107/H107 -> #DIV/0! | J107: =J33 -> 0 | K107: =K33 -> 0 | L107: =M107/K107 -> #DIV/0! | M107: =M33 -> 0 | N107: =N33 -> 0 | O107: =P107/N107 -> #DIV/0! | P107: =P33 -> 0 | Q107: =Q33 -> 0 | R107: =S107/Q107 -> #DIV/0! | S107: =S33 -> 0 | T107: =T33 -> 0 | U107: =V107/T107 -> #DIV/0! | V107: =V33 -> 0 | W107: =W33 -> 0 | X107: =Y107/W107 -> #DIV/0! | Y107: =Y33 -> 0 | Z107: =Z33 -> 0 | AA107: =AB107/Z107 -> #DIV/0! | AB107: =AB33 -> 0 | AC107: =AC33 -> 0 | AD107: =AE107/AC107 -> #DIV/0! | AE107: =AE33 -> 0 | AF107: =AF33 -> 0 | AG107: =AH107/AF107 -> #DIV/0! | AH107: =AH33 -> 0 | AI107: =AI33 -> 0 | AJ107: =AK107/AI107 -> #DIV/0! | AK107: =AK33 -> 0 | AL107: =AL33 -> 0 | AM107: =AN107/AL107 -> #DIV/0! | AN107: =AN33 -> 0
B108: =B105+B106-B107 -> 66208 | C108: =D108/B108 -> 107.36878 | D108: =D105+D106-D107 -> 7108672 | E108: =E105+E106-E107 -> 62458 | F108: =G108/E108 -> 127.68705 | G108: =G105+G106-G107 -> 7975078 | H108: =H105+H106-H107 -> 92299 | I108: =J108/H108 -> 155.48953 | J108: =J105+J106-J107 -> 14351528 | K108: =K105+K106-K107 -> 0 | L108: =M108/K108 -> #DIV/0! | M108: =M105+M106-M107 -> 0 | N108: =N105+N106-N107 -> -1 | O108: =P108/N108 -> 0 | P108: =P105+P106-P107 -> 0 | Q108: =Q105+Q106-Q107 -> 0 | R108: =S108/Q108 -> #DIV/0! | S108: =S105+S106-S107 -> 0 | T108: =T105+T106-T107 -> 0 | U108: =V108/T108 -> #DIV/0! | V108: =V105+V106-V107 -> 0 | W108: =W105+W106-W107 -> 0 | X108: =Y108/W108 -> #DIV/0! | Y108: =Y105+Y106-Y107 -> 0 | Z108: =Z105+Z106-Z107 -> 0 | AA108: =AB108/Z108 -> #DIV/0! | AB108: =AB105+AB106-AB107 -> 0 | AC108: =AC105+AC106-AC107 -> 0 | AD108: =AE108/AC108 -> #DIV/0! | AE108: =AE105+AE106-AE107 -> 0 | AF108: =AF105+AF106-AF107 -> 0 | AG108: =AH108/AF108 -> #DIV/0! | AH108: =AH105+AH106-AH107 -> 0 | AI108: =AI105+AI106-AI107 -> 0 | AJ108: =AK108/AI108 -> #DIV/0! | AK108: =AK105+AK106-AK107 -> 0 | AL108: =AL105+AL106-AL107 -> 220964 | AM108: =AN108/AL108 -> 133.213 | AN108: =AN105+AN106-AN107 -> 29435278
A109: Monofil Produced | B109: =B108-B112 -> 66208 | C109: =D109/B109 -> 107.36878 | D109: =D108-D112 -> 7108672 | E109: =E108-E112 -> 62433 | F109: =G109/E109 -> 127.58602 | G109: =G108-G112 -> 7965578 | H109: =H108-H112 -> 92299 | I109: =J109/H109 -> 155.48953 | J109: =J108-J112 -> 14351528 | K109: =K108-K112 -> 0 | L109: =M109/K109 -> #DIV/0! | M109: =M108-M112 -> 0 | N109: =N108-N112 -> -1 | O109: =P109/N109 -> 0 | P109: =P108-P112 -> 0 | Q109: =Q108-Q112 -> 0 | R109: =S109/Q109 -> #DIV/0! | S109: =S108-S112 -> 0 | T109: =T108-T112 -> 0 | U109: =V109/T109 -> #DIV/0! | V109: =V108-V112 -> 0 | W109: =W108-W112 -> 0 | X109: =Y109/W109 -> #DIV/0! | Y109: =Y108-Y112 -> 0 | Z109: =Z108-Z112 -> 0 | AA109: =AB109/Z109 -> #DIV/0! | AB109: =AB108-AB112 -> 0 | AC109: =AC108-AC112 -> 0 | AD109: =AE109/AC109 -> #DIV/0! | AE109: =AE108-AE112 -> 0 | AF109: =AF108-AF112 -> 0 | AG109: =AH109/AF109 -> #DIV/0! | AH109: =AH108-AH112 -> 0 | AI109: =AI108-AI112 -> 0 | AJ109: =AK109/AI109 -> #DIV/0! | AK109: =AK108-AK112 -> 0 | AL109: =AL108-AL112 -> 220939 | AM109: =AN109/AL109 -> 133.18508 | AN109: =AN108-AN112 -> 29425778
...

Sheet PAL I
AQ1: Expns/Ssalary/P&L
