Workbook

Sheet Table of Contents
B2: Table of Contents
Q3: Remarks
Q4: 1 Reconcile sheet is comapring Tally Inventory with Tarka
Q5: 2.Review Purchase sheet is redundnt Started to compare Purchases & reconcile
Q6: 3.Qty Analysis is Made by Accounts dept
Q7: 4. Input -Purchase comes from Tally
Q8: 5.Input-Dirct Expns from Tally
Q9: 6.Input-Indirect Expns from Tally
Q10: 7.Input-Stock Vauation from Tally
Q11: 8.Input-Inventory Sales Recobciles Gross Sales to Net Sales
Q12: 9.Output- Cost OF Good Sold (COGS)
Q13: 10.Output-PAL1 Gross P& L compares with Tally P& L fro data Validation with Quantities
Q14: 11.Output_Trading PL is checking on Trading monthly performance
... Q17: 14,15,16,17 OUTPUT from abve sheets for MIS understanding

Sheet Reconcile(HMT)
B2: Op Stock | E2: Apr | H2: May | K2: Jun | N2: Jul | Q2: Aug | T2: Sep | W2: Oct | Z2: Nov | AC2: Dec | AF2: Jan | AI2: Feb | AL2: Mar
B3: HMT | C3: CRK | D3: Diff | E3: HMT | F3: CRK | G3: Diff | H3: HMT | I3: CRK | J3: Diff | K3: HMT | L3: CRK | M3: Diff | N3: HMT | O3: CRK | P3: Diff | Q3: HMT | R3: CRK | S3: Diff | T3: HMT | U3: CRK | V3: Diff | W3: HMT | X3: CRK | Y3: Diff | Z3: HMT | AA3: CRK | AB3: Diff | AC3: HMT | AD3: CRK | AE3: Diff | AF3: HMT | AG3: CRK | AH3: Diff | AI3: HMT | AJ3: CRK | AK3: Diff | AL3: HMT | AM3: CRK | AN3: Diff
A4: HDPE | B4: 195845 | C4: ='Stock Valuation (FIFO)'!B5 -> 195845 | D4: =B4-C4 -> 0 | E4: 180315 | F4: ='Stock Valuation (FIFO)'!E5 -> 180315 | G4: =IF(F4=0,0,(E4-F4)) -> 0 | H4: 147410 | I4: ='Stock Valuation (FIFO)'!H5 -> 147410 | J4: =IF(I4=0,0,(H4-I4)) -> 0 | K4: 164125 | L4: ='Stock Valuation (FIFO)'!K5 -> 164125 | M4: =IF(L4=0,0,(K4-L4)) -> 0 | N4: 146140 | O4: ='Stock Valuation (FIFO)'!N5 -> 146140 | P4: =IF(O4=0,0,(N4-O4)) -> 0 | Q4: 187620 | R4: =' Qty Analysis'!N8 -> 187620 | S4: =IF(R4=0,0,(Q4-R4)) -> 0 | T4: 114680 | U4: ='Stock Valuation (FIFO)'!T5 -> 114680 | V4: =IF(U4=0,0,(T4-U4)) -> 0 | W4: 139725 | X4: ='Stock Valuation (FIFO)'!W5 -> 139725 | Y4: =IF(X4=0,0,(W4-X4)) -> 0 | Z4: 164310 | AA4: ='Stock Valuation (FIFO)'!Z5 -> 164310 | AB4: =IF(AA4=0,0,(Z4-AA4)) -> 0 | AC4: 135475 | AD4: ='Stock Valuation (FIFO)'!AC5 -> 135475 | AE4: =IF(AD4=0,0,(AC4-AD4)) -> 0 | AF4: 174670 | AG4: 174670 | AH4: =IF(AG4=0,0,(AF4-AG4)) -> 0 | AI4: 154290 | AJ4: ='Stock Valuation (FIFO)'!AI5 -> 154290 | AK4: =IF(AJ4=0,0,(AI4-AJ4)) -> 0 | AL4: 141140 | AM4: ='Stock Valuation (FIFO)'!AL5 -> 141140 | AN4: =IF(AM4=0,0,(AL4-AM4)) -> 0
A5: MB | B5: 1664 | C5: ='Stock Valuation (FIFO)'!B6 -> 1664 | D5: =B5-C5 -> 0 | E5: 2120.4 | F5: ='Stock Valuation (FIFO)'!E6 -> 2120 | G5: =IF(F5=0,0,(E5-F5)) -> 0.4 | H5: 2293.7 | I5: ='Stock Valuation (FIFO)'!H6 -> 2294 | J5: =IF(I5=0,0,(H5-I5)) -> -0.3 | K5: 2613.1 | L5: ='Stock Valuation (FIFO)'!K6 -> 2613 | M5: =IF(L5=0,0,(K5-L5)) -> 0.1 | N5: 2768.7 | O5: ='Stock Valuation (FIFO)'!N6 -> 2769 | P5: =IF(O5=0,0,(N5-O5)) -> -0.3 | Q5: 3082.1 | R5: =' Qty Analysis'!N21 -> 3082 | S5: =IF(R5=0,0,(Q5-R5)) -> 0.1 | T5: 2819.3 | U5: ='Stock Valuation (FIFO)'!T6 -> 2819 | V5: =IF(U5=0,0,(T5-U5)) -> 0.3 | W5: 2895.3 | X5: ='Stock Valuation (FIFO)'!W6 -> 2895 | Y5: =IF(X5=0,0,(W5-X5)) -> 0.3 | Z5: 2396.4 | AA5: ='Stock Valuation (FIFO)'!Z6 -> 2396 | AB5: =IF(AA5=0,0,(Z5-AA5)) -> 0.4 | AC5: 2395.2 | AD5: ='Stock Valuation (FIFO)'!AC6 -> 2395 | AE5: =IF(AD5=0,0,(AC5-AD5)) -> 0.2 | AF5: 2511.2 | AG5: 2511 | AH5: =IF(AG5=0,0,(AF5-AG5)) -> 0.2 | AI5: 3260.1 | AJ5: ='Stock Valuation (FIFO)'!AI6 -> 3260 | AK5: =IF(AJ5=0,0,(AI5-AJ5)) -> 0.1 | AL5: 2329.6 | AM5: ='Stock Valuation (FIFO)'!AL6 -> 2330 | AN5: =IF(AM5=0,0,(AL5-AM5)) -> -0.4
A6: CP | B6: 32 | C6: ='Stock Valuation (FIFO)'!B7 -> 32 | D6: =B6-C6 -> 0 | E6: 28.2 | F6: ='Stock Valuation (FIFO)'!E7 -> 28 | G6: =IF(F6=0,0,(E6-F6)) -> 0.2 | H6: 40.1 | I6: ='Stock Valuation (FIFO)'!H7 -> 37 | J6: =IF(I6=0,0,(H6-I6)) -> 3.1 | K6: 40.1 | L6: ='Stock Valuation (FIFO)'!K7 -> 40 | M6: =IF(L6=0,0,(K6-L6)) -> 0.1 | N6: 38.4 | O6: ='Stock Valuation (FIFO)'!N7 -> 38 | P6: =IF(O6=0,0,(N6-O6)) -> 0.4 | Q6: 25.6 | R6: =' Qty Analysis'!N33 -> 26 | S6: =IF(R6=0,0,(Q6-R6)) -> -0.4 | T6: 16.2 | U6: ='Stock Valuation (FIFO)'!T7 -> 16 | V6: =IF(U6=0,0,(T6-U6)) -> 0.2 | W6: 40.9 | X6: ='Stock Valuation (FIFO)'!W7 -> 41 | Y6: =IF(X6=0,0,(W6-X6)) -> -0.1 | Z6: 46 | AA6: ='Stock Valuation (FIFO)'!Z7 -> 46 | AB6: =IF(AA6=0,0,(Z6-AA6)) -> 0 | AC6: 40.3 | AD6: ='Stock Valuation (FIFO)'!AC7 -> 40 | AE6: =IF(AD6=0,0,(AC6-AD6)) -> 0.3 | AF6: 40.1 | AG6: 40 | AH6: =IF(AG6=0,0,(AF6-AG6)) -> 0.1 | AI6: 38.8 | AJ6: ='Stock Valuation (FIFO)'!AI7 -> 38 | AK6: =IF(AJ6=0,0,(AI6-AJ6)) -> 0.8 | AL6: 19 | AM6: ='Stock Valuation (FIFO)'!AL7 -> 19 | AN6: =IF(AM6=0,0,(AL6-AM6)) -> 0
A7: RM Total | B7: =SUM(B4:B6) -> 197541 | C7: =SUM(C4:C6) -> 197541 | D7: =B7-C7 -> 0 | E7: =SUM(E4:E6) -> 182463.6 | F7: =SUM(F4:F6) -> 182463 | G7: =IF(F7=0,0,(E7-F7)) -> 0.6 | H7: =SUM(H4:H6) -> 149743.8 | I7: =SUM(I4:I6) -> 149741 | J7: =IF(I7=0,0,(H7-I7)) -> 2.8 | K7: =SUM(K4:K6) -> 166778.2 | L7: =SUM(L4:L6) -> 166778 | M7: =IF(L7=0,0,(K7-L7)) -> 0.2 | N7: =SUM(N4:N6) -> 148947.1 | O7: =SUM(O4:O6) -> 148947 | P7: =IF(O7=0,0,(N7-O7)) -> 0.1 | Q7: =SUM(Q4:Q6) -> 190727.7 | R7: =SUM(R4:R6) -> 190728 | S7: =IF(R7=0,0,(Q7-R7)) -> -0.3 | T7: =SUM(T4:T6) -> 117515.5 | U7: =SUM(U4:U6) -> 117515 | V7: =IF(U7=0,0,(T7-U7)) -> 0.5 | W7: =SUM(W4:W6) -> 142661.2 | X7: =SUM(X4:X6) -> 142661 | Y7: =IF(X7=0,0,(W7-X7)) -> 0.2 | Z7: =SUM(Z4:Z6) -> 166752.4 | AA7: =SUM(AA4:AA6) -> 166752 | AB7: =IF(AA7=0,0,(Z7-AA7)) -> 0.4 | AC7: =SUM(AC4:AC6) -> 137910.5 | AD7: =SUM(AD4:AD6) -> 137910 | AE7: =IF(AD7=0,0,(AC7-AD7)) -> 0.5 | AF7: =SUM(AF4:AF6) -> 177221.3 | AG7: =SUM(AG4:AG6) -> 177221 | AH7: =IF(AG7=0,0,(AF7-AG7)) -> 0.3 | AI7: =SUM(AI4:AI6) -> 157588.9 | AJ7: =SUM(AJ4:AJ6) -> 157588 | AK7: =IF(AJ7=0,0,(AI7-AJ7)) -> 0.9 | AL7: =SUM(AL4:AL6) -> 143488.6 | AM7: =SUM(AM4:AM6) -> 143489 | AN7: =IF(AM7=0,0,(AL7-AM7)) -> -0.4
A8: Yarn Factory | B8: 49725 | C8: ='Stock Valuation (FIFO)'!B10 -> 49725 | D8: =B8-C8 -> 0 | E8: 56270 | F8: ='Stock Valuation (FIFO)'!E10 -> 56270 | G8: =IF(F8=0,0,(E8-F8)) -> 0 | H8: 46564 | I8: ='Stock Valuation (FIFO)'!H10 -> 46564 | J8: =IF(I8=0,0,(H8-I8)) -> 0 | K8: 52761.2 | L8: ='Stock Valuation (FIFO)'!K10 -> 52761 | M8: =IF(L8=0,0,(K8-L8)) -> 0.2 | N8: 48737.1 | O8: ='Stock Valuation (FIFO)'!N10 -> 48737 | P8: =IF(O8=0,0,(N8-O8)) -> 0.1 | Q8: 49389.9 | R8: =' Qty Analysis'!N61 -> 49389.9 | S8: =IF(R8=0,0,(Q8-R8)) -> 0 | T8: 56273.8 | U8: ='Stock Valuation (FIFO)'!T10 -> 56274 | V8: =IF(U8=0,0,(T8-U8)) -> -0.2 | W8: 60795.6 | X8: ='Stock Valuation (FIFO)'!W10 -> 60796 | Y8: =IF(X8=0,0,(W8-X8)) -> -0.4 | Z8: 57317.4 | AA8: ='Stock Valuation (FIFO)'!Z10 -> 57318 | AB8: =IF(AA8=0,0,(Z8-AA8)) -> -0.6 | AC8: 54865.8 | AD8: ='Stock Valuation (FIFO)'!AC10 -> 54866 | AE8: =IF(AD8=0,0,(AC8-AD8)) -> -0.2 | AF8: 47773.2 | AG8: 47774 | AH8: =IF(AG8=0,0,(AF8-AG8)) -> -0.8 | AI8: 51821.9 | AJ8: ='Stock Valuation (FIFO)'!AI10 -> 51822 | AK8: =IF(AJ8=0,0,(AI8-AJ8)) -> -0.1 | AL8: 37996 | AM8: 37996 | AN8: =IF(AM8=0,0,(AL8-AM8)) -> 0
A9: Yarn Fabrctr | B9: 76468 | C9: ='Stock Valuation (FIFO)'!B11 -> 76468 | D9: =B9-C9 -> 0 | E9: 63905.6 | F9: ='Stock Valuation (FIFO)'!E11 -> 63906 | G9: =IF(F9=0,0,(E9-F9)) -> -0.4 | H9: 61851.2 | I9: ='Stock Valuation (FIFO)'!H11 -> 61851 | J9: =IF(I9=0,0,(H9-I9)) -> 0.2 | K9: 66528 | L9: ='Stock Valuation (FIFO)'!K11 -> 66528 | M9: =IF(L9=0,0,(K9-L9)) -> 0 | N9: 73740.4 | O9: ='Stock Valuation (FIFO)'!N11 -> 73740 | P9: =IF(O9=0,0,(N9-O9)) -> 0.4 | Q9: 77586 | R9: =' Qty Analysis'!N71 -> 77584.9 | S9: =IF(R9=0,0,(Q9-R9)) -> 1.1 | T9: =79105.0999999999-25 -> 79080.1 | U9: ='Stock Valuation (FIFO)'!T11 -> 79080 | V9: =IF(U9=0,0,(T9-U9)) -> 0.1 | W9: 80193.4 | X9: ='Stock Valuation (FIFO)'!W11 -> 80193 | Y9: =IF(X9=0,0,(W9-X9)) -> 0.4 | Z9: 85004.2 | AA9: ='Stock Valuation (FIFO)'!Z11 -> 85004 | AB9: =IF(AA9=0,0,(Z9-AA9)) -> 0.2 | AC9: 91727.2 | AD9: ='Stock Valuation (FIFO)'!AC11 -> 91727 | AE9: =IF(AD9=0,0,(AC9-AD9)) -> 0.2 | AF9: 91742.2 | AG9: 91742 | AH9: =IF(AG9=0,0,(AF9-AG9)) -> 0.2 | AI9: 86543.9 | AJ9: ='Stock Valuation (FIFO)'!AI11 -> 86544 | AK9: =IF(AJ9=0,0,(AI9-AJ9)) -> -0.1 | AL9: 84657.29 | AM9: 64171 | AN9: =IF(AM9=0,0,(AL9-AM9)) -> 20486.29
A10: Yarn Total | B10: =SUM(B8:B9) -> 126193 | C10: =SUM(C8:C9) -> 126193 | D10: =B10-C10 -> 0 | E10: =SUM(E8:E9) -> 120175.6 | F10: =SUM(F8:F9) -> 120176 | G10: =IF(F10=0,0,(E10-F10)) -> -0.4 | H10: =SUM(H8:H9) -> 108415.2 | I10: =SUM(I8:I9) -> 108415 | J10: =IF(I10=0,0,(H10-I10)) -> 0.2 | K10: =SUM(K8:K9) -> 119289.2 | L10: =SUM(L8:L9) -> 119289 | M10: =IF(L10=0,0,(K10-L10)) -> 0.2 | N10: =SUM(N8:N9) -> 122477.5 | O10: =SUM(O8:O9) -> 122477 | P10: =IF(O10=0,0,(N10-O10)) -> 0.5 | Q10: =SUM(Q8:Q9) -> 126975.9 | R10: =SUM(R8:R9) -> 126974.8 | S10: =IF(R10=0,0,(Q10-R10)) -> 1.1 | T10: =SUM(T8:T9) -> 135353.9 | U10: =SUM(U8:U9) -> 135354 | V10: =IF(U10=0,0,(T10-U10)) -> -0.1 | W10: =SUM(W8:W9) -> 140989 | X10: =SUM(X8:X9) -> 140989 | Y10: =IF(X10=0,0,(W10-X10)) -> 0 | Z10: =SUM(Z8:Z9) -> 142321.6 | AA10: =SUM(AA8:AA9) -> 142322 | AB10: =IF(AA10=0,0,(Z10-AA10)) -> -0.4 | AC10: =SUM(AC8:AC9) -> 146593 | AD10: =SUM(AD8:AD9) -> 146593 | AE10: =IF(AD10=0,0,(AC10-AD10)) -> 0 | AF10: =SUM(AF8:AF9) -> 139515.4 | AG10: =SUM(AG8:AG9) -> 139516 | AH10: =IF(AG10=0,0,(AF10-AG10)) -> -0.6 | AI10: =SUM(AI8:AI9) -> 138365.8 | AJ10: =SUM(AJ8:AJ9) -> 138366 | AK10: =IF(AJ10=0,0,(AI10-AJ10)) -> -0.2 | AL10: =SUM(AL8:AL9) -> 122653.29 | AM10: =SUM(AM8:AM9) -> 102167 | AN10: =IF(AM10=0,0,(AL10-AM10)) -> 20486.29 | AO10: Water Content Fabricator
A11: Fabric | B11: 206027 | C11: ='Stock Valuation (FIFO)'!B14 -> 206027 | D11: =B11-C11 -> 0 | E11: 224044.9 | F11: ='Stock Valuation (FIFO)'!E14 -> 224045 | G11: =IF(F11=0,0,(E11-F11)) -> -0.1 | H11: 201846.3 | I11: ='Stock Valuation (FIFO)'!H14 -> 168371 | J11: =IF(I11=0,0,(H11-I11)) -> 33475.3 | K11: 191275.2 | L11: ='Stock Valuation (FIFO)'!K14 -> 140447 | M11: =IF(L11=0,0,(K11-L11)) -> 50828.2 | N11: 197795.1 | O11: ='Stock Valuation (FIFO)'!N14 -> 130199 | P11: =IF(O11=0,0,(N11-O11)) -> 67596.1 | Q11: 202309.3 | R11: ='Stock Valuation (FIFO)'!Q14 -> 202593 | S11: =IF(R11=0,0,(Q11-R11)) -> -283.7 | T11: 228721.4 | U11: ='Stock Valuation (FIFO)'!T14 -> 228722 | V11: =IF(U11=0,0,(T11-U11)) -> -0.6 | W11: 237947.3 | X11: ='Stock Valuation (FIFO)'!W14 -> 237947 | Y11: =IF(X11=0,0,(W11-X11)) -> 0.3 | Z11: 218950.4 | AA11: ='Stock Valuation (FIFO)'!Z14 -> 218951 | AB11: =IF(AA11=0,0,(Z11-AA11)) -> -0.6 | AC11: 255945.6 | AD11: ='Stock Valuation (FIFO)'!AC14 -> 255947 | AE11: =IF(AD11=0,0,(AC11-AD11)) -> -1.4 | AF11: 261815 | AG11: 261816 | AH11: =IF(AG11=0,0,(AF11-AG11)) -> -1 | AI11: 239651.2 | AJ11: ='Stock Valuation (FIFO)'!AI14 -> 239651 | AK11: =IF(AJ11=0,0,(AI11-AJ11)) -> 0.2 | AL11: 200810.4 | AM11: ='Stock Valuation (FIFO)'!AL14 -> 200810 | AN11: =IF(AM11=0,0,(AL11-AM11)) -> 0.4
A12: TSN | B12: 244 | C12: ='Trading PL'!B42 -> 244 | D12: =B12-C12 -> 0 | E12: 256.6 | F12: ='Trading PL'!B35 -> 257 | G12: =IF(F12=0,0,(E12-F12)) -> -0.4 | H12: 257 | I12: ='Trading PL'!E35 -> 257 | J12: =IF(I12=0,0,(H12-I12)) -> 0 | K12: 197.1 | L12: ='Trading PL'!H35 -> 257 | M12: =IF(L12=0,0,(K12-L12)) -> -59.9 | N12: 197.1 | O12: ='Trading PL'!K35 -> 197 | P12: =IF(O12=0,0,(N12-O12)) -> 0.1 | Q12: 197.1 | R12: ='Trading PL'!N35 -> 197 | S12: =IF(R12=0,0,(Q12-R12)) -> 0.1 | T12: 183.1 | U12: ='Stock Valuation (FIFO)'!T16 -> 183 | V12: =IF(U12=0,0,(T12-U12)) -> 0.1 | W12: 183.1 | X12: ='Stock Valuation (FIFO)'!W16 -> 183 | Y12: =IF(X12=0,0,(W12-X12)) -> 0.1 | Z12: =423.5-36.5 -> 387 | AA12: ='Stock Valuation (FIFO)'!Z15 -> 387 | AB12: =IF(AA12=0,0,(Z12-AA12)) -> 0 | AC12: =423.5-AC16 -> 387 | AD12: ='Stock Valuation (FIFO)'!AC15 -> 387 | AE12: =IF(AD12=0,0,(AC12-AD12)) -> 0 | AF12: =423.5-37 -> 386.5 | AG12: 387 | AH12: =IF(AG12=0,0,(AF12-AG12)) -> -0.5 | AI12: =423.5-AI16 -> 386.5 | AJ12: ='Stock Valuation (FIFO)'!AI15 -> 387 | AK12: =IF(AJ12=0,0,(AI12-AJ12)) -> -0.5 | AL12: =423.5-AL16 -> 386.5 | AM12: ='Stock Valuation (FIFO)'!AL15 -> 387 | AN12: =IF(AM12=0,0,(AL12-AM12)) -> -0.5
A13: MSN | B13: 387 | C13: ='Trading PL'!B41 -> 387 | D13: =B13-C13 -> 0 | E13: 387 | F13: ='Trading PL'!B34 -> 387 | G13: =IF(F13=0,0,(E13-F13)) -> 0 | H13: 387 | I13: ='Trading PL'!E34 -> 387 | J13: =IF(I13=0,0,(H13-I13)) -> 0 | K13: 387 | L13: ='Trading PL'!H34 -> 387 | M13: =IF(L13=0,0,(K13-L13)) -> 0 | N13: 387 | O13: ='Trading PL'!K34 -> 387 | P13: =IF(O13=0,0,(N13-O13)) -> 0 | Q13: 404 | R13: ='Trading PL'!N34 -> 387 | S13: =IF(R13=0,0,(Q13-R13)) -> 17 | T13: 410 | U13: ='Stock Valuation (FIFO)'!T15 -> 387 | V13: =IF(U13=0,0,(T13-U13)) -> 23 | W13: 410 | X13: ='Stock Valuation (FIFO)'!W15 -> 387 | Y13: =IF(X13=0,0,(W13-X13)) -> 23 | Z13: 183.1 | AA13: ='Stock Valuation (FIFO)'!Z16 -> 183 | AB13: =IF(AA13=0,0,(Z13-AA13)) -> 0.1 | AC13: 179.1 | AD13: ='Stock Valuation (FIFO)'!AC16 -> 179 | AE13: =IF(AD13=0,0,(AC13-AD13)) -> 0.1 | AF13: 179.1 | AG13: 179 | AH13: =IF(AG13=0,0,(AF13-AG13)) -> 0.1 | AI13: 177.9 | AJ13: ='Stock Valuation (FIFO)'!AI16 -> 178 | AK13: =IF(AJ13=0,0,(AI13-AJ13)) -> -0.1 | AL13: 171.9 | AM13: ='Stock Valuation (FIFO)'!AL16 -> 172 | AN13: =IF(AM13=0,0,(AL13-AM13)) -> -0.1
A14: PP Sacks | C14: ='Trading PL'!B44 -> 0 | D14: =B14-C14 -> 0 | E14: 0 | F14: ='Trading PL'!B38 -> 0 | G14: =IF(F14=0,0,(E14-F14)) -> 0 | H14: 0 | I14: ='Trading PL'!E38 -> 0 | J14: =IF(I14=0,0,(H14-I14)) -> 0 | K14: 0 | L14: ='Trading PL'!H38 -> 0 | M14: =IF(L14=0,0,(K14-L14)) -> 0 | N14: 0 | O14: ='Trading PL'!K38 -> 0 | P14: =IF(O14=0,0,(N14-O14)) -> 0 | S14: =IF(R14=0,0,(Q14-R14)) -> 0 | T14: 0 | V14: =IF(U14=0,0,(T14-U14)) -> 0 | W14: 0 | Y14: =IF(X14=0,0,(W14-X14)) -> 0 | Z14: 804.1 | AA14: ='Stock Valuation (FIFO)'!Z17 -> 804 | AB14: =IF(AA14=0,0,(Z14-AA14)) -> 0.1 | AC14: 391.2 | AD14: ='Stock Valuation (FIFO)'!AC17 -> 391 | AE14: =IF(AD14=0,0,(AC14-AD14)) -> 0.2 | AF14: 196.2 | AG14: 196 | AH14: =IF(AG14=0,0,(AF14-AG14)) -> 0.2 | AK14: =IF(AJ14=0,0,(AI14-AJ14)) -> 0 | AL14: 0 | AN14: =IF(AM14=0,0,(AL14-AM14)) -> 0
A15: Weed Mat | B15: 75 | C15: ='Trading PL'!B43 -> 75 | D15: =B15-C15 -> 0 | E15: 46.8 | F15: ='Trading PL'!B37 -> 0 | G15: =IF(F15=0,0,(E15-F15)) -> 0 | H15: 36.1 | I15: ='Trading PL'!E37 -> 0 | J15: =IF(I15=0,0,(H15-I15)) -> 0 | K15: 26.1 | L15: ='Trading PL'!H37 -> 0 | M15: =IF(L15=0,0,(K15-L15)) -> 0 | N15: 129.1 | O15: ='Trading PL'!K37 -> 0 | P15: =IF(O15=0,0,(N15-O15)) -> 0 | Q15: 153.1 | R15: ='Trading PL'!N36 -> 153 | S15: =IF(R15=0,0,(R15-Q15)) -> -0.1 | T15: 450.1 | U15: ='Stock Valuation (FIFO)'!T17 -> 450 | V15: =IF(U15=0,0,(T15-U15)) -> 0.1 | W15: 172.1 | X15: ='Stock Valuation (FIFO)'!W17 -> 172 | Y15: =IF(X15=0,0,(W15-X15)) -> 0.1 | AB15: =IF(AA15=0,0,(Z15-AA15)) -> 0 | AD15: ='Stock Valuation (FIFO)'!AC18 -> 0 | AE15: =IF(AD15=0,0,(AC15-AD15)) -> 0 | AH15: =IF(AG15=0,0,(AF15-AG15)) -> 0 | AI15: 446.2 | AJ15: ='Stock Valuation (FIFO)'!AI17 -> 446 | AK15: =IF(AJ15=0,0,(AI15-AJ15)) -> 0.2 | AL15: 446.2 | AM15: ='Stock Valuation (FIFO)'!AL17 -> 446 | AN15: =IF(AM15=0,0,(AL15-AM15)) -> 0.2
A16: PP Fabric | D16: =B16-C16 -> 0 | G16: =IF(F16=0,0,(E16-F16)) -> 0 | J16: =IF(I16=0,0,(H16-I16)) -> 0 | M16: =IF(L16=0,0,(K16-L16)) -> 0 | P16: =IF(O16=0,0,(N16-O16)) -> 0 | R16: ='Trading PL'!N38 -> 17 | S16: =IF(R16=0,0,(R16-Q16)) -> 17 | U16: ='Stock Valuation (FIFO)'!T19 -> 17 | X16: ='Stock Valuation (FIFO)'!W19 -> 23 | Y16: =IF(X16=0,0,(W16-X16)) -> -23 | Z16: 36.5 | AA16: ='Stock Valuation (FIFO)'!Z19 -> 37 | AB16: =IF(AA16=0,0,(Z16-AA16)) -> -0.5 | AC16: 36.5 | AD16: ='Stock Valuation (FIFO)'!AC19 -> 37 | AE16: =IF(AD16=0,0,(AC16-AD16)) -> -0.5 | AF16: 37 | AG16: 37 | AH16: =IF(AG16=0,0,(AF16-AG16)) -> 0 | AI16: 37 | AJ16: ='Stock Valuation (FIFO)'!AI19 -> 37 | AK16: =IF(AJ16=0,0,(AI16-AJ16)) -> 0 | AL16: 37 | AM16: ='Stock Valuation (FIFO)'!AL19 -> 37 | AN16: =IF(AM16=0,0,(AL16-AM16)) -> 0
A17: Fabric Total | B17: =SUM(B11:B16) -> 206733 | C17: =SUM(C11:C16) -> 206733 | D17: =B17-C17 -> 0 | E17: =SUM(E11:E16) -> 224735.3 | F17: =SUM(F11:F16) -> 224689 | G17: =IF(F17=0,0,(E17-F17)) -> 46.3 | H17: =SUM(H11:H16) -> 202526.4 | I17: =SUM(I11:I16) -> 169015 | J17: =IF(I17=0,0,(H17-I17)) -> 33511.4 | K17: =SUM(K11:K16) -> 191885.4 | L17: =SUM(L11:L16) -> 141091 | M17: =IF(L17=0,0,(K17-L17)) -> 50794.4 | N17: =SUM(N11:N16) -> 198508.3 | O17: =SUM(O11:O16) -> 130783 | P17: =IF(O17=0,0,(N17-O17)) -> 67725.3 | Q17: =SUM(Q11:Q16) -> 203063.5 | R17: =SUM(R11:R15) -> 203330 | S17: =IF(R17=0,0,(Q17-R17)) -> -266.5 | T17: =SUM(T11:T16) -> 229764.6 | U17: =SUM(U11:U16) -> 229759 | V17: =IF(U17=0,0,(T17-U17)) -> 5.6 | W17: =SUM(W11:W16) -> 238712.5 | X17: =SUM(X11:X16) -> 238712 | Y17: =IF(X17=0,0,(W17-X17)) -> 0.5 | Z17: =SUM(Z11:Z16) -> 220361.1 | AA17: =SUM(AA11:AA16) -> 220362 | AB17: =IF(AA17=0,0,(Z17-AA17)) -> -0.9 | AC17: =SUM(AC11:AC16) -> 256939.4 | AD17: =SUM(AD11:AD16) -> 256941 | AE17: =IF(AD17=0,0,(AC17-AD17)) -> -1.6 | AF17: =SUM(AF11:AF16) -> 262613.8 | AG17: =SUM(AG11:AG16) -> 262615 | AH17: =IF(AG17=0,0,(AF17-AG17)) -> -1.2 | AI17: =SUM(AI11:AI16) -> 240698.8 | AJ17: =SUM(AJ11:AJ16) -> 240699 | AK17: =IF(AJ17=0,0,(AI17-AJ17)) -> -0.2 | AL17: =SUM(AL11:AL16) -> 201852 | AM17: =SUM(AM11:AM16) -> 201852 | AN17: =IF(AM17=0,0,(AL17-AM17)) -> 0
A18: TOTAL | B18: =B7+B10+B17 -> 530467 | C18: =C7+C10+C17 -> 530467 | D18: =B18-C18 -> 0 | E18: =E7+E10+E17 -> 527374.5 | F18: =F7+F10+F17 -> 527328 | G18: =IF(F18=0,0,(E18-F18)) -> 46.5 | H18: =H7+H10+H17 -> 460685.4 | I18: =I7+I10+I17 -> 427171 | J18: =IF(I18=0,0,(H18-I18)) -> 33514.4 | K18: =K7+K10+K17 -> 477952.8 | L18: =L7+L10+L17 -> 427158 | M18: =IF(L18=0,0,(K18-L18)) -> 50794.8 | N18: =N7+N10+N17 -> 469932.9 | O18: =O7+O10+O17 -> 402207 | P18: =IF(O18=0,0,(N18-O18)) -> 67725.9 | Q18: =Q7+Q10+Q17 -> 520767.1 | R18: =R7+R10+R17 -> 521032.8 | S18: =IF(R18=0,0,(Q18-R18)) -> -265.7 | T18: =T7+T10+T17 -> 482634 | U18: =U7+U10+U17 -> 482628 | V18: =IF(U18=0,0,(T18-U18)) -> 6 | W18: =W7+W10+W17 -> 522362.7 | X18: =X7+X10+X17 -> 522362 | Y18: =IF(X18=0,0,(W18-X18)) -> 0.7 | Z18: =Z7+Z10+Z17 -> 529435.1 | AA18: =AA7+AA10+AA17 -> 529436 | AB18: =IF(AA18=0,0,(Z18-AA18)) -> -0.9 | AC18: =AC7+AC10+AC17 -> 541442.9 | AD18: =AD7+AD10+AD17 -> 541444 | AE18: =IF(AD18=0,0,(AC18-AD18)) -> -1.1 | AF18: =AF7+AF10+AF17 -> 579350.5 | AG18: =AG7+AG10+AG17 -> 579352 | AH18: =IF(AG18=0,0,(AF18-AG18)) -> -1.5 | AI18: =AI7+AI10+AI17 -> 536653.5 | AJ18: =AJ7+AJ10+AJ17 -> 536653 | AK18: =IF(AJ18=0,0,(AI18-AJ18)) -> 0.5 | AL18: =AL7+AL10+AL17 -> 467993.89 | AM18: =AM7+AM10+AM17 -> 447508 | AN18: =IF(AM18=0,0,(AL18-AM18)) -> 20485.89
A20: SFG/FG | B20: =B18-B7 -> 332926 | C20: =C18-C7 -> 332926 | D20: =B20-C20 -> 0 | E20: =E18-E7 -> 344910.9 | F20: =F18-F7 -> 344865 | G20: =IF(F20=0,0,(E20-F20)) -> 45.9 | H20: =H18-H7 -> 310941.6 | I20: =I18-I7 -> 277430 | J20: =IF(I20=0,0,(H20-I20)) -> 33511.6 | K20: =K18-K7 -> 311174.6 | L20: =L18-L7 -> 260380 | M20: =IF(L20=0,0,(K20-L20)) -> 50794.6 | N20: =N18-N7 -> 320985.8 | O20: =O18-O7 -> 253260 | P20: =IF(O20=0,0,(N20-O20)) -> 67725.8 | Q20: =Q18-Q7 -> 330039.4 | R20: =R18-R7 -> 330304.8 | S20: =IF(R20=0,0,(Q20-R20)) -> -265.4 | T20: =T18-T7 -> 365118.5 | U20: =U18-U7 -> 365113 | V20: =IF(U20=0,0,(T20-U20)) -> 5.5 | W20: =W18-W7 -> 379701.5 | X20: =X18-X7 -> 379701 | Y20: =IF(X20=0,0,(W20-X20)) -> 0.5 | Z20: =Z18-Z7 -> 362682.7 | AA20: =AA18-AA7 -> 362684 | AB20: =IF(AA20=0,0,(Z20-AA20)) -> -1.3 | AC20: =AC18-AC7 -> 403532.4 | AD20: =AD18-AD7 -> 403534 | AE20: =IF(AD20=0,0,(AC20-AD20)) -> -1.6 | AF20: =AF18-AF7 -> 402129.2 | AG20: =AG18-AG7 -> 402131 | AH20: =IF(AG20=0,0,(AF20-AG20)) -> -1.8 | AI20: =AI18-AI7 -> 379064.6 | AJ20: =AJ18-AJ7 -> 379065 | AK20: =IF(AJ20=0,0,(AI20-AJ20)) -> -0.4 | AL20: =AL18-AL7 -> 324505.29 | AM20: =AM18-AM7 -> 304019 | AN20: =IF(AM20=0,0,(AL20-AM20)) -> 20486.29
E21: =E20-B20 -> 11984.9 | H21: =H20-E20 -> -33969.3 | K21: =K20-H20 -> 233 | N21: =N20-K20 -> 9811.2 | Q21: =Q20-N20 -> 9053.6 | T21: =T20-Q20 -> 35079.1 | W21: =W20-T20 -> 14583
E22: =E20-$B$20 -> 11984.9 | H22: =H20-$B$20 -> -21984.4 | K22: =K20-$B$20 -> -21751.4 | N22: =N20-$B$20 -> -11940.2 | Q22: =Q20-$B$20 -> -2886.6 | T22: =T20-$B$20 -> 32192.5 | W22: =W20-$B$20 -> 46775.5
A23: Tarka->
A24: HDPE | H24: =63410+93000 -> 156410 | I24: =H4-H24 -> -9000
A25: MB | H25: 2240 | I25: =H5-H25 -> 53.7
A26: CP | H26: 80 | I26: =H6-H26 -> -39.9
A27: RM Total | H27: =SUM(H24:H26) -> 158730 | I27: =SUM(I24:I26) -> -8986.2
A28: Yarn Factory | H28: 30450 | I28: =H8-H28 -> 16114
A29: Yarn Fabrctr | H29: 64627 | I29: =H9-H29 -> -2775.8
A30: Yarn Total | H30: =SUM(H28:H29) -> 95077 | I30: =SUM(I28:I29) -> 13338.2
A31: Fabric | H31: 332260 | I31: =H11-H31 -> -130413.7
A32: TSN | H32: 108 | I32: =H12-H32 -> 149
A33: MSN | H33: 1015 | I33: =H13-H33 -> -628
A34: Weed Mat
A35: PP Fab
A36: PP Sacks | Q36: 942.6
A37: Fabric Total | H37: =SUM(H31:H36) -> 333383 | I37: =SUM(I31:I36) -> -130892.7
A38: TOTAL | H38: =H27+H30+H37 -> 587190 | I38: =I27+I30+I37 -> -126540.7
A40: SFG/FG | H40: =H38-H27 -> 428460 | I40: =I38-I27 -> -117554.5

Sheet Inventory Sales
A2: Particulars | B2: Apr | E2: May | H2: Jun | K2: Jul | N2: Aug | Q2: Sep | T2: Oct | W2: Nov | Z2: Dec | AC2: Jan | AF2: Feb | AI2: Mar | AL2: Total
A3: Finished Goods | B3: Outwards Qty | C3: Rate | D3: Amount | E3: Outwards Qty | F3: Rate | G3: Amount | H3: Outwards Qty | I3: Rate | J3: Amount | K3: Outwards Qty | L3: Rate | M3: Amount | N3: Outwards Qty | O3: Rate | P3: Amount | Q3: Outwards Qty | R3: Rate | S3: Amount | T3: Outwards Qty | U3: Rate | V3: Amount | W3: Outwards Qty | X3: Rate | Y3: Amount | Z3: Outwards Qty | AA3: Rate | AB3: Amount | AC3: Outwards Qty | AD3: Rate | AE3: Amount | AF3: Outwards Qty | AG3: Rate | AH3: Amount | AI3: Outwards Qty | AJ3: Rate | AK3: Amount | AL3: Outwards Qty | AM3: Rate | AN3: Amount
A5: MCF | B5: 41120.23 | C5: =IF(B5=0,0,D5/B5) -> 265.6654 | D5: 10924222 | E5: 72520.71 | F5: =IF(E5=0,0,G5/E5) -> 270.28471 | G5: 19601239 | H5: 66711.07 | I5: =IF(H5=0,0,J5/H5) -> 275.40072 | J5: 18372276 | K5: 54632.46 | L5: =IF(K5=0,0,M5/K5) -> 280.06473 | M5: 15300625 | N5: 43167.19 | O5: =IF(N5=0,0,P5/N5) -> 278.77556 | P5: 12033958 | Q5: 38963.1 | R5: =IF(Q5=0,0,S5/Q5) -> 275.56432 | S5: 10736840 | T5: 50565.14 | U5: =IF(T5=0,0,V5/T5) -> 263.90285 | V5: 13344284 | W5: 42420.62 | X5: =IF(W5=0,0,Y5/W5) -> 262.15435 | Y5: 11120750 | Z5: 29769.32 | AA5: =IF(Z5=0,0,AB5/Z5) -> 265.79562 | AB5: 7912555 | AC5: 39918.5 | AD5: =IF(AC5=0,0,AE5/AC5) -> 265.37483 | AE5: 10593365 | AF5: 60348.07 | AG5: =IF(AF5=0,0,AH5/AF5) -> 268.19502 | AH5: 16185052 | AI5: 77562.79 | AJ5: =IF(AI5=0,0,AK5/AI5) -> 285.65156 | AK5: 22155932 | AL5: =SUM(B5,E5,H5,K5,N5,Q5,T5,W5,Z5,AC5,AF5,AI5) -> 617699.2 | AM5: =IF(AL5=0,0,AN5/AL5) -> 272.43211 | AN5: =SUM(D5,G5,J5,M5,P5,S5,V5,Y5,AB5,AE5,AH5,AK5) -> 168281099 | AQ5: =AM5 -> 272.43211 | AR5: =AM6 -> 260.884
A6: WMF | B6: 52570.56 | C6: =IF(B6=0,0,D6/B6) -> 252.51645 | D6: 13274931 | E6: 53892.04 | F6: =IF(E6=0,0,G6/E6) -> 258.49398 | G6: 13930768 | H6: 46431.97 | I6: =IF(H6=0,0,J6/H6) -> 277.11921 | J6: 12867191 | K6: 50356.34 | L6: =IF(K6=0,0,M6/K6) -> 262.57795 | M6: 13222464 | N6: 59476.5 | O6: =IF(N6=0,0,P6/N6) -> 255.71268 | P6: 15208895 | Q6: 49063.76 | R6: =IF(Q6=0,0,S6/Q6) -> 259.38175 | S6: 12726244 | T6: 36661.11 | U6: =IF(T6=0,0,V6/T6) -> 257.84578 | V6: 9452912.5 | W6: 76513.39 | X6: =IF(W6=0,0,Y6/W6) -> 249.27027 | Y6: 19072514 | Z6: 46944.17 | AA6: =IF(Z6=0,0,AB6/Z6) -> 252.25225 | AB6: 11841772 | AC6: 70387 | AD6: =IF(AC6=0,0,AE6/AC6) -> 260.00611 | AE6: 18301050 | AF6: 58203.1 | AG6: =IF(AF6=0,0,AH6/AF6) -> 263.23728 | AH6: 15321226 | AI6: 70675.97 | AJ6: =IF(AI6=0,0,AK6/AI6) -> 281.27086 | AK6: 19879091 | AL6: =SUM(B6,E6,H6,K6,N6,Q6,T6,W6,Z6,AC6,AF6,AI6) -> 671175.91 | AM6: =IF(AL6=0,0,AN6/AL6) -> 260.884 | AN6: =SUM(D6,G6,J6,M6,P6,S6,V6,Y6,AB6,AE6,AH6,AK6) -> 175099059 | AP6: ='PAL I'!AN5+'PAL I'!AN8 -> 209386214 | AQ6: =(AP6/(AL11)) -> 148.77815 | AR6: =AQ6 -> 148.77815
A7: MONOFILAMENT FABRIC INSECT BAGS | C7: =IF(B7=0,0,D7/B7) -> 0 | I7: =IF(H7=0,0,J7/H7) -> 0 | L7: =IF(K7=0,0,M7/K7) -> 0 | R7: =IF(Q7=0,0,S7/Q7) -> 0 | U7: =IF(T7=0,0,V7/T7) -> 0 | X7: =IF(W7=0,0,Y7/W7) -> 0 | AA7: =IF(Z7=0,0,AB7/Z7) -> 0 | AD7: =IF(AC7=0,0,AE7/AC7) -> 0 | AG7: =IF(AF7=0,0,AH7/AF7) -> 0 | AJ7: =IF(AI7=0,0,AK7/AI7) -> 0 | AL7: =SUM(B7,E7,H7,K7,N7,Q7,T7,W7,Z7,AC7,AF7,AI7) -> 0 | AM7: =IF(AL7=0,0,AN7/AL7) -> 0 | AN7: =SUM(D7,G7,J7,M7,P7,S7,V7,Y7,AB7,AE7,AH7,AK7) -> 0 | AQ7: =AQ5-AQ6 -> 123.65397 | AR7: =AR5-AR6 -> 112.10586
A8: MONOFILAMENT FABRIC INSECT NET | B8: 30.08 | C8: =IF(B8=0,0,D8/B8) -> 376.16356 | D8: 11315 | H8: 1039.9 | I8: =IF(H8=0,0,J8/H8) -> 359.63073 | J8: 373980 | K8: 6 | L8: =IF(K8=0,0,M8/K8) -> 390 | M8: 2340 | R8: =IF(Q8=0,0,S8/Q8) -> 0 | T8: 26 | U8: =IF(T8=0,0,V8/T8) -> 360 | V8: 9360 | W8: 389.2 | X8: =IF(W8=0,0,Y8/W8) -> 412.84687 | Y8: 160680 | AA8: =IF(Z8=0,0,AB8/Z8) -> 0 | AD8: =IF(AC8=0,0,AE8/AC8) -> 0 | AF8: 271.7 | AG8: =IF(AF8=0,0,AH8/AF8) -> 336.5035 | AH8: 91428 | AJ8: =IF(AI8=0,0,AK8/AI8) -> 0 | AL8: =SUM(B8,E8,H8,K8,N8,Q8,T8,W8,Z8,AC8,AF8,AI8) -> 1762.88 | AM8: =IF(AL8=0,0,AN8/AL8) -> 368.206 | AN8: =SUM(D8,G8,J8,M8,P8,S8,V8,Y8,AB8,AE8,AH8,AK8) -> 649103
A9: MONOFILAMENT FABRIC HAPPA | C9: =IF(B9=0,0,D9/B9) -> 0 | E9: 23 | F9: =IF(E9=0,0,G9/E9) -> 660.86957 | G9: 15200 | I9: =IF(H9=0,0,J9/H9) -> 0 | L9: =IF(K9=0,0,M9/K9) -> 0 | N9: 217.8 | O9: =IF(N9=0,0,P9/N9) -> 977.95684 | P9: 212999 | Q9: 236.9 | R9: =IF(Q9=0,0,S9/Q9) -> 886.44998 | S9: 210000 | T9: 93.4 | U9: =IF(T9=0,0,V9/T9) -> 1027.8373 | V9: 96000 | X9: =IF(W9=0,0,Y9/W9) -> 0 | Z9: 196.3 | AA9: =IF(Z9=0,0,AB9/Z9) -> 937.3408 | AB9: 184000 | AD9: =IF(AC9=0,0,AE9/AC9) -> 0 | AG9: =IF(AF9=0,0,AH9/AF9) -> 0 | AI9: 6 | AJ9: =IF(AI9=0,0,AK9/AI9) -> 1257.125 | AK9: 7542.75 | AL9: =SUM(B9,E9,H9,K9,N9,Q9,T9,W9,Z9,AC9,AF9,AI9) -> 773.4 | AM9: =IF(AL9=0,0,AN9/AL9) -> 938.37826 | AN9: =SUM(D9,G9,J9,M9,P9,S9,V9,Y9,AB9,AE9,AH9,AK9) -> 725741.75 | AP9: MCF/WMF | AQ9: =ROUND((AQ7*AL5),0) -> 76380956 | AR9: =ROUND((AR7*AL6),0) -> 75242750
A10: NWF/Yarn / Twisted Yarn | B10: 9900 | C10: =IF(B10=0,0,D10/B10) -> 130.79545 | D10: 1294875 | E10: 12025 | F10: =IF(E10=0,0,G10/E10) -> 129.7817 | G10: 1560625 | H10: 8080.9 | I10: =IF(H10=0,0,J10/H10) -> 129.43138 | J10: 1045922 | K10: 8625 | L10: =IF(K10=0,0,M10/K10) -> 128.66667 | M10: 1109750 | N10: 7500 | O10: =IF(N10=0,0,P10/N10) -> 126.33333 | P10: 947500 | Q10: 7750 | R10: =IF(Q10=0,0,S10/Q10) -> 126.93548 | S10: 983750 | T10: 6375 | U10: =IF(T10=0,0,V10/T10) -> 128.13725 | V10: 816875 | W10: 10250 | X10: =IF(W10=0,0,Y10/W10) -> 129.07317 | Y10: 1323000 | Z10: 10291.4 | AA10: =IF(Z10=0,0,AB10/Z10) -> 127.77348 | AB10: 1314968 | AC10: 9500 | AD10: =IF(AC10=0,0,AE10/AC10) -> 127.63158 | AE10: 1212500 | AF10: 9394 | AG10: =IF(AF10=0,0,AH10/AF10) -> 128.41761 | AH10: 1206355 | AI10: 16269.4 | AJ10: =IF(AI10=0,0,AK10/AI10) -> 120.63932 | AK10: 1962729.4 | AL10: =SUM(B10,E10,H10,K10,N10,Q10,T10,W10,Z10,AC10,AF10,AI10) -> 115960.7 | AM10: =IF(AL10=0,0,AN10/AL10) -> 127.44705 | AN10: =SUM(D10,G10,J10,M10,P10,S10,V10,Y10,AB10,AE10,AH10,AK10) -> 14778849 | AQ10: =AQ9+AR9 -> 151623706
B11: =SUM(B5:B10) -> 103620.87 | C11: =IF(B11=0,0,D11/B11) -> 246.14099 | D11: =SUM(D5:D10) -> 25505344 | E11: =SUM(E5:E10) -> 138460.75 | F11: =IF(E11=0,0,G11/E11) -> 253.55801 | G11: =SUM(G5:G10) -> 35107832 | H11: =SUM(H5:H10) -> 122263.84 | I11: =IF(H11=0,0,J11/H11) -> 267.12207 | J11: =SUM(J5:J10) -> 32659370 | K11: =SUM(K5:K10) -> 113619.8 | L11: =IF(K11=0,0,M11/K11) -> 260.8276 | M11: =SUM(M5:M10) -> 29635180 | N11: =SUM(N5:N10) -> 110361.49 | O11: =IF(N11=0,0,P11/N11) -> 257.36651 | P11: =SUM(P5:P10) -> 28403352 | Q11: =SUM(Q5:Q10) -> 96013.76 | R11: =IF(Q11=0,0,S11/Q11) -> 256.80521 | S11: =SUM(S5:S10) -> 24656834 | T11: =SUM(T5:T10) -> 93720.65 | U11: =IF(T11=0,0,V11/T11) -> 253.08651 | V11: =SUM(V5:V10) -> 23719432 | W11: =SUM(W5:W10) -> 129573.21 | X11: =IF(W11=0,0,Y11/W11) -> 244.4714 | Y11: =SUM(Y5:Y10) -> 31676944 | Z11: =SUM(Z5:Z10) -> 87201.19 | AA11: =IF(Z11=0,0,AB11/Z11) -> 243.72713 | AB11: =SUM(AB5:AB10) -> 21253296 | AC11: =SUM(AC5:AC10) -> 119805.5 | AD11: =IF(AC11=0,0,AE11/AC11) -> 251.29827 | AE11: =SUM(AE5:AE10) -> 30106915 | AF11: =SUM(AF5:AF10) -> 128216.87 | AG11: =IF(AF11=0,0,AH11/AF11) -> 255.84824 | AH11: =SUM(AH5:AH10) -> 32804061 | AI11: =SUM(AI5:AI10) -> 164514.16 | AJ11: =IF(AI11=0,0,AK11/AI11) -> 267.48637 | AK11: =SUM(AK5:AK10) -> 44005295 | AL11: =SUM(AL5:AL10) -> 1407372.1 | AM11: =IF(AL11=0,0,AN11/AL11) -> 255.46467 | AN11: =SUM(AN5:AN10) -> 3.5953385e+08 | AP11: Othr MF | AQ11: =SUM(AN7:AN10) -> 16153694 | AR11: ='PAL I'!AN26 -> 160821412
A12: MSN | E12: 1908 | F12: =IF(E12=0,0,G12/E12) -> 263.19706 | G12: 502180 | H12: 580 | I12: =IF(H12=0,0,J12/H12) -> 282.41379 | J12: 163800 | N12: =405+15 -> 420 | O12: =IF(N12=0,0,P12/N12) -> 326.71429 | P12: =126000+11220 -> 137220 | R12: =IF(Q12=0,0,S12/Q12) -> 0 | T12: 653 | U12: =IF(T12=0,0,V12/T12) -> 250.84227 | V12: 163800 | X12: =IF(W12=0,0,Y12/W12) -> 0 | Z12: 205 | AA12: =IF(Z12=0,0,AB12/Z12) -> 266.34146 | AB12: 54600 | AC12: 415 | AD12: =IF(AC12=0,0,AE12/AC12) -> 303.61446 | AE12: 126000 | AF12: 1263 | AG12: =IF(AF12=0,0,AH12/AF12) -> 266.47664 | AH12: 336560 | AI12: 90 | AJ12: =IF(AI12=0,0,AK12/AI12) -> 320 | AK12: 28800 | AL12: =SUM(B12,E12,H12,K12,N12,Q12,T12,W12,Z12,AC12,AF12,AI12) -> 5534 | AM12: =IF(AL12=0,0,AN12/AL12) -> 273.39357 | AN12: =SUM(D12,G12,J12,M12,P12,S12,V12,Y12,AB12,AE12,AH12,AK12) -> 1512960 | AP12: Inc from MF | AQ12: =SUM(AQ10:AQ11) -> 1.677774e+08
A13: TSN | B13: 887.91 | C13: =IF(B13=0,0,D13/B13) -> 227.27754 | D13: 201802 | E13: 195 | F13: =IF(E13=0,0,G13/E13) -> 267.40513 | G13: 52144 | H13: 348 | I13: =IF(H13=0,0,J13/H13) -> 239.56897 | J13: 83370 | K13: 168 | L13: =IF(K13=0,0,M13/K13) -> 261.78571 | M13: 43980 | Q13: 14 | R13: =IF(Q13=0,0,S13/Q13) -> 342.85714 | S13: 4800 | T13: 128 | U13: =IF(T13=0,0,V13/T13) -> 236.25 | V13: 30240 | W13: 117 | X13: =IF(W13=0,0,Y13/W13) -> 226.92308 | Y13: 26550 | Z13: 381 | AA13: =IF(Z13=0,0,AB13/Z13) -> 220.95801 | AB13: 84185 | AC13: 828 | AD13: =IF(AC13=0,0,AE13/AC13) -> 216.30435 | AE13: 179100 | AF13: 55.2 | AG13: =IF(AF13=0,0,AH13/AF13) -> 228.07971 | AH13: 12590 | AI13: 917.5 | AJ13: =IF(AI13=0,0,AK13/AI13) -> 265.65907 | AK13: 243742.2 | AL13: =SUM(B13,E13,H13,K13,N13,Q13,T13,W13,Z13,AC13,AF13,AI13) -> 4039.61 | AM13: =IF(AL13=0,0,AN13/AL13) -> 238.26637 | AN13: =SUM(D13,G13,J13,M13,P13,S13,V13,Y13,AB13,AE13,AH13,AK13) -> 962503.2 | AP13: Trading Inc | AQ13: =ROUND((AN18-'PAL I'!AN6),0) -> 2077971
A14: PP Woven Sacks | B14: 4797.6 | C14: =IF(B14=0,0,D14/B14) -> 166.02885 | D14: 796540 | E14: 5704.65 | F14: =IF(E14=0,0,G14/E14) -> 165.74917 | G14: 945541 | H14: 4826 | I14: =IF(H14=0,0,J14/H14) -> 169.20659 | J14: 816591 | K14: 6780.8 | L14: =IF(K14=0,0,M14/K14) -> 169.49254 | M14: 1149295 | N14: 4998.6 | O14: =IF(N14=0,0,P14/N14) -> 168.75185 | P14: 843523 | Q14: 5020.2 | R14: =IF(Q14=0,0,S14/Q14) -> 163.75264 | S14: =847407-S37 -> 822071 | T14: 5785.2 | U14: =IF(T14=0,0,V14/T14) -> 168.65519 | V14: 975704 | W14: 5688.5 | X14: =IF(W14=0,0,Y14/W14) -> 169.15338 | Y14: 962229 | Z14: 4737.4 | AA14: =IF(Z14=0,0,AB14/Z14) -> 169.27998 | AB14: 801947 | AC14: 2164.2 | AD14: =IF(AC14=0,0,AE14/AC14) -> 165.76287 | AE14: 358744 | AF14: 5103.1 | AG14: =IF(AF14=0,0,AH14/AF14) -> 167.88011 | AH14: =899249-AH37 -> 856709 | AI14: 2928.6 | AJ14: =IF(AI14=0,0,AK14/AI14) -> 168.10216 | AK14: =543352-AK37 -> 492304 | AL14: =SUM(B14,E14,H14,K14,N14,Q14,T14,W14,Z14,AC14,AF14,AI14) -> 58534.85 | AM14: =IF(AL14=0,0,AN14/AL14) -> 167.78377 | AN14: =SUM(D14,G14,J14,M14,P14,S14,V14,Y14,AB14,AE14,AH14,AK14) -> 9821198 | AP14: RM Inco | AQ14: =ROUND((AN25),0) -> 41330800
A15: ANTI BIRD NET / Rope/MULCH/FIBC | B15: 1 | C15: =IF(B15=0,0,D15/B15) -> 720 | D15: 720 | N15: 282 | O15: =IF(N15=0,0,P15/N15) -> 131.17021 | P15: 36990 | Q15: 292 | R15: =IF(Q15=0,0,S15/Q15) -> 144.0137 | S15: 42052 | U15: =IF(T15=0,0,V15/T15) -> 0 | W15: 8994.5 | X15: =IF(W15=0,0,Y15/W15) -> 117.73273 | Y15: 1058947 | Z15: 110 | AA15: =IF(Z15=0,0,AB15/Z15) -> 153.15455 | AB15: 16847 | AD15: =IF(AC15=0,0,AE15/AC15) -> 0 | AG15: =IF(AF15=0,0,AH15/AF15) -> 0 | AJ15: =IF(AI15=0,0,AK15/AI15) -> 0 | AL15: =SUM(B15,E15,H15,K15,N15,Q15,T15,W15,Z15,AC15,AF15,AI15) -> 9679.5 | AM15: =IF(AL15=0,0,AN15/AL15) -> 119.38179 | AN15: =SUM(D15,G15,J15,M15,P15,S15,V15,Y15,AB15,AE15,AH15,AK15) -> 1155556 | AP15: Asset Inc | AQ15: =AN22 -> 270339
A16: Knitted Fabric 8" Red/60" D Green | H16: 51 | I16: =IF(H16=0,0,J16/H16) -> 890.7451 | J16: 45428 | N16: 646.92 | O16: =IF(N16=0,0,P16/N16) -> 215.63717 | P16: 139500 | Q16: 49 | R16: =IF(Q16=0,0,S16/Q16) -> 875.5102 | S16: 42900 | T16: 27 | U16: =IF(T16=0,0,V16/T16) -> 995.2963 | V16: 26873 | X16: =IF(W16=0,0,Y16/W16) -> 0 | Z16: 15 | AA16: =IF(Z16=0,0,AB16/Z16) -> 480.53333 | AB16: 7208 | AC16: 38 | AD16: =IF(AC16=0,0,AE16/AC16) -> 903.15789 | AE16: 34320 | AF16: 157.34 | AG16: =IF(AF16=0,0,AH16/AF16) -> 264.61167 | AH16: 41634 | AJ16: =IF(AI16=0,0,AK16/AI16) -> 0 | AL16: =SUM(B16,E16,H16,K16,N16,Q16,T16,W16,Z16,AC16,AF16,AI16) -> 984.26 | AM16: =IF(AL16=0,0,AN16/AL16) -> 343.26601 | AN16: =SUM(D16,G16,J16,M16,P16,S16,V16,Y16,AB16,AE16,AH16,AK16) -> 337863 | AP16: Waste Inc | AQ16: =AN21+AN20 -> 676652
A17: Weed Mat | B17: 2058.25 | C17: =IF(B17=0,0,D17/B17) -> 183.90866 | D17: 378530 | E17: 870.65 | F17: =IF(E17=0,0,G17/E17) -> 193.84942 | G17: 168775 | H17: 1226 | I17: =IF(H17=0,0,J17/H17) -> 190.6199 | J17: 233700 | K17: 1580 | L17: =IF(K17=0,0,M17/K17) -> 190.63291 | M17: 301200 | N17: 715 | P17: 137160 | Q17: 508 | R17: =IF(Q17=0,0,S17/Q17) -> 189.4685 | S17: 96250 | T17: 856 | U17: =IF(T17=0,0,V17/T17) -> 193.63318 | V17: 165750 | W17: 378 | X17: =IF(W17=0,0,Y17/W17) -> 200.89947 | Y17: 75940 | Z17: 1223 | AA17: =IF(Z17=0,0,AB17/Z17) -> 192.59035 | AB17: 235538 | AC17: 1005 | AD17: =IF(AC17=0,0,AE17/AC17) -> 189.02985 | AE17: 189975 | AF17: 250 | AG17: =IF(AF17=0,0,AH17/AF17) -> 190 | AH17: 47500 | AI17: 2040 | AJ17: =IF(AI17=0,0,AK17/AI17) -> 236.47059 | AK17: 482400 | AL17: =SUM(B17,E17,H17,K17,N17,Q17,T17,W17,Z17,AC17,AF17,AI17) -> 12709.9 | AM17: =IF(AL17=0,0,AN17/AL17) -> 197.6977 | AN17: =SUM(D17,G17,J17,M17,P17,S17,V17,Y17,AB17,AE17,AH17,AK17) -> 2512718 | AP17: Other Inc | AQ17: ='PAL I'!AN17 -> 148503
B18: =SUM(B12:B17) -> 7744.76 | C18: =IF(B18=0,0,D18/B18) -> 177.87407 | D18: =SUM(D12:D17) -> 1377592 | E18: =SUM(E12:E17) -> 8678.3 | F18: =IF(E18=0,0,G18/E18) -> 192.27729 | G18: =SUM(G12:G17) -> 1668640 | H18: =SUM(H12:H17) -> 7031 | I18: =IF(H18=0,0,J18/H18) -> 190.99545 | J18: =SUM(J12:J17) -> 1342889 | K18: =SUM(K12:K17) -> 8528.8 | L18: =IF(K18=0,0,M18/K18) -> 175.22688 | M18: =SUM(M12:M17) -> 1494475 | N18: =SUM(N12:N17) -> 7062.52 | O18: =IF(N18=0,0,P18/N18) -> 183.27637 | P18: =SUM(P12:P17) -> 1294393 | Q18: =SUM(Q12:Q17) -> 5883.2 | R18: =IF(Q18=0,0,S18/Q18) -> 171.34774 | S18: =SUM(S12:S17) -> 1008073 | T18: =SUM(T12:T17) -> 7449.2 | U18: =IF(T18=0,0,V18/T18) -> 182.88769 | V18: =SUM(V12:V17) -> 1362367 | W18: =SUM(W12:W17) -> 15178 | X18: =IF(W18=0,0,Y18/W18) -> 139.91738 | Y18: =SUM(Y12:Y17) -> 2123666 | Z18: =SUM(Z12:Z17) -> 6671.4 | AA18: =IF(Z18=0,0,AB18/Z18) -> 179.92101 | AB18: =SUM(AB12:AB17) -> 1200325 | AC18: =SUM(AC12:AC17) -> 4450.2 | AD18: =IF(AC18=0,0,AE18/AC18) -> 199.57283 | AE18: =SUM(AE12:AE17) -> 888139 | AF18: =SUM(AF12:AF17) -> 6828.64 | AG18: =IF(AF18=0,0,AH18/AF18) -> 189.64142 | AH18: =SUM(AH12:AH17) -> 1294993 | AI18: =SUM(AI12:AI17) -> 5976.1 | AJ18: =IF(AI18=0,0,AK18/AI18) -> 208.70571 | AK18: =SUM(AK12:AK17) -> 1247246.2 | AL18: =SUM(AL12:AL17) -> 91482.12 | AM18: =IF(AL18=0,0,AN18/AL18) -> 178.20748 | AN18: =SUM(AN12:AN17) -> 16302798 | AO18: =AL11+AL18 -> 1498854.2 | AQ18: =SUM(AQ10:AQ17) -> 3.8005907e+08 | AR18: =SUM(AR11:AR17) -> 160821412
A19: Flexible Intermediate Bulk Container | F19: =IF(E19=0,0,G19/E19) -> 0 | R19: =IF(Q19=0,0,S19/Q19) -> 0 | AA19: =IF(Z19=0,0,AB19/Z19) -> 0 | AD19: =IF(AC19=0,0,AE19/AC19) -> 0 | AG19: =IF(AF19=0,0,AH19/AF19) -> 0 | AJ19: =IF(AI19=0,0,AK19/AI19) -> 0 | AL19: =SUM(B19,E19,H19,K19,N19,Q19,T19,W19,Z19,AC19,AF19,AI19) -> 0 | AM19: =IF(AL19=0,0,AN19/AL19) -> 0 | AN19: =SUM(D19,G19,J19,M19,P19,S19,V19,Y19,AB19,AE19,AH19,AK19) -> 0 | AR19: =AQ18-AR18 -> 2.1923765e+08
A20: Packing Materials / Old use Batteries | F20: =IF(E20=0,0,G20/E20) -> 0 | R20: =IF(Q20=0,0,S20/Q20) -> 0 | U20: =IF(T20=0,0,V20/T20) -> 0 | AA20: =IF(Z20=0,0,AB20/Z20) -> 0 | AL20: =SUM(B20,E20,H20,K20,N20,Q20,T20,W20,Z20,AC20,AF20,AI20) -> 0 | AM20: =IF(AL20=0,0,AN20/AL20) -> 0 | AN20: =SUM(D20,G20,J20,M20,P20,S20,V20,Y20,AB20,AE20,AH20,AK20) -> 0
A21: HDPE Monofilament Waste | B21: 2110 | C21: =IF(B21=0,0,D21/B21) -> 10 | D21: 21100 | E21: 7739 | F21: =IF(E21=0,0,G21/E21) -> 10 | G21: 77390 | H21: 5654 | I21: =IF(H21=0,0,J21/H21) -> 10 | J21: 56540 | K21: 5340.5 | L21: =IF(K21=0,0,M21/K21) -> 10 | M21: 53405 | N21: 5389 | O21: =IF(N21=0,0,P21/N21) -> 10 | P21: 53890 | Q21: 7178 | R21: =IF(Q21=0,0,S21/Q21) -> 10 | S21: 71780 | T21: 3584 | U21: =IF(T21=0,0,V21/T21) -> 10 | V21: 35840 | W21: 5507 | X21: =IF(W21=0,0,Y21/W21) -> 10 | Y21: 55070 | Z21: 6958 | AA21: =IF(Z21=0,0,AB21/Z21) -> 10 | AB21: 69580 | AC21: 4497 | AD21: =IF(AC21=0,0,AE21/AC21) -> 10 | AE21: 44970 | AF21: 7534.5 | AG21: =IF(AF21=0,0,AH21/AF21) -> 10 | AH21: 75345 | AI21: 5864.6 | AJ21: =IF(AI21=0,0,AK21/AI21) -> 10.527913 | AK21: 61742 | AL21: =SUM(B21,E21,H21,K21,N21,Q21,T21,W21,Z21,AC21,AF21,AI21) -> 67355.6 | AM21: =IF(AL21=0,0,AN21/AL21) -> 10.045965 | AN21: =SUM(D21,G21,J21,M21,P21,S21,V21,Y21,AB21,AE21,AH21,AK21) -> 676652
A22: Sale of Asset Etc | P22: 270339 | R22: =IF(Q22=0,0,S22/Q22) -> 0 | U22: =IF(T22=0,0,V22/T22) -> 0 | X22: =IF(W22=0,0,Y22/W22) -> 0 | AA22: =IF(Z22=0,0,AB22/Z22) -> 0 | AL22: =SUM(B22,E22,H22,K22,N22,Q22,T22,W22,Z22,AC22,AF22,AI22) -> 0 | AM22: =IF(AL22=0,0,AN22/AL22) -> 0 | AN22: =SUM(D22,G22,J22,M22,P22,S22,V22,Y22,AB22,AE22,AH22,AK22) -> 270339
A23: Colour Pigment | B23: 10 | C23: =IF(B23=0,0,D23/B23) -> 1000 | D23: 10000 | K23: 2 | L23: =IF(K23=0,0,M23/K23) -> 2200 | M23: 4400 | N23: 4 | O23: =IF(N23=0,0,P23/N23) -> 1000 | P23: 4000 | R23: =IF(Q23=0,0,S23/Q23) -> 0 | U23: =IF(T23=0,0,V23/T23) -> 0 | X23: =IF(W23=0,0,Y23/W23) -> 0 | AA23: =IF(Z23=0,0,AB23/Z23) -> 0 | AL23: =SUM(B23,E23,H23,K23,N23,Q23,T23,W23,Z23,AC23,AF23,AI23) -> 16 | AM23: =IF(AL23=0,0,AN23/AL23) -> 1150 | AN23: =SUM(D23,G23,J23,M23,P23,S23,V23,Y23,AB23,AE23,AH23,AK23) -> 18400
A24: Master Batch | B24: 211 | C24: =IF(B24=0,0,D24/B24) -> 310.45024 | D24: 65505 | E24: 25 | F24: =IF(E24=0,0,G24/E24) -> 200 | G24: 5000 | H24: 228 | I24: =IF(H24=0,0,J24/H24) -> 298.20175 | J24: 67990 | K24: 227 | L24: =IF(K24=0,0,M24/K24) -> 304.6696 | M24: 69160 | N24: 367 | O24: =IF(N24=0,0,P24/N24) -> 305.20436 | P24: 112010 | Q24: 229 | R24: =IF(Q24=0,0,S24/Q24) -> 302.48908 | S24: 69270 | T24: 221 | U24: =IF(T24=0,0,V24/T24) -> 309.86425 | V24: 68480 | W24: 285 | X24: =IF(W24=0,0,Y24/W24) -> 286.14035 | Y24: 81550 | Z24: 175 | AA24: =IF(Z24=0,0,AB24/Z24) -> 274.28571 | AB24: 48000 | AC24: 215 | AD24: =IF(AC24=0,0,AE24/AC24) -> 310.69767 | AE24: 66800 | AF24: 237 | AG24: =IF(AF24=0,0,AH24/AF24) -> 329.36709 | AH24: 78060 | AI24: 90 | AJ24: =IF(AI24=0,0,AK24/AI24) -> 324.88889 | AK24: 29240 | AL24: =SUM(B24,E24,H24,K24,N24,Q24,T24,W24,Z24,AC24,AF24,AI24) -> 2510 | AM24: =IF(AL24=0,0,AN24/AL24) -> 303.21315 | AN24: =SUM(D24,G24,J24,M24,P24,S24,V24,Y24,AB24,AE24,AH24,AK24) -> 761065
A25: HDPE | B25: 40000 | C25: =IF(B25=0,0,D25/B25) -> 99.7 | D25: 3988000 | E25: 14000 | F25: =IF(E25=0,0,G25/E25) -> 95 | G25: 1330000 | H25: 51000 | I25: =IF(H25=0,0,J25/H25) -> 94.784314 | J25: 4834000 | K25: 55000 | L25: =IF(K25=0,0,M25/K25) -> 98.614545 | M25: 5423800 | N25: 58000 | O25: =IF(N25=0,0,P25/N25) -> 99.12069 | P25: 5749000 | Q25: 31000 | R25: =IF(Q25=0,0,S25/Q25) -> 97.580645 | S25: 3025000 | T25: 24000 | U25: =IF(T25=0,0,V25/T25) -> 95.791667 | V25: 2299000 | W25: 15000 | X25: =IF(W25=0,0,Y25/W25) -> 96.666667 | Y25: 1450000 | Z25: 31000 | AA25: =IF(Z25=0,0,AB25/Z25) -> 92 | AB25: 2852000 | AC25: 38000 | AD25: =IF(AC25=0,0,AE25/AC25) -> 96.605263 | AE25: 3671000 | AF25: 37000 | AG25: =IF(AF25=0,0,AH25/AF25) -> 100.83784 | AH25: 3731000 | AI25: 25000 | AJ25: =IF(AI25=0,0,AK25/AI25) -> 119.12 | AK25: 2978000 | AL25: =SUM(B25,E25,H25,K25,N25,Q25,T25,W25,Z25,AC25,AF25,AI25) -> 419000 | AM25: =IF(AL25=0,0,AN25/AL25) -> 98.641527 | AN25: =SUM(D25,G25,J25,M25,P25,S25,V25,Y25,AB25,AE25,AH25,AK25) -> 41330800 | AO25: =AO18+AL25 -> 1917854.2
B26: =SUM(B19:B25) -> 42331 | C26: =IF(B26=0,0,D26/B26) -> 96.492051 | D26: =SUM(D19:D25) -> 4084605 | E26: =SUM(E19:E25) -> 21764 | F26: =IF(E26=0,0,G26/E26) -> 64.895699 | G26: =SUM(G19:G25) -> 1412390 | H26: =SUM(H19:H25) -> 56882 | I26: =IF(H26=0,0,J26/H26) -> 87.172216 | J26: =SUM(J19:J25) -> 4958530 | K26: =SUM(K19:K25) -> 60569.5 | L26: =IF(K26=0,0,M26/K26) -> 91.642906 | M26: =SUM(M19:M25) -> 5550765 | N26: =SUM(N19:N25) -> 63760 | O26: =IF(N26=0,0,P26/N26) -> 97.070875 | P26: =SUM(P19:P25) -> 6189239 | Q26: =SUM(Q19:Q25) -> 38407 | R26: =IF(Q26=0,0,S26/Q26) -> 82.434192 | S26: =SUM(S19:S25) -> 3166050 | T26: =SUM(T19:T25) -> 27805 | U26: =IF(T26=0,0,V26/T26) -> 86.434814 | V26: =SUM(V19:V25) -> 2403320 | W26: =SUM(W19:W25) -> 20792 | X26: =IF(W26=0,0,Y26/W26) -> 76.309157 | Y26: =SUM(Y19:Y25) -> 1586620 | Z26: =SUM(Z19:Z25) -> 38133 | AA26: =IF(Z26=0,0,AB26/Z26) -> 77.874282 | AB26: =SUM(AB19:AB25) -> 2969580 | AC26: =SUM(AC19:AC25) -> 42712 | AD26: =IF(AC26=0,0,AE26/AC26) -> 88.564572 | AE26: =SUM(AE19:AE25) -> 3782770 | AF26: =SUM(AF19:AF25) -> 44771.5 | AG26: =IF(AF26=0,0,AH26/AF26) -> 86.760662 | AH26: =SUM(AH19:AH25) -> 3884405 | AI26: =SUM(AI19:AI25) -> 30954.6 | AJ26: =IF(AI26=0,0,AK26/AI26) -> 99.144618 | AK26: =SUM(AK19:AK25) -> 3068982 | AL26: =SUM(AL19:AL25) -> 488881.6 | AM26: =IF(AL26=0,0,AN26/AL26) -> 88.072973 | AN26: =SUM(AN19:AN25) -> 43057256
A27: Grand total: | B27: =SUM(B11,B18,B26) -> 153696.63 | C27: =IF(B27=0,0,D27/B27) -> 201.48484 | D27: =SUM(D11,D18,D26) -> 30967540 | E27: =SUM(E11,E18,E26) -> 168903.05 | F27: =IF(E27=0,0,G27/E27) -> 226.0993 | G27: =SUM(G11,G18,G26) -> 38188862 | H27: =SUM(H11,H18,H26) -> 186176.84 | I27: =IF(H27=0,0,J27/H27) -> 209.26764 | J27: =SUM(J11,J18,J26) -> 38960788 | K27: =SUM(K11,K18,K26) -> 182718.1 | L27: =IF(K27=0,0,M27/K27) -> 200.74869 | M27: =SUM(M11,M18,M26) -> 36680420 | N27: =SUM(N11,N18,N26) -> 181184.01 | O27: =IF(N27=0,0,P27/N27) -> 198.06926 | P27: =SUM(P11,P18,P26) -> 35886984 | Q27: =SUM(Q11,Q18,Q26) -> 140303.96 | R27: =IF(Q27=0,0,S27/Q27) -> 205.48926 | S27: =SUM(S11,S18,S26) -> 28830957 | T27: =SUM(T11,T18,T26) -> 128974.85 | U27: =IF(T27=0,0,V27/T27) -> 213.10449 | V27: =SUM(V11,V18,V26) -> 27485119 | W27: =SUM(W11,W18,W26) -> 165543.21 | X27: =IF(W27=0,0,Y27/W27) -> 213.76431 | Y27: =SUM(Y11,Y18,Y26) -> 35387230 | Z27: =SUM(Z11,Z18,Z26) -> 132005.59 | AA27: =IF(Z27=0,0,AB27/Z27) -> 192.59185 | AB27: =SUM(AB11,AB18,AB26) -> 25423200 | AC27: =SUM(AC11,AC18,AC26) -> 166967.7 | AD27: =IF(AC27=0,0,AE27/AC27) -> 208.29073 | AE27: =SUM(AE11,AE18,AE26) -> 34777824 | AF27: =SUM(AF11,AF18,AF26) -> 179817.01 | AG27: =IF(AF27=0,0,AH27/AF27) -> 211.23396 | AH27: =SUM(AH11,AH18,AH26) -> 37983459 | AI27: =SUM(AI11,AI18,AI26) -> 201444.86 | AJ27: =IF(AI27=0,0,AK27/AI27) -> 239.87469 | AK27: =SUM(AK11,AK18,AK26) -> 48321523 | AL27: =SUM(AL11,AL18,AL26) -> 1987735.8 | AM27: =IF(AL27=0,0,AN27/AL27) -> 210.73923 | AN27: =SUM(AN11,AN18,AN26) -> 4.1889391e+08 | AO27: =AN27-AN21 -> 4.1821725e+08
A28: Other Income | D28: 17.85 | G28: 798.67 | J28: 41 | M28: 4.49 | P28: 51.29 | S28: 0.26 | V28: 90.25 | Y28: 4.57 | AB28: 37847.24 | AE28: 0.5 | AH28: 50448.9 | AK28: 59197.67 | AN28: =SUM(D28,G28,J28,M28,P28,S28,V28,Y28,AB28,AE28,AH28,AK28) -> 148502.69
D29: =ROUND((D27-D21),0) -> 30946441 | G29: =ROUND((G27-G21),0) -> 38111472 | J29: =ROUND((J27-J21),0) -> 38904249 | M29: =ROUND((M27-M21),0) -> 36627015 | P29: =ROUND((P27-P21),0) -> 35833094 | S29: =ROUND((S27-S21),0) -> 28759177 | V29: =ROUND((V27-V21),0) -> 27449279 | Y29: =ROUND((Y27-Y21),0) -> 35332160 | AB29: =ROUND((AB27-AB21),0) -> 25353621 | AE29: =ROUND((AE27-AE21),0) -> 34732854 | AH29: =ROUND((AH27-AH21),0) -> 37908114 | AK29: =ROUND((AK27-AK21),0) -> 48259781 | AL29: =AL11+AL18 -> 1498854.2 | AM29: =AN29/AL29 -> 250.7493 | AN29: =AN11+AN18 -> 3.7583665e+08 | AP29: Sales extract value | AQ29: Sales extract kgs
A30: Gross sales | D30: 33048761 | G30: 40365923 | J30: 41624497 | M30: 39437879 | P30: 38487670 | S30: 30634990 | V30: 29269753 | Y30: 37272442 | AB30: 26988536 | AE30: 36691119 | AH30: 40235065 | AK30: 49127787 | AN30: =SUM(D30,G30,J30,M30,P30,S30,V30,Y30,AB30,AE30,AH30,AK30) -> 4.4318442e+08 | AP30: 2.0954089e+08 | AQ30: 1012982.9
A31: tax | D31: 2263250.1 | G31: 2243080.5 | J31: 2763631.2 | M31: 2770897.1 | P31: 2617607 | S31: 1897146.9 | V31: 1807715.8 | Y31: 1897513.5 | AB31: 1745590.6 | AE31: 2045320.7 | AH31: 2406110.5 | AK31: 2779015.6 | AN31: =SUM(D31,G31,J31,M31,P31,S31,V31,Y31,AB31,AE31,AH31,AK31) -> 27236879 | AP31: =AN27-AP30 -> 2.0935302e+08 | AQ31: =AL27-AQ30 -> 974752.92
A32: TCS | D32: 0 | AN32: =SUM(D32,G32,J32,M32,P32,S32,V32,Y32,AB32,AE32,AH32,AK32) -> 0
D33: =D31+D32 -> 2263250.1 | G33: =G31+G32 -> 2243080.5 | J33: =J31+J32 -> 2763631.2 | M33: =M31+M32 -> 2770897.1 | P33: =P31+P32 -> 2617607 | S33: =S31+S32 -> 1897146.9 | V33: =V31+V32 -> 1807715.8 | Y33: =Y31+Y32 -> 1897513.5 | AB33: =AB31+AB32 -> 1745590.6 | AE33: =AE31+AE32 -> 2045320.7 | AH33: =AH31+AH32 -> 2406110.5 | AK33: =AK31+AK32 -> 2779015.6 | AN33: =SUM(AN31:AN32) -> 27236879 | AQ33: P/L sales
D34: =D30-D33 -> 30785511 | G34: =G30-G33 -> 38122842 | J34: =J30-J33 -> 38860866 | M34: =M30-M33 -> 36666982 | P34: =P30-P33 -> 35870064 | S34: =S30-S33 -> 28737843 | V34: =V30-V33 -> 27462037 | Y34: =Y30-Y33 -> 35374929 | AB34: =AB30-AB33 -> 25242946 | AE34: =AE30-AE33 -> 34645798 | AH34: =AH30-AH33 -> 37828954 | AK34: =AK30-AK33 -> 46348771 | AN34: =AN30-AN33 -> 4.1594754e+08 | AQ34: 2.0874843e+08 | AR34: =AQ34-AN34 -> -2.0719911e+08
A35: Discount | D35: 182030 | G35: 66020 | J35: 99922 | M35: 13438 | P35: 16920 | S35: 118450 | V35: 23083.2 | Y35: 12300 | AB35: 180255 | AE35: 132026 | AH35: 197045 | AK35: =2023800+2 -> 2023802 | AN35: =SUM(D35,G35,J35,M35,P35,S35,V35,Y35,AB35,AE35,AH35,AK35) -> 3065291.2 | AR35: =AP30-AQ34 -> 792455 | AS35: OLD USED EICHER 10.90H. MGV VEHICLE NO.KA02AA6749
D36: =D34+D35-D37 -> 30967541 | G36: =G34+G35-G37 -> 38188862 | J36: =J34+J35 -> 38960788 | M36: =M34+M35-M37 -> 36680420 | P36: =P34+P35 -> 35886984 | S36: =S34+S35 -> 28856293 | V36: =V34+V35 -> 27485120 | Y36: =Y34+Y35 -> 35387229 | AB36: =AB34+AB35 -> 25423200 | AE36: =AE34+AE35 -> 34777824 | AH36: =AH34+AH35 -> 38026000 | AK36: =AK34+AK35-AK37 -> 48321525 | AN36: =AN34+AN35 -> 4.1901283e+08 | AO36: =AN27-AN36 -> -118927.03 | AR36: =AN35 -> 3065291.2 | AS36: Discount
A37: Credit Note | P37: 270339 | S37: 25336 | Y37: =Y36-Y27 -> -0.5 | AB37: =AB36-AB27 -> 0 | AH37: 42540 | AK37: 51048 | AN37: =SUM(D37,G37,J37,M37,P37,S37,V37,Y37,AB37,AE37,AH37,AK37) -> 389262.5
D38: =D27-D36 -> -0.18 | G38: =G27-G36 -> -0.2 | J38: =J27-J36 -> 1 | M38: =M27-M36 -> 0 | P38: =P27-P36 -> 0 | Y38: =Y27-Y36 -> 0.5 | AB38: =AB27-AB36 -> 0 | AR38: =AR35-AR36 -> -2272836.2
A39: PAL I- FINAL SALES +Less Waste & Discount | D39: =ROUND((D27-(D21+D22+D35)),0) -> 30764411 | G39: =ROUND((G27-(G21+G35)),0) -> 38045452 | J39: =ROUND((J27-(J21+J22+J35)),0) -> 38804327 | M39: =ROUND((M27-(M21+M22+M35)),0) -> 36613577 | P39: =ROUND((P27-(P21+P22+P35)),0) -> 35545835 | S39: =ROUND((S27-(S21+S22+S35)),0) -> 28640727 | V39: =ROUND((V27-(V21+V22+V35)),0) -> 27426196 | Y39: =ROUND((Y27-(Y21+Y22+Y35)),0) -> 35319860 | AB39: =ROUND((AB27-(AB21+AB22+AB35)),0) -> 25173366 | AE39: =ROUND((AE27-(AE21+AE22+AE35)),0) -> 34600828 | AH39: =ROUND((AH27-(AH21+AH22+AH35)),0) -> 37711069 | AK39: =ROUND((AK27-(AK21+AK22+AK35)),0) -> 46235979 | AN39: =ROUND((AN27-(AN21+AN22+AN35)),0) -> 414881624 | AR39: =AP31+AR38 -> 2.0708018e+08
AN40: =ROUND((AN39-(AN5+AN6)),0) -> 71501466
AN41: =AN36-AN27 -> 118927.03
A42: RM Purchase for sales | B42: =B25+B23+B24 -> 40221 | C42: 95.23 | D42: =ROUND((B25*C42),0) -> 3809200 | E42: =E25+E23+E24 -> 14025 | F42: 99.13 | G42: =ROUND((E25*F42),0) -> 1387820 | H42: =H25+H23+H24 -> 51228 | I42: 93.5 | J42: =ROUND((H25*I42),0) -> 4768500 | K42: =K25+K23+K24 -> 55229 | L42: 94.68 | M42: =ROUND((K25*L42),0) -> 5207400 | N42: =N25+N23+N24 -> 58371 | O42: 95.54 | P42: =ROUND((N25*O42),0) -> 5541320 | Q42: =Q25+Q23+Q24 -> 31229 | R42: 96.7 | S42: =ROUND((Q25*R42),0) -> 2997700 | T42: =T25+T23+T24 -> 24221 | U42: 98.89 | V42: =ROUND((T25*U42),0) -> 2373360 | W42: =W25+W23+W24 -> 15285 | X42: 93.12 | Y42: =ROUND((W25*X42),0) -> 1396800 | Z42: =Z25+Z24+Z23 -> 31175 | AA42: 94.15 | AB42: =ROUND((Z25*AA42),0) -> 2918650 | AC42: =AC25+AC23+AC24 -> 38215 | AD42: 95.39 | AE42: =ROUND((AC25*AD42),0) -> 3624820 | AF42: =AF25+AF23+AF24 -> 37237 | AG42: 96.32 | AH42: =ROUND((AF25*AG42),0) -> 3563840 | AI42: =AI25+AI23+AI24 -> 25090 | AJ42: 104 | AK42: =ROUND((AI25*AJ42),0) -> 2600000 | AL42: =SUM(B42,E42,H42,K42,N42,Q42,T42,W42,Z42,AC42,AF42,AI42) -> 421526 | AM42: =AN42/AL42 -> 95.34266 | AN42: =SUM(D42,G42,J42,M42,P42,S42,V42,Y42,AB42,AE42,AH42,AK42) -> 40189410
C43: =C25-C42 -> 4.47 | F43: =F25-F42 -> -4.13 | I43: =I25-I42 -> 1.2843137 | L43: =L25-L42 -> 3.9345455 | O43: =O25-O42 -> 3.5806897 | R43: =R25-R42 -> 0.88064516 | U43: =U25-U42 -> -3.0983333 | X43: =X25-X42 -> 3.5466667 | AA43: =AA25-AA42 -> -2.15 | AD43: =AD25-AD42 -> 1.2152632 | AG43: =AG25-AG42 -> 4.5178378 | AJ43: =AJ25-AJ42 -> 15.12 | AM43: =AM25-AM42 -> 3.2988677 | AN43: =AN25-AN42 -> 1141390
A44: Monofil Fabric Sales | B44: =B11-(B10) -> 93720.87 | C44: =D44/B44 -> 256.38301 | D44: =D11-(D10+D35) -> 24028438 | E44: =E11-(E10) -> 126435.75 | F44: =G44/E44 -> 264.80791 | G44: =G11-(G10+G35) -> 33481187 | H44: =H11-(H10) -> 114182.94 | I44: =J44/H44 -> 275.99154 | J44: =J11-(J10+J35) -> 31513526 | K44: =K11-(K10) -> 104994.8 | L44: =M44/K44 -> 271.55622 | M44: =M11-(M10+M35) -> 28511992 | N44: =N11-(N10) -> 102861.49 | O44: =P44/N44 -> 266.75612 | P44: =P11-(P10+P35) -> 27438932 | Q44: =Q11-(Q10) -> 88263.76 | R44: =S44/Q44 -> 266.86642 | S44: =S11-(S10+S35) -> 23554634 | T44: =T11-(T10) -> 87345.65 | U44: =V44/T44 -> 261.94177 | V44: =V11-(V10+V35) -> 22879474 | W44: =W11-(W10) -> 119323.21 | X44: =Y44/W44 -> 254.28115 | Y44: =Y11-(Y10+Y35) -> 30341644 | Z44: =Z11-(Z10) -> 76909.79 | AA44: =AB44/Z44 -> 256.89932 | AB44: =AB11-(AB10+AB35) -> 19758072 | AC44: =AC11-(AC10) -> 110305.5 | AD44: =AE44/AC44 -> 260.75208 | AE44: =AE11-(AE10+AE35) -> 28762389 | AF44: =ROUND((AF11-(AF10)),0) -> 118823 | AG44: =AH44/AF44 -> 264.26417 | AH44: =AH11-(AH10+AH35) -> 31400661 | AI44: =(AI11-(AI10)) -> 148244.76 | AJ44: =AK44/AI44 -> 269.95061 | AK44: =ROUND((AK11-(AK10+AK35)),0) -> 40018764 | AL44: =AL11-(AL10) -> 1291411.4 | AM44: =AN44/AL44 -> 264.58626 | AN44: =ROUND((AN11-(AN10+AN35)),0) -> 341689712 | AO44: YTD | AP44: =AN42-AN44 -> -301500302 | AQ44: MB CP Income
A45: Sales From Purchase | B45: =Purchase!$I22 -> 23693 | C45: =IF(B45=0,0,D45/B45) -> 256.38302 | D45: =ROUND((B45*C44),0) -> 6074483 | E45: =Purchase!$I23 -> 20429 | F45: =IF(E45=0,0,G45/E45) -> 264.80792 | G45: =ROUND((E45*F44),0) -> 5409761 | H45: =Purchase!$I24 -> 24698 | I45: =IF(H45=0,0,J45/H45) -> 275.99154 | J45: =ROUND((H45*I44),0) -> 6816439 | K45: =Purchase!$I25 -> 20991 | L45: =IF(K45=0,0,M45/K45) -> 271.55624 | M45: =ROUND((K45*L44),0) -> 5700237 | N45: =Purchase!$I26 -> 25077 | O45: =IF(N45=0,0,P45/N45) -> 266.75611 | P45: =ROUND((N45*O44),0) -> 6689443 | Q45: =Purchase!$I27 -> 23552 | R45: =IF(Q45=0,0,S45/Q45) -> 266.86642 | S45: =ROUND((Q45*R44),0) -> 6285238 | T45: =Purchase!$I28 -> 26146 | U45: =IF(T45=0,0,V45/T45) -> 261.94175 | V45: =ROUND((T45*U44),0) -> 6848729 | W45: =Purchase!$I29 -> 21566 | X45: =IF(W45=0,0,Y45/W45) -> 254.28114 | Y45: =ROUND((W45*X44),0) -> 5483827 | Z45: =ROUND((Purchase!$I30),0) -> 25953 | AA45: =IF(Z45=0,0,AB45/Z45) -> 256.89932 | AB45: =ROUND((Z45*AA44),0) -> 6667308 | AC45: =ROUND((Purchase!$I31),0) -> 26468 | AD45: =IF(AC45=0,0,AE45/AC45) -> 260.75208 | AE45: =ROUND((AC45*AD44),0) -> 6901586 | AF45: =ROUND((Purchase!$I32),0) -> 15612 | AG45: =IF(AF45=0,0,AH45/AF45) -> 264.26416 | AH45: =ROUND((AF45*AG44),0) -> 4125692 | AI45: =ROUND((Purchase!$I33),0) -> 28225 | AJ45: =IF(AI45=0,0,AK45/AI45) -> 269.95061 | AK45: =ROUND((AI45*AJ44),0) -> 7619356 | AL45: =ROUND((Purchase!$I34),0) -> 282409 | AM45: =IF(AL45=0,0,AN45/AL45) -> 264.58626 | AN45: =ROUND((AL45*AM44),0) -> 74721542
A46: Sales from Production | B46: =B44-B45 -> 70027.87 | C46: =IF(B46=0,0,D46/B46) -> 256.383 | D46: =D44-D45 -> 17953956 | E46: =E44-E45 -> 106006.75 | F46: =IF(E46=0,0,G46/E46) -> 264.80791 | G46: =G44-G45 -> 28071426 | H46: =H44-H45 -> 89484.94 | I46: =IF(H46=0,0,J46/H46) -> 275.99154 | J46: =J44-J45 -> 24697086 | K46: =K44-K45 -> 84003.8 | L46: =IF(K46=0,0,M46/K46) -> 271.55622 | M46: =M44-M45 -> 22811754 | N46: =N44-N45 -> 77784.49 | O46: =IF(N46=0,0,P46/N46) -> 266.75612 | P46: =P44-P45 -> 20749488 | Q46: =Q44-Q45 -> 64711.76 | R46: =IF(Q46=0,0,S46/Q46) -> 266.86642 | S46: =S44-S45 -> 17269396 | T46: =T44-T45 -> 61199.65 | U46: =IF(T46=0,0,V46/T46) -> 261.94177 | V46: =V44-V45 -> 16030745 | W46: =W44-W45 -> 97757.21 | X46: =IF(W46=0,0,Y46/W46) -> 254.28116 | Y46: =Y44-Y45 -> 24857816 | Z46: =Z44-Z45 -> 50956.79 | AA46: =IF(Z46=0,0,AB46/Z46) -> 256.89932 | AB46: =AB44-AB45 -> 13090764 | AC46: =AC44-AC45 -> 83837.5 | AD46: =IF(AC46=0,0,AE46/AC46) -> 260.75209 | AE46: =AE44-AE45 -> 21860803 | AF46: =AF44-AF45 -> 103211 | AG46: =IF(AF46=0,0,AH46/AF46) -> 264.26417 | AH46: =AH44-AH45 -> 27274969 | AI46: =AI44-AI45 -> 120019.76 | AJ46: =IF(AI46=0,0,AK46/AI46) -> 269.95061 | AK46: =AK44-AK45 -> 32399408 | AL46: =AL44-AL45 -> 1009002.4 | AM46: =IF(AL46=0,0,AN46/AL46) -> 264.58626 | AN46: =AN44-AN45 -> 266968170
A47: Trading Sales

Sheet Stock Valuation (FIFO)
B2: Opening Stock 01 Apr 25 | E2: 45748 | H2: 45778 | K2: 45809 | N2: 45839 | Q2: 45870 | T2: 45901 | W2: 45931 | Z2: 45962 | AC2: 45992 | AF2: 46023 | AI2: 46054 | AL2: 46082 | AO2: Bank Stock Statement Dec'25
A3: RAW MATERIALS: | B3: QTY IN KGS. | C3: BASIC RATE | D3: BASIC VALUE | E3: QTY IN KGS. | F3: BASIC RATE | G3: BASIC VALUE | H3: QTY IN KGS. | I3: BASIC RATE | J3: BASIC VALUE | K3: QTY IN KGS. | L3: BASIC RATE | M3: BASIC VALUE | N3: QTY IN KGS. | O3: BASIC RATE | P3: BASIC VALUE | Q3: QTY IN KGS. | R3: BASIC RATE | S3: BASIC VALUE | T3: QTY IN KGS. | U3: BASIC RATE | V3: BASIC VALUE | W3: QTY IN KGS. | X3: BASIC RATE | Y3: BASIC VALUE | Z3: QTY IN KGS. | AA3: BASIC RATE | AB3: BASIC VALUE | AC3: QTY IN KGS. | AD3: BASIC RATE | AE3: BASIC VALUE | AF3: QTY IN KGS. | AG3: BASIC RATE | AH3: BASIC VALUE | AI3: QTY IN KGS. | AJ3: BASIC RATE | AK3: BASIC VALUE | AL3: QTY IN KGS. | AM3: BASIC RATE | AN3: BASIC VALUE | AO3: QTY IN KGS. | AP3: BASIC RATE | AQ3: BASIC VALUE | AR3: QTY IN KGS. | AS3: BASIC RATE | AT3: BASIC VALUE | AU3: QTY IN KGS. | AV3: BASIC RATE | AW3: BASIC VALUE
AX4: Incr/(Decr)Stk | BA4: Stk frm Tarka as om 01 Apr(Srp) | BE4: Physical
A5: HDPE Granules | B5: 195845 | C5: =D5/B5 -> 100.68931 | D5: 19719497 | E5: 180315 | F5: =ROUND(IF(G5=0,0,(G5/E5)),0) -> 100 | G5: 17959508 | H5: 147410 | I5: =IF(J5=0,0,(J5/H5)) -> 97.488915 | J5: 14370841 | K5: 164125 | L5: =IF(M5=0,0,(M5/K5)) -> 97.338395 | M5: 15975664 | N5: 146140 | O5: =IF(P5=0,0,(P5/N5)) -> 99.437929 | P5: 14531859 | Q5: 187620 | R5: =IF(S5=0,0,(S5/Q5)) -> 101.20382 | S5: 18987861 | T5: 114680 | U5: =IF(V5=0,0,(V5/T5)) -> 100.40339 | V5: 11514261 | W5: 139725 | X5: =IF(Y5=0,0,(Y5/W5)) -> 98.732253 | Y5: 13795364 | Z5: 164310 | AA5: =IF(AB5=0,0,(AB5/Z5)) -> 97.311454 | AB5: 15989245 | AC5: 135475 | AD5: =IF(AE5=0,0,(AE5/AC5)) -> 96.066846 | AE5: 13014656 | AF5: 174670 | AG5: =IF(AH5=0,0,(AH5/AF5)) -> 98.956106 | AH5: 17284663 | AI5: 154290 | AJ5: =IF(AK5=0,0,(AK5/AI5)) -> 103.4773 | AK5: 15965513 | AL5: 141140 | AM5: =IF(AN5=0,0,(AN5/AL5)) -> 121.97507 | AN5: 17215561 | AO5: 141140 | AP5: =IF(AQ5=0,0,(AQ5/AO5)) -> 121.97507 | AQ5: 17215561 | AR5: =' Qty Analysis'!BE15 -> 0 | AT5: =ROUND((AS5*AR5),0) -> 0 | AU5: =' Qty Analysis'!BH15 -> 0 | AW5: =ROUND((AV5*AU5),0) -> 0 | AX5: =Z5-B5 -> -31535 | AY5: =AX5/B5 -> -0.16102019 | BA5: =125000+40000 -> 165000 | BB5: 101 | BC5: =ROUND((BA5*BB5),0) -> 16665000 | BE5: 163575
A6: Master Batches | B6: 1664 | C6: =D6/B6 -> 223.625 | D6: 372112 | E6: 2120 | F6: =ROUND(IF(G6=0,0,(G6/E6)),0) -> 227 | G6: 481968 | H6: 2294 | I6: =IF(J6=0,0,(J6/H6)) -> 249.52964 | J6: 572421 | K6: 2613 | L6: =IF(M6=0,0,(M6/K6)) -> 236.99732 | M6: 619274 | N6: 2769 | O6: =IF(P6=0,0,(P6/N6)) -> 264.36114 | P6: 732016 | Q6: 3082 | R6: =IF(S6=0,0,(S6/Q6)) -> 263.87897 | S6: 813275 | T6: 2819 | U6: =IF(V6=0,0,(V6/T6)) -> 256.02838 | V6: 721744 | W6: 2895 | X6: =IF(Y6=0,0,(Y6/W6)) -> 236.59896 | Y6: 684954 | Z6: 2396 | AA6: =IF(AB6=0,0,(AB6/Z6)) -> 227.95659 | AB6: 546184 | AC6: 2395 | AD6: =IF(AE6=0,0,(AE6/AC6)) -> 237.1666 | AE6: 568014 | AF6: 2511 | AG6: =IF(AH6=0,0,(AH6/AF6)) -> 241.37634 | AH6: 606096 | AI6: 3260 | AJ6: =IF(AK6=0,0,(AK6/AI6)) -> 233.5911 | AK6: 761507 | AL6: 2330 | AM6: =IF(AN6=0,0,(AN6/AL6)) -> 226.92532 | AN6: 528736 | AO6: 2330 | AP6: =IF(AQ6=0,0,(AQ6/AO6)) -> 226.92532 | AQ6: 528736 | AR6: =' Qty Analysis'!BE27 -> 0 | AT6: =ROUND((AS6*AR6),0) -> 0 | AU6: =' Qty Analysis'!BH27 -> 0 | AW6: =ROUND((AV6*AU6),0) -> 0 | AX6: =Z6-B6 -> 732 | AY6: =AX6/B6 -> 0.43990385 | BA6: 2730 | BB6: 215 | BC6: =ROUND((BA6*BB6),0) -> 586950 | BE6: 2645
A7: Colour Pigments | B7: 32 | C7: =D7/B7 -> 996.90625 | D7: 31901 | E7: 28 | F7: =ROUND(IF(G7=0,0,(G7/E7)),0) -> 1529 | G7: 42808 | H7: 37 | I7: =IF(J7=0,0,(J7/H7)) -> 1769.8919 | J7: 65486 | K7: 40 | L7: =IF(M7=0,0,(M7/K7)) -> 1466.775 | M7: 58671 | N7: 38 | O7: =IF(P7=0,0,(P7/N7)) -> 1621.3158 | P7: 61610 | Q7: 26 | R7: =IF(S7=0,0,(S7/Q7)) -> 1642.8846 | S7: 42715 | T7: 16 | U7: =IF(V7=0,0,(V7/T7)) -> 1711.25 | V7: 27380 | W7: 41 | X7: =IF(Y7=0,0,(Y7/W7)) -> 1775.9024 | Y7: 72812 | Z7: 46 | AA7: =IF(AB7=0,0,(AB7/Z7)) -> 1659.0435 | AB7: 76316 | AC7: 40 | AD7: =IF(AE7=0,0,(AE7/AC7)) -> 1629.45 | AE7: 65178 | AF7: 40 | AG7: =IF(AH7=0,0,(AH7/AF7)) -> 1629.45 | AH7: 65178 | AI7: 38 | AJ7: =IF(AK7=0,0,(AK7/AI7)) -> 1606.7368 | AK7: 61056 | AL7: 19 | AM7: =IF(AN7=0,0,(AN7/AL7)) -> 1597.3684 | AN7: 30350 | AO7: 19 | AP7: =IF(AQ7=0,0,(AQ7/AO7)) -> 1597.3684 | AQ7: 30350 | AR7: =' Qty Analysis'!BE39 -> 0 | AT7: =ROUND((AS7*AR7),0) -> 0 | AU7: =' Qty Analysis'!BH39 -> 0 | AW7: =ROUND((AV7*AU7),0) -> 0 | AX7: =Z7-B7 -> 14 | AY7: =AX7/B7 -> 0.4375 | BA7: 30 | BB7: 2280 | BC7: =ROUND((BA7*BB7),0) -> 68400 | BE7: 45.3
A8: Total | B8: =SUM(B5:B7) -> 197541 | C8: =D8/B8 -> 101.87004 | D8: =SUM(D5:D7) -> 20123510 | E8: =SUM(E5:E7) -> 182463 | F8: =IF(G8=0,0,(G8/E8)) -> 101.30429 | G8: =SUM(G5:G7) -> 18484284 | H8: =SUM(H5:H7) -> 149741 | I8: =IF(J8=0,0,(J8/H8)) -> 100.23139 | J8: =SUM(J5:J7) -> 15008748 | K8: =SUM(K5:K7) -> 166778 | L8: =IF(M8=0,0,(M8/K8)) -> 99.854951 | M8: =SUM(M5:M7) -> 16653609 | N8: =SUM(N5:N7) -> 148947 | O8: =IF(P8=0,0,(P8/N8)) -> 102.8922 | P8: =SUM(P5:P7) -> 15325485 | Q8: =SUM(Q5:Q7) -> 190728 | R8: =IF(S8=0,0,(S8/Q8)) -> 104.04267 | S8: =ROUND(SUM(S5:S7),0) -> 19843851 | T8: =SUM(T5:T7) -> 117515 | U8: =IF(V8=0,0,(V8/T8)) -> 104.35591 | V8: =SUM(V5:V7) -> 12263385 | W8: =SUM(W5:W7) -> 142661 | X8: =IF(Y8=0,0,(Y8/W8)) -> 102.01197 | Y8: =SUM(Y5:Y7) -> 14553130 | Z8: =SUM(Z5:Z7) -> 166752 | AA8: =IF(AB8=0,0,(AB8/Z8)) -> 99.619465 | AB8: =SUM(AB5:AB7) -> 16611745 | AC8: =SUM(AC5:AC7) -> 137910 | AD8: =IF(AE8=0,0,(AE8/AC8)) -> 98.96199 | AE8: =SUM(AE5:AE7) -> 13647848 | AF8: =SUM(AF5:AF7) -> 177221 | AG8: =IF(AH8=0,0,(AH8/AF8)) -> 101.31947 | AH8: =SUM(AH5:AH7) -> 17955937 | AI8: =SUM(AI5:AI7) -> 157588 | AJ8: =IF(AK8=0,0,(AK8/AI8)) -> 106.53144 | AK8: =SUM(AK5:AK7) -> 16788076 | AL8: =SUM(AL5:AL7) -> 143489 | AM8: =IF(AN8=0,0,(AN8/AL8)) -> 123.87463 | AN8: =SUM(AN5:AN7) -> 17774647 | AO8: =SUM(AO5:AO7) -> 143489 | AP8: =IF(AQ8=0,0,(AQ8/AO8)) -> 123.87463 | AQ8: =SUM(AQ5:AQ7) -> 17774647 | AR8: =SUM(AR5:AR7) -> 0 | AT8: =SUM(AT5:AT7) -> 0 | AU8: =SUM(AU5:AU7) -> 0 | AW8: =SUM(AW5:AW7) -> 0 | AX8: =Z8-B8 -> -30789 | AY8: =AX8/B8 -> -0.15586131 | BA8: =SUM(BA5:BA7) -> 167760 | BB8: =BC8/BA8 -> 103.24481 | BC8: =SUM(BC5:BC7) -> 17320350 | BE8: =SUM(BE5:BE7) -> 166265.3
A9: Work in Progress
A10: HDPE Tape - Factory | B10: 49725 | C10: 154 | D10: =B10*C10 -> 7657650 | E10: 56270 | F10: 153 | G10: =ROUND(E10*F10,0) -> 8609310 | H10: 46564 | I10: 153 | J10: =ROUND(H10*I10,0) -> 7124292 | K10: 52761 | L10: 153 | M10: =ROUND(K10*L10,0) -> 8072433 | N10: 48737 | O10: 147 | P10: =ROUND(N10*O10,0) -> 7164339 | Q10: 49390 | R10: 149 | S10: =ROUND(Q10*R10,0) -> 7359110 | T10: =56274 -> 56274 | U10: 150 | V10: =ROUND(T10*U10,0) -> 8441100 | W10: 60796 | X10: 149 | Y10: =ROUND((W10*X10),0) -> 9058604 | Z10: 57318 | AA10: 147 | AB10: =ROUND((Z10*AA10),0) -> 8425746 | AC10: 54866 | AD10: =IF(AE10=0,0,(AE10/AC10)) -> 146 | AE10: 8010436 | AF10: 47774 | AG10: =IF(AH10=0,0,(AH10/AF10)) -> 147 | AH10: 7022778 | AI10: 51822 | AJ10: 151 | AK10: 7825122 | AL10: 37996 | AM10: 167 | AN10: 6345333 | AO10: 37996 | AP10: =IF(AQ10=0,0,(AQ10/AO10)) -> 167 | AQ10: 6345332 | AR10: =' Qty Analysis'!BE66 -> 0 | AT10: =ROUND((AS10*AR10),0) -> 0 | AU10: =' Qty Analysis'!BH66 -> 0 | AW10: =ROUND((AV10*AU10),0) -> 0 | AX10: =Z10-B10 -> 7593 | AY10: =AX10/B10 -> 0.15269985 | BA10: 24480 | BB10: 163 | BC10: =ROUND((BA10*BB10),0) -> 3990240 | BE10: 24112
A11: HDPE Tape - Job Work | B11: 76468 | C11: 154 | D11: =B11*C11 -> 11776072 | E11: 63906 | F11: =F10 -> 153 | G11: =ROUND(E11*F11,0) -> 9777618 | H11: 61851 | I11: =I10 -> 153 | J11: =ROUND(H11*I11,0) -> 9463203 | K11: 66528 | L11: =L10 -> 153 | M11: =ROUND(K11*L11,0) -> 10178784 | N11: 73740 | O11: 147 | P11: =ROUND(N11*O11,0) -> 10839780 | Q11: 77585 | R11: =R10 -> 149 | S11: =ROUND(Q11*R11,0) -> 11560165 | T11: 79080 | U11: =U10 -> 150 | V11: =ROUND(T11*U11,0) -> 11862000 | W11: 80193 | X11: 149 | Y11: =ROUND((W11*X11),0)-1 -> 11948756 | Z11: 85004 | AA11: =AA10 -> 147 | AB11: =ROUND((Z11*AA11),0) -> 12495588 | AC11: 91727 | AD11: =IF(AE11=0,0,(AE11/AC11)) -> 146 | AE11: 13392142 | AF11: 91742 | AG11: =IF(AH11=0,0,(AH11/AF11)) -> 147 | AH11: 13486074 | AI11: 86544 | AJ11: =AJ10 -> 151 | AK11: 13068144 | AL11: 64171 | AM11: 167 | AN11: 10716557 | AO11: 64171 | AP11: =IF(AQ11=0,0,(AQ11/AO11)) -> 167 | AQ11: 10716557 | AR11: =' Qty Analysis'!BE81 -> 0 | AT11: =ROUND((AS11*AR11),0) -> 0 | AU11: =' Qty Analysis'!BH81 -> 0 | AW11: =ROUND((AV11*AU11),0) -> 0 | AX11: =Z11-B11 -> 8536 | AY11: =AX11/B11 -> 0.11162839 | BA11: 66292 | BB11: 163 | BC11: =ROUND((BA11*BB11),0) -> 10805596 | BE11: 66292
A12: Total | B12: =SUM(B10:B11) -> 126193 | C12: =D12/B12 -> 154 | D12: =SUM(D10:D11) -> 19433722 | E12: =SUM(E10:E11) -> 120176 | F12: =G12/E12 -> 153 | G12: =SUM(G10:G11) -> 18386928 | H12: =SUM(H10:H11) -> 108415 | J12: =SUM(J10:J11) -> 16587495 | K12: =SUM(K10:K11) -> 119289 | M12: =SUM(M10:M11) -> 18251217 | N12: =SUM(N10:N11) -> 122477 | P12: =SUM(P10:P11) -> 18004119 | Q12: =SUM(Q10:Q11) -> 126975 | S12: =SUM(S10:S11) -> 18919275 | T12: =SUM(T10:T11) -> 135354 | V12: =SUM(V10:V11) -> 20303100 | W12: =SUM(W10:W11) -> 140989 | X12: =IF(Y12=0,0,(Y12/W12)) -> 148.99999 | Y12: =SUM(Y10:Y11) -> 21007360 | Z12: =SUM(Z10:Z11) -> 142322 | AB12: =SUM(AB10:AB11) -> 20921334 | AC12: =SUM(AC10:AC11) -> 146593 | AD12: =IF(AE12=0,0,(AE12/AC12)) -> 146 | AE12: =SUM(AE10:AE11) -> 21402578 | AF12: =SUM(AF10:AF11) -> 139516 | AH12: =SUM(AH10:AH11) -> 20508852 | AI12: =SUM(AI10:AI11) -> 138366 | AK12: =SUM(AK10:AK11) -> 20893266 | AL12: =SUM(AL10:AL11) -> 102167 | AN12: =SUM(AN10:AN11) -> 17061890 | AO12: =SUM(AO10:AO11) -> 102167 | AP12: =IF(AQ12=0,0,(AQ12/AO12)) -> 167 | AQ12: =SUM(AQ10:AQ11) -> 17061889 | AR12: =SUM(AR10:AR11) -> 0 | AT12: =SUM(AT10:AT11) -> 0 | AU12: =SUM(AU10:AU11) -> 0 | AW12: =SUM(AW10:AW11) -> 0 | AX12: =Z12-B12 -> 16129 | AY12: =AX12/B12 -> 0.12781216 | BA12: =SUM(BA10:BA11) -> 90772 | BB12: =BC12/BA12 -> 163 | BC12: =SUM(BC10:BC11) -> 14795836 | BE12: =SUM(BE10:BE11) -> 90404
A13: FINISHED GOODS:
A14: HDPE Fishnet Fabrics | B14: 206027 | C14: 220 | D14: =B14*C14 -> 45325940 | E14: 224045 | F14: 219 | G14: =ROUND(E14*F14,0)+14027 -> 49079882 | H14: =ROUND((' Qty Analysis'!E92),0) -> 168371 | I14: 219 | J14: =ROUND(H14*I14,0)+7262 -> 36880511 | K14: =ROUND((' Qty Analysis'!H92),0) -> 140447 | L14: 219 | M14: =ROUND(K14*L14,0) -> 30757893 | N14: =ROUND((' Qty Analysis'!K92),0) -> 130199 | O14: 218 | P14: =ROUND(N14*O14,0) -> 28383382 | Q14: 202593 | R14: 220 | S14: =ROUND(Q14*R14,0) -> 44570460 | T14: 228722 | U14: 221 | V14: =ROUND(T14*U14,0) -> 50547562 | W14: 237947 | X14: =IF(Y14=0,0,(Y14/W14)) -> 219 | Y14: 52110393 | Z14: 218951 | AA14: =IF(AB14=0,0,(AB14/Z14)) -> 217 | AB14: 47512367 | AC14: 255947 | AD14: =IF(AE14=0,0,(AE14/AC14)) -> 216 | AE14: 55284552 | AF14: 261816 | AG14: =IF(AH14=0,0,(AH14/AF14)) -> 217 | AH14: 56814072 | AI14: 239651 | AJ14: 222 | AK14: 53202522 | AL14: 200810 | AM14: =IF(AN14=0,0,(AN14/AL14)) -> 238 | AN14: 47792780 | AO14: 201852 | AP14: =IF(AQ14=0,0,(AQ14/AO14)) -> 237.91615 | AQ14: 48023850 | AR14: =' Qty Analysis'!BE101 -> 0 | AT14: =ROUND((AS14*AR14),0) -> 0 | AU14: =' Qty Analysis'!BH101 -> 0 | AW14: =ROUND((AV14*AU14),0) -> 0 | AX14: =Z14-B14 -> 12924 | AY14: =AX14/B14 -> 0.062729642 | BA14: 289350 | BB14: 228 | BC14: =ROUND((BA14*BB14),0) -> 65971800
A15: Monofilament Shade Net -MSN | B15: 387 | C15: =IF(B15=0,0,(D15/B15)) -> 213.38501 | D15: 82580 | E15: 387 | F15: =IF(E15=0,0,(G15/E15)) -> 213.38501 | G15: 82580 | H15: 387 | I15: =IF(H15=0,0,(J15/H15)) -> 215 | J15: 83205 | K15: 387 | L15: =IF(K15=0,0,(M15/K15)) -> 215 | M15: 83205 | N15: 387 | O15: =IF(N15=0,0,(P15/N15)) -> 215 | P15: 83205 | Q15: 387 | R15: =S15/Q15 -> 215 | S15: 83205 | T15: 387 | U15: =V15/T15 -> 215 | V15: 83205 | W15: 387 | X15: =IF(Y15=0,0,(Y15/W15)) -> 220 | Y15: 85140 | Z15: 387 | AA15: =IF(AB15=0,0,(AB15/Z15)) -> 220 | AB15: 85140 | AC15: 387 | AD15: =IF(AE15=0,0,(AE15/AC15)) -> 220 | AE15: 85140 | AF15: 387 | AG15: =IF(AH15=0,0,(AH15/AF15)) -> 210 | AH15: 81270 | AI15: 387 | AJ15: 210 | AK15: 81270 | AL15: 387 | AM15: =IF(AN15=0,0,(AN15/AL15)) -> 214.65116 | AN15: 83070 | AP15: =IF(AQ15=0,0,(AQ15/AO15)) -> 0 | AR15: =' Qty Analysis'!BE122 -> 0 | AU15: =' Qty Analysis'!BH122 -> 0 | AX15: =Z15-B15 -> 0 | AY15: =AX15/B15 -> 0 | BA15: 810 | BB15: =BC15/BA15 -> 214.81481 | BC15: 174000
A16: Tape Shade Net-TSN | B16: 244 | C16: =IF(B16=0,0,(D16/B16)) -> 198 | D16: 48312 | E16: 257 | F16: =IF(E16=0,0,(G16/E16)) -> 182.33074 | G16: 46859 | H16: 257 | I16: =IF(H16=0,0,(J16/H16)) -> 203.42412 | J16: 52280 | K16: 257 | L16: =IF(K16=0,0,(M16/K16)) -> 155.74319 | M16: 40026 | N16: 197 | O16: =IF(N16=0,0,(P16/N16)) -> 200.67005 | P16: 39532 | Q16: 197 | R16: =S16/Q16 -> 200.67005 | S16: 39532 | T16: 183 | U16: =V16/T16 -> 200.12568 | V16: 36623 | W16: 183 | X16: =IF(Y16=0,0,(Y16/W16)) -> 199.31694 | Y16: 36475 | Z16: 183 | AA16: =IF(AB16=0,0,(AB16/Z16)) -> 198.10929 | AB16: 36254 | AC16: 179 | AD16: =IF(AE16=0,0,(AE16/AC16))-0.11 -> 198.00173 | AE16: 35462 | AF16: 179 | AG16: =IF(AH16=0,0,(AH16/AF16)) -> 166.37989 | AH16: 29782 | AI16: 178 | AJ16: 178 | AK16: 31686 | AL16: 172 | AM16: =IF(AN16=0,0,(AN16/AL16)) -> 240.73837 | AN16: 41407 | AX16: =Z16-B16 -> -61 | AY16: =AX16/B16 -> -0.25
A17: Weed Mat | B17: 75 | C17: =IF(B17=0,0,(D17/B17)) -> 164.22667 | D17: 12317 | E17: 47 | F17: =IF(E17=0,0,(G17/E17)) -> 157.97872 | G17: 7425 | H17: 36 | I17: =IF(H17=0,0,(J17/H17)) -> 171.47222 | J17: 6173 | K17: 36 | L17: =IF(K17=0,0,(M17/K17)) -> 123.97222 | M17: 4463 | N17: 129 | O17: =IF(N17=0,0,(P17/N17)) -> 171.13178 | P17: 22076 | Q17: 153 | R17: =S17/Q17 -> 171.11111 | S17: 26180 | T17: 450 | U17: =V17/T17 -> 171.03778 | V17: 76967 | W17: 172 | X17: =IF(Y17=0,0,(Y17/W17)) -> 171.09884 | Y17: 29429 | Z17: 804 | AA17: =IF(AB17=0,0,(AB17/Z17)) -> 171.02114 | AB17: 137501 | AC17: 391 | AD17: =IF(AE17=0,0,(AE17/AC17))+0.14 -> 167.99934 | AE17: 65633 | AF17: 196 | AG17: =IF(AH17=0,0,(AH17/AF17)) -> 171.17347 | AH17: 33550 | AI17: 446 | AJ17: 171 | AK17: 76300 | AL17: 446 | AM17: =IF(AN17=0,0,(AN17/AL17)) -> 228.60314 | AN17: 101957 | AX17: =Z17-B17 -> 729 | AY17: =AX17/B17 -> 9.72
A18: PP Fabric & Sacks | C18: =IF(B18=0,0,(D18/B18)) -> 0 | E18: 0 | F18: =IF(E18=0,0,(G18/E18)) -> 0 | G18: 0 | H18: 0 | I18: =IF(H18=0,0,(J18/H18)) -> 0 | J18: 0 | K18: 0 | L18: =IF(K18=0,0,(M18/K18)) -> 0 | M18: 0 | N18: 0 | O18: =IF(N18=0,0,(P18/N18)) -> 0 | P18: 0 | AA18: =IF(AB18=0,0,(AB18/Z18)) -> 0 | AD18: =IF(AE18=0,0,(AE18/AC18)) -> 0 | AG18: =IF(AH18=0,0,(AH18/AF18)) -> 0
A19: Miscellaneous | B19: 0 | C19: =IF(B19=0,0,(D19/B19)) -> 0 | E19: 0 | F19: =IF(E19=0,0,(G19/E19)) -> 0 | G19: 0 | H19: 0 | I19: =IF(H19=0,0,(J19/H19)) -> 0 | J19: 0 | K19: 0 | L19: =IF(K19=0,0,(M19/K19)) -> 0 | M19: 0 | N19: 0 | O19: =IF(N19=0,0,(P19/N19)) -> 0 | P19: 0 | Q19: 17 | R19: =IF(S19=0,0,(S19/Q19)) -> 127 | S19: 2159 | T19: 17 | U19: =IF(V19=0,0,(V19/T19)) -> 174.94118 | V19: 2974 | W19: 23 | X19: =IF(Y19=0,0,(Y19/W19)) -> 129.34783 | Y19: 2975 | Z19: 37 | AA19: =IF(AB19=0,0,(AB19/Z19)) -> 110.37838 | AB19: 4084 | AC19: 37 | AD19: =IF(AE19=0,0,(AE19/AC19))-0.3 -> 124.9973 | AE19: 4636 | AF19: 37 | AG19: =IF(AH19=0,0,(AH19/AF19)) -> 125.2973 | AH19: 4636 | AI19: 37 | AJ19: 127 | AK19: 4636 | AL19: 37 | AM19: =IF(AN19=0,0,(AN19/AL19)) -> 125.27027 | AN19: 4635 | AP19: =IF(AQ19=0,0,(AQ19/AO19)) -> 0
A20: Total | B20: =SUM(B14:B19) -> 206733 | C20: =D20/B20 -> 219.94142 | D20: =SUM(D14:D19) -> 45469149 | E20: =SUM(E14:E19) -> 224736 | F20: =G20/E20 -> 218.99805 | G20: =SUM(G14:G19) -> 49216746 | H20: =SUM(H14:H19) -> 169051 | J20: =SUM(J14:J19) -> 37022169 | K20: =SUM(K14:K19) -> 141127 | M20: =SUM(M14:M19) -> 30885587 | N20: =SUM(N14:N19) -> 130912 | P20: =SUM(P14:P19) -> 28528195 | Q20: =SUM(Q14:Q19) -> 203347 | R20: =S20/Q20 -> 219.9272 | S20: =SUM(S14:S19) -> 44721536 | T20: =SUM(T14:T19) -> 229759 | V20: =SUM(V14:V19) -> 50747331 | W20: =SUM(W14:W19) -> 238712 | Y20: =SUM(Y14:Y19) -> 52264412 | Z20: =SUM(Z14:Z19) -> 220362 | AB20: =SUM(AB14:AB19) -> 47775346 | AC20: =SUM(AC14:AC19) -> 256941 | AE20: =SUM(AE14:AE19) -> 55475423 | AF20: =SUM(AF14:AF19) -> 262615 | AH20: =SUM(AH14:AH19) -> 56963310 | AI20: =SUM(AI14:AI19) -> 240699 | AK20: =SUM(AK14:AK19) -> 53396414 | AL20: =SUM(AL14:AL19) -> 201852 | AN20: =SUM(AN14:AN19) -> 48023849 | AO20: =SUM(AO14:AO19) -> 201852 | AP20: =AQ20/AO20 -> 237.91615 | AQ20: =SUM(AQ14:AQ19) -> 48023850 | AR20: =SUM(AR14:AR19) -> 0 | AT20: =SUM(AT14:AT19) -> 0 | AU20: =SUM(AU14:AU19) -> 0 | AW20: =SUM(AW14:AW19) -> 0 | AX20: =Z20-B20 -> 13629 | AY20: =AX20/B20 -> 0.065925614 | BA20: =SUM(BA14:BA15) -> 290160 | BB20: =BC20/BA20 -> 227.96319 | BC20: =SUM(BC14:BC15) -> 66145800
A21: Trading Total | B21: =SUM(B15:B19) -> 706 | C21: =IF(B21=0,0,(D21/B21)) -> 202.84561 | D21: =SUM(D15:D19) -> 143209 | E21: =SUM(E15:E19) -> 691 | F21: =IF(E21=0,0,(G21/E21)) -> 198.06657 | G21: =SUM(G15:G19) -> 136864 | H21: =SUM(H15:H19) -> 680 | I21: =IF(H21=0,0,(J21/H21)) -> 208.32059 | J21: =SUM(J15:J19) -> 141658 | K21: =SUM(K15:K19) -> 680 | L21: =IF(K21=0,0,(M21/K21)) -> 187.78529 | M21: =SUM(M15:M19) -> 127694 | N21: =SUM(N15:N19) -> 713 | O21: =IF(N21=0,0,(P21/N21)) -> 203.10379 | P21: =SUM(P15:P19) -> 144813 | Q21: =SUM(Q15:Q19) -> 754 | R21: =IF(Q21=0,0,(S21/Q21)) -> 200.36605 | S21: =SUM(S15:S19) -> 151076 | T21: =SUM(T15:T19) -> 1037 | U21: =IF(T21=0,0,(V21/T21)) -> 192.64127 | V21: =SUM(V15:V19) -> 199769 | W21: =SUM(W15:W19) -> 765 | X21: =IF(W21=0,0,(Y21/W21)) -> 201.33203 | Y21: =SUM(Y15:Y19) -> 154019 | Z21: =SUM(Z15:Z19) -> 1411 | AA21: =IF(Z21=0,0,(AB21/Z21)) -> 186.37775 | AB21: =SUM(AB15:AB19) -> 262979 | AC21: =SUM(AC15:AC19) -> 994 | AD21: 167.85934 | AE21: =SUM(AE15:AE19) -> 190871 | AF21: =SUM(AF15:AF19) -> 799 | AG21: =IF(AH21=0,0,(AH21/AF21)) -> 186.78098 | AH21: =SUM(AH15:AH19) -> 149238 | AI21: =SUM(AI15:AI19) -> 1048 | AJ21: 185 | AK21: =SUM(AK15:AK19) -> 193892 | AL21: =SUM(AL15:AL19) -> 1042 | AN21: =SUM(AN15:AN19) -> 231069 | AP21: S Dr | AQ21: 19316148
A22: Packing Materials | AP22: LC & Cr | AQ22: =-13213606-1991206 -> -15204812 | AR22: =' Qty Analysis'!BE44 -> 0 | AU22: =' Qty Analysis'!BH44 -> 0
A23: Seconds | G23: =ROUND((E23*F23),0) -> 0 | J23: =ROUND((H23*I23),0) -> 0 | M23: =ROUND((K23*L23),0) -> 0 | P23: =ROUND((N23*O23),0) -> 0 | S23: =ROUND((Q23*R23),0) -> 0 | V23: =ROUND((T23*U23),0) -> 0 | Y23: =ROUND((W23*X23),0) -> 0 | AB23: =ROUND((Z23*AA23),0) -> 0 | AE23: =ROUND((AC23*AD23),0) -> 0 | AH23: =ROUND((AF23*AG23),0) -> 0 | AK23: =ROUND((AI23*AJ23),0) -> 0 | AN23: =ROUND((AL23*AM23),0) -> 0 | AR23: =' Qty Analysis'!BE132 -> 0 | AU23: =' Qty Analysis'!BH132 -> 0
A24: Total | AQ24: =SUM(AQ21:AQ23) -> 4111336
A25: Grand Total | B25: =B20+B12+B8 -> 530467 | C25: =D25/B25 -> 160.2859 | D25: =D20+D12+D8 -> 85026381 | E25: =E20+E12+E8 -> 527375 | F25: =IF(E25=0,0,G25/E25) -> 163.2386 | G25: =G20+G12+G8 -> 86087958 | H25: =H20+H12+H8 -> 427207 | I25: =IF(H25=0,0,J25/H25) -> 160.62099 | J25: =J20+J12+J8 -> 68618412 | K25: =K20+K12+K8 -> 427194 | L25: =IF(K25=0,0,M25/K25) -> 154.00594 | M25: =M20+M12+M8 -> 65790413 | N25: =N20+N12+N8 -> 402336 | O25: =IF(N25=0,0,P25/N25) -> 153.74662 | P25: =P20+P12+P8 -> 61857799 | Q25: =Q20+Q12+Q8 -> 521050 | R25: =IF(Q25=0,0,S25/Q25) -> 160.2239 | S25: =S20+S12+S8 -> 83484662 | T25: =T20+T12+T8 -> 482628 | U25: =IF(T25=0,0,V25/T25) -> 172.62533 | V25: =V20+V12+V8 -> 83313816 | W25: =W20+W12+W8 -> 522362 | X25: =IF(W25=0,0,Y25/W25) -> 168.13034 | Y25: =Y20+Y12+Y8 -> 87824902 | Z25: =Z20+Z12+Z8 -> 529436 | AA25: =IF(Z25=0,0,AB25/Z25) -> 161.13076 | AB25: =AB20+AB12+AB8 -> 85308425 | AC25: =AC20+AC12+AC8 -> 541444 | AD25: =IF(AC25=0,0,AE25/AC25) -> 167.19337 | AE25: =AE20+AE12+AE8 -> 90525849 | AF25: =AF20+AF12+AF8 -> 579352 | AG25: =IF(AF25=0,0,AH25/AF25) -> 164.71523 | AH25: =AH20+AH12+AH8 -> 95428099 | AI25: =AI20+AI12+AI8 -> 536653 | AJ25: =IF(AI25=0,0,AK25/AI25) -> 169.71443 | AK25: =AK20+AK12+AK8 -> 91077756 | AL25: =AL20+AL12+AL8 -> 447508 | AM25: =IF(AL25=0,0,AN25/AL25) -> 185.15956 | AN25: =AN20+AN12+AN8 -> 82860386 | AO25: =AO20+AO12+AO8 -> 447508 | AP25: =IF(AO25=0,0,AQ25/AO25) -> 151.18294 | AQ25: =(AQ8+AQ20+AQ12)+AQ22 -> 67655574 | AR25: =AR20+AR12+AR8 -> 0 | AT25: =AT20+AT12+AT8 -> 0 | AU25: =AU20+AU12+AU8 -> 0 | AW25: =AW20+AW12+AW8 -> 0 | AX25: =Z25-B25 -> -1031 | AY25: =AX25/B25 -> -0.0019435705 | BA25: =BA20+BA12+BA8 -> 548692 | BB25: =IF(BA25=0,0,BC25/BA25) -> 179.08405 | BC25: =BC20+BC12+BC8 -> 98261986
A26: SFG/FG | B26: =B25-B8 -> 332926 | C26: =D26/B26 -> 194.94684 | D26: =D25-D8 -> 64902871 | E26: =E25-E8 -> 344912 | F26: =IF(E26=0,0,G26/E26) -> 196.00267 | G26: =G25-G8 -> 67603674 | H26: =H25-H8 -> 277466 | I26: =IF(H26=0,0,J26/H26) -> 193.21165 | J26: =J25-J8 -> 53609664 | K26: =K25-K8 -> 260416 | L26: =IF(K26=0,0,M26/K26) -> 188.68581 | M26: =M25-M8 -> 49136804 | N26: =N25-N8 -> 253389 | O26: =IF(N26=0,0,P26/N26) -> 183.63983 | P26: =P25-P8 -> 46532314 | Q26: =Q25-Q8 -> 330322 | R26: =IF(Q26=0,0,S26/Q26) -> 192.66295 | S26: =S25-S8 -> 63640811 | T26: =T25-T8 -> 365113 | U26: =IF(T26=0,0,V26/T26) -> 194.59847 | V26: =V25-V8 -> 71050431 | W26: =W25-W8 -> 379701 | X26: =IF(W26=0,0,Y26/W26) -> 192.97229 | Y26: =Y25-Y8 -> 73271772 | Z26: =Z25-Z8 -> 362684 | AA26: =IF(Z26=0,0,AB26/Z26) -> 189.41194 | AB26: =AB25-AB8 -> 68696680 | AC26: =AC25-AC8 -> 403534 | AD26: =IF(AC26=0,0,AE26/AC26) -> 190.51183 | AE26: =AE25-AE8 -> 76878001 | AF26: =AF25-AF8 -> 402131 | AG26: =IF(AF26=0,0,AH26/AF26) -> 192.65404 | AH26: =AH25-AH8 -> 77472162 | AI26: =AI25-AI8 -> 379065 | AJ26: =IF(AI26=0,0,AK26/AI26) -> 195.98138 | AK26: =AK25-AK8 -> 74289680 | AL26: =AL25-AL8 -> 304019 | AM26: =IF(AL26=0,0,AN26/AL26) -> 214.08445 | AN26: =AN25-AN8 -> 65085739 | AP26: 0.25 | AQ26: =ROUND(((AQ25)*25%),0) -> 16913894 | AR26: =AR25-AR8 -> 0 | AS26: =AT26/AR26 -> #DIV/0! | AT26: =AT25-AT8 -> 0 | AU26: =AU25-AU8 -> 0 | AV26: =AW26/AU26 -> #DIV/0! | AW26: =AW25-AW8 -> 0 | BA26: =BA25-BA8 -> 380932 | BC26: =BC25-BC8 -> 80941636
A27: Diff in SFG/FG | E27: =B26-E26 -> -11986 | G27: =D26-G26 -> -2700803 | H27: =E26-H26 -> 67446 | J27: =G26-J26 -> 13994010 | K27: =H26-K26 -> 17050 | M27: =J26-M26 -> 4472860 | N27: =K26-N26 -> 7027 | O27: =P27/N27 -> 370.64039 | P27: =M26-P26 -> 2604490 | Q27: =N26-Q26 -> -76933 | R27: =S27/Q27 -> 222.38177 | S27: =P26-S26 -> -17108497 | T27: =Q26-T26 -> -34791 | U27: =V27/T27 -> 212.97519 | V27: =S26-V26 -> -7409620 | W27: =T26-W26 -> -14588 | X27: =Y27/W27 -> 152.2718 | Y27: =V26-Y26 -> -2221341 | Z27: =W26-Z26 -> 17017 | AA27: =AB27/Z27 -> 268.8542 | AB27: =Y26-AB26 -> 4575092 | AC27: =Z26-AC26 -> -40850 | AD27: =AE27/AC27 -> 200.27714 | AE27: =AB26-AE26 -> -8181321 | AF27: =AC26-AF26 -> 1403 | AG27: =AH27/AF27 -> -423.49323 | AH27: =AE26-AH26 -> -594161 | AI27: =AF26-AI26 -> 23066 | AJ27: =AK27/AI27 -> 137.97286 | AK27: =AH26-AK26 -> 3182482 | AL27: =AL26-AI26 -> -75046 | AM27: =AN27/AL27 -> -122.64399 | AN27: =AK26-AN26 -> 9203941 | AQ27: =(AQ25)-AQ26+AQ21 -> 70057828 | AR27: =AO26-AR26 -> 0 | AS27: =AT27/AR27 -> #DIV/0! | AT27: =AQ26-AT26 -> 16913894 | AU27: =AR26-AU26 -> 0 | AV27: =AW27/AU27 -> #DIV/0! | AW27: =AT26-AW26 -> 0 | BB27: Month | BC27: =AK26-BC26 -> -6651956
A28: Monofil | E28: =E27-E29 -> -12001 | G28: =G27-G29 -> -2707148 | H28: =H27-H29 -> 67435 | J28: =J27-J29 -> 13998804 | K28: =K27-K29 -> 17050 | M28: =M27-M29 -> 4458896 | N28: =N27-N29 -> 7060 | P28: =P27-P29 -> 2621609 | Q28: =Q27-Q29 -> -76892 | S28: =S27-S29 -> -17102234 | T28: =T27-T29 -> -34508 | V28: =V27-V29 -> -7360927 | W28: =W27-W29 -> -14860 | Y28: =Y27-Y29 -> -2267091 | Z28: =Z27-Z29 -> 17663 | AB28: =AB27-AB29 -> 4684052 | AC28: =AC27-AC29 -> -41267 | AE28: =AE27-AE29 -> -8253429 | AF28: =AF27-AF29 -> 1208 | AH28: =AH27-AH29 -> -635794 | AI28: =AI27-AI29 -> 23315 | AK28: =AK27-AK29 -> 3227136 | AL28: =AL27-AL29 -> -75052 | AN28: =AN27-AN29 -> 9241118 | AQ28: =AQ29-AQ27 -> 12802558
A29: Trading | E29: =SUM(B15:B19)-SUM(E15:E19) -> 15 | G29: =SUM(D15:D19)-SUM(G15:G19) -> 6345 | H29: =SUM(E15:E19)-SUM(H15:H19) -> 11 | J29: =SUM(G15:G19)-SUM(J15:J19) -> -4794 | K29: =SUM(H15:H19)-SUM(K15:K19) -> 0 | M29: =SUM(J15:J19)-SUM(M15:M19) -> 13964 | N29: =SUM(K15:K19)-SUM(N15:N19) -> -33 | P29: =SUM(M15:M19)-SUM(P15:P19) -> -17119 | Q29: =SUM(N15:N19)-SUM(Q15:Q19) -> -41 | S29: =SUM(P15:P19)-SUM(S15:S19) -> -6263 | T29: =SUM(Q15:Q19)-SUM(T15:T19) -> -283 | V29: =SUM(S15:S19)-SUM(V15:V19) -> -48693 | W29: =SUM(T15:T19)-SUM(W15:W19) -> 272 | Y29: =SUM(V15:V19)-SUM(Y15:Y19) -> 45750 | Z29: =SUM(W15:W19)-SUM(Z15:Z19) -> -646 | AB29: =SUM(Y15:Y19)-SUM(AB15:AB19) -> -108960 | AC29: =SUM(Z15:Z19)-SUM(AC15:AC19) -> 417 | AE29: =SUM(AB15:AB19)-SUM(AE15:AE19) -> 72108 | AF29: =SUM(AC15:AC19)-SUM(AF15:AF19) -> 195 | AH29: =SUM(AE15:AE19)-SUM(AH15:AH19) -> 41633 | AI29: =SUM(AF15:AF19)-SUM(AI15:AI19) -> -249 | AK29: =SUM(AH15:AH19)-SUM(AK15:AK19) -> -44654 | AL29: =AI21-AL21 -> 6 | AN29: =AK21-AN21 -> -37177 | AQ29: =AQ8+AQ12+AQ14 -> 82860386
E30: =$B$26-E26 -> -11986 | G30: =$D$26-G26 -> -2700803 | H30: =$B$26-H26 -> 55460 | J30: =$D$26-J26 -> 11293207 | K30: =$B$26-K26 -> 72510 | M30: =$D$26-M26 -> 15766067 | N30: =$B$26-N26 -> 79537 | P30: =$D$26-P26 -> 18370557 | Q30: =$B$26-Q26 -> 2604 | S30: =$D$26-S26 -> 1262060 | T30: =$B$26-T26 -> -32187 | V30: =$D$26-V26 -> -6147560 | W30: =$B$26-W26 -> -46775 | Y30: =$D$26-Y26 -> -8368901 | Z30: =$B$26-Z26 -> -29758 | AB30: =$D$26-AB26 -> -3793809 | AC30: =B26-AC26 -> -70608 | AE30: =D26-AE26 -> -11975130 | AF30: =B26-AF26 -> -69205 | AH30: =D26-AH26 -> -12569291 | AI30: =B26-AI26 -> -46139 | AK30: =D26-AK26 -> -9386809 | AL30: =B26-AL26 -> 28907 | AN30: =D26-AN26 -> -182868 | AO30: =AQ25-M25 -> 1865161 | AR30: =AQ8-AQ30 -> 17774647 | AS30: =AT30/#REF! -> #REF! | AT30: =AH40-AT26 -> 0 | AU30: =AI40-AU26 -> #VALUE! | AV30: =AW30/AU30 -> #VALUE! | AW30: =AK41-AW26 -> 20094482 | BB30: YTD | BC30: =D26-BC26 -> -16038765
A31: Monofil | E31: =E30-E32 -> -12001 | G31: =G30-G32 -> -2707148 | H31: =H30-H32 -> 55434 | J31: =J30-J32 -> 11291656 | K31: =K30-K32 -> 72484 | M31: =M30-M32 -> 15750552 | N31: =N30-N32 -> 79544 | P31: =P30-P32 -> 18372161 | Q31: =Q30-Q32 -> 2652 | S31: =S30-S32 -> 1269927 | T31: =T30-T32 -> -31856 | V31: =V30-V32 -> -6091000 | W31: =W30-W32 -> -46716 | Y31: =Y30-Y32 -> -8358091 | Z31: =Z30-Z32 -> -29053 | AB31: =AB30-AB32 -> -3674039 | AC31: =AC30-AC32 -> -70320 | AE31: =AE30-AE32 -> -11927468 | AF31: =AF30-AF32 -> -69112 | AH31: =AH30-AH32 -> -12563262 | AI31: =AI30-AI32 -> -45797 | AK31: =AK30-AK32 -> -9336126 | AL31: =AL30-AL32 -> 29243 | AN31: =AN30-AN32 -> -95008
A32: Trading | E32: =$B$21-E21 -> 15 | G32: =$D$21-G21 -> 6345 | H32: =$B$21-H21 -> 26 | J32: =$D$21-J21 -> 1551 | K32: =$B$21-K21 -> 26 | M32: =$D$21-M21 -> 15515 | N32: =$B$21-N21 -> -7 | P32: =$D$21-P21 -> -1604 | Q32: =$B$21-Q21 -> -48 | S32: =$D$21-S21 -> -7867 | T32: =$B$21-T21 -> -331 | V32: =$D$21-V21 -> -56560 | W32: =$B$21-W21 -> -59 | Y32: =$D$21-Y21 -> -10810 | Z32: =$B$21-Z21 -> -705 | AB32: =$D$21-AB21 -> -119770 | AC32: =$B$21-AC21 -> -288 | AE32: =$D$21-AE21 -> -47662 | AF32: =$B$21-AF21 -> -93 | AH32: =$D$21-AH21 -> -6029 | AI32: =$B$21-AI21 -> -342 | AK32: =$D$21-AK21 -> -50683 | AL32: =$B$21-AL21 -> -336 | AN32: =$D$21-AN21 -> -87860
A34: SFG RM (FIFO) | F34: 144 | G34: =E12*F34 -> 17305344 | I34: 147 | J34: =H12*I34 -> 15937005 | L34: 144 | M34: =K12*L34 -> 17177616 | O34: 100 | P34: =N12*O34 -> 12247700 | R34: 101 | U34: 103 | V34: =ROUND((V12-(T12*T34)),0) -> 20303100 | X34: 100 | AA34: 101 | AD34: 99 | AG34: 99 | AJ34: 101 | AM34: 101 | AO34: Bank Cl Stk Value | AQ34: =AQ8+AQ12+AQ20 -> 82860386 | AS34: 78.57 | AT34: =AT12-(AR12*AR34) -> 0
A35: FG RM (FIFO) | F35: 212 | G35: =E14*F35 -> 47497540 | I35: 217 | J35: =H14*I35 -> 36536507 | L35: 214 | M35: =K14*L35 -> 30055658 | O35: 99 | P35: =N14*O35 -> 12889701 | R35: 103 | U35: 103 | V35: =ROUND((V14-(T14*T35)),0) -> 50547562 | X35: 101 | AA35: 100 | AD35: 99 | AG35: 99 | AJ35: 100 | AM35: 101 | AQ35: =V25-AQ34 -> 453430 | AS35: 78.25 | AT35: =AT14-(AR14*AR35) -> 0
J36: =SUM(J34:J35) -> 52473512 | M36: =SUM(M34:M35) -> 47233274 | P36: =SUM(P34:P35) -> 25137401 | R36: =S36/(Q12+Q14) -> 0 | V36: =SUM(V34:V35) -> 70850662 | AJ36: =(AK15+AK19)/(AI15+AI19) -> 202.60849 | AT36: =SUM(AT34:AT35) -> 0
A37: YARN | G37: =G25-G38 -> 1582342 | J37: =(J12+J14)-J36 -> 994494 | M37: =(M12+M14)-M36 -> 1775836 | P37: =(P12+P14)-P36 -> 21250100 | AI37: Rm | AJ37: =C8-AJ8 -> -4.6613942 | AK37: =ROUND((AI8*AJ37),0) -> -734580 | AQ37: =AQ25+AE33-AB36 -> 67655574
A38: Costing Report | G38: =G25-G14+G35 -> 84505616 | J38: =J25-J37 -> 67623918 | M38: =M25-M37 -> 64014577 | P38: =P25-P37 -> 40607699 | AI38: SFG | AJ38: =C12-AJ12 -> 154 | AK38: =ROUND((AI12*AJ38),0) -> 21308364 | AQ38: =AQ37-AQ34 -> -15204812
A39: CSV Report | AI39: FG | AJ39: =C14-AJ14 -> -2 | AK39: =ROUND((AI14*AJ39),0) -> -479302
A40: FABRIC | AI40: Trading | AK40: =ROUND(((AI15+AI19)*AJ40),0) -> 0 | AQ40: =AQ38-AB39 -> -15204812
A41: Costing Report | AK41: =SUM(AK37:AK40) -> 20094482
A42: CSV Report
A46: Manufacturing SFG/FG | B46: =B12+B14 -> 332220 | C46: =D46/B46 -> 194.93005 | D46: =D12+D14 -> 64759662 | E46: =E12+E14 -> 344221 | F46: =G46/E46 -> 195.99853 | G46: =G12+G14 -> 67466810 | H46: =H12+H14 -> 276786 | I46: =J46/H46 -> 193.17453 | J46: =J12+J14 -> 53468006 | K46: =K12+K14 -> 259736 | L46: =M46/K46 -> 188.68817 | M46: =M12+M14 -> 49009110 | N46: =N12+N14 -> 252676 | O46: =P46/N46 -> 183.58491 | P46: =P12+P14 -> 46387501 | Q46: =Q12+Q14 -> 329568 | R46: =S46/Q46 -> 192.64533 | S46: =S12+S14 -> 63489735 | T46: =T12+T14 -> 364076 | U46: =V46/T46 -> 194.60404 | V46: =V12+V14 -> 70850662
A47: Trading SFG/FG | B47: =B15+B19 -> 387 | C47: =D47/B47 -> 213.38501 | D47: =D15+D19 -> 82580 | E47: =E15+E19 -> 387 | F47: =G47/E47 -> 213.38501 | G47: =G15+G19 -> 82580 | H47: =H15+H19 -> 387 | I47: =J47/H47 -> 215 | J47: =J15+J19 -> 83205 | K47: =K15+K19 -> 387 | L47: =M47/K47 -> 215 | M47: =M15+M19 -> 83205 | N47: =N15+N19 -> 387 | O47: =P47/N47 -> 215 | P47: =P15+P19 -> 83205 | Q47: =Q15+Q19 -> 404 | R47: =S47/Q47 -> 211.29703 | S47: =S15+S19 -> 85364 | T47: =T15+T19 -> 404 | U47: =V47/T47 -> 213.31436 | V47: =V15+V19 -> 86179
A48: Total | B48: =SUM(B46:B47) -> 332607 | C48: =D48/B48 -> 194.95153 | D48: =SUM(D46:D47) -> 64842242 | E48: =SUM(E46:E47) -> 344608 | F48: =G48/E48 -> 196.01806 | G48: =SUM(G46:G47) -> 67549390 | H48: =SUM(H46:H47) -> 277173 | I48: =J48/H48 -> 193.20501 | J48: =SUM(J46:J47) -> 53551211 | K48: =SUM(K46:K47) -> 260123 | L48: =M48/K48 -> 188.72731 | M48: =SUM(M46:M47) -> 49092315 | N48: =SUM(N46:N47) -> 253063 | O48: =P48/N48 -> 183.63295 | P48: =SUM(P46:P47) -> 46470706 | Q48: =SUM(Q46:Q47) -> 329972 | R48: =S48/Q48 -> 192.66816 | S48: =SUM(S46:S47) -> 63575099 | T48: =SUM(T46:T47) -> 364480 | U48: =V48/T48 -> 194.62478 | V48: =SUM(V46:V47) -> 70936841
A50: Manufacturing SFG/FG | E50: =B46-E46 -> -12001 | G50: =D46-G46 -> -2707148 | H50: =E46-H46 -> 67435 | J50: =G46-J46 -> 13998804 | K50: =H46-K46 -> 17050 | M50: =J46-M46 -> 4458896 | N50: =K46-N46 -> 7060 | P50: =M46-P46 -> 2621609 | Q50: =N46-Q46 -> -76892 | S50: =P46-S46 -> -17102234
A51: Trading SFG/FG | E51: =B47-E47 -> 0 | G51: =D47-G47 -> 0 | H51: =E47-H47 -> 0 | J51: =G47-J47 -> -625 | K51: =H47-K47 -> 0 | M51: =J47-M47 -> 0 | N51: =K47-N47 -> 0 | P51: =M47-P47 -> 0 | Q51: =N47-Q47 -> -17 | S51: =P47-S47 -> -2159
A52: Total | E52: =SUM(E50:E51) -> -12001 | G52: =SUM(G50:G51) -> -2707148 | H52: =SUM(H50:H51) -> 67435 | J52: =SUM(J50:J51) -> 13998179 | K52: =SUM(K50:K51) -> 17050 | M52: =SUM(M50:M51) -> 4458896 | N52: =SUM(N50:N51) -> 7060 | P52: =SUM(P50:P51) -> 2621609 | Q52: =SUM(Q50:Q51) -> -76909 | S52: =SUM(S50:S51) -> -17104393
K54: =B46-K46 -> 72484 | M54: =D46-M46 -> 15750552
K55: =B47-K47 -> 0 | M55: =D47-M47 -> -625
K56: =SUM(K54:K55) -> 72484 | M56: =SUM(M54:M55) -> 15749927

Sheet Purchase
B3: HDPE | E3: MB | H3: CP | K3: TOTAL | N3: Discount
A4: MONTH | B4: Kgs | C4: Value | D4: Rate | E4: Kgs | F4: Value | G4: Rate | H4: Kgs | I4: Value | J4: Rate | K4: Kgs | L4: Value | M4: Rate | O4: HD -Discount | P4: RM -Disc
A5: APRIL | B5: 101000 | C5: 9968910 | D5: =IF(B5=0,0,C5/B5) -> 98.702079 | E5: 1522 | F5: 357457.6 | G5: =IF(E5=0,0,F5/E5) -> 234.86045 | H5: 10 | I5: 15925 | J5: =IF(H5=0,0,I5/H5) -> 1592.5 | K5: =B5+E5+H5 -> 102532 | L5: =C5+F5+I5 -> 10342293 | M5: =IF(K5=0,0,L5/K5) -> 100.86892 | N5: 801916 | O5: =C5-N5 -> 9166994 | P5: =ROUND((O5+F5+I5),0) -> 9540377
A6: MAY | B6: 57000 | C6: 5411506 | D6: =IF(B6=0,0,C6/B6) -> 94.938702 | E6: 1174.4 | F6: 300480.4 | G6: =IF(E6=0,0,F6/E6) -> 255.85865 | H6: 11 | I6: 16300 | J6: =IF(H6=0,0,I6/H6) -> 1481.8182 | K6: =B6+E6+H6 -> 58185.4 | L6: =C6+F6+I6 -> 5728286.4 | M6: =IF(K6=0,0,L6/K6) -> 98.448862 | N6: 217000 | O6: =C6-N6 -> 5194506 | P6: =ROUND((O6+F6+I6),0) -> 5511286
A7: JUNE | B7: 151000 | C7: 14716058 | D7: =IF(B7=0,0,C7/B7) -> 97.457338 | E7: 1663.9 | F7: 391639 | G7: =IF(E7=0,0,F7/E7) -> 235.37412 | H7: 4 | I7: 8740 | J7: =IF(H7=0,0,I7/H7) -> 2185 | K7: =B7+E7+H7 -> 152667.9 | L7: =C7+F7+I7 -> 15116437 | M7: =IF(K7=0,0,L7/K7) -> 99.015163 | N7: 142550 | O7: =C7-N7 -> 14573508 | P7: =ROUND((O7+F7+I7),0) -> 14973887
A8: JULY | B8: 137000 | C8: 13639925 | D8: =IF(B8=0,0,C8/B8) -> 99.561496 | E8: 1650 | F8: 431750 | G8: =IF(E8=0,0,F8/E8) -> 261.66667 | H8: 11 | I8: 15020 | J8: =IF(H8=0,0,I8/H8) -> 1365.4545 | K8: =B8+E8+H8 -> 138661 | L8: =C8+F8+I8 -> 14086695 | M8: =IF(K8=0,0,L8/K8) -> 101.59089 | N8: 1032850 | O8: =C8-N8 -> 12607075 | P8: =ROUND((O8+F8+I8),0) -> 13053845
A9: AUGUST | B9: 174000 | C9: 17622085 | D9: =IF(B9=0,0,C9/B9) -> 101.27635 | E9: 1596.2 | F9: 420275.9 | G9: =IF(E9=0,0,F9/E9) -> 263.29777 | H9: 13 | I9: 23980 | J9: =IF(H9=0,0,I9/H9) -> 1844.6154 | K9: =B9+E9+H9 -> 175609.2 | L9: =C9+F9+I9 -> 18066341 | M9: =IF(K9=0,0,L9/K9) -> 102.8781 | N9: 180000 | O9: =C9-N9 -> 17442085 | P9: =ROUND((O9+F9+I9),0) -> 17886341
A10: SEPT | B10: 37000 | C10: 3697235 | D10: =IF(B10=0,0,C10/B10) -> 99.92527 | E10: 844.1 | F10: 194084 | G10: =IF(E10=0,0,F10/E10) -> 229.9301 | J10: =IF(H10=0,0,I10/H10) -> 0 | K10: =B10+E10+H10 -> 37844.1 | L10: =C10+F10+I10 -> 3891319 | M10: =IF(K10=0,0,L10/K10) -> 102.82498 | N10: 675450 | O10: =C10-N10 -> 3021785 | P10: =ROUND((O10+F10+I10),0) -> 3215869
A11: OCT | B11: 128000 | C11: 12619787 | D11: =IF(B11=0,0,C11/B11) -> 98.592086 | E11: 1196.4 | F11: 270343.2 | G11: =IF(E11=0,0,F11/E11) -> 225.96389 | H11: 33 | I11: 55870 | J11: =IF(H11=0,0,I11/H11) -> 1693.0303 | K11: =B11+E11+H11 -> 129229.4 | L11: =C11+F11+I11 -> 12946000 | M11: =IF(K11=0,0,L11/K11) -> 100.17844 | N11: 270400 | O11: =C11-N11 -> 12349387 | P11: =ROUND((O11+F11+I11),0) -> 12675600
A12: NOV | B12: 120000 | C12: 11611725 | D12: =IF(B12=0,0,C12/B12) -> 96.764375 | E12: 945.2 | F12: 214712.4 | G12: =IF(E12=0,0,F12/E12) -> 227.16081 | H12: 14 | I12: 22830 | J12: =IF(H12=0,0,I12/H12) -> 1630.7143 | K12: =B12+E12+H12 -> 120959.2 | L12: =C12+F12+I12 -> 11849267 | M12: =IF(K12=0,0,L12/K12) -> 97.960861 | N12: 712800 | O12: =C12-N12 -> 10898925 | P12: =ROUND((O12+F12+I12),0) -> 11136467
A13: DEC | B13: 106000 | C13: 10160896 | D13: =IF(B13=0,0,C13/B13) -> 95.857509 | E13: 1571.6 | F13: 376869.2 | G13: =IF(E13=0,0,F13/E13) -> 239.79969 | H13: 2 | I13: 4560 | J13: =IF(H13=0,0,I13/H13) -> 2280 | K13: =B13+E13+H13 -> 107573.6 | L13: =C13+F13+I13 -> 10542325 | M13: =IF(K13=0,0,L13/K13) -> 98.001045 | N13: 603750 | O13: =C13-N13 -> 9557146 | P13: =ROUND((O13+F13+I13),0) -> 9938575
A14: JAN | B14: 169000 | C14: 16731441 | D14: =IF(B14=0,0,C14/B14) -> 99.00261 | E14: 1449 | F14: 338551 | G14: =IF(E14=0,0,F14/E14) -> 233.64458 | J14: =IF(H14=0,0,I14/H14) -> 0 | K14: =B14+E14+H14 -> 170449 | L14: =C14+F14+I14 -> 17069992 | M14: =IF(K14=0,0,L14/K14) -> 100.14721 | N14: 330050 | O14: =C14-N14 -> 16401391 | P14: =ROUND((O14+F14+I14),0) -> 16739942
A15: FEB | B15: 116000 | C15: 12144053 | D15: =IF(B15=0,0,C15/B15) -> 104.69011 | E15: 1870.7 | F15: 435977.8 | G15: =IF(E15=0,0,F15/E15) -> 233.05597 | H15: 4 | I15: 9060 | J15: =IF(H15=0,0,I15/H15) -> 2265 | K15: =B15+E15+H15 -> 117874.7 | L15: =C15+F15+I15 -> 12589091 | M15: =IF(K15=0,0,L15/K15) -> 106.80062 | N15: 614900 | O15: =C15-N15 -> 11529153 | P15: =ROUND((O15+F15+I15),0) -> 11974191
A16: MARCH | B16: 98000 | C16: =12734951.02+3501 -> 12738452 | D16: =IF(B16=0,0,C16/B16) -> 129.9842 | G16: =IF(E16=0,0,F16/E16) -> 0 | J16: =IF(H16=0,0,I16/H16) -> 0 | K16: =B16+E16+H16 -> 98000 | L16: =C16+F16+I16 -> 12738452 | M16: =IF(K16=0,0,L16/K16) -> 129.9842 | N16: 321250 | O16: =C16-N16 -> 12417202 | P16: =ROUND((O16+F16+I16),0) -> 12417202
A17: TOTAL | B17: =SUM(B5:B16) -> 1394000 | C17: =SUM(C5:C16) -> 1.4106207e+08 | D17: =IF(B17=0,0,(C17/B17)) -> 101.1923 | E17: =SUM(E5:E16) -> 15483.5 | F17: =SUM(F5:F16) -> 3732140.5 | G17: =IF(E17=0,0,(F17/E17)) -> 241.03985 | H17: =SUM(H5:H16) -> 102 | I17: =SUM(I5:I16) -> 172285 | J17: =IF(H17=0,0,(I17/H17)) -> 1689.0686 | K17: =SUM(K5:K16) -> 1409585.5 | L17: =SUM(L5:L16) -> 1.449665e+08 | M17: =IF(K17=0,0,(L17/K17)) -> 102.84335 | N17: =SUM(N5:N16) -> 5902916 | O17: =C17-N17 -> 1.3515916e+08 | P17: =SUM(P5:P16) -> 139063582
L18: =L17-N17 -> 1.3906358e+08 | N18: =N17/B17 -> 4.2345165 | R18: =P17-L18 -> -0.53
A20: Misc Monofil Purchases
A21: MONTH | B21: Sravya | E21: Other Purchases | H21: Consumables | I21: Monofil Fabric Purchase | L21: Yarn Purchase | O21: Mono Fabric Pur
A22: APRIL | B22: 6741 | C22: 1404660 | D22: =IF(B22=0,0,C22/B22) -> 208.37561 | E22: =23693-B22 -> 16952 | F22: =5524517-(C22+375) -> 4119482 | G22: =IF(E22=0,0,F22/E22) -> 243.00861 | H22: =28608.07+185674.5 -> 214282.57 | I22: =ROUND((B22+E22),0) -> 23693 | J22: =ROUND((C22+F22+H22),0) -> 5738425 | K22: =IF(I22=0,0,J22/I22) -> 242.19917 | L22: 18891 | M22: 2338463.8 | N22: =IF(L22=0,0,M22/L22) -> 123.78719 | O22: =ROUND((I22+L22),0) -> 42584 | P22: =ROUND((J22+M22),0) -> 8076889 | Q22: ='PAL I'!D8+'PAL I'!D7 -> 8076889
A23: MAY | B23: 3898 | C23: 863540 | D23: =IF(B23=0,0,C23/B23) -> 221.53412 | E23: =20429-B23 -> 16531 | F23: =4823996-C23 -> 3960456 | G23: =IF(E23=0,0,F23/E23) -> 239.57752 | H23: =128594.51+180144 -> 308738.51 | I23: =ROUND((B23+E23),0) -> 20429 | J23: =ROUND((C23+F23+H23),0) -> 5132735 | K23: =IF(I23=0,0,J23/I23) -> 251.24749 | L23: 11834 | M23: 1494262.5 | N23: =IF(L23=0,0,M23/L23) -> 126.26859 | O23: =ROUND((I23+L23),0) -> 32263 | P23: =ROUND((J23+M23),0) -> 6626998 | Q23: ='PAL I'!G7+'PAL I'!G8 -> 6626998
A24: JUNE | B24: 7345 | C24: 1761078 | D24: =IF(B24=0,0,C24/B24) -> 239.76555 | E24: =24698-B24 -> 17353 | F24: =5872515-C24 -> 4111437 | G24: =IF(E24=0,0,F24/E24) -> 236.92946 | H24: =258208.06+172874 -> 431082.06 | I24: =ROUND((B24+E24),0) -> 24698 | J24: =ROUND((C24+F24+H24),0) -> 6303597 | K24: =IF(I24=0,0,J24/I24) -> 255.22702 | L24: 18632 | M24: 2292675 | N24: =IF(L24=0,0,M24/L24) -> 123.0504 | O24: =ROUND((I24+L24),0) -> 43330 | P24: =ROUND((J24+M24),0) -> 8596272 | Q24: ='PAL I'!J7+'PAL I'!J8 -> 8596272
A25: JULY | B25: 4223.5 | C25: 1008061.5 | D25: =IF(B25=0,0,C25/B25) -> 238.67918 | E25: =20990.9-B25 -> 16767.4 | F25: =5145421.3-C25 -> 4137359.8 | G25: =IF(E25=0,0,F25/E25) -> 246.75023 | H25: 611377.53 | I25: =ROUND((B25+E25),0) -> 20991 | J25: =ROUND((C25+F25+H25),0) -> 5756799 | K25: =IF(I25=0,0,J25/I25) -> 274.25082 | L25: 9076 | M25: 1098736.4 | N25: =IF(L25=0,0,M25/L25) -> 121.05954 | O25: =ROUND((I25+L25),0) -> 30067 | P25: =ROUND((J25+M25),0) -> 6855535 | Q25: ='PAL I'!M7+'PAL I'!M8 -> 6855535
A26: AUGUST | B26: 9190 | C26: 2114093.1 | D26: =IF(B26=0,0,C26/B26) -> 230.04277 | E26: =25077.12-B26 -> 15887.12 | F26: =5997189.1-C26 -> 3883096 | G26: =IF(E26=0,0,F26/E26) -> 244.41787 | H26: =75131.09+182958.08 -> 258089.17 | I26: =ROUND((B26+E26),0) -> 25077 | J26: =ROUND((C26+F26+H26),0) -> 6255278 | K26: =IF(I26=0,0,J26/I26) -> 249.44284 | L26: 24209.7 | M26: 2949800.3 | N26: =IF(L26=0,0,M26/L26) -> 121.84374 | O26: =ROUND((I26+L26),0) -> 49287 | P26: =ROUND((J26+M26),0) -> 9205078 | Q26: ='PAL I'!P7+'PAL I'!P8 -> 9205078
A27: SEPT | B27: 8506 | C27: 1883382.8 | D27: =IF(B27=0,0,C27/B27) -> 221.41815 | E27: =23551.9-B27 -> 15045.9 | F27: =5382679.75-C27 -> 3499297 | G27: =IF(E27=0,0,F27/E27) -> 232.57479 | H27: 352825.96 | I27: =ROUND((B27+E27),0) -> 23552 | J27: =ROUND((C27+F27+H27),0) -> 5735506 | K27: =IF(I27=0,0,J27/I27) -> 243.52522 | L27: 34618.4 | M27: 4235333.7 | N27: =IF(L27=0,0,M27/L27) -> 122.34343 | O27: =ROUND((I27+L27),0) -> 58170 | P27: =ROUND((J27+M27),0) -> 9970840 | Q27: ='PAL I'!S7+'PAL I'!S8 -> 9970840
A28: OCT | B28: 10656 | C28: 2328966 | D28: =IF(B28=0,0,C28/B28) -> 218.55912 | E28: =25744.72-B28-56.6+457.4 -> 15489.52 | F28: =5861222.6-C28-6682+109425 -> 3634999.6 | G28: =IF(E28=0,0,F28/E28) -> 234.67477 | H28: 653532.17 | I28: =ROUND((B28+E28),0) -> 26146 | J28: =ROUND((C28+F28+H28),0) -> 6617498 | K28: =IF(I28=0,0,J28/I28) -> 253.09791 | L28: 7140.1 | M28: 785255.8 | N28: =IF(L28=0,0,M28/L28) -> 109.97826 | O28: =ROUND((I28+L28),0) -> 33286 | P28: =ROUND((J28+M28),0) -> 7402754 | Q28: ='PAL I'!V7+'PAL I'!V8 -> 7402754
A29: NOV | B29: 7326.5 | C29: 1589661 | D29: =IF(B29=0,0,C29/B29) -> 216.97413 | E29: =21566.1-B29 -> 14239.6 | F29: =4923369-C29 -> 3333708 | G29: =IF(E29=0,0,F29/E29) -> 234.11528 | H29: 250063.1 | I29: =ROUND((B29+E29),0) -> 21566 | J29: =ROUND((C29+F29+H29),0) -> 5173432 | K29: =IF(I29=0,0,J29/I29) -> 239.88834 | L29: 15516.05 | M29: 1847197.6 | N29: =IF(L29=0,0,M29/L29) -> 119.05076 | O29: =ROUND((I29+L29),0) -> 37082 | P29: =ROUND((J29+M29),0) -> 7020630 | Q29: ='PAL I'!Y7+'PAL I'!Y8 -> 7020630
A30: DEC | B30: 9680.5 | C30: 2127879 | D30: =IF(B30=0,0,C30/B30) -> 219.81086 | E30: 16272.7 | F30: 3818296.2 | G30: =IF(E30=0,0,F30/E30) -> 234.64429 | H30: 245756.22 | I30: =B30+E30 -> 25953.2 | J30: =ROUND((C30+F30+H30),0) -> 6191931 | K30: =IF(I30=0,0,J30/I30) -> 238.58064 | L30: 8732.9 | M30: 960211.9 | N30: =IF(L30=0,0,M30/L30) -> 109.95338 | O30: =ROUND((I30+L30),0) -> 34686 | P30: =ROUND((J30+M30),0) -> 7152143 | Q30: ='PAL I'!AB7+'PAL I'!AB8 -> 7152143
A31: JAN | B31: 10816.5 | C31: 2375910 | D31: =IF(B31=0,0,C31/B31) -> 219.65608 | E31: 15651.2 | F31: 3652413.5 | G31: =IF(E31=0,0,F31/E31) -> 233.36316 | H31: 402780.6 | I31: =B31+E31 -> 26467.7 | J31: =C31+F31+H31 -> 6431104.1 | K31: =IF(I31=0,0,J31/I31) -> 242.97933 | L31: 4709.65 | M31: 570095.8 | N31: =IF(L31=0,0,M31/L31) -> 121.04844 | O31: =ROUND((I31+L31),0) -> 31177 | P31: =ROUND((J31+M31),0) -> 7001200 | Q31: ='PAL I'!AE7+'PAL I'!AE8 -> 7001200
A32: FEB | B32: 5576.5 | C32: 1250109.5 | D32: =IF(B32=0,0,C32/B32) -> 224.17457 | E32: 10035.9 | F32: =2490942 -> 2490942 | G32: =IF(E32=0,0,F32/E32) -> 248.20315 | H32: 346634 | I32: =B32+E32 -> 15612.4 | J32: =ROUND((C32+F32+H32),0) -> 4087686 | K32: =IF(I32=0,0,J32/I32) -> 261.82304 | L32: 5000 | M32: 560000 | N32: =IF(L32=0,0,M32/L32) -> 112 | O32: =ROUND((I32+L32),0) -> 20612 | P32: =ROUND((J32+M32),0) -> 4647686 | Q32: ='PAL I'!AH7+'PAL I'!AH8 -> 4647686
A33: MARCH | B33: 12344 | C33: =2780989.5+26415 -> 2807404.5 | D33: =IF(B33=0,0,C33/B33) -> 227.4307 | E33: 15880.6 | F33: 3861341 | G33: =IF(E33=0,0,F33/E33) -> 243.14831 | H33: 229895.4 | I33: =B33+E33 -> 28224.6 | J33: =ROUND((C33+F33+H33),0) -> 6898641 | K33: =IF(I33=0,0,J33/I33) -> 244.41944 | L33: 2983.8 | M33: 372906 | N33: =IF(L33=0,0,M33/L33) -> 124.97688 | O33: =ROUND((I33+L33),0) -> 31208 | P33: =ROUND((J33+M33),0) -> 7271547 | Q33: ='PAL I'!AK7+'PAL I'!AK8 -> 7271547
A34: TOTAL | B34: =SUM(B22:B33) -> 96303.5 | C34: =SUM(C22:C33) -> 21514745 | D34: =IF(B34=0,0,(C34/B34)) -> 223.40564 | E34: =SUM(E22:E33) -> 186105.94 | F34: =SUM(F22:F33) -> 44502828 | G34: =IF(E34=0,0,(F34/E34)) -> 239.12632 | H34: =SUM(H22:H33) -> 4305057.3 | I34: =B34+E34 -> 282409.44 | J34: =ROUND((C34+F34+H34),0) -> 70322631 | K34: =IF(I34=0,0,J34/I34) -> 249.00949 | L34: =SUM(L22:L33) -> 161343.6 | M34: =SUM(M22:M33) -> 19504939 | N34: =IF(L34=0,0,(M34/L34)) -> 120.89069 | O34: =SUM(O22:O33) -> 443752 | P34: =SUM(P22:P33) -> 89827572 | Q34: =SUM(Q22:Q33) -> 89827572 | R34: =SUM(R22:R33) -> 0
A36: MONTH | B36: TSN | E36: MSN | H36: PPS | K36: TOTAL
A37: APRIL | B37: 900.45 | C37: 162626.5 | D37: =IF(B37=0,0,C37/B37) -> 180.60581 | G37: =IF(E37=0,0,F37/E37) -> 0 | H37: 4797.6 | I37: 702370 | J37: =IF(H37=0,0,I37/H37) -> 146.40028 | K37: =SUM(B37,E37,H37) -> 5698.05 | L37: =SUM(C37,F37,I37) -> 864996.5 | M37: =IF(K37=0,0,L37/K37) -> 151.80571
A38: MAY | B38: 195 | C38: 40083 | D38: =IF(B38=0,0,C38/B38) -> 205.55385 | E38: =1908 -> 1908 | F38: =412345 -> 412345 | G38: =IF(E38=0,0,F38/E38) -> 216.11373 | H38: 5704.65 | I38: 840700 | J38: =IF(H38=0,0,I38/H38) -> 147.371 | K38: =SUM(B38,E38,H38) -> 7807.65 | L38: =SUM(C38,F38,I38) -> 1293128 | M38: =IF(K38=0,0,L38/K38) -> 165.6232
A39: JUNE | B39: 289 | C39: 58267 | D39: =IF(B39=0,0,C39/B39) -> 201.61592 | E39: =580 -> 580 | F39: =124700 -> 124700 | G39: =IF(E39=0,0,F39/E39) -> 215 | H39: =4825.9+0.1 -> 4826 | I39: 725655 | J39: =IF(H39=0,0,I39/H39) -> 150.36366 | K39: =SUM(B39,E39,H39) -> 5695 | L39: =SUM(C39,F39,I39) -> 908622 | M39: =IF(K39=0,0,L39/K39) -> 159.54732
A40: JULY | B40: 168 | C40: 33485 | D40: =IF(B40=0,0,C40/B40) -> 199.31548 | G40: =IF(E40=0,0,F40/E40) -> 0 | H40: 6780.8 | I40: 1013210 | J40: =IF(H40=0,0,I40/H40) -> 149.42337 | K40: =SUM(B40,E40,H40) -> 6948.8 | L40: =SUM(C40,F40,I40) -> 1046695 | M40: =IF(K40=0,0,L40/K40) -> 150.62961
A41: AUGUST | D41: =IF(B41=0,0,C41/B41) -> 0 | E41: =405 -> 405 | F41: =87075 -> 87075 | G41: =IF(E41=0,0,F41/E41) -> 215 | H41: 4998.6 | I41: 747142 | J41: =IF(H41=0,0,I41/H41) -> 149.47025 | K41: =SUM(B41,E41,H41) -> 5403.6 | L41: =SUM(C41,F41,I41) -> 834217 | M41: =IF(K41=0,0,L41/K41) -> 154.38171
A42: SEPT | D42: =IF(B42=0,0,C42/B42) -> 0 | G42: =IF(E42=0,0,F42/E42) -> 0 | H42: 5020.2 | I42: =750225-22480 -> 727745 | J42: =IF(H42=0,0,I42/H42) -> 144.96335 | K42: =SUM(B42,E42,H42) -> 5020.2 | L42: =SUM(C42,F42,I42) -> 727745 | M42: =IF(K42=0,0,L42/K42) -> 144.96335
A43: OCT | B43: 128 | C43: 25344 | D43: =IF(B43=0,0,C43/B43) -> 198 | E43: 653 | F43: 143660 | G43: =IF(E43=0,0,F43/E43) -> 220 | H43: 5785.2 | I43: 861274 | J43: =IF(H43=0,0,I43/H43) -> 148.87541 | K43: =SUM(B43,E43,H43) -> 6566.2 | L43: =SUM(C43,F43,I43) -> 1030278 | M43: =IF(K43=0,0,L43/K43) -> 156.90628
A44: NOV | B44: 117 | C44: 23166 | D44: =IF(B44=0,0,C44/B44) -> 198 | G44: =IF(E44=0,0,F44/E44) -> 0 | H44: 5688.3 | I44: 854400 | J44: =IF(H44=0,0,I44/H44) -> 150.20305 | K44: =SUM(B44,E44,H44) -> 5805.3 | L44: =SUM(C44,F44,I44) -> 877566 | M44: =IF(K44=0,0,L44/K44) -> 151.16635
A45: DEC | B45: 377 | C45: 74646 | D45: =IF(B45=0,0,C45/B45) -> 198 | E45: 220 | F45: 48810 | G45: =IF(E45=0,0,F45/E45) -> 221.86364 | H45: 4737.3 | I45: 709170 | J45: =IF(H45=0,0,I45/H45) -> 149.6992 | K45: =SUM(B45,E45,H45) -> 5334.3 | L45: =SUM(C45,F45,I45) -> 832626 | M45: =IF(K45=0,0,L45/K45) -> 156.08908
A46: JAN | B46: 828 | C46: 139752 | D46: =IF(B46=0,0,C46/B46) -> 168.78261 | E46: 453 | F46: 105630 | G46: =IF(E46=0,0,F46/E46) -> 233.17881 | H46: 2164.2 | I46: 318776 | J46: =IF(H46=0,0,I46/H46) -> 147.29507 | K46: =SUM(B46,E46,H46) -> 3445.2 | L46: =SUM(C46,F46,I46) -> 564158 | M46: =IF(K46=0,0,L46/K46) -> 163.75189
A47: FEB | B47: 54 | C47: 10812 | D47: =IF(B47=0,0,C47/B47) -> 200.22222 | E47: 1263 | F47: 264910 | G47: =IF(E47=0,0,F47/E47) -> 209.74663 | H47: 5103.1 | I47: 807620 | J47: =IF(H47=0,0,I47/H47) -> 158.26067 | K47: =SUM(B47,E47,H47) -> 6420.1 | L47: =SUM(C47,F47,I47) -> 1083342 | M47: =IF(K47=0,0,L47/K47) -> 168.74223
A48: MARCH | B48: 911.5 | C48: 214126.5 | D48: =IF(B48=0,0,C48/B48) -> 234.91662 | E48: 90 | F48: 20700 | G48: =IF(E48=0,0,F48/E48) -> 230 | H48: 2928.6 | I48: 470125 | J48: =IF(H48=0,0,I48/H48) -> 160.52892 | K48: =SUM(B48,E48,H48) -> 3930.1 | L48: =SUM(C48,F48,I48) -> 704951.5 | M48: =IF(K48=0,0,L48/K48) -> 179.37241
A49: TOTAL | B49: =SUM(B37:B48) -> 3967.95 | C49: =SUM(C37:C48) -> 782308 | D49: =IF(B49=0,0,(C49/B49)) -> 197.15672 | E49: =SUM(E37:E48) -> 5572 | F49: =SUM(F37:F48) -> 1207830 | G49: =IF(E49=0,0,(F49/E49)) -> 216.76777 | H49: =SUM(H37:H48) -> 58534.55 | I49: =SUM(I37:I48) -> 8778187 | J49: =IF(H49=0,0,(I49/H49)) -> 149.96591 | K49: =SUM(K37:K48) -> 68074.5 | L49: =SUM(L37:L48) -> 10768325 | M49: =IF(K49=0,0,(L49/K49)) -> 158.18442
K50: =K49+B64 -> 81155.6
A51: MONTH | B51: Weed Mat | E51: Misc | H51: TOTAL | K51: TOTAL TRADING PURCHASES
A52: APRIL | B52: 2030 | C52: 329505 | D52: =IF(B52=0,0,C52/B52) -> 162.31773 | F52: 375 | G52: =IF(E52=0,0,F52/E52) -> 0 | H52: =B52+E52 -> 2030 | I52: =C52+F52 -> 329880 | J52: =IF(H52=0,0,I52/H52) -> 162.50246 | K52: =K37+H52 -> 7728.05 | L52: =ROUNDDOWN((L37+I52),0) -> 1194876 | M52: =IF(K52=0,0,L52/K52) -> 154.61546
A53: MAY | B53: 860 | C53: 144191 | D53: =IF(B53=0,0,C53/B53) -> 167.66395 | G53: =IF(E53=0,0,F53/E53) -> 0 | H53: =B53+E53 -> 860 | I53: =C53+F53 -> 144191 | J53: =IF(H53=0,0,I53/H53) -> 167.66395 | K53: =K38+H53 -> 8667.65 | L53: =L38+I53 -> 1437319 | M53: =IF(K53=0,0,L53/K53) -> 165.82569
A54: JUNE | B54: 1216 | C54: =212310 -> 212310 | D54: =IF(B54=0,0,C54/B54) -> 174.59704 | E54: 50.9 | F54: 25760 | G54: =IF(E54=0,0,F54/E54) -> 506.09037 | H54: =B54+E54 -> 1266.9 | I54: =C54+F54 -> 238070 | J54: =IF(H54=0,0,I54/H54) -> 187.91538 | K54: =K39+H54 -> 6961.9 | L54: =L39+I54 -> 1146692 | M54: =IF(K54=0,0,L54/K54) -> 164.70963
A55: JULY | B55: 1683 | C55: 286425 | D55: =IF(B55=0,0,C55/B55) -> 170.18717 | G55: =IF(E55=0,0,F55/E55) -> 0 | H55: =B55+E55 -> 1683 | I55: =C55+F55 -> 286425 | J55: =IF(H55=0,0,I55/H55) -> 170.18717 | K55: =K40+H55 -> 8631.8 | L55: =L40+I55 -> 1333120 | M55: =IF(K55=0,0,L55/K55) -> 154.44287
A56: AUGUST | B56: 739 | C56: 126369 | D56: =IF(B56=0,0,C56/B56) -> 171 | E56: =15+299 -> 314 | F56: =5775+37973 -> 43748 | G56: =IF(E56=0,0,F56/E56) -> 139.32484 | H56: =B56+E56 -> 1053 | I56: =C56+F56 -> 170117 | J56: =IF(H56=0,0,I56/H56) -> 161.55461 | K56: =K41+H56 -> 6456.6 | L56: =L41+I56 -> 1004334 | M56: =IF(K56=0,0,L56/K56) -> 155.55153
A57: SEPT | B57: 805 | C57: 137655 | D57: =IF(B57=0,0,C57/B57) -> 171 | E57: =49+298 -> 347 | F57: =23100+39118 -> 62218 | G57: =IF(E57=0,0,F57/E57) -> 179.30259 | H57: =B57+E57 -> 1152 | I57: =C57+F57 -> 199873 | J57: =IF(H57=0,0,I57/H57) -> 173.50087 | K57: =K42+H57 -> 6172.2 | L57: =L42+I57 -> 927618 | M57: =IF(K57=0,0,L57/K57) -> 150.28969
A58: OCT | B58: 578 | C58: 98838 | D58: =IF(B58=0,0,C58/B58) -> 171 | E58: 27 | F58: 13832 | G58: =IF(E58=0,0,F58/E58) -> 512.2963 | H58: =B58+E58 -> 605 | I58: =C58+F58 -> 112670 | J58: =IF(H58=0,0,I58/H58) -> 186.2314 | K58: =K43+H58 -> 7171.2 | L58: =L43+I58 -> 1142948 | M58: =IF(K58=0,0,L58/K58) -> 159.3803
A59: NOV | B59: 1010 | C59: 172710 | D59: =IF(B59=0,0,C59/B59) -> 171 | E59: 9008 | F59: 1009481 | G59: =IF(E59=0,0,F59/E59) -> 112.06494 | H59: =B59+E59 -> 10018 | I59: =C59+F59 -> 1182191 | J59: =IF(H59=0,0,I59/H59) -> 118.00669 | K59: =K44+H59 -> 15823.3 | L59: =L44+I59 -> 2059757 | M59: =IF(K59=0,0,L59/K59) -> 130.1724
A60: DEC | B60: 810.1 | C60: 137265 | D60: =IF(B60=0,0,C60/B60) -> 169.44204 | E60: 110 | F60: 13970 | G60: =IF(E60=0,0,F60/E60) -> 127 | H60: =B60+E60 -> 920.1 | I60: =C60+F60 -> 151235 | J60: =IF(H60=0,0,I60/H60) -> 164.368 | K60: =K45+H60 -> 6254.4 | L60: =L45+I60 -> 983861 | M60: =IF(K60=0,0,L60/K60) -> 157.30702
A61: JAN | B61: 810 | C61: 138510 | D61: =IF(B61=0,0,C61/B61) -> 171 | G61: =IF(E61=0,0,F61/E61) -> 0 | H61: =B61+E61 -> 810 | I61: =C61+F61 -> 138510 | J61: =IF(H61=0,0,I61/H61) -> 171 | K61: =K46+B61 -> 4255.2 | L61: =L46+I61 -> 702668 | M61: =IF(K61=0,0,L61/K61) -> 165.1316
A62: FEB | B62: 500 | C62: 85500 | D62: =IF(B62=0,0,C62/B62) -> 171 | G62: =IF(E62=0,0,F62/E62) -> 0 | H62: =B62+E62 -> 500 | I62: =C62+F62 -> 85500 | J62: =IF(H62=0,0,I62/H62) -> 171 | K62: =K47+B62 -> 6920.1 | L62: =L47+I62 -> 1168842 | M62: =IF(K62=0,0,L62/K62) -> 168.90536
A63: MARCH | B63: 2040 | C63: 417840 | D63: =IF(B63=0,0,C63/B63) -> 204.82353 | G63: =IF(E63=0,0,F63/E63) -> 0 | H63: =B63+E63 -> 2040 | I63: =C63+F63 -> 417840 | J63: =IF(H63=0,0,I63/H63) -> 204.82353 | K63: =K48+B63 -> 5970.1 | L63: =ROUND((L48+I63),0) -> 1122792 | M63: =IF(K63=0,0,L63/K63) -> 188.06921
A64: TOTAL | B64: =SUM(B52:B63) -> 13081.1 | C64: =SUM(C52:C63) -> 2287118 | D64: =IF(B64=0,0,(C64/B64)) -> 174.84141 | E64: =SUM(E52:E63) -> 9856.9 | F64: =SUM(F52:F63) -> 1169384 | G64: =IF(E64=0,0,(F64/E64)) -> 118.63608 | H64: =SUM(H52:H63) -> 22938 | I64: =SUM(I52:I63) -> 3456502 | J64: =IF(H64=0,0,(I64/H64)) -> 150.6889 | K64: =SUM(K52:K63) -> 91012.5 | L64: =SUM(L52:L63) -> 14224827 | M64: =L64/K64 -> 156.29531

Sheet Direct Expns
A1: Group Summary
A2: Particulars | B2: Apr | C2: May | D2: Jun | E2: Jul | F2: Aug | G2: Sep | H2: Oct | I2: Nov | J2: Dec | K2: Jan | L2: Feb | M2: Mar | N2: Total | O2: Average | P2: Sale | S2: ='Inventory Sales'!$B$11 -> 103620.87 | T2: ='Inventory Sales'!$E$11 -> 138460.75 | U2: ='Inventory Sales'!$H$11 -> 122263.84 | V2: ='Inventory Sales'!$K$11 -> 113619.8 | W2: ='Inventory Sales'!$N$11 -> 110361.49 | X2: ='Inventory Sales'!$Q$11 -> 96013.76 | Y2: ='Inventory Sales'!$T$11 -> 93720.65 | Z2: ='Inventory Sales'!$W$11 -> 129573.21 | AA2: ='Inventory Sales'!$Z$11 -> 87201.19 | AB2: ='Inventory Sales'!$AC$11 -> 119805.5 | AC2: ='Inventory Sales'!$AF$11 -> 128216.87 | AD2: ='Inventory Sales'!$AI$11 -> 164514.16 | AE2: =SUM(S2:AD2) -> 1407372.1 | AG2: 12
A3: Manufacturing Expenses | O3: 7 | P3: ='PAL I'!AN12 -> 414881627 | R3: VARIABLE & DIRECT EXPNS | S3: Apr | T3: May | U3: Jun | V3: Jul | W3: Aug | X3: Sep | Y3: Oct | Z3: Nov | AA3: Dec | AB3: Jan | AC3: Feb | AD3: Mar | AE3: Total | AG3: Avg | AI3: =N4/'PAL I'!$AN$12 -> 0.096644796
A4: Employees Remunaration & Benefits | B4: 3164931 | C4: 3100992 | D4: 3145755 | E4: 3504798 | F4: 3304573 | G4: 4259816 | H4: 3239750 | I4: =3265646+4660 -> 3270306 | J4: 3311626 | K4: 3262509 | L4: =3252773+384 -> 3253157 | M4: 3277937 | N4: =SUM(B4:M4) -> 40096150 | O4: =ROUND((N4/$O$3),0) -> 5728021 | P4: =N4/$P$3 -> 0.096644796 | Q4: =(G4-F4) -> 955243 | R4: Wages-Fabric | S4: 260305 | T4: 266537 | U4: 253195 | V4: 245019 | W4: 230894 | X4: 227525 | Y4: 234148 | Z4: 191864 | AA4: 206054 | AB4: 245081 | AC4: 253196 | AD4: 263443 | AE4: =SUM(S4:AD4) -> 2877261 | AF4: =AE4/$AE$2 -> 2.044421 | AG4: =AE4/$AG$2 -> 239771.75 | AH4: =AE4/'PAL I'!$AN$12 -> 0.0069351372
A5: Cooli & Cartage | B5: 4458 | C5: 8456 | D5: 5760 | E5: 5152 | F5: 5949 | G5: =6874+560 -> 7434 | H5: 9762 | I5: 8539 | J5: 8883 | K5: 8308 | L5: 3175 | M5: 5578 | N5: =SUM(B5:M5) -> 81454 | O5: =ROUND((N5/$O$3),0) -> 11636 | P5: =N5/$P$3 -> 0.0001963307 | R5: Wages-Inspection & Dispatch | S5: 641461 | T5: 630793 | U5: 623439 | V5: 635423 | W5: 657932 | X5: 672730 | Y5: 645098 | Z5: 630488 | AA5: 632107 | AB5: 617622 | AC5: 626838 | AD5: 553496 | AE5: =SUM(S5:AD5) -> 7567427 | AF5: =AE5/$AE$2 -> 5.376991 | AG5: =AE5/$AG$2 -> 630618.92 | AH5: =AE5/'PAL I'!$AN$12 -> 0.018239967
A6: Depreciation | B6: 125000 | C6: 125000 | D6: 125000 | E6: 125000 | F6: 125000 | G6: 125000 | H6: 125000 | I6: 125000 | J6: 125000 | K6: 125000 | L6: 125000 | M6: 125000 | N6: =SUM(B6:M6) -> 1500000 | O6: =ROUND((N6/$O$3),0) -> 214286 | P6: =N6/$P$3 -> 0.0036154891 | R6: Fabrication charges | S6: =B7+B8 -> 6769519.5 | T6: =C7+C8 -> 6325290 | U6: =D7+D8 -> 6012211 | V6: =E7+E8 -> 7034404 | W6: =F7+F8 -> 6751563.8 | X6: =G7+G8 -> 7111108.5 | Y6: =H7+H8 -> 5407395.5 | Z6: =INT(I7+I8) -> 5947703 | AA6: =INT(J7+J8) -> 6577862 | AB6: =INT(K7+K8) -> 6880405 | AC6: =INT(L7+L8) -> 6337386 | AD6: =INT(M7+M8) -> 6046500 | AE6: =SUM(S6:AD6) -> 77201348 | AF6: =AE6/$AE$2 -> 54.854966 | AG6: =AE6/$AG$2 -> 6433445.7 | AH6: =AE6/'PAL I'!$AN$12 -> 0.18608042
A7: Fabrication Charges - B-Lore. | B7: =1239242+5006840 -> 6246082 | C7: =1126041+4390366 -> 5516407 | D7: =1134716+4164532.5 -> 5299248.5 | E7: =1555947+4671255 -> 6227202 | F7: =1472853+4555197.5 -> 6028050.5 | G7: 6168526.5 | H7: =1077265+3719991.5 -> 4797256.5 | I7: 5156520.5 | J7: 5851885 | K7: 6102673 | L7: 5274204 | M7: 5085664 | N7: =SUM(B7:M7) -> 67753720 | O7: =ROUND((N7/$O$3),0) -> 9679103 | P7: =N7/$P$3 -> 0.16330856 | R7: Wages-Yarn | S7: 722294 | T7: 674897 | U7: 721644 | V7: 815210 | W7: 866453 | X7: 865380 | Y7: 824245 | Z7: 808151 | AA7: 854802 | AB7: 852278 | AC7: 830833 | AD7: 629815 | AE7: =SUM(S7:AD7) -> 9466002 | AF7: =AE7/$AE$2 -> 6.7260123 | AG7: =AE7/$AG$2 -> 788833.5 | AH7: =AE7/'PAL I'!$AN$12 -> 0.022816151
A8: Fabrication Charges-M/H & TN | B8: =31500+491937.5 -> 523437.5 | C8: =58500+750383 -> 808883 | D8: =63000+649962.5 -> 712962.5 | E8: =67500+739702 -> 807202 | F8: =22500+701013.25 -> 723513.25 | G8: 942582 | H8: =72000+538139 -> 610139 | I8: 791183 | J8: 725977 | K8: 777732 | L8: 1063182 | M8: 960836 | N8: =SUM(B8:M8) -> 9447629.2 | O8: =ROUND((N8/$O$3),0) -> 1349661 | P8: =N8/$P$3 -> 0.022771867 | R8: Yarn Processing charges | S8: =B20+B17 -> 373275 | T8: =C20+C17 -> 602228.5 | U8: =D20+D17 -> 750975 | V8: =E20+E17 -> 915880 | W8: =F20+F17 -> 512492 | X8: =G20+G17 -> 548327.7 | Y8: =H20+H17 -> 699500 | Z8: =INT(I20+I17) -> 600012 | AA8: =J20+J17 -> 1055638.1 | AB8: =K20+K17 -> 847422 | AC8: =L20+L17 -> 896541.8 | AD8: =M20+M17 -> 1071418.8 | AE8: =SUM(S8:AD8) -> 8873710.9 | AF8: =AE8/$AE$2 -> 6.3051633 | AG8: =AE8/$AG$2 -> 739475.91 | AH8: =AE8/'PAL I'!$AN$12 -> 0.021388537
A9: Factory Repairs & Maintanance | B9: =18990+1250 -> 20240 | C9: =41668+1500 -> 43168 | D9: =32016+3200+16500 -> 51716 | E9: 55245 | F9: 120766 | G9: 45900 | H9: =132593+600 -> 133193 | I9: 102838 | J9: =58409-7387.72 -> 51021.28 | K9: 53451 | L9: 35682 | M9: 47352.49 | N9: =SUM(B9:M9) -> 760572.77 | O9: =ROUND((N9/$O$3),0) -> 108653 | P9: =N9/$P$3 -> 0.0018332284 | R9: Freight Inward | S9: =B11 -> 58220.07 | T9: =C11 -> 77587.53 | U9: =D11 -> 71958.95 | V9: =E11 -> 98443.62 | W9: =F11 -> 62956.34 | X9: =G11 -> 107294.74 | Y9: =H11 -> 96278 | Z9: =INT(I11) -> 67642 | AA9: =J11 -> 86345 | AB9: =K11 -> 74433 | AC9: =L11 -> 115943.68 | AD9: =M11 -> 87288.84 | AE9: =SUM(S9:AD9) -> 1004391.8 | AF9: =AE9/$AE$2 -> 0.71366469 | AG9: =AE9/$AG$2 -> 83699.314
A10: Forwarding Charges Paid | N10: =SUM(B10:M10) -> 0 | O10: =ROUND((N10/$O$3),0) -> 0 | P10: =N10/$P$3 -> 0 | R10: Power Bill | S10: =B16 -> 521659 | T10: =C16 -> 619315 | U10: =D16 -> 460719 | V10: =E16 -> 727536 | W10: =F16 -> 536113 | X10: =G16 -> 777552 | Y10: =H16 -> 508329 | Z10: =I16 -> 540192 | ... AD10: =M16 -> 511713 | AE10: =SUM(S10:AD10) -> 7135604 | AF10: =AE10/$AE$2 -> 5.0701616 | AG10: =AE10/$AG$2 -> 594633.67 | AH10: =AE10/'PAL I'!$AN$12 -> 0.017199132
A11: Freight Inwards | B11: =6835.07+51385 -> 58220.07 | C11: =200+14067.53+63320 -> 77587.53 | D11: =1700+20952.95+49306 -> 71958.95 | E11: =21538.62+76200+705 -> 98443.62 | F11: =3204+9002.34+50750 -> 62956.34 | G11: 107294.74 | H11: =341+31017+64920 -> 96278 | I11: =67742.68-100 -> 67642.68 | J11: 86345 | K11: =75433-1000 -> 74433 | L11: 115943.68 | M11: =84663.84+2625 -> 87288.84 | N11: =SUM(B11:M11) -> 1004392.4 | O11: =ROUND((N11/$O$3),0) -> 143485 | P11: =N11/$P$3 -> 0.0024209133 | R11: R & M-Machinery | S11: =B19 -> 11500 | T11: =C19 -> 22245.76 | U11: =D19 -> 0 | V11: =E19 -> 0 | W11: =F19 -> 0 | Z11: =I19 -> 24000 | AA11: =J19 -> 0 | AB11: =K19 -> 0 | AC11: =L19 -> 0 | AD11: =M19 -> 0 | AE11: =SUM(S11:AD11) -> 57745.76 | AF11: =AE11/$AE$2 -> 0.041030912 | AG11: =AE11/$AG$2 -> 4812.1467 | AH11: =AE11/'PAL I'!$AN$12 -> 0.00013918611
A12: Insurance on Assets | B12: =28177+5900 -> 34077 | C12: =18420+29000 -> 47420 | D12: 13596 | E12: =406486+5900 -> 412386 | F12: 5900 | G12: 173051.4 | H12: =-159630.4+5900 -> -153730.4 | I12: 17400 | J12: 29500 | K12: 5900 | L12: 22231 | N12: =SUM(B12:M12) -> 607731 | O12: =ROUND((N12/$O$3),0) -> 86819 | P12: =J12/$P$3 -> 7.1104619e-05 | R12: R & M-Electricals | S12: =B9 -> 20240 | T12: =C9 -> 43168 | U12: =D9 -> 51716 | V12: =E9 -> 55245 | W12: =F9 -> 120766 | X12: =G9 -> 45900 | Y12: =H9 -> 133193 | Z12: =I9 -> 102838 | ... AD12: =M9 -> 47352.49 | AE12: =SUM(S12:AD12) -> 760572.77 | AF12: =AE12/$AE$2 -> 0.54042053 | AG12: =AE12/$AG$2 -> 63381.064 | AH12: =AE12/'PAL I'!$AN$12 -> 0.0018332284
A13: ITC Reversal 2018-19 | N13: =SUM(B13:K13) -> 0 | O13: =ROUND((N13/$O$3),0) -> 0 | P13: =N13/$P$3 -> 0 | R13: Rent | S13: =B18 -> 270500 | T13: =C18 -> 740500 | U13: =D18 -> 505500 | V13: =E18 -> 505500 | W13: =F18 -> 513400 | X13: =G18 -> 513400 | Y13: =H18 -> 513400 | Z13: =I18 -> 513400 | ... AD13: =M18 -> 518400 | AE13: =SUM(S13:AD13) -> 6149200 | AF13: ` | AG13: =AE13/$AG$2 -> 512433.33 | AH13: =AE13/'PAL I'!$AN$12 -> 0.014821577
A14: Medical Exps | N14: =SUM(B14:L14) -> 0 | O14: =ROUND((N14/$O$3),0) -> 0 | P14: =N14/$P$3 -> 0 | R14: Packing charges | AE14: =SUM(S14:AD14) -> 0 | AF14: =AE14/$AE$2 -> 0 | AG14: =AE14/$AG$2 -> 0 | AH14: =AE14/'PAL I'!$AN$12 -> 0
A15: Packing Materials (Consumables) | B15: 2300 | F15: 4600 | L15: 2300 | N15: =SUM(B15:M15) -> 9200 | O15: =ROUND((N15/$O$3),0) -> 1314 | P15: =N15/$P$3 -> 2.2175e-05 | R15: Misc | S15: =SUM(B5,B12,B14,B15) -> 40835 | T15: =SUM(C5,C12,C14,C15) -> 55876 | U15: =SUM(D5,D12,D14,D15) -> 19356 | V15: =SUM(E5,E12,E14,E15) -> 417538 | W15: =SUM(F5,F12,F14,F15) -> 16449 | X15: =SUM(G5,G12,G14,G15) -> 180485.4 | Y15: =SUM(H5,H12,H14,H15) -> -143968.4 | Z15: =SUM(I5,I12,I14,I15) -> 25939 | ... AD15: =SUM(M5,M12,M14,M15) -> 5578 | AE15: =SUM(S15:AD15) -> 698385 | AF15: =AE15/$AE$2 -> 0.49623337 | AG15: =AE15/$AG$2 -> 58198.75 | AH15: =AE15/'PAL I'!$AN$12 -> 0.0016833356
A16: Electricity & power | B16: 521659 | C16: 619315 | D16: 460719 | E16: 727536 | F16: 536113 | G16: 777552 | H16: 508329 | I16: 540192 | J16: 633832 | K16: 559471 | L16: 739172.99 | M16: 511713 | N16: =SUM(B16:M16) -> 7135604 | O16: =ROUND((N16/$O$3),0) -> 1019372 | P16: =N16/$P$3 -> 0.017199132 | S16: =SUM(S4:S15) -> 9689808.6 | T16: =SUM(T4:T15) -> 10058438 | U16: =SUM(U4:U15) -> 9470713.9 | V16: =SUM(V4:V15) -> 11450199 | W16: =SUM(W4:W15) -> 10269019 | X16: =SUM(X4:X15) -> 11049703 | Y16: =SUM(Y4:Y15) -> 8917618.1 | Z16: =SUM(Z4:Z15) -> 9452229 | ... AE16: =SUM(AE4:AE15) -> 1.2179165e+08 | AF16: =AE16/$AE$2 -> 86.538343 | AG16: =SUM(AG4:AG15) -> 10149304
A17: Processing Charges | C17: 25441 | D17: 49650 | E17: 54816 | F17: 2592 | G17: 93952.7 | J17: 147863.1 | K17: 58172 | L17: 37516.8 | M17: 12000 | N17: =SUM(B17:M17) -> 482003.6 | O17: =ROUND((N17/$O$3),0) -> 68858 | P17: =N17/$P$3 -> 0.0011617858 | R17: Working Capital-Bank Charges | S17: ='Indirect Expns'!B42 -> 266753.8 | T17: ='Indirect Expns'!C42 -> -307783.57 | U17: ='Indirect Expns'!D42 -> 45828.88 | V17: ='Indirect Expns'!E42 -> 1788.88 | W17: ='Indirect Expns'!F42 -> 13681.5 | X17: ='Indirect Expns'!G42 -> 2919.32 | Y17: ='Indirect Expns'!H42 -> 8139.44 | Z17: ='Indirect Expns'!I42 -> 5330.06 | ... AD17: ='Indirect Expns'!M42 -> -40500 | AE17: =SUM(S17:AD17) -> 277753.74 | AF17: =AE17/$AE$2 -> 0.19735629 | AG17: =AE17/$AG$2 -> 23146.145
A18: Rent | B18: =23000+78750+168750 -> 270500 | C18: =23000+548750+168750 -> 740500 | D18: =23000+313750+168750 -> 505500 | E18: =23000+313750+168750 -> 505500 | F18: =23000+317700+172700 -> 513400 | G18: 513400 | H18: =23000+317700+172700 -> 513400 | I18: 513400 | J18: 518400 | K18: 518400 | L18: 518400 | M18: 518400 | N18: =SUM(B18:M18) -> 6149200 | O18: =ROUND((N18/$O$3),0) -> 878457 | P18: =N18/$P$3 -> 0.014821577 | R18: Working Capital-LC | S18: ='Indirect Expns'!B43 -> 93178.04 | T18: ='Indirect Expns'!C43 -> 67561.22 | U18: ='Indirect Expns'!D43 -> 246851.6 | V18: ='Indirect Expns'!E43 -> 78924.09 | W18: ='Indirect Expns'!F43 -> 176894.54 | X18: ='Indirect Expns'!G43 -> 75411.38 | Y18: ='Indirect Expns'!H43 -> 240037.43 | Z18: =INT('Indirect Expns'!I43) -> 160177 | AA18: ='Indirect Expns'!J43 -> 60382.97 | AB18: ='Indirect Expns'!K43 -> 269005.98 | AC18: ='Indirect Expns'!L43 -> 193238.52 | AD18: ='Indirect Expns'!M43 -> 1360.14 | AE18: =SUM(S18:AD18) -> 1663022.9 | AF18: =AE18/$AE$2 -> 1.1816512 | AG18: =AE18/$AG$2 -> 138585.24
A19: Repair & Maintenance AMC | B19: 11500 | C19: =24000-1754.24 -> 22245.76 | I19: 24000 | N19: =SUM(B19:M19) -> 57745.76 | O19: =ROUND((N19/$O$3),0) -> 8249 | P19: =N19/$P$3 -> 0.00013918611 | R19: Working Capital-OCC | S19: ='Indirect Expns'!B46 -> 492588 | T19: ='Indirect Expns'!C46 -> 436562 | U19: ='Indirect Expns'!D46 -> 457625 | V19: ='Indirect Expns'!E46 -> 452620 | W19: ='Indirect Expns'!F46 -> 439686 | X19: ='Indirect Expns'!G46 -> 395256 | Y19: ='Indirect Expns'!H46 -> 409245 | Z19: ='Indirect Expns'!I46 -> 453758 | ... AD19: ='Indirect Expns'!M46 -> 372704 | AE19: =SUM(S19:AD19) -> 5219826 | AF19: =AE19/$AE$2 -> 3.7089168 | AG19: =AE19/$AG$2 -> 434985.5
A20: Yarn Processing Charges | B20: 373275 | C20: 576787.5 | D20: 701325 | E20: 861064 | F20: 509900 | G20: 454375 | H20: =313000+386500 -> 699500 | I20: 600012.5 | J20: 907775 | K20: 789250 | L20: 859025 | M20: 1059418.8 | N20: =SUM(B20:M20) -> 8391707.8 | O20: =ROUND((N20/$O$3),0) -> 1198815 | P20: =N20/$P$3 -> 0.020226752 | S20: =SUM(S17:S19) -> 852519.84 | T20: =SUM(T17:T19) -> 196339.65 | U20: =SUM(U17:U19) -> 750305.48 | V20: =SUM(V17:V19) -> 533332.97 | W20: =SUM(W17:W19) -> 630262.04 | X20: =SUM(X17:X19) -> 473586.7 | Y20: =SUM(Y17:Y19) -> 657421.87 | Z20: =SUM(Z17:Z19) -> 619265.06 | ... AE20: =SUM(AE17:AE19) -> 7160602.7 | AF20: =AE20/$AE$2 -> 5.0879243 | AG20: =SUM(AG17:AG19) -> 596716.89
O21: =+N21/$O$3 -> 0 | P21: =N21/$P$3 -> 0 | S21: =S16+S20 -> 10542328 | T21: =T16+T20 -> 10254777 | U21: =U16+U20 -> 10221019 | V21: =V16+V20 -> 11983532 | W21: =W16+W20 -> 10899281 | X21: =X16+X20 -> 11523290 | Y21: =Y16+Y20 -> 9575040 | Z21: =Z16+Z20 -> 10071494 | ... AE21: =AE16+AE20 -> 1.2895225e+08 | AF21: =AE21/$AE$2 -> 91.626267 | AG21: =AG16+AG20 -> 10746021
A22: Grand Total | B22: =SUM(B4:B21) -> 11355680 | C22: =SUM(C4:C21) -> 11712203 | D22: =SUM(D4:D21) -> 11143191 | E22: =SUM(E4:E21) -> 13384345 | F22: =SUM(F4:F21) -> 11943313 | G22: =SUM(G4:G21) -> 13668884 | H22: =SUM(H4:H21) -> 10578877 | I22: =SUM(I4:I21) -> 11217034 | ... O22: =SUM(O4:O21) -> 20496729 | P22: =N22/$P$3 -> 0.34582662 | AE22: Less Fabrn | AF22: =(AE21-AE6)/AE2 -> 36.771301
P23: =N23/$P$3 -> 0 | R23: FIXED EXPNS | AF23: =AE23/$AE$2 -> 0
A24: Manufacturing | B24: =ROUND((B22-(B25+B26+B27+B29)),0) -> 3927909 | C24: =ROUND((C22-(C25+C26+C27+C29)),0) -> 4438586 | D24: =ROUND((D22-(D25+D26+D27+D29)),0) -> 4305682 | E24: =ROUND((E22-(E25+E26+E27+E29)),0) -> 5418106 | F24: =ROUND((F22-(F25+F26+F27+F29)),0) -> 4395283 | G24: =ROUND((G22-(G25+G26+G27+G29)),0) -> 5710287 | H24: =ROUND((H22-(H25+H26+H27+H29)),0) -> 4255210 | I24: =ROUND((I22-(I25+I26+I27+I29)),0) -> 4520254 | ... N24: =ROUND((N22-(N25+N26+N27+N29)),0) -> 56409413 | O24: =ROUND((N24/$O$3),0) -> 8058488 | R24: Employees welfare exp | S24: =B4-(S4+S5+S7+S25+S26) -> 644797 | T24: =C4-(T4+T5+T7+T25+T26) -> 631736 | U24: =D4-(U4+U5+U7+U25+U26) -> 650057 | V24: =E4-(V4+V5+V7+V25+V26) -> 903646 | W24: =F4-(W4+W5+W7+W25+W26) -> 643794 | X24: =G4-(X4+X5+X7+X25+X26) -> 1588481 | Y24: =H4-(Y4+Y5+Y7+Y25+Y26) -> 630559 | Z24: =I4-(Z4+Z5+Z7+Z25+Z26) -> 813603 | ... AD24: =M4-(AD4+AD5+AD7+AD25+AD26) -> 920383 | AE24: =SUM(S24:AD24) -> 9403137 | AF24: =AE24/$AE$2 -> 6.681344 | AG24: =AE24/$AG$2 -> 783594.75
A25: ITC Reversed | B25: =B13 -> 0 | C25: =C13 -> 0 | D25: =D13 -> 0 | E25: =E13 -> 0 | F25: =F13 -> 0 | G25: =G13 -> 0 | H25: =H13 -> 0 | I25: =I13 -> 0 | ... N25: =N13 -> 0 | O25: =+N25/$O$3 -> 0 | R25: Salaries Office | S25: 371074 | T25: 372029 | U25: 372420 | V25: 380500 | W25: 380500 | X25: 380700 | Y25: 380700 | Z25: 301200 | AA25: 385800 | AB25: 385800 | AC25: 385800 | AD25: 385800 | AE25: =SUM(S25:AD25) -> 4482323 | AF25: =AE25/$AE$2 -> 3.1848884 | AG25: =AE25/$AG$2 -> 373526.92
A26: In House Fabrn | B26: 533251 | C26: 823327 | D26: 700298 | E26: 806835 | F26: 671466 | G26: 722488 | H26: 791271 | I26: 624076 | J26: 632326 | K26: 721180 | L26: 716280 | M26: 623548 | N26: =SUM(B26:M26) -> 8366346 | O26: =ROUND((N26/$O$3),0) -> 1195192 | R26: Directors Remuneration | S26: 525000 | T26: 525000 | U26: 525000 | V26: 525000 | W26: =V26 -> 525000 | X26: 525000 | Y26: 525000 | Z26: 525000 | AA26: 525000 | AB26: 525000 | AC26: 525000 | AD26: 525000 | AE26: =SUM(S26:AD26) -> 6300000 | AF26: =AE26/$AE$2 -> 4.4764281 | AG26: =AE26/$AG$2 -> 525000
A27: Fabrn | B27: =ROUND((B7+B8),0) -> 6769520 | C27: =ROUND((C7+C8),0) -> 6325290 | D27: =ROUND((D7+D8),0) -> 6012211 | E27: =ROUND((E7+E8),0) -> 7034404 | F27: =ROUND((F7+F8),0) -> 6751564 | G27: =ROUND((G7+G8),0) -> 7111109 | H27: =ROUND((H7+H8),0) -> 5407396 | I27: =ROUND((I7+I8),0) -> 5947704 | ... L27: =ROUND((L7+L8),0) -> 6337386 | M27: =M7+M8 -> 6046500 | N27: =SUM(B27:M27) -> 77201351 | O27: =ROUND((N27/$O$3),0) -> 11028764 | R27: Depreciation | S27: =B6 -> 125000 | T27: =C6 -> 125000 | U27: =D6 -> 125000 | V27: 125000 | W27: =V27 -> 125000 | X27: =G6 -> 125000 | Y27: =H6 -> 125000 | Z27: =I6 -> 125000 | AA27: =J6 -> 125000 | AB27: =K6 -> 125000 | AC27: =L6 -> 125000 | AD27: =M6 -> 125000 | AE27: =SUM(S27:AD27) -> 1500000 | AF27: =AE27/$AE$2 -> 1.0658162 | AG27: =AE27/$AG$2 -> 125000
A28: Direct Expns | B28: =SUM(B24:B27) -> 11230680 | C28: =SUM(C24:C27) -> 11587203 | D28: =SUM(D24:D27) -> 11018191 | E28: =SUM(E24:E27) -> 13259345 | F28: =SUM(F24:F27) -> 11818313 | G28: =SUM(G24:G27) -> 13543884 | H28: =SUM(H24:H27) -> 10453877 | I28: =SUM(I24:I27) -> 11092034 | ... M28: =SUM(M24:M27) -> 11566188 | N28: =SUM(B28:M28) -> 141977110 | O28: =ROUND((N28/$O$3),0) -> 20282444 | R28: Admn Expns | S28: ='Indirect Expns'!B3 -> 433740 | T28: ='Indirect Expns'!C3 -> 513190.13 | U28: ='Indirect Expns'!D3 -> 575240.25 | V28: ='Indirect Expns'!E3 -> 413383.32 | W28: ='Indirect Expns'!F3 -> 449879.61 | X28: ='Indirect Expns'!G3 -> 359223.49 | Y28: ='Indirect Expns'!H3 -> 510924.17 | Z28: =INT('Indirect Expns'!I3) -> 466534 | AA28: ='Indirect Expns'!J3 -> 547704.57 | AB28: ='Indirect Expns'!K3 -> 349480.88 | AC28: ='Indirect Expns'!L3 -> 599924.47 | AD28: ='Indirect Expns'!M3 -> 656534.52 | AE28: =SUM(S28:AD28) -> 5875759.4 | AF28: =AE28/$AE$2 -> 4.1749865 | AG28: =AE28/$AG$2 -> 489646.62
A29: Deprn | B29: =B6 -> 125000 | C29: =C6 -> 125000 | D29: =D6 -> 125000 | E29: =E6 -> 125000 | F29: =F6 -> 125000 | G29: =G6 -> 125000 | H29: =H6 -> 125000 | I29: =I6 -> 125000 | ... N29: =N6 -> 1500000 | O29: =ROUND((N29/$O$3),0) -> 214286 | R29: Selling Expns | S29: ='Indirect Expns'!B52 -> 32614.21 | T29: ='Indirect Expns'!C52 -> 61101.17 | U29: ='Indirect Expns'!D52 -> 327067.65 | V29: ='Indirect Expns'!E52 -> 62212.6 | W29: ='Indirect Expns'!F52 -> 117848 | X29: ='Indirect Expns'!G52 -> 58017.23 | Y29: ='Indirect Expns'!H52 -> 36302.25 | Z29: =INT('Indirect Expns'!I52) -> 269668 | AA29: ='Indirect Expns'!J52 -> 191554.43 | AB29: ='Indirect Expns'!K52 -> 155623.25 | AC29: ='Indirect Expns'!L52 -> 229687.48 | AD29: ='Indirect Expns'!M52 -> 109039.18 | AE29: =SUM(S29:AD29) -> 1650735.4 | AF29: =AE29/$AE$2 -> 1.1729204 | AG29: =AE29/$AG$2 -> 137561.29
A30: Total | B30: =SUM(B28:B29) -> 11355680 | C30: =SUM(C28:C29) -> 11712203 | D30: =SUM(D28:D29) -> 11143191 | E30: =SUM(E28:E29) -> 13384345 | F30: =SUM(F28:F29) -> 11943313 | G30: =SUM(G28:G29) -> 13668884 | H30: =SUM(H28:H29) -> 10578877 | I30: =SUM(I28:I29) -> 11217034 | ... N30: =SUM(N28:N29) -> 143477110 | O30: =ROUND((N30/$O$3),0) -> 20496730 | R30: Finance Cost-Int On Term Loan | S30: ='Indirect Expns'!B48+'Indirect Expns'!B50 -> 0 | T30: ='Indirect Expns'!C48+'Indirect Expns'!C50 -> 0 | U30: ='Indirect Expns'!D48+'Indirect Expns'!D50 -> 0 | V30: ='Indirect Expns'!E48+'Indirect Expns'!E50 -> 11170 | W30: ='Indirect Expns'!F48+'Indirect Expns'!F50 -> 14192 | X30: ='Indirect Expns'!G48+'Indirect Expns'!G50 -> 13838 | Y30: ='Indirect Expns'!H48+'Indirect Expns'!H50 -> 13481 | Z30: ='Indirect Expns'!I48+'Indirect Expns'!I50 -> 13122 | ... AD30: ='Indirect Expns'!M48+'Indirect Expns'!M50 -> 11655 | AE30: =SUM(S30:AD30) -> 114637 | AF30: =AE30/$AE$2 -> 0.081454649 | AG30: =AE30/$AG$2 -> 9553.0833
A31: Fabrn | B31: =B26+B27 -> 7302771 | C31: =C26+C27 -> 7148617 | D31: =D26+D27 -> 6712509 | E31: =E26+E27 -> 7841239 | F31: =F26+F27 -> 7423030 | G31: =G26+G27 -> 7833597 | H31: =H26+H27 -> 6198667 | I31: =I26+I27 -> 6571780 | ... N31: =N26+N27 -> 85567697 | O31: =ROUND((N31/$O$3),0) -> 12223957 | R31: Finance Cost-Int On Deposits | S31: ='Indirect Expns'!B44+'Indirect Expns'!B51+1 -> 97334 | T31: ='Indirect Expns'!C44+'Indirect Expns'!C51 -> 97333 | U31: ='Indirect Expns'!D44+'Indirect Expns'!D51 -> 454333 | V31: ='Indirect Expns'!E44+'Indirect Expns'!E51 -> 97333 | W31: ='Indirect Expns'!F44+'Indirect Expns'!F51 -> 97333 | X31: ='Indirect Expns'!G44+'Indirect Expns'!G51 -> 452333 | Y31: ='Indirect Expns'!H44+'Indirect Expns'!H51 -> 93618 | Z31: ='Indirect Expns'!I44+'Indirect Expns'!I51 -> 93224 | AA31: ='Indirect Expns'!J44+'Indirect Expns'!J51 -> 446410 | ... AD31: ='Indirect Expns'!M44+'Indirect Expns'!M51 -> 439012 | AE31: =SUM(S31:AD31) -> 2542568 | AF31: =AE31/$AE$2 -> 1.8066068 | AG31: =AE31/$AG$2 -> 211880.67
S32: =SUM(S24:S31) -> 2229559.2 | T32: =SUM(T24:T31) -> 2325389.3 | U32: =SUM(U24:U31) -> 3029117.9 | V32: =SUM(V24:V31) -> 2518244.9 | W32: =SUM(W24:W31) -> 2353546.6 | X32: =SUM(X24:X31) -> 3502592.7 | Y32: =SUM(Y24:Y31) -> 2315584.4 | Z32: =SUM(Z24:Z31) -> 2607351 | ... AE32: =SUM(AE24:AE31) -> 31869160 | AF32: =AE32/$AE$2 -> 22.644445 | AG32: =SUM(AG24:AG31) -> 2655763.3
A33: In House Qty | B33: 8386.9 | C33: 9115.9 | D33: 8230.5 | E33: 7433.3 | F33: 6910.3 | G33: 8618.4 | H33: 6085.3 | I33: 7778 | J33: 9706.9 | K33: 9658 | L33: 8769.8 | M33: 11284.7 | N33: =SUM(B33:M33) -> 101978 | R33: Total Expns | S33: =S21+S32 -> 12771888 | T33: =T21+T32 -> 12580167 | U33: =U21+U32 -> 13250137 | V33: =V21+V32 -> 14501777 | W33: =W21+W32 -> 13252828 | X33: =X21+X32 -> 15025883 | Y33: =Y21+Y32 -> 11890624 | Z33: =Z21+Z32 -> 12678845 | ... AE33: =AE21+AE32 -> 1.6082141e+08 | AF33: =AE33/$AE$2 -> 114.27071 | AG33: =AE33/$AG$2 -> 13401784
A34: Fabricators Qty | B34: 79666.8 | C34: 74692.4 | D34: 70683.1 | E34: 83091 | F34: 76318.9 | G34: 82224.2 | H34: 64342.8 | I34: 70982.7 | J34: 78244.4 | K34: 80049.2 | L34: 72433.1 | M34: 69895.7 | N34: =SUM(B34:M34) -> 902624.3 | R34: Tally Total-PAL1 | S34: ='PAL I'!D26 -> 12771887 | T34: ='PAL I'!G26 -> 12580167 | U34: ='PAL I'!J26 -> 13250137 | V34: ='PAL I'!M26 -> 14501777 | W34: ='PAL I'!P26 -> 13252828 | X34: ='PAL I'!S26 -> 15025882 | Y34: ='PAL I'!V26 -> 11890624 | Z34: ='PAL I'!Y26 -> 12678849 | AA34: ='PAL I'!AB26 -> 14081473 | AB34: ='PAL I'!AE26 -> 13657981 | AC34: ='PAL I'!AH26 -> 13888814 | AD34: ='PAL I'!AK26 -> 13240993 | AE34: ='PAL I'!AN26 -> 160821412 | AF34: =AE34/$AE$2 -> 114.27071
A35: Yarn Processing Qty (In & Out) | B35: =54698+21500 -> 76198 | C35: =49466+26500 -> 75966 | D35: =56391+25800 -> 82191 | E35: =61071+36761 -> 97832 | F35: =51789+22775 -> 74564 | G35: =56781+20225 -> 77006 | H35: =48715+29325 -> 78040 | I35: 78954 | J35: 100149 | K35: 91272 | L35: 88473 | M35: 64885 | N35: =SUM(B35:M35) -> 985530 | S35: =S33-S34 -> 0.62 | T35: =T33-T34 -> -0.26 | U35: =U33-U34 -> 0.33 | V35: =V33-V34 -> -0.49 | W35: =W33-W34 -> -0.26 | X35: =X33-X34 -> 0.76 | Y35: =Y33-Y34 -> 0.39 | Z35: =Z33-Z34 -> -3.94 | ... AE35: =AE33-AE34 -> -1.05
A36: Indirect | B36: ='Indirect Expns'!B75 -> 1416207 | C36: ='Indirect Expns'!C75 -> 867964 | D36: ='Indirect Expns'!D75 -> 2106946 | E36: ='Indirect Expns'!E75 -> 1117432 | F36: ='Indirect Expns'!F75 -> 1309515 | G36: ='Indirect Expns'!G75 -> 1356998 | H36: ='Indirect Expns'!H75 -> 1311747 | I36: ='Indirect Expns'!I75 -> 1461815 | ... N36: ='Indirect Expns'!N75 -> 17344303 | O36: =ROUND((N36/$O$3),0) -> 2477758 | R36: Wages | S36: =SUM(S4,S5,S7)+S24+S25+S26 -> 3164931 | T36: =SUM(T4,T5,T7)+T24+T25+T26 -> 3100992 | U36: =SUM(U4,U5,U7)+U24+U25+U26 -> 3145755 | V36: =SUM(V4,V5,V7)+V24+V25+V26 -> 3504798 | W36: =SUM(W4:W5)+W24+W25 -> 1913120 | X36: =SUM(X4:X5)+X24+X25 -> 2869436 | Y36: =SUM(Y4:Y5)+Y24+Y25 -> 1890505 | Z36: =SUM(Z4:Z5)+Z24+Z25 -> 1937155 | AA36: =SUM(AA4:AA5)+AA24+AA25 -> 1931824 | AB36: =SUM(AB4:AB5)+AB24+AB25 -> 1885231 | AC36: =SUM(AC4:AC5)+AC24+AC25 -> 1897324 | AD36: =SUM(AD4:AD5)+AD24+AD25 -> 2123122 | AE36: =SUM(AE4:AE5)+AE24+AE25 -> 24330148 | AF36: =AE36/$AE$2 -> 17.287644 | AG36: =AE36/$AG$2 -> 2027512.3
A37: Total Expns | B37: =B30+B36 -> 12771887 | C37: =C30+C36 -> 12580167 | D37: =D30+D36 -> 13250137 | E37: =E30+E36 -> 14501777 | F37: =F30+F36 -> 13252828 | G37: =G30+G36 -> 15025882 | H37: =H30+H36 -> 11890624 | I37: =I30+I36 -> 12678849 | ... N37: =N30+N36 -> 160821413 | O37: =ROUND((N37/$O$3),0) -> 22974488 | S37: =B4 -> 3164931 | T37: =C4 -> 3100992 | U37: =D4 -> 3145755 | V37: =E4 -> 3504798 | W37: =F4 -> 3304573 | X37: =G4 -> 4259816 | Y37: =H4 -> 3239750 | Z37: =I4 -> 3270306 | ... AE37: =N4 -> 40096150 | AF37: =AE37/$AE$2 -> 28.490085
A39: P/L | B39: 11355680 | C39: 11712203 | D39: 11143191 | E39: 13384345 | F39: 11943313 | G39: 13668884 | H39: 10578877 | I39: 11212374 | J39: 12405495 | N39: 1.0740436e+08 | R39: Direct From Above | S39: =S16+SUM(S24:S27) -> 11355680 | T39: =T16+SUM(T24:T27) -> 11712203 | U39: =U16+SUM(U24:U27) -> 11143191 | V39: =V16+SUM(V24:V27) -> 13384345 | W39: =W16+SUM(W24:W27) -> 11943313 | X39: =X16+SUM(X24:X27) -> 13668884 | Y39: =Y16+SUM(Y24:Y27) -> 10578877 | Z39: =Z16+SUM(Z24:Z27) -> 11217032 | ... AE39: =AE16+SUM(AE24:AE27) -> 1.4347711e+08 | AF39: =AE39/$AE$2 -> 101.94682 | AG39: =AE39/$AG$2 -> 11956426
B40: =B22-B39 -> 0 | C40: =C22-C39 -> 0 | D40: =D22-D39 -> 0 | E40: =E22-E39 -> 0 | F40: =F22-F39 -> 0 | G40: =G22-G39 -> 0 | H40: =H22-H39 -> 0 | I40: =I22-I39 -> 4660 | ... L40: =L22-L39 -> 12048989 | N40: =SUM(B39:M39) -> 1.0740436e+08 | R40: Indirect form Above | S40: =S28+S29+S30+S31+S20 -> 1416208.1 | T40: =T28+T29+T30+T31+T20 -> 867963.95 | U40: =U28+U29+U30+U31+U20 -> 2106946.4 | V40: =V28+V29+V30+V31+V20 -> 1117431.9 | W40: =W28+W29+W30+W31+W20 -> 1309514.6 | X40: =X28+X29+X30+X31+X20 -> 1356998.4 | Y40: =Y28+Y29+Y30+Y31+Y20 -> 1311747.3 | Z40: =Z28+Z29+Z30+Z31+Z20 -> 1461813.1 | ... AE40: =AE28+AE29+AE30+AE31+AE20 -> 17344303 | AF40: =AE40/$AE$2 -> 12.323893 | AG40: =AE40/$AG$2 -> 1445358.5
N41: =N39-N40 -> 0 | S41: =SUM(S39:S40) -> 12771888 | T41: =SUM(T39:T40) -> 12580167 | U41: =SUM(U39:U40) -> 13250137 | V41: =SUM(V39:V40) -> 14501777 | W41: =SUM(W39:W40) -> 13252828 | X41: =SUM(X39:X40) -> 15025883 | Y41: =SUM(Y39:Y40) -> 11890624 | Z41: =SUM(Z39:Z40) -> 12678845 | ... AE41: =SUM(AE39:AE40) -> 1.6082141e+08 | AF41: =AE41/$AE$2 -> 114.27071 | AG41: =SUM(AG39:AG40) -> 13401784
N42: =N22-N39 -> 36072749 | R42: Direct | S42: =B22 -> 11355680 | T42: =C22 -> 11712203 | U42: =D22 -> 11143191 | V42: =E22 -> 13384345 | W42: =F22 -> 11943313 | X42: =G22 -> 13668884 | Y42: =H22 -> 10578877 | Z42: =I22 -> 11217034 | ... AE42: =N22 -> 1.4347711e+08 | AF42: =AE42/$AE$2 -> 101.94682
R43: Indirect | S43: ='Indirect Expns'!B65 -> 1416207.1 | T43: ='Indirect Expns'!C65 -> 867963.95 | U43: ='Indirect Expns'!D65 -> 2106946.4 | V43: ='Indirect Expns'!E65 -> 1117431.9 | W43: ='Indirect Expns'!F65 -> 1309514.6 | X43: ='Indirect Expns'!G65 -> 1356998.4 | Y43: ='Indirect Expns'!H65 -> 1311747.3 | Z43: ='Indirect Expns'!I65 -> 1461814.6 | ... AE43: ='Indirect Expns'!N65 -> 17344303 | AF43: =AE43/$AE$2 -> 12.323893
S44: =SUM(S42:S43) -> 12771887 | T44: =SUM(T42:T43) -> 12580167 | U44: =SUM(U42:U43) -> 13250137 | V44: =SUM(V42:V43) -> 14501777 | W44: =SUM(W42:W43) -> 13252828 | X44: =SUM(X42:X43) -> 15025883 | Y44: =SUM(Y42:Y43) -> 11890624 | Z44: =SUM(Z42:Z43) -> 12678848 | ... AE44: =SUM(AE42:AE43) -> 1.6082141e+08 | AF44: =AE44/$AE$2 -> 114.27071
R46: Variable-Yarn Cost | S46: =ROUND((S21-(S47+S48+S49)),0) -> 1921090 | T46: =ROUND((T21-(T47+T48+T49)),0) -> 2738517 | U46: =ROUND((U21-(U47+U48+U49)),0) -> 2484833 | V46: =ROUND((V21-(V47+V48+V49)),0) -> 3437574 | W46: =ROUND((W21-(W47+W48+W49)),0) -> 2531197 | X46: =ROUND((X21-(X47+X48+X49)),0) -> 2940897 | Y46: =ROUND((Y21-(Y47+Y48+Y49)),0) -> 2533676 | Z46: =Z21-(Z47+Z48+Z49) -> 2585006.1 | AA46: =ROUND((AA21-(AA47+AA48+AA49)),0) -> 3141202 | AB46: =AB21-(AB47+AB48+AB49) -> 2822099.2 | AC46: =AC21-(AC47+AC48+AC49) -> 3066979.5 | AD46: =AD21-(AD47+AD48+AD49) -> 2774530.3 | AE46: =ROUND((AE21-(AE47+AE48+AE49)),0) -> 32977604 | AF46: =AE46/$AE$2 -> 23.432043 | AG46: =AE46/$AG$2 -> 2748133.7 | AH46: =AE46/'PAL I'!$AN$12 -> 0.079486779 | AI46: =AE46/CONSUMPTION!$AN$74 -> 0.16083155
R47: Variable-Fabric Cost | S47: =ROUND((S4+S5+S6),0) -> 7671286 | T47: =ROUND((T4+T5+T6),0) -> 7222620 | U47: =ROUND((U4+U5+U6),0) -> 6888845 | V47: =ROUND((V4+V5+V6),0) -> 7914846 | W47: =ROUND((W4+W5+W6),0) -> 7640390 | X47: =ROUND((X4+X5+X6),0) -> 8011364 | Y47: =ROUND((Y4+Y5+Y6),0) -> 6286642 | Z47: =Z4+Z5+Z6 -> 6770055 | AA47: =AA4+AA5+AA6 -> 7416023 | AB47: =AB4+AB5+AB6 -> 7743108 | AC47: =AC4+AC5+AC6 -> 7217420 | AD47: =AD4+AD5+AD6 -> 6863439 | AE47: =ROUND((AE4+AE5+AE6),0) -> 87646036 | AF47: =AE47/(N34+N35) -> 46.418895 | AG47: =AE47/$AG$2 -> 7303836.3 | AH47: =AE47/'PAL I'!$AN$12 -> 0.21125553 | AI47: =AE47/CONSUMPTION!$AN$74 -> 0.42744913
R48: Variable-Trading | S48: 97432 | T48: 97300 | U48: 97036 | V48: 97779 | W48: 97432 | X48: 97442 | Y48: 97300 | Z48: 97168 | AA48: =94000+3219 -> 97219 | AB48: =94000+3564 -> 97564 | AC48: =94000+3300 -> 97300 | AD48: 97036 | AE48: =SUM(S48:AD48) -> 1168008 | AF48: =(AE48/'Trading PL'!AL4) -> 12.886025 | AG48: =AE48/$AG$2 -> 97334 | AH48: =AE48/'PAL I'!$AN$12 -> 0.0028152801 | AI48: =AE48/CONSUMPTION!$AN$74 -> 0.0056963672
R49: Variable-Finance | S49: =ROUND((S20),0) -> 852520 | T49: =ROUND((T20),0) -> 196340 | U49: =ROUND((U20),0) -> 750305 | V49: =ROUND((V20),0) -> 533333 | W49: =ROUND((W20),0) -> 630262 | X49: =ROUND((X20),0) -> 473587 | Y49: =ROUND((Y20),0) -> 657422 | Z49: =ROUND((Z20),0) -> 619265 | ... AE49: =ROUND((AE20),0) -> 7160603 | AG49: =AE49/$AG$2 -> 596716.92 | AH49: =AE49/'PAL I'!$AN$12 -> 0.017259388 | AI49: =AE49/CONSUMPTION!$AN$74 -> 0.034922213
R50: Fixed Cost | S50: =ROUND((S32-S51),0) -> 2104559 | T50: =ROUND((T32-T51),0) -> 2200389 | U50: =ROUND((U32-U51),0) -> 2904118 | V50: =ROUND((V32-V51),0) -> 2393245 | W50: =ROUND((W32-W51),0) -> 2228547 | X50: =ROUND((X32-X51),0) -> 3377593 | Y50: =ROUND((Y32-Y51),0) -> 2190584 | Z50: =Z32-Z51 -> 2482351 | AA50: =AA32-AA51 -> 2817091 | AB50: =AB32-AB51 -> 2153077.1 | AC50: =AC32-AC51 -> 2470182 | AD50: =AD32-AD51 -> 3047423.7 | AE50: =ROUND((AE32-AE51),0) -> 30369160 | AF50: =AE50/$AE$2 -> 21.578629 | AG50: =AE50/$AG$2 -> 2530763.3 | AH50: =AE50/'PAL I'!$AN$12 -> 0.073199578 | AI50: =AE50/CONSUMPTION!$AN$74 -> 0.14811019
R51: Deprn | S51: =S27 -> 125000 | T51: =T27 -> 125000 | U51: =U27 -> 125000 | V51: =V27 -> 125000 | W51: =W27 -> 125000 | X51: =X27 -> 125000 | Y51: =Y27 -> 125000 | Z51: =Z27 -> 125000 | ... AE51: =AE27 -> 1500000 | AF51: =AE51/$AE$2 -> 1.0658162 | AG51: =AE51/$AG$2 -> 125000 | AH51: =AE51/'PAL I'!$AN$12 -> 0.0036154891 | AI51: =AE51/CONSUMPTION!$AN$74 -> 0.00731549
S52: =SUM(S46:S51) -> 12771887 | T52: =SUM(T46:T51) -> 12580166 | U52: =SUM(U46:U51) -> 13250137 | V52: =SUM(V46:V51) -> 14501777 | W52: =SUM(W46:W51) -> 13252828 | X52: =SUM(X46:X51) -> 15025883 | Y52: =SUM(Y46:Y51) -> 11890624 | Z52: =SUM(Z46:Z51) -> 12678845 | ... AE52: =SUM(AE46:AE51) -> 160821411 | AF52: =AE52/$AE$2 -> 114.27071 | AG52: =SUM(AG50:AG51) -> 2655763.3 | AH52: =AE52/'PAL I'!$AN$12 -> 0.38763204 | AI52: =AE52/CONSUMPTION!$AN$74 -> 0.78432495
R53: Fixed Expns Break up
R54: Salaries | S54: =ROUND((S24+S25+S26),0) -> 1540871 | T54: =ROUND((T24+T25+T26),0) -> 1528765 | U54: =ROUND((U24+U25+U26),0) -> 1547477 | V54: =ROUND((V24+V25+V26),0) -> 1809146 | W54: =ROUND((W24+W25+W26),0) -> 1549294 | X54: =ROUND((X24+X25+X26),0) -> 2494181 | Y54: =ROUND((Y24+Y25+Y26),0) -> 1536259 | Z54: =ROUND((Z24+Z25+Z26),0) -> 1639803 | ... AE54: =ROUND((AE24+AE25+AE26),0) -> 20185460 | AF54: =AE54/$AE$59 -> 0.6333854
R55: Admn | S55: =ROUND((S28),0) -> 433740 | T55: =ROUND((T28),0) -> 513190 | U55: =ROUND((U28),0) -> 575240 | V55: =ROUND((V28),0) -> 413383 | W55: =ROUND((W28),0) -> 449880 | X55: =ROUND((X28),0) -> 359223 | Y55: =ROUND((Y28),0) -> 510924 | Z55: =ROUND((Z28),0) -> 466534 | ... AE55: =ROUND((AE28),0) -> 5875759 | AF55: =AE55/$AE$59 -> 0.18437132
R56: Selling | S56: =ROUND((S29),) -> 32614 | T56: =ROUND((T29),) -> 61101 | U56: =ROUND((U29),) -> 327068 | V56: =ROUND((V29),) -> 62213 | W56: =ROUND((W29),) -> 117848 | X56: =ROUND((X29),) -> 58017 | Y56: =ROUND((Y29),) -> 36302 | Z56: =ROUND((Z29),) -> 269668 | ... AE56: =ROUND((AE29),) -> 1650735 | AF56: =AE56/$AE$59 -> 0.051797256
R57: Deprnn | S57: =ROUND((S27),0) -> 125000 | T57: =ROUND((T27),0) -> 125000 | U57: =ROUND((U27),0) -> 125000 | V57: =ROUND((V27),0) -> 125000 | W57: =ROUND((W27),0) -> 125000 | X57: =ROUND((X27),0) -> 125000 | Y57: =ROUND((Y27),0) -> 125000 | Z57: =ROUND((Z27),0) -> 125000 | ... AE57: =ROUND((AE27),0) -> 1500000 | AF57: =AE57/$AE$59 -> 0.047067449
R58: Interest | S58: =ROUND((S30+S31),) -> 97334 | T58: =ROUND((T30+T31),) -> 97333 | U58: =ROUND((U30+U31),) -> 454333 | V58: =ROUND((V30+V31),) -> 108503 | W58: =ROUND((W30+W31),) -> 111525 | X58: =ROUND((X30+X31),) -> 466171 | Y58: =ROUND((Y30+Y31),) -> 107099 | Z58: =ROUND((Z30+Z31),) -> 106346 | ... AE58: =ROUND((AE30+AE31),) -> 2657205 | AF58: =AE58/$AE$59 -> 0.083378573
S59: =SUM(S54:S58) -> 2229559 | T59: =SUM(T54:T58) -> 2325389 | U59: =SUM(U54:U58) -> 3029118 | V59: =SUM(V54:V58) -> 2518245 | W59: =SUM(W54:W58) -> 2353547 | X59: =SUM(X54:X58) -> 3502592 | Y59: =SUM(Y54:Y58) -> 2315584 | Z59: =SUM(Z54:Z58) -> 2607351 | ... AE59: =SUM(AE54:AE58) -> 31869159
R61: Financial Expns | S61: =S49+S58 -> 949854 | T61: =T49+T58 -> 293673 | U61: =U49+U58 -> 1204638 | V61: =V49+V58 -> 641836 | W61: =W49+W58 -> 741787 | X61: =X49+X58 -> 939758 | Y61: =Y49+Y58 -> 764521 | Z61: =Z49+Z58 -> 725611 | ... AE61: =AE49+AE58 -> 9817808

Sheet Indirect Expns
A1: Indirect Expenses
A2: Particulars | B2: Apr | C2: May | D2: Jun | E2: Jul | F2: Aug | G2: Sep | H2: Oct | I2: Nov | J2: Dec | K2: Jan | L2: Feb | M2: Mar | N2: TOTAL | O2: Average | P2: 12 | Q2: =ROUND(('PAL I'!AN12),0) -> 414881627 | R2: Sales T/o
A3: Administrative Expenses | B3: =SUM(B4:B40) -> 433740 | C3: =SUM(C4:C40) -> 513190.13 | D3: =SUM(D4:D40) -> 575240.25 | E3: =SUM(E4:E40) -> 413383.32 | F3: =SUM(F4:F40) -> 449879.61 | G3: =SUM(G4:G40) -> 359223.49 | H3: =SUM(H4:H40) -> 510924.17 | I3: =SUM(I4:I40) -> 466534.31 | ... M3: =SUM(M4:M40) -> 656534.52 | N3: =SUM(B3:M3) -> 5875759.7 | O3: =ROUND((N3/$P$2),0) -> 489647 | P3: =N3/$Q$2 -> 0.014162497
A4: Vehicle Four Wheelers Expenses | B4: 76271 | C4: 107695.83 | D4: 125920.58 | E4: 60475 | F4: 57312 | G4: 35815 | H4: 36321 | I4: 85424 | J4: 77960 | K4: 74811.18 | L4: 126808.3 | M4: 67843 | N4: =SUM(B4:M4) -> 932656.89 | O4: =ROUND((N4/$P$2),0) -> 77721 | P4: =IF(N4=0,0,N4/$Q$2) -> 0.0022480072
A5: Installation & Programming Charges | N5: =SUM(B5:M5) -> 0 | O5: =ROUND((N5/$P$2),0) -> 0 | P5: =IF(N5=0,0,N5/$Q$2) -> 0
A6: Arrears of Tax | N6: =SUM(B6:M6) -> 0 | O6: =ROUND((N6/$P$2),0) -> 0 | P6: =IF(N6=0,0,N6/$Q$2) -> 0
A7: Audit Fees | B7: 30000 | C7: 30000 | D7: 30000 | E7: 30000 | F7: 30000 | G7: 30000 | H7: 30000 | I7: 30000 | J7: 30000 | K7: 30000 | L7: 30000 | M7: 30000 | N7: =SUM(B7:M7) -> 360000 | O7: =ROUND((N7/$P$2),0) -> 30000 | P7: =IF(N7=0,0,N7/$Q$2) -> 0.00086771738
A8: Books & Periodical | B8: 320 | C8: 310 | D8: 300 | F8: 600 | I8: 620 | J8: 300 | K8: 300 | M8: 600 | N8: =SUM(B8:M8) -> 3350 | O8: =ROUND((N8/$P$2),0) -> 279 | P8: =IF(N8=0,0,N8/$Q$2) -> 8.0745923e-06
A9: Building Repair & Maintence Exp | N9: =SUM(B9:M9) -> 0 | O9: =ROUND((N9/$P$2),0) -> 0
A10: Computer Stores & Maint. | B10: 43363.14 | C10: 50130 | D10: 41450 | E10: 39574 | F10: 56300 | G10: 101950 | H10: 36000 | I10: 63203.39 | J10: 69003.39 | K10: 30000 | L10: 58759.58 | M10: 31500 | N10: =SUM(B10:M10) -> 621233.5 | O10: =ROUND((N10/$P$2),0) -> 51769 | P10: =IF(N10=0,0,N10/$Q$2) -> 0.0014973753
A11: Conveyance Charges | B11: 4482 | C11: 3552 | D11: 10069 | E11: 8000 | F11: 4232 | G11: 3552 | H11: 3970 | I11: 3741 | J11: 3219 | K11: 3684 | L11: 6300 | M11: 3536 | N11: =SUM(B11:M11) -> 58337 | O11: =ROUND((N11/$P$2),0) -> 4861 | P11: =IF(N11=0,0,N11/$Q$2) -> 0.00014061119
A12: Contract/Consultancy Service Chrgs 18% | N12: =SUM(B12:M12) -> 0 | O12: =ROUND((N12/$P$2),0) -> 0 | P12: =IF(N12=0,0,N12/$Q$2) -> 0
A13: Donation | E13: 8100 | F13: 11000 | K13: 10000 | N13: =SUM(B13:M13) -> 29100 | O13: =ROUND((N13/$P$2),0) -> 2425 | P13: =IF(N13=0,0,N13/$Q$2) -> 7.0140489e-05
A14: General Expenses | B14: 8236.91 | C14: 2499 | D14: 141 | E14: 1711 | F14: 10324 | G14: 986 | H14: 12704.64 | I14: 1322 | J14: 427 | K14: 3014.42 | L14: 2658 | M14: 7282.33 | N14: =SUM(B14:M14) -> 51306.3 | O14: =ROUND((N14/$P$2),0) -> 4276 | P14: =IF(N14=0,0,N14/$Q$2) -> 0.00012366491
A15: General Repairs & Maintanance | B15: 638 | D15: 13999.1 | F15: 1000 | J15: 2386 | K15: 1185 | L15: 3100 | N15: =SUM(B15:M15) -> 22308.1 | O15: =ROUND((N15/$P$2),0) -> 1859 | P15: =IF(N15=0,0,N15/$Q$2) -> 5.3769795e-05
A16: Audit Fees GST | N16: =SUM(B16:M16) -> 0 | O16: =ROUND((N16/$P$2),0) -> 0 | P16: =IF(N16=0,0,N16/$Q$2) -> 0
A17: Income Tax Exps | N17: =SUM(B17:M17) -> 0 | O17: =ROUND((N17/$P$2),0) -> 0 | P17: =IF(N17=0,0,N17/$Q$2) -> 0
A18: Medical Expenses | N18: =SUM(B18:M18) -> 0 | O18: =ROUND((N18/$P$2),0) -> 0 | P18: =IF(N18=0,0,N18/$Q$2) -> 0
A19: Mediclaim Exps | B19: 1200 | N19: =SUM(B19:M19) -> 1200 | O19: =ROUND((N19/$P$2),0) -> 100 | P19: =IF(N19=0,0,N19/$Q$2) -> 2.8923913e-06
A20: Office Maintenance | B20: =1170+850 -> 2020 | L20: 4500 | M20: 2200 | N20: =SUM(B20:M20) -> 8720 | O20: =ROUND((N20/$P$2),0) -> 727 | P20: =IF(N20=0,0,N20/$Q$2) -> 2.1018043e-05
A21: Pooja Expenses | B21: 6390 | C21: 7200 | D21: 6008 | E21: 6655 | F21: 8970 | G21: 6645 | H21: 70890 | I21: 7612 | J21: 5735 | K21: 6575 | L21: 5860 | M21: 8535 | N21: =SUM(B21:M21) -> 147075 | O21: =ROUND((N21/$P$2),0) -> 12256 | P21: =IF(N21=0,0,N21/$Q$2) -> 0.00035449871
A22: Postage,Tel, Telex Charges | B22: =763+14094+1274.4 -> 16131.4 | C22: =446+3711.85 -> 4157.85 | D22: =1471.84+5017.04+3723.7 -> 10212.58 | E22: =1469+8694+3222.7 -> 13385.7 | F22: =184+4084.25 -> 4268.25 | G22: 8142.19 | H22: 8310.5 | I22: 22227.05 | J22: =2910.84+3615.4 -> 6526.24 | K22: 8484.85 | L22: 11311.62 | M22: 13612.64 | N22: =SUM(B22:M22) -> 126770.87 | O22: =ROUND((N22/$P$2),0) -> 10564 | P22: =IF(N22=0,0,N22/$Q$2) -> 0.00030555913
A23: Printing & Stationary | B23: 75852 | C23: 26649 | D23: 37281 | E23: 29103 | F23: 33140 | G23: 26554 | H23: 27180 | I23: 62306 | J23: 25850 | K23: 20379 | L23: 50006 | M23: 12950 | N23: =SUM(B23:M23) -> 427250 | O23: =ROUND((N23/$P$2),0) -> 35604 | P23: =IF(N23=0,0,N23/$Q$2) -> 0.0010298118
A24: Professional Charges | B24: 5500 | C24: 47500 | D24: 5500 | E24: =41500+1500 -> 43000 | F24: 5500 | G24: 17500 | H24: 5500 | I24: 2500 | J24: =8500 -> 8500 | K24: 2500 | L24: 8500 | M24: 167500 | N24: =SUM(B24:M24) -> 319500 | O24: =ROUND((N24/$P$2),0) -> 26625 | P24: =IF(N24=0,0,N24/$Q$2) -> 0.00077009918
A25: Professional Consultation Charges | C25: 1500 | D25: =1500+10000+5000 -> 16500 | F25: =1500+10000 -> 11500 | G25: 1500 | H25: 11500 | I25: 1500 | J25: =1500+10000+75000 -> 86500 | K25: 27221 | L25: 1500 | M25: 90500 | N25: =SUM(B25:M25) -> 249721 | O25: =ROUND((N25/$P$2),0) -> 20810 | P25: =IF(N25=0,0,N25/$Q$2) -> 0.00060190904
A26: Rates & Taxes | B26: 59935 | C26: 54000 | D26: 614 | G26: 500 | I26: 1938 | J26: 1314 | L26: 3178 | M26: 120 | N26: =SUM(B26:M26) -> 121599 | O26: =ROUND((N26/$P$2),0) -> 10133 | P26: =IF(N26=0,0,N26/$Q$2) -> 0.00029309324
A27: Registration & Renewal | B27: 7500 | D27: 5133 | H27: 15060 | L27: 5160 | N27: =SUM(B27:M27) -> 32853 | O27: =ROUND((N27/$P$2),0) -> 2738 | P27: =IF(N27=0,0,N27/$Q$2) -> 7.9186442e-05
A28: Repairs & Service Charges | B28: 2000 | C28: =3000+14000 -> 17000 | G28: 2000 | K28: 2200 | L28: 2000 | N28: =SUM(B28:M28) -> 25200 | O28: =ROUND((N28/$P$2),0) -> 2100
A29: Freight charges | N29: =SUM(B29:M29) -> 0 | O29: =ROUND((N29/$P$2),0) -> 0 | P29: =IF(N29=0,0,N29/$Q$2) -> 0
A30: Round Off (+-) | B30: 6.52 | C30: 5.66 | D30: 14.13 | E30: 14.65 | F30: -3.07 | G30: 1.64 | H30: 3.28 | I30: 7.98 | J30: 7.85 | K30: 7.11 | L30: 15.27 | M30: =91.67+1 -> 92.67 | N30: =SUM(B30:M30) -> 173.69 | O30: =ROUND((N30/$P$2),0) -> 14 | P30: =IF(N30=0,0,N30/$Q$2) -> 4.1864953e-07
A31: Seminar, Training, Dvpt. Exp. | G31: 3540 | N31: =SUM(B31:M31) -> 3540 | O31: =ROUND((N31/$P$2),0) -> 295 | P31: =IF(N31=0,0,N31/$Q$2) -> 8.5325543e-06
A32: Software maintenance | B32: =11852.31+35000 -> 46852.31 | C32: =15000-4675.26 -> 10324.74 | D32: =1368.97+30000+20000 -> 51368.97 | E32: 1368.97 | F32: =2067.97+4500+56000 -> 62567.97 | G32: =47867.97-2999 -> 44868.97 | H32: 16464.97 | I32: 27379.76 | J32: =1368.97+53000 -> 54368.97 | K32: 39011.58 | L32: 87215.58 | M32: 28614.58 | N32: =SUM(B32:M32) -> 470407.37 | O32: =ROUND((N32/$P$2),0) -> 39201 | P32: =IF(N32=0,0,N32/$Q$2) -> 0.0011338351
A33: RCM Freight paid | N33: =SUM(B33:M33) -> 0 | O33: =ROUND((N33/$P$2),0) -> 0 | P33: =IF(N33=0,0,N33/$Q$2) -> 0
A34: Subscription & Membership | B34: 31572 | C34: 13459 | D34: 4609 | E34: 27635.04 | F34: 4609 | G34: 9440.87 | H34: 11121.5 | I34: 15681 | J34: 34452 | K34: 2500 | N34: =SUM(B34:M34) -> 155079.41 | O34: =ROUND((N34/$P$2),0) -> 12923 | P34: =IF(N34=0,0,N34/$Q$2) -> 0.00037379194
A35: TDS - Interest on TDS | N35: =SUM(B35:M35) -> 0 | O35: =ROUND((N35/$P$2),0) -> 0 | P35: =IF(N35=0,0,N35/$Q$2) -> 0
A36: Telephone Charges-Airtel | B36: 6199.72 | C36: 6612.72 | D36: 6609.18 | E36: 6603.28 | F36: 16035.02 | G36: 16639.18 | H36: 15040.28 | I36: 6597.38 | J36: 6648.12 | K36: 6599.74 | L36: 7400.96 | M36: 6780.28 | N36: =SUM(B36:M36) -> 107765.86 | O36: =ROUND((N36/$P$2),0) -> 8980 | P36: =IF(N36=0,0,N36/$Q$2) -> 0.00025975086
A37: Telephone Charges-BSNL | B37: 7710 | C37: 5351 | D37: 6412 | E37: 6416 | F37: 4658 | G37: 4008 | H37: 4008 | I37: 4007 | J37: 4007 | K37: 4008 | L37: 4006 | M37: 4008 | N37: =SUM(B37:M37) -> 58599 | O37: =ROUND((N37/$P$2),0) -> 4883 | P37: =IF(N37=0,0,N37/$Q$2) -> 0.0001412427
A38: Fluctuation In Foreign Currency | N38: =SUM(B38:M38) -> 0 | O38: =ROUND((N38/$P$2),0) -> 0 | P38: =IF(N38=0,0,N38/$Q$2) -> 0
A39: VEHICLE MAINTENANCE | B39: 1560 | C39: 2360 | D39: 10760 | E39: 5050 | F39: 60 | N39: =SUM(B39:M39) -> 19790 | O39: =ROUND((N39/$P$2),0) -> 1649 | P39: =IF(N39=0,0,N39/$Q$2) -> 4.7700353e-05
A40: Watch & Ward | C40: =70000+52883.33 -> 122883.33 | D40: =140000+52338.71 -> 192338.71 | E40: =77000+49291.68 -> 126291.68 | F40: =77000+50806.44 -> 127806.44 | G40: 45580.64 | H40: 206850 | I40: 130467.75 | J40: =77000+53500 -> 130500 | K40: 77000 | L40: 181645.16 | M40: 180860.02 | N40: =SUM(B40:M40) -> 1522223.7 | O40: =ROUND((N40/$P$2),0) -> 126852 | P40: =IF(N40=0,0,N40/$Q$2) -> 0.0036690555
A41: Financial Expenses | B41: =SUM(B42:B51) -> 949852.84 | C41: =SUM(C42:C51) -> 293672.65 | D41: =SUM(D42:D51) -> 1204638.5 | E41: =SUM(E42:E51) -> 641835.97 | F41: =SUM(F42:F51) -> 741787.04 | G41: =SUM(G42:G51) -> 939757.7 | H41: =SUM(H42:H51) -> 764520.87 | I41: =SUM(I42:I51) -> 725611.56 | ... M41: =SUM(M42:M51) -> 784231.14 | N41: =SUM(B41:M41) -> 9817807.2 | O41: =ROUND((N41/$P$2),0) -> 818151 | P41: =N41/Q2 -> 0.023664116
A42: Bank Charges | B42: =263753.8+3000 -> 266753.8 | C42: =225000-532783.57 -> -307783.57 | D42: =270828.88-225000 -> 45828.88 | E42: 1788.88 | F42: =13681.5 -> 13681.5 | G42: =10082.5-7163.18 -> 2919.32 | H42: 8139.44 | I42: 5330.06 | J42: =1787.7+5 -> 1792.7 | K42: 8977.19 | L42: 270825.54 | M42: -40500 | N42: =SUM(B42:M42) -> 277753.74 | O42: =ROUND((N42/$P$2),0) -> 23146 | P42: =IF(N42=0,0,N42/$Q$2) -> 0.00066947708
A43: Interest & Bank Charges -ILC | B43: =70597.29+5500+17080.75 -> 93178.04 | C43: =51332.76+4074.46+12154 -> 67561.22 | D43: =206269.27+1829.9+38752.43 -> 246851.6 | E43: =52394.29+11528.82+15000.98 -> 78924.09 | F43: =155626.21+3590.9+17677.43 -> 176894.54 | G43: =61537.76+6871.28+7002.34 -> 75411.38 | H43: 240037.43 | I43: 160177.5 | J43: =33873+7367.25+19142.72 -> 60382.97 | K43: 269005.98 | L43: 193238.52 | M43: 1360.14 | N43: =SUM(B43:M43) -> 1663023.4 | O43: =ROUND((N43/$P$2),0) -> 138585 | P43: =IF(N43=0,0,N43/$Q$2) -> 0.0040084287
A44: Interest on Unsecured Loans (Monthly) | B44: 97333 | C44: 97333 | D44: 97333 | E44: 97333 | F44: 97333 | G44: 95333 | H44: 93618 | I44: 93224 | J44: 89410 | K44: 88051 | L44: 86254 | M44: 82012 | N44: =SUM(B44:M44) -> 1114567 | O44: =ROUND((N44/$P$2),0) -> 92881 | P44: =IF(N44=0,0,N44/$Q$2) -> 0.0026864699
A45: Interest on Car Loans | N45: =SUM(B45:M45) -> 0 | O45: =ROUND((N45/$P$2),0) -> 0 | P45: =IF(N45=0,0,N45/$Q$2) -> 0
A46: Interest on O.C.C | B46: 492588 | C46: 436562 | D46: 457625 | E46: 452620 | F46: 439686 | G46: 395256 | H46: 409245 | I46: 453758 | J46: 422762 | K46: 439150 | L46: 447870 | M46: 372704 | N46: =SUM(B46:M46) -> 5219826 | O46: =ROUND((N46/$P$2),0) -> 434986 | P46: =IF(N46=0,0,N46/$Q$2) -> 0.012581483
A47: Interest on PNB Housing Finance | N47: =SUM(B47:M47) -> 0 | O47: =ROUND((N47/$P$2),0) -> 0 | P47: =IF(N47=0,0,N47/$Q$2) -> 0
A48: Interest On Term Loan | N48: =SUM(B48:M48) -> 0 | O48: =ROUND((N48/$P$2),0) -> 0 | P48: =IF(N48=0,0,N48/$Q$2) -> 0
A49: Loan Processing charges | N49: =SUM(B49:M49) -> 0 | O49: =ROUND((N49/$P$2),0) -> 0 | P49: =IF(N49=0,0,N49/$Q$2) -> 0
A50: Interest to others (VSL) | E50: 11170 | F50: 14192 | G50: 13838 | H50: 13481 | I50: 13122 | J50: 12759 | K50: 12394 | L50: 12026 | M50: 11655 | N50: =SUM(B50:M50) -> 114637 | O50: =ROUND((N50/$P$2),0) -> 9553 | P50: =IF(N50=0,0,N50/$Q$2) -> 0.00027631255
A51: Interest to Depositors | D51: 357000 | G51: 357000 | J51: 357000 | M51: 357000 | N51: =SUM(B51:M51) -> 1428000 | O51: =ROUND((N51/$P$2),0) -> 119000 | P51: =IF(N51=0,0,N51/$Q$2) -> 0.0034419456
A52: Selling Expenses | B52: =SUM(B53:B64) -> 32614.21 | C52: =SUM(C53:C64) -> 61101.17 | D52: =SUM(D53:D64) -> 327067.65 | E52: =SUM(E53:E64) -> 62212.6 | F52: =SUM(F53:F64) -> 117848 | G52: =SUM(G53:G64) -> 58017.23 | H52: =SUM(H53:H64) -> 36302.25 | I52: =SUM(I53:I64) -> 269668.75 | ... M52: =SUM(M53:M64) -> 109039.18 | N52: =SUM(B52:M52) -> 1650736.2 | O52: =ROUND((N52/$P$2),0) -> 137561 | P52: =N52/Q2 -> 0.0039788125
A53: Advertisement | E53: 26000 | N53: =SUM(B53:M53) -> 26000 | O53: =ROUND((N53/$P$2),0) -> 2167 | P53: =IF(N53=0,0,N53/$Q$2) -> 6.2668478e-05
A54: Lab Testing Charges | E54: 2150 | F54: 750 | N54: =SUM(B54:M54) -> 2900 | O54: =ROUND((N54/$P$2),0) -> 242 | P54: =IF(N54=0,0,N54/$Q$2) -> 6.9899456e-06
A55: Commission on sales | C55: 50800 | D55: 22650 | J55: 12000 | L55: 3450 | M55: 38400 | N55: =SUM(B55:M55) -> 127300 | O55: =ROUND((N55/$P$2),0) -> 10608 | P55: =IF(N55=0,0,N55/$Q$2) -> 0.00030683451
A56: Debit Balances Written Off | B56: 3.21 | C56: 8.17 | D56: 27.65 | E56: 4.6 | F56: 17 | G56: 86.23 | H56: 0.25 | I56: 41000.25 | J56: 0.95 | K56: 10.25 | L56: 0.48 | M56: 4757.18 | N56: =SUM(B56:M56) -> 45916.22 | O56: =ROUND((N56/$P$2),0) -> 3826 | P56: =IF(N56=0,0,N56/$Q$2) -> 0.00011067306
A57: Freight Outwards/Ocean Freight | B57: 17000 | D57: =24000+38100 -> 62100 | E57: 17000 | F57: =62450+32000 -> 94450 | G57: 36700 | J57: =900+737.48+124400+37800 -> 163837.48 | K57: =74200+2304 -> 76504 | L57: 70847 | M57: 6664 | N57: =SUM(B57:M57) -> 545102.48 | O57: =ROUND((N57/$P$2),0) -> 45425 | P57: =IF(N57=0,0,N57/$Q$2) -> 0.0013138747
A58: Gift Articles | N58: =SUM(B58:M58) -> 0 | O58: =ROUND((N58/$P$2),0) -> 0 | P58: =IF(N58=0,0,N58/$Q$2) -> 0
A59: Marketing Expenses | C59: 736 | I59: 7294 | L59: 6000 | N59: =SUM(B59:M59) -> 14030 | O59: =ROUND((N59/$P$2),0) -> 1169 | P59: =IF(N59=0,0,N59/$Q$2) -> 3.3816875e-05
A60: Sales Promotion | I60: 110910.5 | L60: 150000 | N60: =SUM(B60:M60) -> 260910.5 | O60: =ROUND((N60/$P$2),0) -> 21743 | P60: =IF(N60=0,0,N60/$Q$2) -> 0.00062887938
A61: Transportation charges | B61: 15611 | C61: 9873 | D61: 55247 | E61: 17058 | F61: 22631 | G61: 6231 | H61: 16364 | I61: 22238 | J61: 15716 | K61: =26413-652-652 -> 25109 | L61: -610 | M61: 12763 | N61: =SUM(B61:M61) -> 218231 | O61: =ROUND((N61/$P$2),0) -> 18186 | P61: =IF(N61=0,0,N61/$Q$2) -> 0.00052600787
A62: Travelling Expenses | D62: 6493 | G62: 15000 | H62: 19938 | I62: 87754 | N62: =SUM(B62:M62) -> 129185 | O62: =ROUND((N62/$P$2),0) -> 10765 | P62: =IF(N62=0,0,N62/$Q$2) -> 0.00031137797
A63: Discount Allowed | D63: 181000 | I63: 472 | N63: =SUM(B63:M63) -> 181472 | O63: =ROUND((N63/$P$2),0) -> 15123 | P63: =IF(N63=0,0,N63/$Q$2) -> 0.00043740669 | Q63: =N63-P63 -> 181472
A64: Discount | C64: -316 | D64: -450 | K64: 54000 | M64: 46455 | N64: =SUM(B64:M64) -> 99689 | O64: =ROUND((N64/$P$2),0) -> 8307 | P64: =IF(N64=0,0,N64/$Q$2) -> 0.000240283
A65: Grand Total | B65: =SUM(B52+B41+B3) -> 1416207.1 | C65: =SUM(C52+C41+C3) -> 867963.95 | D65: =SUM(D52+D41+D3) -> 2106946.4 | E65: =SUM(E52+E41+E3) -> 1117431.9 | F65: =SUM(F52+F41+F3) -> 1309514.6 | G65: =SUM(G52+G41+G3) -> 1356998.4 | H65: =SUM(H52+H41+H3) -> 1311747.3 | I65: =SUM(I52+I41+I3) -> 1461814.6 | ... O65: =SUM(O52+O41+O3) -> 1445359 | P65: =IF(N65=0,0,N65/$Q$2) -> 0.041805426
P66: =IF(N66=0,0,N66/$Q$2) -> 0
A67: Admn | B67: =ROUND((B3),0) -> 433740 | C67: =ROUND((C3),0) -> 513190 | D67: =ROUND((D3),0) -> 575240 | E67: =ROUND((E3),0) -> 413383 | F67: =ROUND((F3),0) -> 449880 | G67: =ROUND((G3),0) -> 359223 | H67: =ROUND((H3),0) -> 510924 | I67: =ROUND((I3),0) -> 466534 | ... O67: =ROUND((O3),0) -> 489647 | P67: =N67/Q2 -> 0.014162497
A68: =A52 -> Selling Expenses | B68: =ROUND((B52),0) -> 32614 | C68: =ROUND((C52),0) -> 61101 | D68: =ROUND((D52),0) -> 327068 | E68: =ROUND((E52),0) -> 62213 | F68: =ROUND((F52),0) -> 117848 | G68: =ROUND((G52),0) -> 58017 | H68: =ROUND((H52),0) -> 36302 | I68: =ROUND((I52),0) -> 269669 | ... N68: =ROUND((N52),0) -> 1650736 | O68: =O52 -> 137561 | P68: =N68/Q2 -> 0.003978812 | Q68: =Q42 -> 0 | R68: =R42 -> 0 | AG68: =AG42 -> 0 | AH68: =AH42 -> 0 | AI68: =AI42 -> 0 | AJ68: =AJ42 -> 0 | AK68: =AK42 -> 0 | AL68: =AL42 -> 0 | AM68: =AM42 -> 0 | AN68: =AN42 -> 0 | ... IV68: =IV42 -> 0
A69: Indirect W/o Fin | B69: =B67+B68 -> 466354 | C69: =C67+C68 -> 574291 | D69: =D67+D68 -> 902308 | E69: =E67+E68 -> 475596 | F69: =F67+F68 -> 567728 | G69: =G67+G68 -> 417240 | H69: =H67+H68 -> 547226 | I69: =I67+I68 -> 736203 | ... N69: =N67+N68 -> 7526496 | O69: =O41 -> 818151 | P69: =N69/Q2 -> 0.018141309 | Q69: =Q45 -> 0 | R69: =R45 -> 0 | AG69: =AG45 -> 0 | AH69: =AH45 -> 0 | AI69: =AI45 -> 0 | AJ69: =AJ45 -> 0 | AK69: =AK45 -> 0 | AL69: =AL45 -> 0 | AM69: =AM45 -> 0 | AN69: =AN45 -> 0 | ... IV69: =IV45 -> 0
A70: W Cap Int | B70: =ROUND((B42+B43+B46),0) -> 852520 | C70: =ROUND((C42+C43+C46),0) -> 196340 | D70: =ROUND((D42+D43+D46),0) -> 750305 | E70: =ROUND((E42+E43+E46),0) -> 533333 | F70: =ROUND((F42+F43+F46),0) -> 630262 | G70: =ROUND((G42+G43+G46),0) -> 473587 | H70: =ROUND((H42+H43+H46),0) -> 657422 | I70: =ROUND((I42+I43+I46),0) -> 619266 | ... K70: =ROUND((K42+K43+K46),0) -> 717133 | L70: =ROUND((L42+L43+L46),0)+L49 -> 911934 | M70: =ROUND((M42+M43+M46),0) -> 333564 | N70: =ROUND((N42+N43+N46),0) -> 7160603 | O70: =ROUND((O42+O43+O46),0) -> 596717 | P70: =N70/Q2 -> 0.017259388 | S70: =S44 -> 0 | T70: =T44 -> 0 | U70: =U44 -> 0 | V70: =V44 -> 0 | W70: =W44 -> 0 | X70: =X44 -> 0 | Y70: =Y44 -> 0 | Z70: =Z44 -> 0 | ... AF70: =AF44 -> 0
A71: Term Loan | B71: =ROUND((B45),0) -> 0 | C71: =ROUND((C45),0) -> 0 | D71: =D49 -> 0 | E71: 0 | F71: =ROUND((F45),0) -> 0 | G71: =ROUND((G45),0) -> 0 | H71: =ROUND((H45),0) -> 0 | I71: =ROUND((I45),0) -> 0 | J71: =ROUND((J45),0) -> 0 | K71: =ROUND((K45),0) -> 0 | L71: =ROUND((L45),0) -> 0 | M71: =ROUND((M45),0) -> 0 | N71: =N49 -> 0 | O71: =ROUND((O45),0) -> 0 | P71: =N71/Q2 -> 0 | S71: =S47 -> 0 | T71: =T47 -> 0 | U71: =U47 -> 0 | V71: =V47 -> 0 | W71: =W47 -> 0 | X71: =X47 -> 0 | Y71: =Y47 -> 0 | Z71: =Z47 -> 0 | ... AF71: =AF47 -> 0
A72: COVID LOAN Int | B72: =ROUND((B48),0) -> 0 | C72: =ROUND((C48),0) -> 0 | D72: =ROUND((D48),0) -> 0 | E72: =ROUND((E48),0) -> 0 | F72: =ROUND((F48),0) -> 0 | G72: =ROUND((G48),0) -> 0 | H72: 0 | I72: =ROUND((I48),0) -> 0 | J72: =ROUND((J48),0) -> 0 | K72: =ROUND((K48),0) -> 0 | L72: =ROUND((L48),0) -> 0 | M72: =ROUND((M48),0) -> 0 | N72: =ROUND((N48),0) -> 0 | O72: =ROUND((O48),0) -> 0 | P72: =N72/Q2 -> 0
A73: Int On Others | B73: =ROUND((B44+B50+B51),0) -> 97333 | C73: =ROUND((C44+C50+C51),0) -> 97333 | D73: =ROUND((D44+D50+D51),0) -> 454333 | E73: =ROUND((E44+E50+E51),0) -> 108503 | F73: =ROUND((F44+F50+F51),0) -> 111525 | G73: =ROUND((G44+G50+G51),0) -> 466171 | H73: =ROUND((H44+H50+H51),0) -> 107099 | I73: =ROUND((I44+I50+I51),0) -> 106346 | ... O73: =ROUND((O44+O50+O51),0) -> 221434 | P73: =N73/Q2 -> 0.0064047281
A74: FIN Cost | B74: =SUM(B70:B73) -> 949853 | C74: =SUM(C70:C73) -> 293673 | D74: =SUM(D70:D73) -> 1204638 | E74: =SUM(E70:E73) -> 641836 | F74: =SUM(F70:F73) -> 741787 | G74: =SUM(G70:G73) -> 939758 | H74: =SUM(H70:H73) -> 764521 | I74: =SUM(I70:I73) -> 725612 | ... O74: =SUM(O70:O73) -> 818151 | P74: =N74/Q2 -> 0.023664116
A75: Indirect COST | B75: =B69+B74 -> 1416207 | C75: =C69+C74 -> 867964 | D75: =D69+D74 -> 2106946 | E75: =E69+E74 -> 1117432 | F75: =F69+F74 -> 1309515 | G75: =G69+G74 -> 1356998 | H75: =H69+H74 -> 1311747 | I75: =I69+I74 -> 1461815 | ... O75: =O69+O74 -> 1636302 | P75: =N75/Q2 -> 0.041805426
D76: =D65-D75 -> 0.38 | J76: =J65-J75 -> -0.33 | K76: =K65-K75 -> 0.3 | L76: =L65-L75 -> 1.01 | M76: =M65-M75 -> -0.16
A78: P/L | B78: ='P&L'!B36 -> 1416207.1 | C78: ='P&L'!C36 -> 867963.95 | D78: ='P&L'!D36 -> 2106946.4 | E78: ='P&L'!E36 -> 1117431.9 | F78: ='P&L'!F36 -> 1309514.6 | G78: ='P&L'!G36 -> 1341998.4 | H78: ='P&L'!H36 -> 1311748.3 | I78: ='P&L'!I36 -> 1579915.6 | ... N78: ='P&L'!N36 -> 17344302
B79: =B65-B78 -> 0 | C79: =C65-C78 -> 0 | D79: =D65-D78 -> 0 | E79: =E65-E78 -> 0 | F79: =F65-F78 -> 0 | G79: =G65-G78 -> 15000 | H79: =H65-H78 -> -1.01 | I79: =I65-I78 -> -118101 | ... N79: =N65-N78 -> 0.89

Sheet CONSUMPTION
A1: Quantitative Analysis of Raw Materials for the Financial Year 2025-26
A2: Particulars | B2: 45748 | E2: 45778 | H2: 45809 | K2: 45474 | N2: 45870 | Q2: 45901 | T2: 45931 | W2: 45962 | Z2: 45992 | AC2: 45658 | AF2: 45689 | AI2: 45717 | AL2: Total | AO2: Srp
A3: HDPE
A4: Opening Stock | B4: ='Stock Valuation (FIFO)'!B5 -> 195845 | C4: =IF(B4=0,0,(D4/B4)) -> 100.68931 | D4: ='Stock Valuation (FIFO)'!D5 -> 19719497 | E4: =B9 -> 180315 | F4: =IF(E4=0,0,(G4/E4)) -> 99.600743 | G4: =D9 -> 17959508 | H4: =E9 -> 147410 | I4: =IF(H4=0,0,(J4/H4)) -> 97.488915 | J4: =G9 -> 14370841 | K4: =H9 -> 164125 | L4: =IF(K4=0,0,(M4/K4)) -> 97.338395 | M4: =J9 -> 15975664 | N4: =K9 -> 146140 | O4: =IF(N4=0,0,(P4/N4)) -> 99.437929 | P4: =M9 -> 14531859 | Q4: =N9 -> 187620 | R4: =IF(Q4=0,0,(S4/Q4)) -> 101.20382 | S4: =P9 -> 18987861 | T4: =Q9 -> 114680 | U4: =IF(T4=0,0,(V4/T4)) -> 100.40339 | V4: =S9 -> 11514261 | W4: =T9 -> 139725 | X4: =IF(W4=0,0,(Y4/W4)) -> 98.732253 | Y4: =V9 -> 13795364 | Z4: =W9 -> 164310 | AA4: =IF(Z4=0,0,(AB4/Z4)) -> 97.311454 | AB4: =Y9 -> 15989245 | AC4: =Z9 -> 135475 | AD4: =IF(AC4=0,0,(AE4/AC4)) -> 96.066846 | AE4: =AB9 -> 13014656 | AF4: =AC9 -> 174670 | AG4: =IF(AF4=0,0,(AH4/AF4)) -> 98.956106 | AH4: =AE9 -> 17284663 | AI4: =AF9 -> 154290 | AJ4: =IF(AI4=0,0,(AK4/AI4)) -> 103.4773 | AK4: =AH9 -> 15965513 | AL4: =B4 -> 195845 | AM4: =IF(AL4=0,0,(AN4/AL4)) -> 100.68931 | AN4: =D4 -> 19719497
A5: Add:- Purchases | B5: =ROUND((Purchase!$B5),0) -> 101000 | C5: =IF(B5=0,0,(D5/B5)) -> 90.762317 | D5: =ROUND((Purchase!$C5-Purchase!$N5),0) -> 9166994 | E5: =ROUND((Purchase!$B6),0) -> 57000 | F5: =IF(E5=0,0,(G5/E5)) -> 91.131684 | G5: =ROUND((Purchase!$C6-Purchase!$N6),0) -> 5194506 | H5: =Purchase!B7 -> 151000 | I5: =IF(H5=0,0,(J5/H5)) -> 96.513298 | J5: =Purchase!C7-Purchase!N7 -> 14573508 | K5: =Purchase!B8 -> 137000 | L5: =IF(K5=0,0,(M5/K5)) -> 92.022445 | M5: =Purchase!C8-Purchase!N8 -> 12607075 | N5: =Purchase!B9 -> 174000 | O5: =IF(N5=0,0,(P5/N5)) -> 100.24187 | P5: =Purchase!C9-Purchase!N9 -> 17442085 | Q5: =Purchase!B10 -> 37000 | R5: =IF(Q5=0,0,(S5/Q5)) -> 81.669865 | S5: =Purchase!C10-Purchase!N10 -> 3021785 | T5: =Purchase!B11 -> 128000 | U5: =IF(T5=0,0,(V5/T5)) -> 96.479586 | V5: =Purchase!C11-Purchase!N11 -> 12349387 | W5: =Purchase!B12 -> 120000 | X5: =IF(W5=0,0,(Y5/W5)) -> 90.824375 | Y5: =ROUND((Purchase!C12-Purchase!N12),0) -> 10898925 | Z5: =Purchase!B13 -> 106000 | AA5: =IF(Z5=0,0,(AB5/Z5)) -> 90.161755 | AB5: =Purchase!C13-Purchase!N13 -> 9557146 | AC5: =Purchase!B14 -> 169000 | AD5: =IF(AC5=0,0,(AE5/AC5)) -> 97.049651 | AE5: =ROUND((Purchase!C14-Purchase!N14),0) -> 16401391 | AF5: =Purchase!B15 -> 116000 | AG5: =IF(AF5=0,0,(AH5/AF5)) -> 99.38925 | AH5: =Purchase!C15-Purchase!N15 -> 11529153 | AI5: =Purchase!B16 -> 98000 | AJ5: =IF(AI5=0,0,(AK5/AI5)) -> 126.70614 | AK5: =Purchase!C16-Purchase!N16 -> 12417202 | AL5: =SUM(B5,E5,H5,K5,N5,Q5,T5,W5,Z5,AC5,AF5,AI5) -> 1394000 | AM5: =IF(AL5=0,0,(AN5/AL5)) -> 96.957788 | AN5: =SUM(D5,G5,J5,M5,P5,S5,V5,Y5,AB5,AE5,AH5,AK5) -> 1.3515916e+08 | AO5: =ROUND((Purchase!C17-Purchase!N17),0) -> 135159157 | AP5: =AN5-AO5 -> 0.020000011
A6: Add:- Consumables | C6: =IF(B6=0,0,(D6/B6)) -> 0 | AL6: =SUM(B6:AI6) -> 0
A7: Less:- Purchase return | C7: =IF(B7=0,0,(D7/B7)) -> 0 | AL7: =SUM(B7:AI7) -> 0
A8: Less :- Sales | B8: ='Inventory Sales'!B25 -> 40000 | C8: =IF(B8=0,0,(D8/B8)) -> 93.342375 | D8: ='Inventory Sales'!D42-(D16+D24) -> 3733695 | E8: ='Inventory Sales'!E25 -> 14000 | F8: =IF(E8=0,0,(G8/E8)) -> 98.772857 | G8: ='Inventory Sales'!G42-(G16+G24) -> 1382820 | H8: ='Inventory Sales'!H25 -> 51000 | I8: =IF(H8=0,0,(J8/H8)) -> 92.166863 | J8: ='Inventory Sales'!J42-(J16+J24) -> 4700510 | K8: ='Inventory Sales'!K25 -> 55000 | L8: =IF(K8=0,0,(M8/K8)) -> 93.342545 | M8: ='Inventory Sales'!M42-(M16+M24) -> 5133840 | N8: ='Inventory Sales'!N25 -> 58000 | O8: =IF(N8=0,0,(P8/N8)) -> 93.539828 | P8: ='Inventory Sales'!P42-(P16+P24) -> 5425310 | Q8: ='Inventory Sales'!Q25 -> 31000 | R8: =IF(Q8=0,0,(S8/Q8)) -> 94.465484 | S8: ='Inventory Sales'!S42-(S16+S24) -> 2928430 | T8: ='Inventory Sales'!T25 -> 24000 | U8: =IF(T8=0,0,(V8/T8)) -> 96.036667 | V8: ='Inventory Sales'!V42-(V16+V24) -> 2304880 | W8: ='Inventory Sales'!W25 -> 15000 | X8: =IF(W8=0,0,(Y8/W8)) -> 87.683333 | Y8: ='Inventory Sales'!Y42-(Y16+Y24) -> 1315250 | Z8: ='Inventory Sales'!Z25 -> 31000 | AA8: =IF(Z8=0,0,(AB8/Z8)) -> 92.601613 | AB8: ='Inventory Sales'!AB42-(AB16+AB24) -> 2870650 | AC8: ='Inventory Sales'!AC25 -> 38000 | AD8: =IF(AC8=0,0,(AE8/AC8)) -> 93.632105 | AE8: ='Inventory Sales'!AE42-(AE16+AE24) -> 3558020 | AF8: ='Inventory Sales'!AF25 -> 37000 | AG8: =IF(AF8=0,0,(AH8/AF8)) -> 94.21027 | AH8: ='Inventory Sales'!AH42-(AH16+AH24) -> 3485780 | AI8: ='Inventory Sales'!AI25 -> 25000 | AJ8: =IF(AI8=0,0,(AK8/AI8)) -> 102.8304 | AK8: ='Inventory Sales'!AK42-(AK16+AK24) -> 2570760 | AL8: =SUM(B8,E8,H8,K8,N8,Q8,T8,W8,Z8,AC8,AF8,AI8) -> 419000 | AM8: =IF(AL8=0,0,(AN8/AL8)) -> 94.057148 | AN8: =SUM(D8,G8,J8,M8,P8,S8,V8,Y8,AB8,AE8,AH8,AK8) -> 39409945 | AO8: ='Inventory Sales'!AN42 -> 40189410 | AP8: =AN8-AO8 -> -779465
A9: Closing Stock | B9: ='Stock Valuation (FIFO)'!E5 -> 180315 | C9: =IF(B9=0,0,(D9/B9)) -> 99.600743 | D9: ='Stock Valuation (FIFO)'!G5 -> 17959508 | E9: ='Stock Valuation (FIFO)'!H5 -> 147410 | F9: =IF(E9=0,0,(G9/E9)) -> 97.488915 | G9: ='Stock Valuation (FIFO)'!J5 -> 14370841 | H9: ='Stock Valuation (FIFO)'!K5 -> 164125 | I9: =IF(H9=0,0,(J9/H9)) -> 97.338395 | J9: ='Stock Valuation (FIFO)'!M5 -> 15975664 | K9: ='Stock Valuation (FIFO)'!N5 -> 146140 | L9: =IF(K9=0,0,(M9/K9)) -> 99.437929 | M9: ='Stock Valuation (FIFO)'!P5 -> 14531859 | N9: ='Stock Valuation (FIFO)'!Q5 -> 187620 | O9: =IF(N9=0,0,(P9/N9)) -> 101.20382 | P9: ='Stock Valuation (FIFO)'!S5 -> 18987861 | Q9: ='Stock Valuation (FIFO)'!T5 -> 114680 | R9: =IF(Q9=0,0,(S9/Q9)) -> 100.40339 | S9: ='Stock Valuation (FIFO)'!V5 -> 11514261 | T9: ='Stock Valuation (FIFO)'!W5 -> 139725 | U9: =IF(T9=0,0,(V9/T9)) -> 98.732253 | V9: ='Stock Valuation (FIFO)'!Y5 -> 13795364 | W9: ='Stock Valuation (FIFO)'!Z5 -> 164310 | X9: =IF(W9=0,0,(Y9/W9)) -> 97.311454 | Y9: ='Stock Valuation (FIFO)'!AB5 -> 15989245 | Z9: ='Stock Valuation (FIFO)'!AC5 -> 135475 | AA9: =IF(Z9=0,0,(AB9/Z9)) -> 96.066846 | AB9: ='Stock Valuation (FIFO)'!AE5 -> 13014656 | AC9: ='Stock Valuation (FIFO)'!AF5 -> 174670 | AD9: =IF(AC9=0,0,(AE9/AC9)) -> 98.956106 | AE9: ='Stock Valuation (FIFO)'!AH5 -> 17284663 | AF9: ='Stock Valuation (FIFO)'!AI5 -> 154290 | AG9: =IF(AF9=0,0,(AH9/AF9)) -> 103.4773 | AH9: ='Stock Valuation (FIFO)'!AK5 -> 15965513 | AI9: ='Stock Valuation (FIFO)'!AL5 -> 141140 | AJ9: =IF(AI9=0,0,(AK9/AI9)) -> 121.97507 | AK9: ='Stock Valuation (FIFO)'!AN5 -> 17215561 | AL9: =AI9 -> 141140 | AM9: =IF(AL9=0,0,(AN9/AL9)) -> 121.97507 | AN9: =AK9 -> 17215561 | AO9: ='Stock Valuation (FIFO)'!AB5 -> 15989245 | AP9: =AN9-AO9 -> 1226316
A10: Consumption HDPE | B10: =(B4+B5+B6)-(B8+B9) -> 76530 | C10: =IF(B10=0,0,(D10/B10)) -> 93.993048 | D10: =(D4+D5)-(D8+D9) -> 7193288 | E10: =(E4+E5)-(E8+E9) -> 75905 | F10: =IF(E10=0,0,(G10/E10)) -> 97.494934 | G10: =(G4+G5)-(G8+G9) -> 7400353 | H10: =(H4+H5)-(H8+H9) -> 83285 | I10: =IF(H10=0,0,(J10/H10)) -> 99.27568 | J10: =(J4+J5)-(J8+J9) -> 8268175 | K10: =(K4+K5)-(K8+K9) -> 99985 | L10: =IF(K10=0,0,(M10/K10)) -> 89.183778 | M10: =(M4+M5)-(M8+M9) -> 8917040 | N10: =(N4+N5)-(N8+N9) -> 74520 | O10: =IF(N10=0,0,(P10/N10)) -> 101.45965 | P10: =(P4+P5)-(P8+P9) -> 7560773 | Q10: =(Q4+Q5)-(Q8+Q9) -> 78940 | R10: =IF(Q10=0,0,(S10/Q10)) -> 95.857043 | S10: =(S4+S5)-(S8+S9) -> 7566955 | T10: =(T4+T5)-(T8+T9) -> 78955 | U10: =IF(T10=0,0,(V10/T10)) -> 98.326946 | V10: =(V4+V5)-(V8+V9) -> 7763404 | W10: =(W4+W5)-(W8+W9) -> 80415 | X10: =IF(W10=0,0,(Y10/W10)) -> 91.895716 | Y10: =(Y4+Y5)-(Y8+Y9) -> 7389794 | Z10: =(Z4+Z5)-(Z8+Z9) -> 103835 | AA10: =IF(Z10=0,0,(AB10/Z10)) -> 93.042664 | AB10: =(AB4+AB5)-(AB8+AB9) -> 9661085 | AC10: =(AC4+AC5)-(AC8+AC9) -> 91805 | AD10: =IF(AC10=0,0,(AE10/AC10)) -> 93.386678 | AE10: =(AE4+AE5)-(AE8+AE9) -> 8573364 | AF10: =(AF4+AF5)-(AF8+AF9) -> 99380 | AG10: =IF(AF10=0,0,(AH10/AF10)) -> 94.209328 | AH10: =(AH4+AH5)-(AH8+AH9) -> 9362523 | AI10: =(AI4+AI5)-(AI8+AI9) -> 86150 | AJ10: =IF(AI10=0,0,(AK10/AI10)) -> 99.784028 | AK10: =(AK4+AK5)-(AK8+AK9) -> 8596394 | AL10: =(AL4+AL5)-(AL8+AL9) -> 1029705 | AM10: =IF(AL10=0,0,(AN10/AL10)) -> 95.418735 | AN10: =(AN4+AN5)-(AN8+AN9) -> 98253148
A11: MB
A12: Opening Stock | B12: ='Stock Valuation (FIFO)'!B6 -> 1664 | C12: =IF(B12=0,0,(D12/B12)) -> 223.625 | D12: ='Stock Valuation (FIFO)'!D6 -> 372112 | E12: =B17 -> 2120 | F12: =IF(E12=0,0,(G12/E12)) -> 227.3434 | G12: =D17 -> 481968 | H12: =E17 -> 2294 | I12: =IF(H12=0,0,(J12/H12)) -> 249.52964 | J12: =G17 -> 572421 | K12: =H17 -> 2613 | L12: =IF(K12=0,0,(M12/K12)) -> 236.99732 | M12: =J17 -> 619274 | N12: =K17 -> 2769 | O12: =IF(N12=0,0,(P12/N12)) -> 264.36114 | P12: =M17 -> 732016 | Q12: =N17 -> 3082 | R12: =IF(Q12=0,0,(S12/Q12)) -> 263.87897 | S12: =P17 -> 813275 | T12: =Q17 -> 2819 | U12: =IF(T12=0,0,(V12/T12)) -> 256.02838 | V12: =S17 -> 721744 | W12: =T17 -> 2895 | X12: =IF(W12=0,0,(Y12/W12)) -> 236.59896 | Y12: =V17 -> 684954 | Z12: =W17 -> 2396 | AA12: =IF(Z12=0,0,(AB12/Z12)) -> 227.95659 | AB12: =Y17 -> 546184 | AC12: =Z17 -> 2395 | AD12: =IF(AC12=0,0,(AE12/AC12)) -> 237.1666 | AE12: =AB17 -> 568014 | AF12: =AC17 -> 2511 | AG12: =IF(AF12=0,0,(AH12/AF12)) -> 241.37634 | AH12: =AE17 -> 606096 | AI12: =AF17 -> 3260 | AJ12: =IF(AI12=0,0,(AK12/AI12)) -> 233.5911 | AK12: =AH17 -> 761507 | AL12: =B12 -> 1664 | AM12: =IF(AL12=0,0,(AN12/AL12)) -> 223.625 | AN12: =D12 -> 372112
A13: Add:- Purchases | B13: =ROUND((Purchase!$E5),0) -> 1522 | C13: =IF(B13=0,0,(D13/B13)) -> 234.86071 | D13: =ROUND((Purchase!$F5),0) -> 357458 | E13: =ROUND((Purchase!$E6),) -> 1174 | F13: =IF(E13=0,0,(G13/E13)) -> 255.94549 | G13: =ROUND((Purchase!$F6),0) -> 300480 | H13: =ROUND((Purchase!$E7),0) -> 1664 | I13: =IF(H13=0,0,(J13/H13)) -> 235.35998 | J13: =ROUND((Purchase!$F7),0) -> 391639 | K13: =ROUND((Purchase!$E8),0) -> 1650 | L13: =IF(K13=0,0,(M13/K13)) -> 261.66667 | M13: =ROUND((Purchase!$F8),0) -> 431750 | N13: =ROUND((Purchase!$E9),0) -> 1596 | O13: =IF(N13=0,0,(P13/N13)) -> 263.33083 | P13: =ROUND((Purchase!$F9),0) -> 420276 | Q13: =ROUND((Purchase!$E10),0) -> 844 | R13: =IF(Q13=0,0,(S13/Q13)) -> 229.95735 | S13: =ROUND((Purchase!$F10),0) -> 194084 | T13: =ROUND((Purchase!$E11),0) -> 1196 | U13: =IF(T13=0,0,(V13/T13)) -> 226.0393 | V13: =ROUND((Purchase!$F11),0) -> 270343 | W13: =ROUND((Purchase!$E12),0) -> 945 | X13: =IF(W13=0,0,(Y13/W13)) -> 227.20847 | Y13: =ROUND((Purchase!$F12),) -> 214712 | Z13: =ROUND((Purchase!E13),0) -> 1572 | AA13: =IF(Z13=0,0,(AB13/Z13)) -> 239.73855 | AB13: =ROUND((Purchase!F13),0) -> 376869 | AC13: =ROUND((Purchase!E14),0) -> 1449 | AD13: =IF(AC13=0,0,(AE13/AC13)) -> 233.64458 | AE13: =ROUND((Purchase!F14),0) -> 338551 | AF13: =ROUND((Purchase!E15),0) -> 1871 | AG13: =IF(AF13=0,0,(AH13/AF13)) -> 233.01871 | AH13: =ROUND((Purchase!F15),0) -> 435978 | AI13: =Purchase!E16 -> 0 | AJ13: =IF(AI13=0,0,(AK13/AI13)) -> 0 | AK13: =ROUND((Purchase!F16),0) -> 0 | AL13: =SUM(B13,E13,H13,K13,N13,Q13,T13,W13,Z13,AC13,AF13,AI13) -> 15483 | AM13: =IF(AL13=0,0,(AN13/AL13)) -> 241.0476 | AN13: =SUM(D13,G13,J13,M13,P13,S13,V13,Y13,AB13,AE13,AH13,AK13) -> 3732140 | AO13: =ROUND((Purchase!F17),0) -> 3732141 | AP13: =AN13-AO13 -> -1
A14: Add:- Job Work Rcpts | C14: =IF(B14=0,0,(D14/B14)) -> 0 | F14: =IF(E14=0,0,(G14/E14)) -> 0 | I14: =IF(H14=0,0,(J14/H14)) -> 0 | L14: =IF(K14=0,0,(M14/K14)) -> 0 | O14: =IF(N14=0,0,(P14/N14)) -> 0 | R14: =IF(Q14=0,0,(S14/Q14)) -> 0 | U14: =IF(T14=0,0,(V14/T14)) -> 0 | X14: =IF(W14=0,0,(Y14/W14)) -> 0 | AA14: =IF(Z14=0,0,(AB14/Z14)) -> 0 | AD14: =IF(AC14=0,0,(AE14/AC14)) -> 0 | AG14: =IF(AF14=0,0,(AH14/AF14)) -> 0 | AJ14: =IF(AI14=0,0,(AK14/AI14)) -> 0 | AL14: =SUM(B14:AI14) -> 0
A15: Less:- Purchase return | C15: =IF(B15=0,0,(D15/B15)) -> 0 | F15: =IF(E15=0,0,(G15/E15)) -> 0 | I15: =IF(H15=0,0,(J15/H15)) -> 0 | L15: =IF(K15=0,0,(M15/K15)) -> 0 | O15: =IF(N15=0,0,(P15/N15)) -> 0 | R15: =IF(Q15=0,0,(S15/Q15)) -> 0 | U15: =IF(T15=0,0,(V15/T15)) -> 0 | X15: =IF(W15=0,0,(Y15/W15)) -> 0 | AA15: =IF(Z15=0,0,(AB15/Z15)) -> 0 | AD15: =IF(AC15=0,0,(AE15/AC15)) -> 0 | AG15: =IF(AF15=0,0,(AH15/AF15)) -> 0 | AJ15: =IF(AI15=0,0,(AK15/AI15)) -> 0 | AL15: =SUM(B15:AI15) -> 0
A16: Less :- Sales | B16: ='Inventory Sales'!B24 -> 211 | C16: =IF(B16=0,0,(D16/B16)) -> 310.45024 | D16: ='Inventory Sales'!D24 -> 65505 | E16: ='Inventory Sales'!E24 -> 25 | F16: =IF(E16=0,0,(G16/E16)) -> 200 | G16: ='Inventory Sales'!G24 -> 5000 | H16: ='Inventory Sales'!H24 -> 228 | I16: =IF(H16=0,0,(J16/H16)) -> 298.20175 | J16: ='Inventory Sales'!J24 -> 67990 | K16: ='Inventory Sales'!K24 -> 227 | L16: =IF(K16=0,0,(M16/K16)) -> 304.6696 | M16: ='Inventory Sales'!M24 -> 69160 | N16: ='Inventory Sales'!N24 -> 367 | O16: =IF(N16=0,0,(P16/N16)) -> 305.20436 | P16: ='Inventory Sales'!P24 -> 112010 | Q16: ='Inventory Sales'!Q24 -> 229 | R16: =IF(Q16=0,0,(S16/Q16)) -> 302.48908 | S16: ='Inventory Sales'!S24 -> 69270 | T16: ='Inventory Sales'!T24 -> 221 | U16: =IF(T16=0,0,(V16/T16)) -> 309.86425 | V16: ='Inventory Sales'!V24 -> 68480 | W16: ='Inventory Sales'!W24 -> 285 | X16: =IF(W16=0,0,(Y16/W16)) -> 286.14035 | Y16: ='Inventory Sales'!Y24 -> 81550 | Z16: ='Inventory Sales'!Z24 -> 175 | AA16: =IF(Z16=0,0,(AB16/Z16)) -> 274.28571 | AB16: ='Inventory Sales'!AB24 -> 48000 | AC16: ='Inventory Sales'!AC24 -> 215 | AD16: =IF(AC16=0,0,(AE16/AC16)) -> 310.69767 | AE16: ='Inventory Sales'!AE24 -> 66800 | AF16: ='Inventory Sales'!AF24 -> 237 | AG16: =IF(AF16=0,0,(AH16/AF16)) -> 329.36709 | AH16: ='Inventory Sales'!AH24 -> 78060 | AI16: ='Inventory Sales'!AI24 -> 90 | AJ16: =IF(AI16=0,0,(AK16/AI16)) -> 324.88889 | AK16: ='Inventory Sales'!AK24 -> 29240 | AL16: =SUM(B16,E16,H16,K16,N16,Q16,T16,W16,Z16,AC16,AF16,AI16) -> 2510 | AM16: =IF(AL16=0,0,(AN16/AL16)) -> 303.21315 | AN16: =SUM(D16,G16,J16,M16,P16,S16,V16,Y16,AB16,AE16,AH16,AK16) -> 761065
A17: Closing Stock | B17: ='Stock Valuation (FIFO)'!E6 -> 2120 | C17: =IF(B17=0,0,(D17/B17)) -> 227.3434 | D17: ='Stock Valuation (FIFO)'!G6 -> 481968 | E17: ='Stock Valuation (FIFO)'!H6 -> 2294 | F17: =IF(E17=0,0,(G17/E17)) -> 249.52964 | G17: ='Stock Valuation (FIFO)'!J6 -> 572421 | H17: ='Stock Valuation (FIFO)'!K6 -> 2613 | I17: =IF(H17=0,0,(J17/H17)) -> 236.99732 | J17: ='Stock Valuation (FIFO)'!M6 -> 619274 | K17: ='Stock Valuation (FIFO)'!N6 -> 2769 | L17: =IF(K17=0,0,(M17/K17)) -> 264.36114 | M17: ='Stock Valuation (FIFO)'!P6 -> 732016 | N17: ='Stock Valuation (FIFO)'!Q6 -> 3082 | O17: =IF(N17=0,0,(P17/N17)) -> 263.87897 | P17: ='Stock Valuation (FIFO)'!S6 -> 813275 | Q17: ='Stock Valuation (FIFO)'!T6 -> 2819 | R17: =IF(Q17=0,0,(S17/Q17)) -> 256.02838 | S17: ='Stock Valuation (FIFO)'!V6 -> 721744 | T17: ='Stock Valuation (FIFO)'!W6 -> 2895 | U17: =IF(T17=0,0,(V17/T17)) -> 236.59896 | V17: ='Stock Valuation (FIFO)'!Y6 -> 684954 | W17: ='Stock Valuation (FIFO)'!Z6 -> 2396 | X17: =IF(W17=0,0,(Y17/W17)) -> 227.95659 | Y17: ='Stock Valuation (FIFO)'!AB6 -> 546184 | Z17: ='Stock Valuation (FIFO)'!AC6 -> 2395 | AA17: =IF(Z17=0,0,(AB17/Z17)) -> 237.1666 | AB17: ='Stock Valuation (FIFO)'!AE6 -> 568014 | AC17: ='Stock Valuation (FIFO)'!AF6 -> 2511 | AD17: =IF(AC17=0,0,(AE17/AC17)) -> 241.37634 | AE17: ='Stock Valuation (FIFO)'!AH6 -> 606096 | AF17: ='Stock Valuation (FIFO)'!AI6 -> 3260 | AG17: =IF(AF17=0,0,(AH17/AF17)) -> 233.5911 | AH17: ='Stock Valuation (FIFO)'!AK6 -> 761507 | AI17: ='Stock Valuation (FIFO)'!AL6 -> 2330 | AJ17: =IF(AI17=0,0,(AK17/AI17)) -> 226.92532 | AK17: ='Stock Valuation (FIFO)'!AN6 -> 528736 | AL17: =AI17 -> 2330 | AM17: =IF(AL17=0,0,(AN17/AL17)) -> 226.92532 | AN17: =AK17 -> 528736 | AO17: ='Stock Valuation (FIFO)'!AB6 -> 546184 | AP17: =AN17-AO17 -> -17448
A18: Consumption MB | B18: =(B12+B13)-(B16+B17) -> 855 | C18: =IF(B18=0,0,(D18/B18)) -> 212.97895 | D18: =(D12+D13)-(D16+D17) -> 182097 | E18: =(E12+E13)-(E16+E17) -> 975 | F18: =IF(E18=0,0,(G18/E18)) -> 210.2841 | G18: =(G12+G13)-(G16+G17) -> 205027 | H18: =(H12+H13)-(H16+H17) -> 1117 | I18: =IF(H18=0,0,(J18/H18)) -> 247.80304 | J18: =(J12+J13)-(J16+J17) -> 276796 | K18: =(K12+K13)-(K16+K17) -> 1267 | L18: =IF(K18=0,0,(M18/K18)) -> 197.19653 | M18: =(M12+M13)-(M16+M17) -> 249848 | N18: =(N12+N13)-(N16+N17) -> 916 | O18: =IF(N18=0,0,(P18/N18)) -> 247.82424 | P18: =(P12+P13)-(P16+P17) -> 227007 | Q18: =(Q12+Q13)-(Q16+Q17) -> 878 | R18: =IF(Q18=0,0,(S18/Q18)) -> 246.40661 | S18: =(S12+S13)-(S16+S17) -> 216345 | T18: =(T12+T13)-(T16+T17) -> 899 | U18: =IF(T18=0,0,(V18/T18)) -> 265.46496 | V18: =(V12+V13)-(V16+V17) -> 238653 | W18: =(W12+W13)-(W16+W17) -> 1159 | X18: =IF(W18=0,0,(Y18/W18)) -> 234.6264 | Y18: =(Y12+Y13)-(Y16+Y17) -> 271932 | Z18: =(Z12+Z13)-(Z16+Z17) -> 1398 | AA18: =IF(Z18=0,0,(AB18/Z18)) -> 219.62732 | AB18: =(AB12+AB13)-(AB16+AB17) -> 307039 | AC18: =(AC12+AC13)-(AC16+AC17) -> 1118 | AD18: =IF(AC18=0,0,(AE18/AC18)) -> 209.00626 | AE18: =(AE12+AE13)-(AE16+AE17) -> 233669 | AF18: =(AF12+AF13)-(AF16+AF17) -> 885 | AG18: =IF(AF18=0,0,(AH18/AF18)) -> 228.82147 | AH18: =(AH12+AH13)-(AH16+AH17) -> 202507 | AI18: =(AI12+AI13)-(AI16+AI17) -> 840 | AJ18: =IF(AI18=0,0,(AK18/AI18)) -> 242.29881 | AK18: =(AK12+AK13)-(AK16+AK17) -> 203531 | AL18: =(AL12+AL13)-(AL16+AL17) -> 12307 | AM18: =IF(AL18=0,0,(AN18/AL18)) -> 228.68701 | AN18: =(AN12+AN13)-(AN16+AN17) -> 2814451
A19: CP
A20: Opening Stock | B20: ='Stock Valuation (FIFO)'!B7 -> 32 | C20: =IF(B20=0,0,(D20/B20)) -> 996.90625 | D20: ='Stock Valuation (FIFO)'!D7 -> 31901 | E20: =B25 -> 28 | F20: =IF(E20=0,0,(G20/E20)) -> 1528.8571 | G20: =D25 -> 42808 | H20: =E25 -> 37 | I20: =IF(H20=0,0,(J20/H20)) -> 1769.8919 | J20: =G25 -> 65486 | K20: =H25 -> 40 | L20: =IF(K20=0,0,(M20/K20)) -> 1466.775 | M20: =J25 -> 58671 | N20: =K25 -> 38 | O20: =IF(N20=0,0,(P20/N20)) -> 1621.3158 | P20: =M25 -> 61610 | Q20: =N25 -> 26 | R20: =IF(Q20=0,0,(S20/Q20)) -> 1642.8846 | S20: =P25 -> 42715 | T20: =Q25 -> 16 | U20: =IF(T20=0,0,(V20/T20)) -> 1711.25 | V20: =S25 -> 27380 | W20: =T25 -> 41 | X20: =IF(W20=0,0,(Y20/W20)) -> 1775.9024 | Y20: =V25 -> 72812 | Z20: =W25 -> 46 | AA20: =IF(Z20=0,0,(AB20/Z20)) -> 1659.0435 | AB20: =Y25 -> 76316 | AC20: =Z25 -> 40 | AD20: =IF(AC20=0,0,(AE20/AC20)) -> 1629.45 | AE20: =AB25 -> 65178 | AF20: =AC25 -> 40 | AG20: =IF(AF20=0,0,(AH20/AF20)) -> 1629.45 | AH20: =AE25 -> 65178 | AI20: =AF25 -> 38 | AJ20: =IF(AI20=0,0,(AK20/AI20)) -> 1606.7368 | AK20: =AH25 -> 61056 | AL20: =B20 -> 32 | AM20: =IF(AL20=0,0,(AN20/AL20)) -> 996.90625 | AN20: =D20 -> 31901
A21: Add:- Purchases | B21: =Purchase!$H5 -> 10 | C21: =IF(B21=0,0,(D21/B21)) -> 1592.5 | D21: =Purchase!$I5 -> 15925 | E21: =Purchase!$H6 -> 11 | F21: =IF(E21=0,0,(G21/E21)) -> 1481.8182 | G21: =Purchase!$I6 -> 16300 | H21: =Purchase!$H7 -> 4 | I21: =IF(H21=0,0,(J21/H21)) -> 2185 | J21: =Purchase!$I7 -> 8740 | K21: =Purchase!$H8 -> 11 | L21: =IF(K21=0,0,(M21/K21)) -> 1365.4545 | M21: =Purchase!$I8 -> 15020 | N21: =ROUND((Purchase!$H9),0)-1 -> 12 | O21: =IF(N21=0,0,(P21/N21)) -> 1998.3333 | P21: =Purchase!$I9 -> 23980 | Q21: =Purchase!$H10 -> 0 | R21: =IF(Q21=0,0,(S21/Q21)) -> 0 | S21: =Purchase!$I10 -> 0 | T21: =ROUND((Purchase!$H11),0) -> 33 | U21: =IF(T21=0,0,(V21/T21)) -> 1693.0303 | V21: =Purchase!$I11 -> 55870 | W21: =Purchase!$H12 -> 14 | X21: =IF(W21=0,0,(Y21/W21)) -> 1630.7143 | Y21: =Purchase!$I12 -> 22830 | Z21: =Purchase!H13 -> 2 | AA21: =IF(Z21=0,0,(AB21/Z21)) -> 2280 | AB21: =Purchase!I13 -> 4560 | AC21: =Purchase!H14 -> 0 | AD21: =IF(AC21=0,0,(AE21/AC21)) -> 0 | AE21: =Purchase!I14 -> 0 | AF21: =Purchase!H15 -> 4 | AG21: =IF(AF21=0,0,(AH21/AF21)) -> 2265 | AH21: =Purchase!I15 -> 9060 | AI21: =Purchase!H16 -> 0 | AJ21: =IF(AI21=0,0,(AK21/AI21)) -> 0 | AK21: =Purchase!I16 -> 0 | AL21: =SUM(B21,E21,H21,K21,N21,Q21,T21,W21,Z21,AC21,AF21,AI21) -> 101 | AM21: =IF(AL21=0,0,(AN21/AL21)) -> 1705.7921 | AN21: =SUM(D21,G21,J21,M21,P21,S21,V21,Y21,AB21,AE21,AH21,AK21) -> 172285 | AO21: =Purchase!I17 -> 172285 | AP21: =AN21-AO21 -> 0
A22: Add:- Job Work Rcpts | C22: =IF(B22=0,0,(D22/B22)) -> 0 | F22: =IF(E22=0,0,(G22/E22)) -> 0 | I22: =IF(H22=0,0,(J22/H22)) -> 0 | L22: =IF(K22=0,0,(M22/K22)) -> 0 | O22: =IF(N22=0,0,(P22/N22)) -> 0 | R22: =IF(Q22=0,0,(S22/Q22)) -> 0 | U22: =IF(T22=0,0,(V22/T22)) -> 0 | X22: =IF(W22=0,0,(Y22/W22)) -> 0 | AA22: =IF(Z22=0,0,(AB22/Z22)) -> 0 | AD22: =IF(AC22=0,0,(AE22/AC22)) -> 0 | AG22: =IF(AF22=0,0,(AH22/AF22)) -> 0 | AJ22: =IF(AI22=0,0,(AK22/AI22)) -> 0 | AL22: =SUM(B22:AI22) -> 0
A23: Less:- Purchase return | C23: =IF(B23=0,0,(D23/B23)) -> 0 | F23: =IF(E23=0,0,(G23/E23)) -> 0 | I23: =IF(H23=0,0,(J23/H23)) -> 0 | L23: =IF(K23=0,0,(M23/K23)) -> 0 | O23: =IF(N23=0,0,(P23/N23)) -> 0 | R23: =IF(Q23=0,0,(S23/Q23)) -> 0 | U23: =IF(T23=0,0,(V23/T23)) -> 0 | X23: =IF(W23=0,0,(Y23/W23)) -> 0 | AA23: =IF(Z23=0,0,(AB23/Z23)) -> 0 | AD23: =IF(AC23=0,0,(AE23/AC23)) -> 0 | AG23: =IF(AF23=0,0,(AH23/AF23)) -> 0 | AJ23: =IF(AI23=0,0,(AK23/AI23)) -> 0 | AL23: =SUM(B23:AI23) -> 0
A24: Less :- Sales | B24: ='Inventory Sales'!B23 -> 10 | C24: =IF(B24=0,0,(D24/B24)) -> 1000 | D24: ='Inventory Sales'!D23 -> 10000 | F24: =IF(E24=0,0,(G24/E24)) -> 0 | I24: =IF(H24=0,0,(J24/H24)) -> 0 | K24: ='Inventory Sales'!K23 -> 2 | L24: =IF(K24=0,0,(M24/K24)) -> 2200 | M24: ='Inventory Sales'!M23 -> 4400 | N24: ='Inventory Sales'!N23 -> 4 | O24: =IF(N24=0,0,(P24/N24)) -> 1000 | P24: ='Inventory Sales'!P23 -> 4000 | R24: =IF(Q24=0,0,(S24/Q24)) -> 0 | U24: =IF(T24=0,0,(V24/T24)) -> 0 | X24: =IF(W24=0,0,(Y24/W24)) -> 0 | AA24: =IF(Z24=0,0,(AB24/Z24)) -> 0 | AD24: =IF(AC24=0,0,(AE24/AC24)) -> 0 | AG24: =IF(AF24=0,0,(AH24/AF24)) -> 0 | AJ24: =IF(AI24=0,0,(AK24/AI24)) -> 0 | AL24: =SUM(B24,E24,H24,K24,N24,Q24,T24,W24,Z24,AC24,AF24,AI24) -> 16 | AM24: =IF(AL24=0,0,(AN24/AL24)) -> 1150 | AN24: =SUM(D24,G24,J24,M24,P24,S24,V24,Y24,AB24,AE24,AH24,AK24) -> 18400
A25: Closing Stock | B25: ='Stock Valuation (FIFO)'!E7 -> 28 | C25: =IF(B25=0,0,(D25/B25)) -> 1528.8571 | D25: ='Stock Valuation (FIFO)'!G7 -> 42808 | E25: ='Stock Valuation (FIFO)'!H7 -> 37 | F25: =IF(E25=0,0,(G25/E25)) -> 1769.8919 | G25: ='Stock Valuation (FIFO)'!J7 -> 65486 | H25: ='Stock Valuation (FIFO)'!K7 -> 40 | I25: =IF(H25=0,0,(J25/H25)) -> 1466.775 | J25: ='Stock Valuation (FIFO)'!M7 -> 58671 | K25: ='Stock Valuation (FIFO)'!N7 -> 38 | L25: =IF(K25=0,0,(M25/K25)) -> 1621.3158 | M25: ='Stock Valuation (FIFO)'!P7 -> 61610 | N25: ='Stock Valuation (FIFO)'!Q7 -> 26 | O25: =IF(N25=0,0,(P25/N25)) -> 1642.8846 | P25: ='Stock Valuation (FIFO)'!S7 -> 42715 | Q25: ='Stock Valuation (FIFO)'!T7 -> 16 | R25: =IF(Q25=0,0,(S25/Q25)) -> 1711.25 | S25: ='Stock Valuation (FIFO)'!V7 -> 27380 | T25: ='Stock Valuation (FIFO)'!W7 -> 41 | U25: =IF(T25=0,0,(V25/T25)) -> 1775.9024 | V25: ='Stock Valuation (FIFO)'!Y7 -> 72812 | W25: ='Stock Valuation (FIFO)'!Z7 -> 46 | X25: =IF(W25=0,0,(Y25/W25)) -> 1659.0435 | Y25: ='Stock Valuation (FIFO)'!AB7 -> 76316 | Z25: ='Stock Valuation (FIFO)'!AC7 -> 40 | AA25: =IF(Z25=0,0,(AB25/Z25)) -> 1629.45 | AB25: ='Stock Valuation (FIFO)'!AE7 -> 65178 | AC25: ='Stock Valuation (FIFO)'!AF7 -> 40 | AD25: =IF(AC25=0,0,(AE25/AC25)) -> 1629.45 | AE25: ='Stock Valuation (FIFO)'!AH7 -> 65178 | AF25: ='Stock Valuation (FIFO)'!AI7 -> 38 | AG25: =IF(AF25=0,0,(AH25/AF25)) -> 1606.7368 | AH25: ='Stock Valuation (FIFO)'!AK7 -> 61056 | AI25: ='Stock Valuation (FIFO)'!AL7 -> 19 | AJ25: =IF(AI25=0,0,(AK25/AI25)) -> 1597.3684 | AK25: ='Stock Valuation (FIFO)'!AN7 -> 30350 | AL25: =AI25 -> 19 | AM25: =IF(AL25=0,0,(AN25/AL25)) -> 1597.3684 | AN25: =AK25 -> 30350 | AO25: ='Stock Valuation (FIFO)'!AB7 -> 76316 | AP25: =AN25-AO25 -> -45966
A26: Consumption CP | B26: =(B20+B21)-(B24+B25) -> 4 | C26: =IF(B26=0,0,(D26/B26)) -> -1245.5 | D26: =(D20+D21)-(D24+D25) -> -4982 | E26: =(E20+E21)-(E24+E25) -> 2 | F26: =IF(E26=0,0,(G26/E26)) -> -3189 | G26: =(G20+G21)-(G24+G25) -> -6378 | H26: =(H20+H21)-(H24+H25) -> 1 | I26: =IF(H26=0,0,(J26/H26)) -> 15555 | J26: =(J20+J21)-(J24+J25) -> 15555 | K26: =(K20+K21)-(K24+K25) -> 11 | M26: =(M20+M21)-(M24+M25) -> 7681 | N26: =(N20+N21)-(N24+N25) -> 20 | O26: =IF(N26=0,0,(P26/N26)) -> 1943.75 | P26: =(P20+P21)-(P24+P25) -> 38875 | Q26: =(Q20+Q21)-(Q24+Q25) -> 10 | R26: =IF(Q26=0,0,(S26/Q26)) -> 1533.5 | S26: =(S20+S21)-(S24+S25) -> 15335 | T26: =(T20+T21)-(T24+T25) -> 8 | U26: =IF(T26=0,0,(V26/T26)) -> 1304.75 | V26: =(V20+V21)-(V24+V25) -> 10438 | W26: =(W20+W21)-(W24+W25) -> 9 | X26: =IF(W26=0,0,(Y26/W26)) -> 2147.3333 | Y26: =(Y20+Y21)-(Y24+Y25) -> 19326 | Z26: =(Z20+Z21)-(Z24+Z25) -> 8 | AA26: =IF(Z26=0,0,(AB26/Z26)) -> 1962.25 | AB26: =(AB20+AB21)-(AB24+AB25) -> 15698 | AC26: =(AC20+AC21)-(AC24+AC25) -> 0 | AD26: =IF(AC26=0,0,(AE26/AC26)) -> 0 | AE26: =(AE20+AE21)-(AE24+AE25) -> 0 | AF26: =(AF20+AF21)-(AF24+AF25) -> 6 | AG26: =IF(AF26=0,0,(AH26/AF26)) -> 2197 | AH26: =(AH20+AH21)-(AH24+AH25) -> 13182 | AI26: =(AI20+AI21)-(AI24+AI25) -> 19 | AJ26: =IF(AI26=0,0,(AK26/AI26)) -> 1616.1053 | AK26: =(AK20+AK21)-(AK24+AK25) -> 30706 | AL26: =(AL20+AL21)-(AL24+AL25) -> 98 | AM26: =IF(AL26=0,0,(AN26/AL26)) -> 1586.0816 | AN26: =(AN20+AN21)-(AN24+AN25) -> 155436
A27: RM CONSUMPTION
A28: Opening Stock | B28: =B4+B12+B20 -> 197541 | C28: =IF(B28=0,0,(D28/B28)) -> 101.87004 | D28: =D4+D12+D20 -> 20123510 | E28: =E4+E12+E20 -> 182463 | F28: =IF(E28=0,0,(G28/E28)) -> 101.30429 | G28: =G4+G12+G20 -> 18484284 | H28: =H4+H12+H20 -> 149741 | I28: =IF(H28=0,0,(J28/H28)) -> 100.23139 | J28: =J4+J12+J20 -> 15008748 | K28: =K4+K12+K20 -> 166778 | L28: =IF(K28=0,0,(M28/K28)) -> 99.854951 | M28: =M4+M12+M20 -> 16653609 | N28: =N4+N12+N20 -> 148947 | O28: =IF(N28=0,0,(P28/N28)) -> 102.8922 | P28: =P4+P12+P20 -> 15325485 | Q28: =Q4+Q12+Q20 -> 190728 | R28: =IF(Q28=0,0,(S28/Q28)) -> 104.04267 | S28: =S4+S12+S20 -> 19843851 | T28: =T4+T12+T20 -> 117515 | U28: =IF(T28=0,0,(V28/T28)) -> 104.35591 | V28: =V4+V12+V20 -> 12263385 | W28: =W4+W12+W20 -> 142661 | X28: =IF(W28=0,0,(Y28/W28)) -> 102.01197 | Y28: =Y4+Y12+Y20 -> 14553130 | Z28: =W33 -> 166752 | AA28: =IF(Z28=0,0,(AB28/Z28)) -> 99.619465 | AB28: =Y33 -> 16611745 | AC28: =Z33 -> 137910 | AD28: =IF(AC28=0,0,(AE28/AC28)) -> 98.96199 | AE28: =AB33 -> 13647848 | AF28: =AC33 -> 177221 | AG28: =IF(AF28=0,0,(AH28/AF28)) -> 101.31947 | AH28: =AE33 -> 17955937 | AI28: =AF33 -> 157588 | AJ28: =IF(AI28=0,0,(AK28/AI28)) -> 106.53144 | AK28: =AH33 -> 16788076 | AL28: =B28 -> 197541 | AM28: =IF(AL28=0,0,(AN28/AL28)) -> 101.87004 | AN28: =D28 -> 20123510
A29: Add:- Purchases | B29: =B5+B13+B21 -> 102532 | C29: =IF(B29=0,0,(D29/B29)) -> 93.0478 | D29: =D5+D13+D21 -> 9540377 | E29: =E5+E13+E21 -> 58185 | F29: =IF(E29=0,0,(G29/E29)) -> 94.720048 | G29: =G5+G13+G21 -> 5511286 | H29: =H5+H13+H21 -> 152668 | I29: =IF(H29=0,0,(J29/H29)) -> 98.081373 | J29: =J5+J13+J21 -> 14973887 | K29: =K5+K13+K21 -> 138661 | L29: =IF(K29=0,0,(M29/K29)) -> 94.142152 | M29: =M5+M13+M21 -> 13053845 | N29: =N5+N13+N21 -> 175608 | O29: =IF(N29=0,0,(P29/N29)) -> 101.85379 | P29: =P5+P13+P21 -> 17886341 | Q29: =Q5+Q13+Q21 -> 37844 | R29: =IF(Q29=0,0,(S29/Q29)) -> 84.976984 | S29: =S5+S13+S21 -> 3215869 | T29: =T5+T13+T21 -> 129229 | U29: =IF(T29=0,0,(V29/T29)) -> 98.086343 | V29: =V5+V13+V21 -> 12675600 | W29: =W5+W13+W21 -> 120959 | X29: =IF(W29=0,0,(Y29/W29)) -> 92.068114 | Y29: =Y5+Y13+Y21 -> 11136467 | Z29: =Z5+Z13+Z21 -> 107574 | AA29: =IF(Z29=0,0,(AB29/Z29)) -> 92.388263 | AB29: =AB5+AB13+AB21 -> 9938575 | AC29: =AC5+AC13+AC21 -> 170449 | AD29: =IF(AC29=0,0,(AE29/AC29)) -> 98.210855 | AE29: =AE5+AE13+AE21 -> 16739942 | AF29: =AF5+AF13+AF21 -> 117875 | AG29: =IF(AF29=0,0,(AH29/AF29)) -> 101.5838 | AH29: =AH5+AH13+AH21 -> 11974191 | AI29: =AI5+AI13+AI21 -> 98000 | AJ29: =IF(AI29=0,0,(AK29/AI29)) -> 126.70614 | AK29: =AK5+AK13+AK21 -> 12417202 | AL29: =AL5+AL13+AL21 -> 1409584 | AM29: =IF(AL29=0,0,(AN29/AL29)) -> 98.655761 | AN29: =AN5+AN13+AN21 -> 1.3906358e+08 | AO29: =AO5+AO13+AO21 -> 139063583 | AP29: =AN29-AO29 -> -0.97999999
A30: Add:- Job Work Rcpts | B30: =B6+B14+B22 -> 0 | C30: =IF(B30=0,0,(D30/B30)) -> 0 | D30: =D6+D14+D22 -> 0 | E30: =E6+E14+E22 -> 0 | F30: =IF(E30=0,0,(G30/E30)) -> 0 | G30: =G6+G14+G22 -> 0 | H30: =H6+H14+H22 -> 0 | I30: =IF(H30=0,0,(J30/H30)) -> 0 | J30: =J6+J14+J22 -> 0 | K30: =K6+K14+K22 -> 0 | L30: =IF(K30=0,0,(M30/K30)) -> 0 | M30: =M6+M14+M22 -> 0 | N30: =N6+N14+N22 -> 0 | O30: =IF(N30=0,0,(P30/N30)) -> 0 | P30: =P6+P14+P22 -> 0 | Q30: =Q6+Q14+Q22 -> 0 | R30: =IF(Q30=0,0,(S30/Q30)) -> 0 | S30: =S6+S14+S22 -> 0 | T30: =T6+T14+T22 -> 0 | U30: =IF(T30=0,0,(V30/T30)) -> 0 | V30: =V6+V14+V22 -> 0 | W30: =W6+W14+W22 -> 0 | X30: =IF(W30=0,0,(Y30/W30)) -> 0 | Y30: =Y6+Y14+Y22 -> 0 | Z30: =Z6+Z14+Z22 -> 0 | AA30: =IF(Z30=0,0,(AB30/Z30)) -> 0 | AB30: =AB6+AB14+AB22 -> 0 | AC30: =AC6+AC14+AC22 -> 0 | AD30: =IF(AC30=0,0,(AE30/AC30)) -> 0 | AE30: =AE6+AE14+AE22 -> 0 | AF30: =AF6+AF14+AF22 -> 0 | AG30: =IF(AF30=0,0,(AH30/AF30)) -> 0 | AH30: =AH6+AH14+AH22 -> 0 | AI30: =AI6+AI14+AI22 -> 0 | AJ30: =IF(AI30=0,0,(AK30/AI30)) -> 0 | AK30: =AK6+AK14+AK22 -> 0 | AL30: =SUM(B30:AI30) -> 0
A31: Less:- Purchase return | C31: =IF(B31=0,0,(D31/B31)) -> 0 | F31: =IF(E31=0,0,(G31/E31)) -> 0 | I31: =IF(H31=0,0,(J31/H31)) -> 0 | L31: =IF(K31=0,0,(M31/K31)) -> 0 | O31: =IF(N31=0,0,(P31/N31)) -> 0 | R31: =IF(Q31=0,0,(S31/Q31)) -> 0 | U31: =IF(T31=0,0,(V31/T31)) -> 0 | X31: =IF(W31=0,0,(Y31/W31)) -> 0 | AA31: =IF(Z31=0,0,(AB31/Z31)) -> 0 | AD31: =IF(AC31=0,0,(AE31/AC31)) -> 0 | AG31: =IF(AF31=0,0,(AH31/AF31)) -> 0 | AJ31: =IF(AI31=0,0,(AK31/AI31)) -> 0 | AL31: =SUM(B31:AI31) -> 0
A32: Less :- Sales | B32: =B8+B16+B24 -> 40221 | C32: =IF(B32=0,0,(D32/B32)) -> 94.706745 | D32: =D8+D16+D24 -> 3809200 | E32: =E8+E16+E24 -> 14025 | F32: =IF(E32=0,0,(G32/E32)) -> 98.953298 | G32: =G8+G16+G24 -> 1387820 | H32: =H8+H16+H24 -> 51228 | I32: =IF(H32=0,0,(J32/H32)) -> 93.08386 | J32: =J8+J16+J24 -> 4768500 | K32: =K8+K16+K24 -> 55229 | L32: =IF(K32=0,0,(M32/K32)) -> 94.287421 | M32: =M8+M16+M24 -> 5207400 | N32: =N8+N16+N24 -> 58371 | O32: =IF(N32=0,0,(P32/N32)) -> 94.932758 | P32: =P8+P16+P24 -> 5541320 | Q32: =Q8+Q16+Q24 -> 31229 | R32: =IF(Q32=0,0,(S32/Q32)) -> 95.990906 | S32: =S8+S16+S24 -> 2997700 | T32: =T8+T16+T24 -> 24221 | U32: =IF(T32=0,0,(V32/T32)) -> 97.987697 | V32: =V8+V16+V24 -> 2373360 | W32: =W8+W16+W24 -> 15285 | X32: =IF(W32=0,0,(Y32/W32)) -> 91.38371 | Y32: =Y8+Y16+Y24 -> 1396800 | Z32: =Z8+Z16+Z24 -> 31175 | AA32: =IF(Z32=0,0,(AB32/Z32)) -> 93.621492 | AB32: =AB8+AB16+AB24 -> 2918650 | AC32: =AC8+AC16+AC24 -> 38215 | AD32: =IF(AC32=0,0,(AE32/AC32)) -> 94.85333 | AE32: =AE8+AE16+AE24 -> 3624820 | AF32: =AF8+AF16+AF24 -> 37237 | AG32: =IF(AF32=0,0,(AH32/AF32)) -> 95.706958 | AH32: =AH8+AH16+AH24 -> 3563840 | AI32: =AI8+AI16+AI24 -> 25090 | AJ32: =IF(AI32=0,0,(AK32/AI32)) -> 103.62694 | AK32: =AK8+AK16+AK24 -> 2600000 | AL32: =SUM(B32,E32,H32,K32,N32,Q32,T32,W32,Z32,AC32,AF32,AI32) -> 421526 | AM32: =IF(AL32=0,0,(AN32/AL32)) -> 95.34266 | AN32: =SUM(D32,G32,J32,M32,P32,S32,V32,Y32,AB32,AE32,AH32,AK32) -> 40189410
A33: Closing Stock | B33: =B9+B17+B25 -> 182463 | C33: =IF(B33=0,0,(D33/B33)) -> 101.30429 | D33: =D9+D17+D25 -> 18484284 | E33: =E9+E17+E25 -> 149741 | F33: =IF(E33=0,0,(G33/E33)) -> 100.23139 | G33: =G9+G17+G25 -> 15008748 | H33: =H9+H17+H25 -> 166778 | I33: =IF(H33=0,0,(J33/H33)) -> 99.854951 | J33: =J9+J17+J25 -> 16653609 | K33: =K9+K17+K25 -> 148947 | L33: =IF(K33=0,0,(M33/K33)) -> 102.8922 | M33: =M9+M17+M25 -> 15325485 | N33: =N9+N17+N25 -> 190728 | O33: =IF(N33=0,0,(P33/N33)) -> 104.04267 | P33: =P9+P17+P25 -> 19843851 | Q33: =Q9+Q17+Q25 -> 117515 | R33: =IF(Q33=0,0,(S33/Q33)) -> 104.35591 | S33: =S9+S17+S25 -> 12263385 | T33: =T9+T17+T25 -> 142661 | U33: =IF(T33=0,0,(V33/T33)) -> 102.01197 | V33: =V9+V17+V25 -> 14553130 | W33: =W9+W17+W25 -> 166752 | X33: =IF(W33=0,0,(Y33/W33)) -> 99.619465 | Y33: =Y9+Y17+Y25 -> 16611745 | Z33: =Z9+Z17+Z25 -> 137910 | AA33: =IF(Z33=0,0,(AB33/Z33)) -> 98.96199 | AB33: =AB9+AB17+AB25 -> 13647848 | AC33: =AC9+AC17+AC25 -> 177221 | AD33: =IF(AC33=0,0,(AE33/AC33)) -> 101.31947 | AE33: =AE9+AE17+AE25 -> 17955937 | AF33: =AF9+AF17+AF25 -> 157588 | AG33: =IF(AF33=0,0,(AH33/AF33)) -> 106.53144 | AH33: =AH9+AH17+AH25 -> 16788076 | AI33: =AI9+AI17+AI25 -> 143489 | AJ33: =IF(AI33=0,0,(AK33/AI33)) -> 123.87463 | AK33: =AK9+AK17+AK25 -> 17774647 | AL33: =AL9+AL17+AL25 -> 143489 | AM33: =IF(AL33=0,0,(AN33/AL33)) -> 123.87463 | AN33: =AN9+AN17+AN25 -> 17774647
A34: Consumption RM | B34: =(B28+B29)-(B32+B33) -> 77389 | C34: =IF(B34=0,0,(D34/B34)) -> 95.23838 | D34: =(D28+D29)-(D32+D33) -> 7370403 | E34: =(E28+E29)-(E32+E33) -> 76882 | F34: =IF(E34=0,0,(G34/E34)) -> 98.839806 | G34: =(G28+G29)-(G32+G33) -> 7599002 | H34: =(H28+H29)-(H32+H33) -> 84403 | I34: =IF(H34=0,0,(J34/H34)) -> 101.42443 | J34: =(J28+J29)-(J32+J33) -> 8560526 | K34: =(K28+K29)-(K32+K33) -> 101263 | L34: =IF(K34=0,0,(M34/K34)) -> 90.601394 | M34: =(M28+M29)-(M32+M33) -> 9174569 | N34: =(N28+N29)-(N32+N33) -> 75456 | O34: =IF(N34=0,0,(P34/N34)) -> 103.72475 | P34: =(P28+P29)-(P32+P33) -> 7826655 | Q34: =(Q28+Q29)-(Q32+Q33) -> 79828 | R34: =IF(Q34=0,0,(S34/Q34)) -> 97.692977 | S34: =(S28+S29)-(S32+S33) -> 7798635 | T34: =(T28+T29)-(T32+T33) -> 79862 | U34: =IF(T34=0,0,(V34/T34)) -> 100.32926 | V34: =(V28+V29)-(V32+V33) -> 8012495 | W34: =(W28+W29)-(W32+W33) -> 81583 | X34: =IF(W34=0,0,(Y34/W34)) -> 94.150154 | Y34: =(Y28+Y29)-(Y32+Y33) -> 7681052 | Z34: =(Z28+Z29)-(Z32+Z33) -> 105241 | AA34: =IF(Z34=0,0,(AB34/Z34)) -> 94.866278 | AB34: =(AB28+AB29)-(AB32+AB33) -> 9983822 | AC34: =(AC28+AC29)-(AC32+AC33) -> 92923 | AD34: =IF(AC34=0,0,(AE34/AC34)) -> 94.777751 | AE34: =(AE28+AE29)-(AE32+AE33) -> 8807033 | AF34: =(AF28+AF29)-(AF32+AF33) -> 100271 | AG34: =IF(AF34=0,0,(AH34/AF34)) -> 95.523252 | AH34: =(AH28+AH29)-(AH32+AH33) -> 9578212 | AI34: =(AI28+AI29)-(AI32+AI33) -> 87009 | AJ34: =IF(AI34=0,0,(AK34/AI34)) -> 101.49101 | AK34: =(AK28+AK29)-(AK32+AK33) -> 8830631 | AL34: =(AL28+AL29)-(AL32+AL33) -> 1042110 | AM34: =IF(AL34=0,0,(AN34/AL34)) -> 97.132774 | AN34: =(AN28+AN29)-(AN32+AN33) -> 1.0122304e+08
A35: COGS -HD | C35: =C10 -> 93.993048 | F35: =F10 -> 97.494934 | I35: =I10 -> 99.27568 | L35: =L10 -> 89.183778 | O35: =O10 -> 101.45965 | R35: =R10 -> 95.857043 | U35: =U10 -> 98.326946 | X35: =X10 -> 91.895716 | AA35: =AA10 -> 93.042664 | AD35: =AD10 -> 93.386678 | AG35: =AG10 -> 94.209328 | AJ35: =AJ10 -> 99.784028 | AM35: =AM10 -> 95.418735
A36: COGS- MB/CP | C36: =C34-C35 -> 1.2453317 | F36: =F34-F35 -> 1.344872 | I36: =I34-I35 -> 2.1487481 | L36: =L34-L35 -> 1.4176168 | O36: =O34-O35 -> 2.2651051 | R36: =R34-R35 -> 1.8359341 | U36: =U34-U35 -> 2.0023097 | X36: =X34-X35 -> 2.2544379 | AA36: =AA34-AA35 -> 1.8236145 | AD36: =AD34-AD35 -> 1.3910732 | AG36: =AG34-AG35 -> 1.3139242 | AJ36: =AJ34-AJ35 -> 1.7069788 | AM36: =AM34-AM35 -> 1.7140394
A38: Monofil Purchases
A39: Opening Stock | C39: =IF(B39=0,0,(D39/B39)) -> 0 | F39: =IF(E39=0,0,(G39/E39)) -> 0 | I39: =IF(H39=0,0,(J39/H39)) -> 0 | L39: =IF(K39=0,0,(M39/K39)) -> 0 | N39: =K48 -> 0 | Q39: =N48 -> 0 | T39: =Q48 -> 0 | W39: =T48 -> 0 | Z39: =W48 -> 0 | AC39: =Z48 -> 0 | AF39: =AC48 -> 0 | AI39: =AF48 -> 0 | AL39: =B39 -> 0 | AM39: =IF(AL39=0,0,(AN39/AL39)) -> 0 | AN39: =D39 -> 0
A40: Add:- Purchases Yarn | B40: =ROUND((Purchase!L22),0) -> 18891 | C40: =IF(B40=0,0,(D40/B40)) -> 123.7872 | D40: =ROUND((Purchase!M22),0) -> 2338464 | E40: =ROUND((Purchase!L23),0) -> 11834 | F40: =IF(E40=0,0,(G40/E40)) -> 126.26863 | G40: =ROUND((Purchase!M23),0) -> 1494263 | H40: =ROUND((Purchase!L24),0) -> 18632 | I40: =IF(H40=0,0,(J40/H40)) -> 123.0504 | J40: =ROUND((Purchase!M24),0) -> 2292675 | K40: =ROUND((Purchase!L25),0) -> 9076 | L40: =IF(K40=0,0,(M40/K40)) -> 121.0595 | M40: =ROUND((Purchase!M25),0) -> 1098736 | N40: =ROUND((Purchase!$L26),) -> 24210 | O40: =IF(N40=0,0,(P40/N40)) -> 121.84221 | P40: =ROUND((Purchase!M26),0) -> 2949800 | Q40: =ROUND((Purchase!$L27),0) -> 34618 | R40: =IF(Q40=0,0,(S40/Q40)) -> 122.34485 | S40: =ROUND((Purchase!$M27),0) -> 4235334 | T40: =ROUND((Purchase!$L28),0) -> 7140 | U40: =IF(T40=0,0,(V40/T40)) -> 109.97983 | V40: =ROUND((Purchase!$M28),0) -> 785256 | W40: =Purchase!$L29 -> 15516.05 | X40: =IF(W40=0,0,(Y40/W40)) -> 119.05076 | Y40: =Purchase!$M29 -> 1847197.6 | Z40: =Purchase!L30 -> 8732.9 | AA40: =IF(Z40=0,0,(AB40/Z40)) -> 109.95338 | AB40: =Purchase!M30 -> 960211.9 | AC40: =ROUND((Purchase!$L31),0) -> 4710 | AD40: =IF(AC40=0,0,(AE40/AC40)) -> 121.03945 | AE40: =Purchase!M31 -> 570095.8 | AF40: =ROUND((Purchase!$L32),0) -> 5000 | AG40: =IF(AF40=0,0,(AH40/AF40)) -> 112 | AH40: =Purchase!M32 -> 560000 | AI40: =ROUND((Purchase!$L33),0) -> 2984 | AJ40: =IF(AI40=0,0,(AK40/AI40)) -> 124.9685 | AK40: =ROUND((Purchase!M33),0) -> 372906 | AL40: =SUM(B40,E40,H40,K40,N40,Q40,T40,W40,Z40,AC40,AF40,AI40) -> 161343.95 | AM40: =IF(AL40=0,0,(AN40/AL40)) -> 120.89043 | AN40: =SUM(D40,G40,J40,M40,P40,S40,V40,Y40,AB40,AE40,AH40,AK40) -> 19504939 | AO40: =2986750+12068972 -> 15055722 | AP40: =AN40-AO40 -> 4449217.3
A41: Porchase Others | B41: =Purchase!$E22 -> 16952 | C41: =IF(B41=0,0,(D41/B41)) -> 243.00861 | D41: =Purchase!$F22 -> 4119482 | E41: =Purchase!$E23 -> 16531 | F41: =IF(E41=0,0,(G41/E41)) -> 239.57752 | G41: =Purchase!$F23 -> 3960456 | H41: =Purchase!$E24 -> 17353 | I41: =IF(H41=0,0,(J41/H41)) -> 236.92946 | J41: =Purchase!$F24 -> 4111437 | K41: =ROUND((Purchase!$E25),0) -> 16767 | L41: =IF(K41=0,0,(M41/K41)) -> 246.75613 | M41: =ROUND((Purchase!$F25),0) -> 4137360 | N41: =ROUND((Purchase!$E26),0) -> 15887 | O41: =IF(N41=0,0,(P41/N41)) -> 244.41971 | P41: =Purchase!$F26 -> 3883096 | Q41: =ROUND((Purchase!$E27),0) -> 15046 | R41: =IF(Q41=0,0,(S41/Q41)) -> 232.57324 | S41: =Purchase!$F27 -> 3499297 | T41: =ROUND((Purchase!$E28),0) -> 15490 | U41: =IF(T41=0,0,(V41/T41)) -> 234.66753 | V41: =ROUND((Purchase!$F28),0) -> 3635000 | W41: =ROUND((Purchase!E29),0) -> 14240 | X41: =IF(W41=0,0,(Y41/W41)) -> 234.10871 | Y41: =Purchase!F29 -> 3333708 | Z41: =ROUND((Purchase!E30),0) -> 16273 | AA41: =IF(Z41=0,0,(AB41/Z41)) -> 234.63996 | AB41: =ROUND((Purchase!F30),0) -> 3818296 | AC41: =ROUND((Purchase!E31),0) -> 15651 | AD41: =IF(AC41=0,0,(AE41/AC41)) -> 233.36617 | AE41: =ROUND((Purchase!F31),0) -> 3652414 | AF41: =ROUND((Purchase!E32),0) -> 10036 | AG41: =IF(AF41=0,0,(AH41/AF41)) -> 248.20068 | AH41: =ROUND((Purchase!F32),0) -> 2490942 | AI41: =ROUND((Purchase!E33),0) -> 15881 | AJ41: =IF(AI41=0,0,(AK41/AI41)) -> 243.14218 | AK41: =ROUND((Purchase!F33),0) -> 3861341 | AL41: =ROUND((Purchase!E34),0) -> 186106 | AM41: =IF(AL41=0,0,(AN41/AL41)) -> 239.12624 | AN41: =ROUND((Purchase!F34),0) -> 44502828
